Workbook

Sheet Расчёт
A1: Waystar Group · Расчёт оплаты 75/25 по показателям
A2: Итого = 75%×Оклад + (25%×Оклад)×Выполнение×Коэффициент компании×Стоп-фактор (переменная — предел 150%)
A4: Коэффициент компании (по чистой прибыли, 0,7–1,3): | F4: 1 | G4: ← 100% плана прибыли = 1,00
A6: № | B6: Сотрудник | C6: Должность | D6: Линия | E6: Оклад (100%), ₸ | F6: Постоянная 75%, ₸ | G6: Переменная целевая 25%, ₸ | H6: Выполнение | I6: Стоп-фактор | J6: Переменная к выплате, ₸ | K6: ИТОГО к выплате, ₸ | L6: Разница к текущему, ₸
A7: 1 | B7: Аманбекова Айгуль | C7: Отдел персонала (руководитель) | D7: Поддержка | E7: 1246243 | F7: =E7*0.75 | G7: =E7*0.25 | H7: =Показатели!E11 | I7: 1 | J7: =G7*MIN(1.5,H7*$F$4*I7) | K7: =F7+J7 | L7: =K7-E7
A8: 2 | B8: Аубакиров Алимбек | C8: Финансовый директор | D8: Передовая | E8: 4347889 | F8: =E8*0.75 | G8: =E8*0.25 | H8: =Показатели!E20 | I8: 1 | J8: =G8*MIN(1.5,H8*$F$4*I8) | K8: =F8+J8 | L8: =K8-E8
A9: 3 | B9: Байльденова Шолпан | C9: Менеджер по персоналу | D9: Поддержка | E9: 614931 | F9: =E9*0.75 | G9: =E9*0.25 | H9: =Показатели!E29 | I9: 1 | J9: =G9*MIN(1.5,H9*$F$4*I9) | K9: =F9+J9 | L9: =K9-E9
A10: 4 | B10: Данияр Алим | C10: Генеральный директор | D10: Передовая | E10: 1246243 | F10: =E10*0.75 | G10: =E10*0.25 | H10: =Показатели!E38 | I10: 1 | J10: =G10*MIN(1.5,H10*$F$4*I10) | K10: =F10+J10 | L10: =K10-E10
A11: 5 | B11: Доолоткулов Данияр | C11: Начальник отдела логистики | D11: Передовая | E11: 1246243 | F11: =E11*0.75 | G11: =E11*0.25 | H11: =Показатели!E47 | I11: 1 | J11: =G11*MIN(1.5,H11*$F$4*I11) | K11: =F11+J11 | L11: =K11-E11
A12: 6 | B12: Жунусова Камила | C12: Менеджер по логистике | D12: Передовая | E12: 230896 | F12: =E12*0.75 | G12: =E12*0.25 | H12: =Показатели!E56 | I12: 1 | J12: =G12*MIN(1.5,H12*$F$4*I12) | K12: =F12+J12 | L12: =K12-E12
A13: 7 | B13: Сейтқадыр Дарын | C13: Менеджер по логистике | D13: Передовая | E13: 236143 | F13: =E13*0.75 | G13: =E13*0.25 | H13: =Показатели!E65 | I13: 1 | J13: =G13*MIN(1.5,H13*$F$4*I13) | K13: =F13+J13 | L13: =K13-E13
A14: 8 | B14: Серикбаев Адиль | C14: Президент | D14: Передовая | E14: 6000139 | F14: =E14*0.75 | G14: =E14*0.25 | H14: =Показатели!E74 | I14: 1 | J14: =G14*MIN(1.5,H14*$F$4*I14) | K14: =F14+J14 | L14: =K14-E14
A15: 9 | B15: Таджимурадова Асем | C15: Менеджер по закрытию | D15: Передовая | E15: 378788 | F15: =E15*0.75 | G15: =E15*0.25 | H15: =Показатели!E82 | I15: 1 | J15: =G15*MIN(1.5,H15*$F$4*I15) | K15: =F15+J15 | L15: =K15-E15
A16: 10 | B16: Ташметов Сакен | C16: Юрист | D16: Поддержка | E16: 1246243 | F16: =E16*0.75 | G16: =E16*0.25 | H16: =Показатели!E91 | I16: 1 | J16: =G16*MIN(1.5,H16*$F$4*I16) | K16: =F16+J16 | L16: =K16-E16
A17: 11 | B17: Унбетпаев Ернар | C17: Операционный директор | D17: Передовая | E17: 1873611 | F17: =E17*0.75 | G17: =E17*0.25 | H17: =Показатели!E100 | I17: 1 | J17: =G17*MIN(1.5,H17*$F$4*I17) | K17: =F17+J17 | L17: =K17-E17
A18: 12 | B18: Белова Полина | C18: Менеджер по логистике (младший) | D18: Передовая | E18: 173011 | F18: =E18*0.75 | G18: =E18*0.25 | H18: =Показатели!E109 | I18: 1 | J18: =G18*MIN(1.5,H18*$F$4*I18) | K18: =F18+J18 | L18: =K18-E18
A19: 13 | B19: Сибагатов Хамардин | C19: Менеджер по логистике (старший) | D19: Передовая | E19: 993718 | F19: =E19*0.75 | G19: =E19*0.25 | H19: =Показатели!E118 | I19: 1 | J19: =G19*MIN(1.5,H19*$F$4*I19) | K19: =F19+J19 | L19: =K19-E19
B20: ИТОГО | E20: =SUM(E7:E19) | F20: =SUM(F7:F19) | G20: =SUM(G7:G19) | J20: =SUM(J7:J19) | K20: =SUM(K7:K19) | L20: =SUM(L7:L19)
B22: Фонд (оклады) в год, ₸: | E22: =E20*12 | J22: Под результатом (25%) в год: | K22: =G20*12
B23: Итого к выплате в год, ₸: | K23: =K20*12
B25: • Жёлтые ячейки — вводимые: Коэффициент компании (F4), Стоп-фактор по строке, выполнение показателей на листе «Показатели».
B26: • Передовая линия — есть личная/командная цель по прибыли (валовая/чистая); Поддержка — доля переменной на чистой прибыли компании.
B27: • Переменная = (25%×оклад) × выполнение × коэффициент компании × стоп-фактор, предел 150% целевой. При 100% и коэффициенте 1,0 «Итого» = текущему окладу.
B28: • Оклад — начисленный (база деления 75/25). Пороги и коэффициент K целей по прибыли настраиваются по управленческой отчётности.

Sheet Показатели
A1: Waystar Group · Показатели эффективности (модель 75/25)
A2: Введите фактическое выполнение по каждому показателю (жёлтые ячейки, 0–150%). Зелёные строки — цель по прибыли (валовая/чистая). Итоговый процент выполнения = сумма(вес×выполнение) переносится в лист «Расчёт».
B4: 1. Аманбекова Айгуль — Отдел персонала (руководитель) [ПОДДЕРЖКА]
B5: Показатель | C5: Вес | D5: Выполнение, % | E5: Вклад
B6: Чистая прибыль компании (общий) | C6: 0.25 | D6: 1 | E6: =C6*D6
B7: Удержание персонала / текучесть | C7: 0.25 | D7: 1 | E7: =C7*D7
B8: Срок закрытия ключевых вакансий | C8: 0.2 | D8: 1 | E8: =C8*D8
B9: Вовлечённость персонала (опрос) | C9: 0.15 | D9: 1 | E9: =C9*D9
B10: Внедрение мотивации / бюджет фонда | C10: 0.15 | D10: 1 | E10: =C10*D10
B11: Итоговое выполнение | C11: =SUM(C6:C10) | E11: =SUM(E6:E10)
B13: 2. Аубакиров Алимбек — Финансовый директор [ПЕРЕДОВАЯ ЛИНИЯ]
B14: Показатель | C14: Вес | D14: Выполнение, % | E14: Вклад
B15: Чистая прибыль компании к плану | C15: 0.35 | D15: 1 | E15: =C15*D15
B16: Запас денежных средств | C16: 0.2 | D16: 1 | E16: =C16*D16
B17: Оборот дебиторской задолженности | C17: 0.15 | D17: 1 | E17: =C17*D17
B18: Точность бюджета | C18: 0.15 | D18: 1 | E18: =C18*D18
B19: Привлечение финансирования | C19: 0.15 | D19: 1 | E19: =C19*D19
B20: Итоговое выполнение | C20: =SUM(C15:C19) | E20: =SUM(E15:E19)
B22: 3. Байльденова Шолпан — Менеджер по персоналу [ПОДДЕРЖКА]
B23: Показатель | C23: Вес | D23: Выполнение, % | E23: Вклад
B24: Чистая прибыль компании (общий) | C24: 0.25 | D24: 1 | E24: =C24*D24
B25: Срок закрытия вакансий | C25: 0.2 | D25: 1 | E25: =C25*D25
B26: Кадровый учёт без нарушений | C26: 0.2 | D26: 1 | E26: =C26*D26
B27: Точность расчёта зарплаты | C27: 0.2 | D27: 1 | E27: =C27*D27
B28: Адаптация новых сотрудников | C28: 0.15 | D28: 1 | E28: =C28*D28
B29: Итоговое выполнение | C29: =SUM(C24:C28) | E29: =SUM(E24:E28)
B31: 4. Данияр Алим — Генеральный директор [ПЕРЕДОВАЯ ЛИНИЯ]
B32: Показатель | C32: Вес | D32: Выполнение, % | E32: Вклад
B33: Чистая прибыль компании к плану | C33: 0.4 | D33: 1 | E33: =C33*D33
B34: Валовая прибыль / рентабельность | C34: 0.2 | D34: 1 | E34: =C34*D34
B35: Выручка к плану | C35: 0.2 | D35: 1 | E35: =C35*D35
B36: Выполнение годового плана | C36: 0.15 | D36: 1 | E36: =C36*D36
B37: Удержание клиентов | C37: 0.05 | D37: 1 | E37: =C37*D37
B38: Итоговое выполнение | C38: =SUM(C33:C37) | E38: =SUM(E33:E37)
B40: 5. Доолоткулов Данияр — Начальник отдела логистики [ПЕРЕДОВАЯ ЛИНИЯ]
B41: Показатель | C41: Вес | D41: Выполнение, % | E41: Вклад
B42: Валовая прибыль отдела перевозок к плану | C42: 0.4 | D42: 1 | E42: =C42*D42
B43: Соблюдение сроков доставки | C43: 0.2 | D43: 1 | E43: =C43*D43
B44: Себестоимость перевозки на рейс/тонну | C44: 0.2 | D44: 1 | E44: =C44*D44
B45: Загрузка транспорта / порожний пробег | C45: 0.1 | D45: 1 | E45: =C45*D45
B46: Сохранность груза / претензии | C46: 0.1 | D46: 1 | E46: =C46*D46
B47: Итоговое выполнение | C47: =SUM(C42:C46) | E47: =SUM(E42:E46)
B49: 6. Жунусова Камила — Менеджер по логистике [ПЕРЕДОВАЯ ЛИНИЯ]
B50: Показатель | C50: Вес | D50: Выполнение, % | E50: Вклад
B51: Валовая маржа по своим перевозкам (≥K×стоимости) | C51: 0.45 | D51: 1 | E51: =C51*D51
B52: Объём перевозок к норме | C52: 0.15 | D52: 1 | E52: =C52*D52
B53: Соблюдение сроков доставки | C53: 0.15 | D53: 1 | E53: =C53*D53
B54: Загрузка / порожний пробег | C54: 0.15 | D54: 1 | E54: =C54*D54
B55: Точность документов / сохранность | C55: 0.1 | D55: 1 | E55: =C55*D55
B56: Итоговое выполнение | C56: =SUM(C51:C55) | E56: =SUM(E51:E55)
B58: 7. Сейтқадыр Дарын — Менеджер по логистике [ПЕРЕДОВАЯ ЛИНИЯ]
B59: Показатель | C59: Вес | D59: Выполнение, % | E59: Вклад
B60: Валовая маржа по своим перевозкам (≥K×стоимости) | C60: 0.45 | D60: 1 | E60: =C60*D60
B61: Объём перевозок к норме | C61: 0.15 | D61: 1 | E61: =C61*D61
B62: Соблюдение сроков доставки | C62: 0.15 | D62: 1 | E62: =C62*D62
B63: Загрузка / порожний пробег | C63: 0.15 | D63: 1 | E63: =C63*D63
B64: Точность документов / сохранность | C64: 0.1 | D64: 1 | E64: =C64*D64
B65: Итоговое выполнение | C65: =SUM(C60:C64) | E65: =SUM(E60:E64)
B67: 8. Серикбаев Адиль — Президент [ПЕРЕДОВАЯ ЛИНИЯ]
B68: Показатель | C68: Вес | D68: Выполнение, % | E68: Вклад
B69: Чистая прибыль компании к плану | C69: 0.5 | D69: 1 | E69: =C69*D69
B70: Выручка к плану | C70: 0.15 | D70: 1 | E70: =C70*D70
B71: Развитие: направления/клиенты/география | C71: 0.2 | D71: 1 | E71: =C71*D71
B72: Денежный поток / финансирование | C72: 0.1 | D72: 1 | E72: =C72*D72
B73: Удержание ключевой команды | C73: 0.05 | D73: 1 | E73: =C73*D73
B74: Итоговое выполнение | C74: =SUM(C69:C73) | E74: =SUM(E69:E73)
B76: 9. Таджимурадова Асем — Менеджер по закрытию [ПЕРЕДОВАЯ ЛИНИЯ]
B77: Показатель | C77: Вес | D77: Выполнение, % | E77: Вклад
B78: Валовая прибыль по закрытым перевозкам к плану | C78: 0.45 | D78: 1 | E78: =C78*D78
B79: Собираемость оплаты в срок | C79: 0.3 | D79: 1 | E79: =C79*D79
B80: Срок закрытия документов | C80: 0.15 | D80: 1 | E80: =C80*D80
B81: Точность / отсутствие расхождений | C81: 0.1 | D81: 1 | E81: =C81*D81
B82: Итоговое выполнение | C82: =SUM(C78:C81) | E82: =SUM(E78:E81)
B84: 10. Ташметов Сакен — Юрист [ПОДДЕРЖКА]
B85: Показатель | C85: Вес | D85: Выполнение, % | E85: Вклад
B86: Чистая прибыль компании (общий) | C86: 0.25 | D86: 1 | E86: =C86*D86
B87: Взысканная дебиторка / споры | C87: 0.25 | D87: 1 | E87: =C87*D87
B88: Согласование договоров в срок | C88: 0.2 | D88: 1 | E88: =C88*D88
B89: Юридические риски: штрафы | C89: 0.15 | D89: 1 | E89: =C89*D89
B90: Сопровождение сделок и перевозок | C90: 0.15 | D90: 1 | E90: =C90*D90
B91: Итоговое выполнение | C91: =SUM(C86:C90) | E91: =SUM(E86:E90)
B93: 11. Унбетпаев Ернар — Операционный директор [ПЕРЕДОВАЯ ЛИНИЯ]
B94: Показатель | C94: Вес | D94: Выполнение, % | E94: Вклад
B95: Валовая прибыль по операциям к плану | C95: 0.4 | D95: 1 | E95: =C95*D95
B96: Соблюдение сроков (в срок и полностью) | C96: 0.2 | D96: 1 | E96: =C96*D96
B97: Себестоимость операций на тонну/км | C97: 0.2 | D97: 1 | E97: =C97*D97
B98: Безопасность / охрана труда | C98: 0.1 | D98: 1 | E98: =C98*D98
B99: Загрузка / порожний пробег | C99: 0.1 | D99: 1 | E99: =C99*D99
B100: Итоговое выполнение | C100: =SUM(C95:C99) | E100: =SUM(E95:E99)
B102: 12. Белова Полина — Менеджер по логистике (младший) [ПЕРЕДОВАЯ ЛИНИЯ]
B103: Показатель | C103: Вес | D103: Выполнение, % | E103: Вклад
B104: Валовая маржа по своим перевозкам (≥K×стоимости) | C104: 0.45 | D104: 1 | E104: =C104*D104
B105: Объём перевозок к норме | C105: 0.15 | D105: 1 | E105: =C105*D105
B106: Соблюдение сроков доставки | C106: 0.15 | D106: 1 | E106: =C106*D106
B107: Загрузка / порожний пробег | C107: 0.15 | D107: 1 | E107: =C107*D107
B108: Точность документов / сохранность | C108: 0.1 | D108: 1 | E108: =C108*D108
B109: Итоговое выполнение | C109: =SUM(C104:C108) | E109: =SUM(E104:E108)
B111: 13. Сибагатов Хамардин — Менеджер по логистике (старший) [ПЕРЕДОВАЯ ЛИНИЯ]
B112: Показатель | C112: Вес | D112: Выполнение, % | E112: Вклад
B113: Валовая маржа по своим перевозкам (≥K×стоимости) | C113: 0.45 | D113: 1 | E113: =C113*D113
...
