Workbook

Sheet Матрица 75-25
A1: ТОО «WayStar Group» · Матрица оплаты 75/25 и показателей
A2: Приложение 1 к приказу (75/25, с 01.01.2026). Три уровня суммы: «на руки», «брутто (оклад)», «полная стоимость (ФОТ)». База деления 75/25 выбирается ячейкой-переключателем ниже; премия = Лимит × мин(100%; факт), не выше лимита (приказ).
A3: База деления 75/25: | C3: Брутто (оклад) | E3: ← выберите: на руки / брутто (оклад) / полная стоимость (ФОТ)
A5: Подразделение | B5: Должность | C5: ФИО | D5: Таб. № | E5: На руки (100%), ₸ | F5: Брутто/оклад (100%), ₸ | G5: Полная стоимость (100%), ₸ | H5: Целевой доход по базе (100%), ₸ | I5: Оклад (75%), ₸ | J5: Лимит премии (25%), ₸ | K5: Дата начала | L5: Факт KPI, % | M5: Начисленная премия, ₸ | N5: Итого (оклад+премия), ₸
A6: Руководство | B6: Президент | C6: Серикбаев Адиль | D6: 8 | E6: 5000000 | F6: 6000139 | G6: 6613107 | H6: =IF($C$3="На руки",E6,IF($C$3="Брутто (оклад)",F6,G6)) | I6: =H6*0.75 | J6: =H6*0.25 | K6: 01.01.2026 | L6: ='Показатели (детально)'!E11 | M6: =J6*MIN(1,L6) | N6: =I6+M6
A7: Руководство | B7: Генеральный директор | C7: Данияр Алим | D7: 4 | E7: 1000000 | F7: 1246243 | G7: 1422801 | H7: =IF($C$3="На руки",E7,IF($C$3="Брутто (оклад)",F7,G7)) | I7: =H7*0.75 | J7: =H7*0.25 | K7: 01.01.2026 | L7: ='Показатели (детально)'!E20 | M7: =J7*MIN(1,L7) | N7: =I7+M7
A8: Финансы | B8: Финансовый директор | C8: Аубакиров Алимбек | D8: 2 | E8: 3500000 | F8: 4347889 | G8: 4861722 | H8: =IF($C$3="На руки",E8,IF($C$3="Брутто (оклад)",F8,G8)) | I8: =H8*0.75 | J8: =H8*0.25 | K8: 01.01.2026 | L8: ='Показатели (детально)'!E29 | M8: =J8*MIN(1,L8) | N8: =I8+M8
A9: Операции | B9: Операционный директор | C9: Унбетпаев Ернар | D9: 11 | E9: 1500000 | F9: 1873611 | G9: 2124280 | H9: =IF($C$3="На руки",E9,IF($C$3="Брутто (оклад)",F9,G9)) | I9: =H9*0.75 | J9: =H9*0.25 | K9: 01.01.2026 | L9: ='Показатели (детально)'!E38 | M9: =J9*MIN(1,L9) | N9: =I9+M9
A10: Логистика | B10: Начальник отдела логистики | C10: Доолоткулов Данияр | D10: 5 | E10: 1000000 | F10: 1246243 | G10: 1422801 | H10: =IF($C$3="На руки",E10,IF($C$3="Брутто (оклад)",F10,G10)) | I10: =H10*0.75 | J10: =H10*0.25 | K10: 01.01.2026 | L10: ='Показатели (детально)'!E47 | M10: =J10*MIN(1,L10) | N10: =I10+M10
A11: Логистика | B11: Менеджер по логистике (старший) | C11: Сибагатов Хамардин | D11: 13 | E11: 800000 | F11: 993718 | G11: 1140528 | H11: =IF($C$3="На руки",E11,IF($C$3="Брутто (оклад)",F11,G11)) | I11: =H11*0.75 | J11: =H11*0.25 | K11: 01.01.2026 | L11: ='Показатели (детально)'!E56 | M11: =J11*MIN(1,L11) | N11: =I11+M11
A12: Логистика | B12: Менеджер по логистике | C12: Жунусова Камила | D12: 6 | E12: 200000 | F12: 230896 | G12: 261836 | H12: =IF($C$3="На руки",E12,IF($C$3="Брутто (оклад)",F12,G12)) | I12: =H12*0.75 | J12: =H12*0.25 | K12: 01.01.2026 | L12: ='Показатели (детально)'!E65 | M12: =J12*MIN(1,L12) | N12: =I12+M12
A13: Логистика | B13: Менеджер по логистике | C13: Сейтқадыр Дарын | D13: 7 | E13: 200000 | F13: 236143 | G13: 274587 | H13: =IF($C$3="На руки",E13,IF($C$3="Брутто (оклад)",F13,G13)) | I13: =H13*0.75 | J13: =H13*0.25 | K13: 01.01.2026 | L13: ='Показатели (детально)'!E74 | M13: =J13*MIN(1,L13) | N13: =I13+M13
A14: Логистика | B14: Менеджер по логистике (младший) | C14: Белова Полина | D14: 12 | E14: 150000 | F14: 173011 | G14: 201177 | H14: =IF($C$3="На руки",E14,IF($C$3="Брутто (оклад)",F14,G14)) | I14: =H14*0.75 | J14: =H14*0.25 | K14: 01.01.2026 | L14: ='Показатели (детально)'!E83 | M14: =J14*MIN(1,L14) | N14: =I14+M14
A15: Расчёты | B15: Менеджер по закрытию | C15: Таджимурадова Асем | D15: 9 | E15: 300000 | F15: 378788 | G15: 440456 | H15: =IF($C$3="На руки",E15,IF($C$3="Брутто (оклад)",F15,G15)) | I15: =H15*0.75 | J15: =H15*0.25 | K15: 01.01.2026 | L15: ='Показатели (детально)'!E91 | M15: =J15*MIN(1,L15) | N15: =I15+M15
A16: Персонал | B16: Руководитель отдела персонала | C16: Аманбекова Айгуль | D16: 1 | E16: 1000000 | F16: 1246243 | G16: 1379182 | H16: =IF($C$3="На руки",E16,IF($C$3="Брутто (оклад)",F16,G16)) | I16: =H16*0.75 | J16: =H16*0.25 | K16: 01.01.2026 | L16: ='Показатели (детально)'!E100 | M16: =J16*MIN(1,L16) | N16: =I16+M16
A17: Персонал | B17: Менеджер по персоналу | C17: Байльденова Шолпан | D17: 3 | E17: 500000 | F17: 614931 | G17: 715042 | H17: =IF($C$3="На руки",E17,IF($C$3="Брутто (оклад)",F17,G17)) | I17: =H17*0.75 | J17: =H17*0.25 | K17: 01.01.2026 | L17: ='Показатели (детально)'!E109 | M17: =J17*MIN(1,L17) | N17: =I17+M17
A18: Юридический | B18: Юрист | C18: Ташметов Сакен | D18: 10 | E18: 1000000 | F18: 1246243 | G18: 1422801 | H18: =IF($C$3="На руки",E18,IF($C$3="Брутто (оклад)",F18,G18)) | I18: =H18*0.75 | J18: =H18*0.25 | K18: 01.01.2026 | L18: ='Показатели (детально)'!E118 | M18: =J18*MIN(1,L18) | N18: =I18+M18
C19: ИТОГО | E19: =SUM(E6:E18) | F19: =SUM(F6:F18) | G19: =SUM(G6:G18) | H19: =SUM(H6:H18) | I19: =SUM(I6:I18) | J19: =SUM(J6:J18) | M19: =SUM(M6:M18) | N19: =SUM(N6:N18)
C21: В год (×12), ₸: | H21: =H19*12 | J21: =J19*12 | M21: =M19*12 | N21: =N19*12
A23: • Три уровня: «на руки» (нетто), «брутто/оклад» (начисленный), «полная стоимость» (ФОТ со всеми налогами работодателя).
A24: • Ячейка C3 — переключатель базы: «Целевой доход по базе» и деление 75/25 пересчитываются автоматически.
A25: • Для трудового договора оклад указывается в брутто. При базе «на руки»/«полная стоимость» оклад (75%) — пересчитать в брутто перед договором.
A26: • Начисленная премия = Лимит × мин(100%; Факт KPI). По приказу (п.4.3) премия не превышает лимит (25%).
A27: • Факт KPI, % — с листа «Показатели (детально)» (вводится там). Таб. № — временный, заменить на реальные ID.

Sheet Показатели (детально)
A1: ТОО «WayStar Group» · Показатели эффективности по сотрудникам (модель 75/25)
A2: Введите фактическое выполнение по каждому показателю (жёлтые ячейки, 0–150%). Зелёные строки — цель по прибыли. Итоговое выполнение = сумма(вес×выполнение) переносится в лист «Матрица 75-25» (столбец «Факт KPI, %»).
B4: Серикбаев Адиль — Президент · Руководство [ПЕРЕДОВАЯ ЛИНИЯ]
B5: Показатель | C5: Вес | D5: Выполнение, % | E5: Вклад
B6: Чистая прибыль компании к плану | C6: 0.5 | D6: 1 | E6: =C6*D6
B7: Выручка к плану | C7: 0.15 | D7: 1 | E7: =C7*D7
B8: Развитие: направления/клиенты/география | C8: 0.2 | D8: 1 | E8: =C8*D8
B9: Денежный поток / финансирование | C9: 0.1 | D9: 1 | E9: =C9*D9
B10: Удержание ключевой команды | C10: 0.05 | D10: 1 | E10: =C10*D10
B11: Итоговое выполнение показателей | C11: =SUM(C6:C10) | E11: =SUM(E6:E10)
B13: Данияр Алим — Генеральный директор · Руководство [ПЕРЕДОВАЯ ЛИНИЯ]
B14: Показатель | C14: Вес | D14: Выполнение, % | E14: Вклад
B15: Чистая прибыль компании к плану | C15: 0.4 | D15: 1 | E15: =C15*D15
B16: Валовая прибыль / рентабельность | C16: 0.2 | D16: 1 | E16: =C16*D16
B17: Выручка к плану | C17: 0.2 | D17: 1 | E17: =C17*D17
B18: Выполнение годового плана | C18: 0.15 | D18: 1 | E18: =C18*D18
B19: Удержание клиентов | C19: 0.05 | D19: 1 | E19: =C19*D19
B20: Итоговое выполнение показателей | C20: =SUM(C15:C19) | E20: =SUM(E15:E19)
B22: Аубакиров Алимбек — Финансовый директор · Финансы [ПЕРЕДОВАЯ ЛИНИЯ]
B23: Показатель | C23: Вес | D23: Выполнение, % | E23: Вклад
B24: Чистая прибыль компании к плану | C24: 0.35 | D24: 1 | E24: =C24*D24
B25: Запас денежных средств | C25: 0.2 | D25: 1 | E25: =C25*D25
B26: Оборот дебиторской задолженности | C26: 0.15 | D26: 1 | E26: =C26*D26
B27: Точность бюджета | C27: 0.15 | D27: 1 | E27: =C27*D27
B28: Привлечение финансирования | C28: 0.15 | D28: 1 | E28: =C28*D28
B29: Итоговое выполнение показателей | C29: =SUM(C24:C28) | E29: =SUM(E24:E28)
B31: Унбетпаев Ернар — Операционный директор · Операции [ПЕРЕДОВАЯ ЛИНИЯ]
B32: Показатель | C32: Вес | D32: Выполнение, % | E32: Вклад
B33: Валовая прибыль по операциям к плану | C33: 0.4 | D33: 1 | E33: =C33*D33
B34: Соблюдение сроков (в срок и полностью) | C34: 0.2 | D34: 1 | E34: =C34*D34
B35: Себестоимость операций на тонну/км | C35: 0.2 | D35: 1 | E35: =C35*D35
B36: Безопасность / охрана труда | C36: 0.1 | D36: 1 | E36: =C36*D36
B37: Загрузка / порожний пробег | C37: 0.1 | D37: 1 | E37: =C37*D37
B38: Итоговое выполнение показателей | C38: =SUM(C33:C37) | E38: =SUM(E33:E37)
B40: Доолоткулов Данияр — Начальник отдела логистики · Логистика [ПЕРЕДОВАЯ ЛИНИЯ]
B41: Показатель | C41: Вес | D41: Выполнение, % | E41: Вклад
B42: Валовая прибыль отдела перевозок к плану | C42: 0.4 | D42: 1 | E42: =C42*D42
B43: Соблюдение сроков доставки | C43: 0.2 | D43: 1 | E43: =C43*D43
B44: Себестоимость перевозки на рейс/тонну | C44: 0.2 | D44: 1 | E44: =C44*D44
B45: Загрузка / порожний пробег | C45: 0.1 | D45: 1 | E45: =C45*D45
B46: Сохранность груза / претензии | C46: 0.1 | D46: 1 | E46: =C46*D46
B47: Итоговое выполнение показателей | C47: =SUM(C42:C46) | E47: =SUM(E42:E46)
B49: Сибагатов Хамардин — Менеджер по логистике (старший) · Логистика [ПЕРЕДОВАЯ ЛИНИЯ]
B50: Показатель | C50: Вес | D50: Выполнение, % | E50: Вклад
B51: Валовая маржа по своим перевозкам (≥K×стоимости) | C51: 0.45 | D51: 1 | E51: =C51*D51
B52: Объём перевозок к норме | C52: 0.15 | D52: 1 | E52: =C52*D52
B53: Соблюдение сроков доставки | C53: 0.15 | D53: 1 | E53: =C53*D53
B54: Загрузка / порожний пробег | C54: 0.15 | D54: 1 | E54: =C54*D54
B55: Точность документов / сохранность | C55: 0.1 | D55: 1 | E55: =C55*D55
B56: Итоговое выполнение показателей | C56: =SUM(C51:C55) | E56: =SUM(E51:E55)
B58: Жунусова Камила — Менеджер по логистике · Логистика [ПЕРЕДОВАЯ ЛИНИЯ]
B59: Показатель | C59: Вес | D59: Выполнение, % | E59: Вклад
B60: Валовая маржа по своим перевозкам (≥K×стоимости) | C60: 0.45 | D60: 1 | E60: =C60*D60
B61: Объём перевозок к норме | C61: 0.15 | D61: 1 | E61: =C61*D61
B62: Соблюдение сроков доставки | C62: 0.15 | D62: 1 | E62: =C62*D62
B63: Загрузка / порожний пробег | C63: 0.15 | D63: 1 | E63: =C63*D63
B64: Точность документов / сохранность | C64: 0.1 | D64: 1 | E64: =C64*D64
B65: Итоговое выполнение показателей | C65: =SUM(C60:C64) | E65: =SUM(E60:E64)
B67: Сейтқадыр Дарын — Менеджер по логистике · Логистика [ПЕРЕДОВАЯ ЛИНИЯ]
B68: Показатель | C68: Вес | D68: Выполнение, % | E68: Вклад
B69: Валовая маржа по своим перевозкам (≥K×стоимости) | C69: 0.45 | D69: 1 | E69: =C69*D69
B70: Объём перевозок к норме | C70: 0.15 | D70: 1 | E70: =C70*D70
B71: Соблюдение сроков доставки | C71: 0.15 | D71: 1 | E71: =C71*D71
B72: Загрузка / порожний пробег | C72: 0.15 | D72: 1 | E72: =C72*D72
B73: Точность документов / сохранность | C73: 0.1 | D73: 1 | E73: =C73*D73
B74: Итоговое выполнение показателей | C74: =SUM(C69:C73) | E74: =SUM(E69:E73)
B76: Белова Полина — Менеджер по логистике (младший) · Логистика [ПЕРЕДОВАЯ ЛИНИЯ]
B77: Показатель | C77: Вес | D77: Выполнение, % | E77: Вклад
B78: Валовая маржа по своим перевозкам (≥K×стоимости) | C78: 0.45 | D78: 1 | E78: =C78*D78
B79: Объём перевозок к норме | C79: 0.15 | D79: 1 | E79: =C79*D79
B80: Соблюдение сроков доставки | C80: 0.15 | D80: 1 | E80: =C80*D80
B81: Загрузка / порожний пробег | C81: 0.15 | D81: 1 | E81: =C81*D81
B82: Точность документов / сохранность | C82: 0.1 | D82: 1 | E82: =C82*D82
B83: Итоговое выполнение показателей | C83: =SUM(C78:C82) | E83: =SUM(E78:E82)
B85: Таджимурадова Асем — Менеджер по закрытию · Расчёты [ПЕРЕДОВАЯ ЛИНИЯ]
B86: Показатель | C86: Вес | D86: Выполнение, % | E86: Вклад
B87: Валовая прибыль по закрытым перевозкам к плану | C87: 0.45 | D87: 1 | E87: =C87*D87
B88: Собираемость оплаты в срок | C88: 0.3 | D88: 1 | E88: =C88*D88
B89: Срок закрытия документов | C89: 0.15 | D89: 1 | E89: =C89*D89
B90: Точность / отсутствие расхождений | C90: 0.1 | D90: 1 | E90: =C90*D90
B91: Итоговое выполнение показателей | C91: =SUM(C87:C90) | E91: =SUM(E87:E90)
B93: Аманбекова Айгуль — Руководитель отдела персонала · Персонал [ПОДДЕРЖКА]
B94: Показатель | C94: Вес | D94: Выполнение, % | E94: Вклад
B95: Чистая прибыль компании (общий) | C95: 0.25 | D95: 1 | E95: =C95*D95
B96: Удержание персонала / текучесть | C96: 0.25 | D96: 1 | E96: =C96*D96
B97: Срок закрытия ключевых вакансий | C97: 0.2 | D97: 1 | E97: =C97*D97
B98: Вовлечённость персонала (опрос) | C98: 0.15 | D98: 1 | E98: =C98*D98
B99: Внедрение мотивации / бюджет фонда | C99: 0.15 | D99: 1 | E99: =C99*D99
B100: Итоговое выполнение показателей | C100: =SUM(C95:C99) | E100: =SUM(E95:E99)
B102: Байльденова Шолпан — Менеджер по персоналу · Персонал [ПОДДЕРЖКА]
B103: Показатель | C103: Вес | D103: Выполнение, % | E103: Вклад
B104: Чистая прибыль компании (общий) | C104: 0.25 | D104: 1 | E104: =C104*D104
B105: Срок закрытия вакансий | C105: 0.2 | D105: 1 | E105: =C105*D105
B106: Кадровый учёт без нарушений | C106: 0.2 | D106: 1 | E106: =C106*D106
B107: Точность расчёта зарплаты | C107: 0.2 | D107: 1 | E107: =C107*D107
B108: Адаптация новых сотрудников | C108: 0.15 | D108: 1 | E108: =C108*D108
B109: Итоговое выполнение показателей | C109: =SUM(C104:C108) | E109: =SUM(E104:E108)
B111: Ташметов Сакен — Юрист · Юридический [ПОДДЕРЖКА]
B112: Показатель | C112: Вес | D112: Выполнение, % | E112: Вклад
B113: Чистая прибыль компании (общий) | C113: 0.25 | D113: 1 | E113: =C113*D113
...

Sheet Справочник показателей
A1: Справочник показателей эффективности (транспортно-логистическая компания)
A2: Библиотека показателей по функциям — можно адаптировать под должности. Тип: индивидуальный / командный.
A4: Функция / роль | B4: Показатель | C4: Метрика | D4: Рекоменд. вес, % | E4: Источник факта | F4: Тип
A5: Руководство | B5: Чистая прибыль компании к плану | C5: % к плану | D5: 40–50 | E5: Управл. отчётность | F5: команд.
A6: Руководство | B6: Выручка к плану | C6: % к плану | D6: 15–20 | E6: Отчёт о продажах | F6: команд.
A7: Руководство | B7: Развитие: новые направления/клиенты | C7: % этапов | D7: 15–20 | E7: План развития | F7: индив.
A8: Финансы | B8: Запас денежных средств / кассовые разрывы | C8: мес. | D8: 20 | E8: Движение средств | F8: команд.
A9: Финансы | B9: Период оборота дебиторской задолженности | C9: дни | D9: 15–20 | E9: Реестр расчётов | F9: команд.
A10: Финансы | B10: Точность бюджета (отклонение факт/план) | C10: % | D10: 15 | E10: План/факт | F10: индив.
A11: Операции | B11: Валовая прибыль по операциям | C11: млн ₸ | D11: 40 | E11: Себестоимость | F11: команд.
A12: Операции | B12: Соблюдение сроков (в срок и в полном объёме) | C12: % рейсов | D12: 20 | E12: Учёт перевозок | F12: команд.
A13: Операции | B13: Себестоимость на тонну/километр | C13: ₸ | D13: 20 | E13: Себестоимость | F13: индив.
A14: Операции | B14: Безопасность: происшествия / охрана труда | C14: кол-во | D14: 10 | E14: Служба безопасности | F14: команд.
A15: Логистика | B15: Валовая маржа по своим перевозкам | C15: ₸ / % ≥K×стоим. | D15: 45 | E15: Себестоимость | F15: индив.
... A28: Все роли | B28: Чистая прибыль компании (общий показатель) | C28: % к плану | D28: 25 | E28: Управл. отчётность | F28: команд.
