Workbook

Sheet Дашборд
A1: WAYSTAR GROUP · Управленческая отчётность
A2: ТОО «WayStar Group» · БИН 240340014287 · транспортно-экспедиторские услуги (ж/д цистерны и вагоны) · июль 2026 · все суммы в тенге
A4: КЛЮЧЕВЫЕ ПОКАЗАТЕЛИ ПЕРИОДА, ₸
A5: Операционная выручка | C5: Валовая прибыль | E5: Операционная прибыль
A6: ='ОПиУ'!C5 | C6: ='ОПиУ'!C13 | E6: ='ОПиУ'!C26
A7: выручка за услуги | C7: маржа 23.0% | E7: рентабельность 14.5%
A9: Операционный ден. поток | C9: Чистый результат (кассовый) | E9: Валовой оборот (5 счетов)
A10: ='ОДДС'!C12 | C10: ='ОПиУ'!C33 | E10: ='Денежные средства'!C13
A11: от операц. деятельности | C11: 12.0% от выручки | E11: 438 операций · «шум» ≈79%
A13: ЭКСПРЕСС-P&L, ₸
A14: Выручка | C14: ='ОПиУ'!C5
A15: (−) Себестоимость | C15: ='ОПиУ'!C6
A16: Валовая прибыль | C16: ='ОПиУ'!C13
A17: (−) Операционные расходы (ФОТ, админ, налоги) | C17: ='ОПиУ'!C15+'ОПиУ'!C18+'ОПиУ'!C25
A18: Операционная прибыль (EBITDA-прокси) | C18: ='ОПиУ'!C26
A19: (−) Финансовые и прочие (нетто) | C19: ='ОПиУ'!C33-'ОПиУ'!C26
A20: Чистый результат периода (кассовый) | C20: ='ОПиУ'!C33
A22: ⚠ КЛЮЧЕВЫЕ РИСКИ
A23: • Концентрация клиентов: QAZAQ-ASTYQ ≈ 49% выручки, топ-2 ≈ 70% — потеря клиента критична.
A24: • Нулевой денежный буфер: остатки по всем счетам к концу месяца ≈ 0, подушки ликвидности нет.
A25: • Валютный риск: RUB — только расход; по USD расход превышает приток; выручка в тенге.
A26: • Займы связанным лицам: выдано 48 млн ₸ (Серикбаев А.Д.) при обслуживании кредита Bank RBK.

Sheet ОПиУ
A1: Отчёт о прибылях и убытках (ОПиУ)
A2: Управленческий P&L · кассовый метод · тенге · ячейки связаны формулами с листом «Реестр операций»
A4: Показатель | C4: Сумма, ₸ | D4: % выручки
A5: ВЫРУЧКА от услуг (ТЭО, аренда вагонов/цистерн) | C5: =SUMIFS('Реестр операций'!$M$5:$M$442,'Реестр операций'!$O$5:$O$442,"Выручка") | D5: =IF($C$5=0,0,C5/$C$5)
A6: СЕБЕСТОИМОСТЬ услуг | C6: =-SUMIFS('Реестр операций'!$L$5:$L$442,'Реестр операций'!$O$5:$O$442,"Себестоимость") | D6: =IF($C$5=0,0,C6/$C$5)
A7: Зарубежные перевозчики/экспедиторы | C7: =-SUMIFS('Реестр операций'!$L$5:$L$442,'Реестр операций'!$P$5:$P$442,"Зарубежные перевозчики/экспедиторы") | D7: =IF($C$5=0,0,C7/$C$5)
A8: Тариф КТЖ (ж/д перевозки) | C8: =-SUMIFS('Реестр операций'!$L$5:$L$442,'Реестр операций'!$P$5:$P$442,"Тариф КТЖ (ж/д перевозки)") | D8: =IF($C$5=0,0,C8/$C$5)
A9: Аренда/предоставление вагонов | C9: =-SUMIFS('Реестр операций'!$L$5:$L$442,'Реестр операций'!$P$5:$P$442,"Аренда/предоставление вагонов") | D9: =IF($C$5=0,0,C9/$C$5)
A10: Операторы вагонов (КТТ и др.) | C10: =-SUMIFS('Реестр операций'!$L$5:$L$442,'Реестр операций'!$P$5:$P$442,"Операторы вагонов (КТТ и др.)") | D10: =IF($C$5=0,0,C10/$C$5)
A11: Прочие ж/д и ТЭУ услуги | C11: =-SUMIFS('Реестр операций'!$L$5:$L$442,'Реестр операций'!$P$5:$P$442,"Прочие ж/д и ТЭУ услуги") | D11: =IF($C$5=0,0,C11/$C$5)
A12: Ремонт вагонов и узлов | C12: =-SUMIFS('Реестр операций'!$L$5:$L$442,'Реестр операций'!$P$5:$P$442,"Ремонт вагонов и узлов") | D12: =IF($C$5=0,0,C12/$C$5)
A13: ВАЛОВАЯ ПРИБЫЛЬ | C13: =C5+C6 | D13: =IF($C$5=0,0,C13/$C$5)
A14: ОПЕРАЦИОННЫЕ РАСХОДЫ
A15: Фонд оплаты труда | C15: =-SUMIFS('Реестр операций'!$L$5:$L$442,'Реестр операций'!$O$5:$O$442,"ФОТ") | D15: =IF($C$5=0,0,C15/$C$5)
A16: Зарплата | C16: =-SUMIFS('Реестр операций'!$L$5:$L$442,'Реестр операций'!$P$5:$P$442,"Зарплата") | D16: =IF($C$5=0,0,C16/$C$5)
A17: Командировки и подотчёт | C17: =-SUMIFS('Реестр операций'!$L$5:$L$442,'Реестр операций'!$P$5:$P$442,"Командировки и подотчёт") | D17: =IF($C$5=0,0,C17/$C$5)
A18: Административные и офисные | C18: =-SUMIFS('Реестр операций'!$L$5:$L$442,'Реестр операций'!$O$5:$O$442,"Админ/офис") | D18: =IF($C$5=0,0,C18/$C$5)
A19: Офис, аренда помещений, хоз. | C19: =-SUMIFS('Реестр операций'!$L$5:$L$442,'Реестр операций'!$P$5:$P$442,"Офис, аренда помещений, хоз.") | D19: =IF($C$5=0,0,C19/$C$5)
A20: Проф. услуги (бухг./юр./конс.) | C20: =-SUMIFS('Реестр операций'!$L$5:$L$442,'Реестр операций'!$P$5:$P$442,"Проф. услуги (бухг./юр./конс.)") | D20: =IF($C$5=0,0,C20/$C$5)
A21: Связь и ИТ | C21: =-SUMIFS('Реестр операций'!$L$5:$L$442,'Реестр операций'!$P$5:$P$442,"Связь и ИТ") | D21: =IF($C$5=0,0,C21/$C$5)
A22: Маркетинг и представит. | C22: =-SUMIFS('Реестр операций'!$L$5:$L$442,'Реестр операций'!$P$5:$P$442,"Маркетинг и представит.") | D22: =IF($C$5=0,0,C22/$C$5)
A23: Хоз. расходы и материалы | C23: =-SUMIFS('Реестр операций'!$L$5:$L$442,'Реестр операций'!$P$5:$P$442,"Хоз. расходы и материалы") | D23: =IF($C$5=0,0,C23/$C$5)
A24: Страхование | C24: =-SUMIFS('Реестр операций'!$L$5:$L$442,'Реестр операций'!$P$5:$P$442,"Страхование") | D24: =IF($C$5=0,0,C24/$C$5)
A25: Налоги и отчисления | C25: =-SUMIFS('Реестр операций'!$L$5:$L$442,'Реестр операций'!$O$5:$O$442,"Налоги") | D25: =IF($C$5=0,0,C25/$C$5)
A26: ОПЕРАЦИОННАЯ ПРИБЫЛЬ (EBITDA-прокси) | C26: =C13+C15+C18+C25 | D26: =IF($C$5=0,0,C26/$C$5)
A27: ФИНАНСОВЫЕ РАСХОДЫ
A28: Проценты по кредиту | C28: =-SUMIFS('Реестр операций'!$L$5:$L$442,'Реестр операций'!$P$5:$P$442,"Проценты по кредиту") | D28: =IF($C$5=0,0,C28/$C$5)
A29: Финансовый лизинг | C29: =-SUMIFS('Реестр операций'!$L$5:$L$442,'Реестр операций'!$P$5:$P$442,"Финансовый лизинг") | D29: =IF($C$5=0,0,C29/$C$5)
A30: Банковские комиссии | C30: =-SUMIFS('Реестр операций'!$L$5:$L$442,'Реестр операций'!$P$5:$P$442,"Банковские комиссии") | D30: =IF($C$5=0,0,C30/$C$5)
A31: Проценты по депозиту (доход) | C31: =SUMIFS('Реестр операций'!$M$5:$M$442,'Реестр операций'!$P$5:$P$442,"Проценты по депозиту") | D31: =IF($C$5=0,0,C31/$C$5)
A32: ПРОЧИЕ / РАЗОВЫЕ (возвраты авансов, спонсорство) | C32: =-(SUMIFS('Реестр операций'!$L$5:$L$442,'Реестр операций'!$O$5:$O$442,"Прочее")-SUMIFS('Реестр операций'!$M$5:$M$442,'Реестр операций'!$O$5:$O$442,"Прочее")) | D32: =IF($C$5=0,0,C32/$C$5)
A33: ЧИСТЫЙ РЕЗУЛЬТАТ ПЕРИОДА (кассовый) | C33: =C26+C28+C29+C30+C31+C32 | D33: =IF($C$5=0,0,C33/$C$5)
A35: Кассовый метод по банковским выпискам. Тело кредита (66,7 млн ₸) и выданные займы (48,1 млн ₸) — движение денег, отражены в ОДДС, а не в ОПиУ; в прибыли учтены только проценты по кредиту. Не учитывает амортизацию, начисления и незакрытые взаиморасчёты. Все суммы — формулы SUMIFS по листу «Реестр операций».

Sheet ОДДС
A1: Отчёт о движении денежных средств (ОДДС)
A2: Прямой метод · тенге · ячейки связаны с реестром · сверка остатка
A4: Статья движения денежных средств | C4: Сумма, ₸
A5: Остаток денежных средств на начало периода | C5: 73255.65
A6: ОПЕРАЦИОННАЯ ДЕЯТЕЛЬНОСТЬ
A7: Поступления от клиентов за услуги | C7: =SUMIFS('Реестр операций'!$M$5:$M$442,'Реестр операций'!$O$5:$O$442,"Выручка")
A8: Оплата перевозчикам, КТЖ, аренда вагонов (себестоимость) | C8: =-SUMIFS('Реестр операций'!$L$5:$L$442,'Реестр операций'!$O$5:$O$442,"Себестоимость")
A9: Оплата труда и командировки | C9: =-SUMIFS('Реестр операций'!$L$5:$L$442,'Реестр операций'!$O$5:$O$442,"ФОТ")
A10: Административные и офисные расходы | C10: =-SUMIFS('Реестр операций'!$L$5:$L$442,'Реестр операций'!$O$5:$O$442,"Админ/офис")
A11: Налоги и отчисления | C11: =-SUMIFS('Реестр операций'!$L$5:$L$442,'Реестр операций'!$O$5:$O$442,"Налоги")
A12: Чистый поток от операционной деятельности | C12: =SUM(C7:C11)
A13: ИНВЕСТИЦИОННАЯ ДЕЯТЕЛЬНОСТЬ
A14: Выдача займов (связанным лицам) | C14: =-SUMIFS('Реестр операций'!$L$5:$L$442,'Реестр операций'!$P$5:$P$442,"Выданные займы (связ. лица)")
A15: Возврат ранее выданных займов | C15: =SUMIFS('Реестр операций'!$M$5:$M$442,'Реестр операций'!$P$5:$P$442,"Возврат выданных займов")
A16: Чистый поток от инвестиционной деятельности | C16: =C14+C15
A17: ФИНАНСОВАЯ ДЕЯТЕЛЬНОСТЬ
A18: Погашение тела кредита | C18: =-SUMIFS('Реестр операций'!$L$5:$L$442,'Реестр операций'!$P$5:$P$442,"Погашение кредита — тело")
A19: Проценты по кредиту | C19: =-SUMIFS('Реестр операций'!$L$5:$L$442,'Реестр операций'!$P$5:$P$442,"Проценты по кредиту")
A20: Финансовый лизинг | C20: =-SUMIFS('Реестр операций'!$L$5:$L$442,'Реестр операций'!$P$5:$P$442,"Финансовый лизинг")
A21: Банковские комиссии | C21: =-SUMIFS('Реестр операций'!$L$5:$L$442,'Реестр операций'!$P$5:$P$442,"Банковские комиссии")
A22: Проценты по депозиту (доход) | C22: =SUMIFS('Реестр операций'!$M$5:$M$442,'Реестр операций'!$P$5:$P$442,"Проценты по депозиту")
A23: Чистый поток от финансовой деятельности | C23: =SUM(C18:C22)
A24: ПРОЧИЕ / РАЗОВЫЕ ОПЕРАЦИИ
A25: Возврат средств контрагентам (авансы) | C25: =-SUMIFS('Реестр операций'!$L$5:$L$442,'Реестр операций'!$P$5:$P$442,"Возврат средств контрагенту")
A26: Спонсорство / благотворительность | C26: =-SUMIFS('Реестр операций'!$L$5:$L$442,'Реестр операций'!$P$5:$P$442,"Спонсорство / благотвор.")
A27: Прочие расходы | C27: =-SUMIFS('Реестр операций'!$L$5:$L$442,'Реестр операций'!$P$5:$P$442,"Прочие расходы")
A28: Прочие поступления | C28: =SUMIFS('Реестр операций'!$M$5:$M$442,'Реестр операций'!$P$5:$P$442,"Возврат средств")
A29: Чистый поток от прочих операций | C29: =SUM(C25:C28)
A30: Перемещения на прочие счета Группы + конвертация валют (нетто) | C30: =(SUMIFS('Реестр операций'!$M$5:$M$442,'Реестр операций'!$N$5:$N$442,"Внутренний перевод")-SUMIFS('Реестр операций'!$L$5:$L$442,'Реестр операций'!$N$5:$N$442,"Внутренний перевод"))+(SUMIFS('Реестр операций'!$M$5:$M$442,'Реестр операций'!$N$5:$N$442,"Конвертация валют")-SUMIFS('Реестр операций'!$L$5:$L$442,'Реестр операций'!$N$5:$N$442,"Конвертация валют"))
A31: ЧИСТОЕ ИЗМЕНЕНИЕ ДЕНЕЖНЫХ СРЕДСТВ | C31: =C12+C16+C23+C29+C30
A32: Остаток денежных средств на конец периода | C32: =C5+C31
A34: Сверка сходится: остаток на начало 73 256 ₸ + чистое изменение = остаток на конец ≈ 0 (см. лист «Денежные средства»). Строка «Перемещения на прочие счета Группы + конвертация» балансирует переводы на счета вне этих выписок и курсовые разницы. Все суммы — формулы по реестру.

Sheet Структура затрат
A1: Структура затрат по назначению
A2: Внешние платежи · формулы SUMIFS по реестру
A4: Группа / статья | C4: Сумма, ₸ | D4: % затрат | E4: % выручки
A5: Себестоимость | C5: =SUMIFS('Реестр операций'!$L$5:$L$442,'Реестр операций'!$O$5:$O$442,"Себестоимость") | D5: =C5/SUMIFS('Реестр операций'!$L$5:$L$442,'Реестр операций'!$N$5:$N$442,"Внешняя операция") | E5: =C5/SUMIFS('Реестр операций'!$M$5:$M$442,'Реестр операций'!$O$5:$O$442,"Выручка")
A6: Зарубежные перевозчики/экспедиторы | C6: =SUMIFS('Реестр операций'!$L$5:$L$442,'Реестр операций'!$P$5:$P$442,"Зарубежные перевозчики/экспедиторы") | D6: =C6/SUMIFS('Реестр операций'!$L$5:$L$442,'Реестр операций'!$N$5:$N$442,"Внешняя операция") | E6: =C6/SUMIFS('Реестр операций'!$M$5:$M$442,'Реестр операций'!$O$5:$O$442,"Выручка")
A7: Тариф КТЖ (ж/д перевозки) | C7: =SUMIFS('Реестр операций'!$L$5:$L$442,'Реестр операций'!$P$5:$P$442,"Тариф КТЖ (ж/д перевозки)") | D7: =C7/SUMIFS('Реестр операций'!$L$5:$L$442,'Реестр операций'!$N$5:$N$442,"Внешняя операция") | E7: =C7/SUMIFS('Реестр операций'!$M$5:$M$442,'Реестр операций'!$O$5:$O$442,"Выручка")
A8: Аренда/предоставление вагонов | C8: =SUMIFS('Реестр операций'!$L$5:$L$442,'Реестр операций'!$P$5:$P$442,"Аренда/предоставление вагонов") | D8: =C8/SUMIFS('Реестр операций'!$L$5:$L$442,'Реестр операций'!$N$5:$N$442,"Внешняя операция") | E8: =C8/SUMIFS('Реестр операций'!$M$5:$M$442,'Реестр операций'!$O$5:$O$442,"Выручка")
A9: Операторы вагонов (КТТ и др.) | C9: =SUMIFS('Реестр операций'!$L$5:$L$442,'Реестр операций'!$P$5:$P$442,"Операторы вагонов (КТТ и др.)") | D9: =C9/SUMIFS('Реестр операций'!$L$5:$L$442,'Реестр операций'!$N$5:$N$442,"Внешняя операция") | E9: =C9/SUMIFS('Реестр операций'!$M$5:$M$442,'Реестр операций'!$O$5:$O$442,"Выручка")
A10: Прочие ж/д и ТЭУ услуги | C10: =SUMIFS('Реестр операций'!$L$5:$L$442,'Реестр операций'!$P$5:$P$442,"Прочие ж/д и ТЭУ услуги") | D10: =C10/SUMIFS('Реестр операций'!$L$5:$L$442,'Реестр операций'!$N$5:$N$442,"Внешняя операция") | E10: =C10/SUMIFS('Реестр операций'!$M$5:$M$442,'Реестр операций'!$O$5:$O$442,"Выручка")
A11: Ремонт вагонов и узлов | C11: =SUMIFS('Реестр операций'!$L$5:$L$442,'Реестр операций'!$P$5:$P$442,"Ремонт вагонов и узлов") | D11: =C11/SUMIFS('Реестр операций'!$L$5:$L$442,'Реестр операций'!$N$5:$N$442,"Внешняя операция") | E11: =C11/SUMIFS('Реестр операций'!$M$5:$M$442,'Реестр операций'!$O$5:$O$442,"Выручка")
A12: ФОТ | C12: =SUMIFS('Реестр операций'!$L$5:$L$442,'Реестр операций'!$O$5:$O$442,"ФОТ") | D12: =C12/SUMIFS('Реестр операций'!$L$5:$L$442,'Реестр операций'!$N$5:$N$442,"Внешняя операция") | E12: =C12/SUMIFS('Реестр операций'!$M$5:$M$442,'Реестр операций'!$O$5:$O$442,"Выручка")
A13: Зарплата | C13: =SUMIFS('Реестр операций'!$L$5:$L$442,'Реестр операций'!$P$5:$P$442,"Зарплата") | D13: =C13/SUMIFS('Реестр операций'!$L$5:$L$442,'Реестр операций'!$N$5:$N$442,"Внешняя операция") | E13: =C13/SUMIFS('Реестр операций'!$M$5:$M$442,'Реестр операций'!$O$5:$O$442,"Выручка")
A14: Командировки и подотчёт | C14: =SUMIFS('Реестр операций'!$L$5:$L$442,'Реестр операций'!$P$5:$P$442,"Командировки и подотчёт") | D14: =C14/SUMIFS('Реестр операций'!$L$5:$L$442,'Реестр операций'!$N$5:$N$442,"Внешняя операция") | E14: =C14/SUMIFS('Реестр операций'!$M$5:$M$442,'Реестр операций'!$O$5:$O$442,"Выручка")
A15: Админ/офис | C15: =SUMIFS('Реестр операций'!$L$5:$L$442,'Реестр операций'!$O$5:$O$442,"Админ/офис") | D15: =C15/SUMIFS('Реестр операций'!$L$5:$L$442,'Реестр операций'!$N$5:$N$442,"Внешняя операция") | E15: =C15/SUMIFS('Реестр операций'!$M$5:$M$442,'Реестр операций'!$O$5:$O$442,"Выручка")
A16: Офис, аренда помещений, хоз. | C16: =SUMIFS('Реестр операций'!$L$5:$L$442,'Реестр операций'!$P$5:$P$442,"Офис, аренда помещений, хоз.") | D16: =C16/SUMIFS('Реестр операций'!$L$5:$L$442,'Реестр операций'!$N$5:$N$442,"Внешняя операция") | E16: =C16/SUMIFS('Реестр операций'!$M$5:$M$442,'Реестр операций'!$O$5:$O$442,"Выручка")
A17: Проф. услуги (бухг./юр./конс.) | C17: =SUMIFS('Реестр операций'!$L$5:$L$442,'Реестр операций'!$P$5:$P$442,"Проф. услуги (бухг./юр./конс.)") | D17: =C17/SUMIFS('Реестр операций'!$L$5:$L$442,'Реестр операций'!$N$5:$N$442,"Внешняя операция") | E17: =C17/SUMIFS('Реестр операций'!$M$5:$M$442,'Реестр операций'!$O$5:$O$442,"Выручка")
A18: Связь и ИТ | C18: =SUMIFS('Реестр операций'!$L$5:$L$442,'Реестр операций'!$P$5:$P$442,"Связь и ИТ") | D18: =C18/SUMIFS('Реестр операций'!$L$5:$L$442,'Реестр операций'!$N$5:$N$442,"Внешняя операция") | E18: =C18/SUMIFS('Реестр операций'!$M$5:$M$442,'Реестр операций'!$O$5:$O$442,"Выручка")
A19: Маркетинг и представит. | C19: =SUMIFS('Реестр операций'!$L$5:$L$442,'Реестр операций'!$P$5:$P$442,"Маркетинг и представит.") | D19: =C19/SUMIFS('Реестр операций'!$L$5:$L$442,'Реестр операций'!$N$5:$N$442,"Внешняя операция") | E19: =C19/SUMIFS('Реестр операций'!$M$5:$M$442,'Реестр операций'!$O$5:$O$442,"Выручка")
A20: Хоз. расходы и материалы | C20: =SUMIFS('Реестр операций'!$L$5:$L$442,'Реестр операций'!$P$5:$P$442,"Хоз. расходы и материалы") | D20: =C20/SUMIFS('Реестр операций'!$L$5:$L$442,'Реестр операций'!$N$5:$N$442,"Внешняя операция") | E20: =C20/SUMIFS('Реестр операций'!$M$5:$M$442,'Реестр операций'!$O$5:$O$442,"Выручка")
A21: Страхование | C21: =SUMIFS('Реестр операций'!$L$5:$L$442,'Реестр операций'!$P$5:$P$442,"Страхование") | D21: =C21/SUMIFS('Реестр операций'!$L$5:$L$442,'Реестр операций'!$N$5:$N$442,"Внешняя операция") | E21: =C21/SUMIFS('Реестр операций'!$M$5:$M$442,'Реестр операций'!$O$5:$O$442,"Выручка")
A22: Налоги | C22: =SUMIFS('Реестр операций'!$L$5:$L$442,'Реестр операций'!$O$5:$O$442,"Налоги") | D22: =C22/SUMIFS('Реестр операций'!$L$5:$L$442,'Реестр операций'!$N$5:$N$442,"Внешняя операция") | E22: =C22/SUMIFS('Реестр операций'!$M$5:$M$442,'Реестр операций'!$O$5:$O$442,"Выручка")
A23: Налоги и отчисления | C23: =SUMIFS('Реестр операций'!$L$5:$L$442,'Реестр операций'!$P$5:$P$442,"Налоги и отчисления") | D23: =C23/SUMIFS('Реестр операций'!$L$5:$L$442,'Реестр операций'!$N$5:$N$442,"Внешняя операция") | E23: =C23/SUMIFS('Реестр операций'!$M$5:$M$442,'Реестр операций'!$O$5:$O$442,"Выручка")
A24: Финансовые | C24: =SUMIFS('Реестр операций'!$L$5:$L$442,'Реестр операций'!$O$5:$O$442,"Финансовые") | D24: =C24/SUMIFS('Реестр операций'!$L$5:$L$442,'Реестр операций'!$N$5:$N$442,"Внешняя операция") | E24: =C24/SUMIFS('Реестр операций'!$M$5:$M$442,'Реестр операций'!$O$5:$O$442,"Выручка")
A25: Погашение кредита — тело | C25: =SUMIFS('Реестр операций'!$L$5:$L$442,'Реестр операций'!$P$5:$P$442,"Погашение кредита — тело") | D25: =C25/SUMIFS('Реестр операций'!$L$5:$L$442,'Реестр операций'!$N$5:$N$442,"Внешняя операция") | E25: =C25/SUMIFS('Реестр операций'!$M$5:$M$442,'Реестр операций'!$O$5:$O$442,"Выручка")
A26: Выданные займы (связ. лица) | C26: =SUMIFS('Реестр операций'!$L$5:$L$442,'Реестр операций'!$P$5:$P$442,"Выданные займы (связ. лица)") | D26: =C26/SUMIFS('Реестр операций'!$L$5:$L$442,'Реестр операций'!$N$5:$N$442,"Внешняя операция") | E26: =C26/SUMIFS('Реестр операций'!$M$5:$M$442,'Реестр операций'!$O$5:$O$442,"Выручка")
A27: Финансовый лизинг | C27: =SUMIFS('Реестр операций'!$L$5:$L$442,'Реестр операций'!$P$5:$P$442,"Финансовый лизинг") | D27: =C27/SUMIFS('Реестр операций'!$L$5:$L$442,'Реестр операций'!$N$5:$N$442,"Внешняя операция") | E27: =C27/SUMIFS('Реестр операций'!$M$5:$M$442,'Реестр операций'!$O$5:$O$442,"Выручка")
A28: Проценты по кредиту | C28: =SUMIFS('Реестр операций'!$L$5:$L$442,'Реестр операций'!$P$5:$P$442,"Проценты по кредиту") | D28: =C28/SUMIFS('Реестр операций'!$L$5:$L$442,'Реестр операций'!$N$5:$N$442,"Внешняя операция") | E28: =C28/SUMIFS('Реестр операций'!$M$5:$M$442,'Реестр операций'!$O$5:$O$442,"Выручка")
A29: Банковские комиссии | C29: =SUMIFS('Реестр операций'!$L$5:$L$442,'Реестр операций'!$P$5:$P$442,"Банковские комиссии") | D29: =C29/SUMIFS('Реестр операций'!$L$5:$L$442,'Реестр операций'!$N$5:$N$442,"Внешняя операция") | E29: =C29/SUMIFS('Реестр операций'!$M$5:$M$442,'Реестр операций'!$O$5:$O$442,"Выручка")
A30: Прочее | C30: =SUMIFS('Реестр операций'!$L$5:$L$442,'Реестр операций'!$O$5:$O$442,"Прочее") | D30: =C30/SUMIFS('Реестр операций'!$L$5:$L$442,'Реестр операций'!$N$5:$N$442,"Внешняя операция") | E30: =C30/SUMIFS('Реестр операций'!$M$5:$M$442,'Реестр операций'!$O$5:$O$442,"Выручка")
A31: Возврат средств контрагенту | C31: =SUMIFS('Реестр операций'!$L$5:$L$442,'Реестр операций'!$P$5:$P$442,"Возврат средств контрагенту") | D31: =C31/SUMIFS('Реестр операций'!$L$5:$L$442,'Реестр операций'!$N$5:$N$442,"Внешняя операция") | E31: =C31/SUMIFS('Реестр операций'!$M$5:$M$442,'Реестр операций'!$O$5:$O$442,"Выручка")
A32: Прочие расходы | C32: =SUMIFS('Реестр операций'!$L$5:$L$442,'Реестр операций'!$P$5:$P$442,"Прочие расходы") | D32: =C32/SUMIFS('Реестр операций'!$L$5:$L$442,'Реестр операций'!$N$5:$N$442,"Внешняя операция") | E32: =C32/SUMIFS('Реестр операций'!$M$5:$M$442,'Реестр операций'!$O$5:$O$442,"Выручка")
A33: Спонсорство / благотвор. | C33: =SUMIFS('Реестр операций'!$L$5:$L$442,'Реестр операций'!$P$5:$P$442,"Спонсорство / благотвор.") | D33: =C33/SUMIFS('Реестр операций'!$L$5:$L$442,'Реестр операций'!$N$5:$N$442,"Внешняя операция") | E33: =C33/SUMIFS('Реестр операций'!$M$5:$M$442,'Реестр операций'!$O$5:$O$442,"Выручка")
A34: ИТОГО расход (внешний) | C34: =SUMIFS('Реестр операций'!$L$5:$L$442,'Реестр операций'!$N$5:$N$442,"Внешняя операция") | D34: 1 | E34: =C34/SUMIFS('Реестр операций'!$M$5:$M$442,'Реестр операций'!$O$5:$O$442,"Выручка")

Sheet Клиенты
A1: Выручка по клиентам (все 25)
A2: Все контрагенты-плательщики за услуги · формулы SUMIFS по реестру
A4: # | B4: Контрагент | C4: Сумма, ₸ | D4: % выручки
A5: 1 | B5: ТОО «QAZAQ-ASTYQ GROUP» | C5: =SUMIFS('Реестр операций'!$M$5:$M$442,'Реестр операций'!$Q$5:$Q$442,"ТОО «QAZAQ-ASTYQ GROUP»",'Реестр операций'!$O$5:$O$442,"Выручка") | D5: =C5/SUMIFS('Реестр операций'!$M$5:$M$442,'Реестр операций'!$O$5:$O$442,"Выручка")
A6: 2 | B6: ALBATAREEQ TRADING LLC (ОАЭ) | C6: =SUMIFS('Реестр операций'!$M$5:$M$442,'Реестр операций'!$Q$5:$Q$442,"ALBATAREEQ TRADING LLC (ОАЭ)",'Реестр операций'!$O$5:$O$442,"Выручка") | D6: =C6/SUMIFS('Реестр операций'!$M$5:$M$442,'Реестр операций'!$O$5:$O$442,"Выручка")
A7: 3 | B7: ТОО «Altyn Shyghys» | C7: =SUMIFS('Реестр операций'!$M$5:$M$442,'Реестр операций'!$Q$5:$Q$442,"ТОО «Altyn Shyghys»",'Реестр операций'!$O$5:$O$442,"Выручка") | D7: =C7/SUMIFS('Реестр операций'!$M$5:$M$442,'Реестр операций'!$O$5:$O$442,"Выручка")
A8: 4 | B8: ТОО ROYAL EXPORT | C8: =SUMIFS('Реестр операций'!$M$5:$M$442,'Реестр операций'!$Q$5:$Q$442,"ТОО ROYAL EXPORT",'Реестр операций'!$O$5:$O$442,"Выручка") | D8: =C8/SUMIFS('Реестр операций'!$M$5:$M$442,'Реестр операций'!$O$5:$O$442,"Выручка")
A9: 5 | B9: ТОО "ШыгысАгроТорг" | C9: =SUMIFS('Реестр операций'!$M$5:$M$442,'Реестр операций'!$Q$5:$Q$442,"ТОО ""ШыгысАгроТорг""",'Реестр операций'!$O$5:$O$442,"Выручка") | D9: =C9/SUMIFS('Реестр операций'!$M$5:$M$442,'Реестр операций'!$O$5:$O$442,"Выручка")
A10: 6 | B10: ТОО "Экспорт-М" | C10: =SUMIFS('Реестр операций'!$M$5:$M$442,'Реестр операций'!$Q$5:$Q$442,"ТОО ""Экспорт-М""",'Реестр операций'!$O$5:$O$442,"Выручка") | D10: =C10/SUMIFS('Реестр операций'!$M$5:$M$442,'Реестр операций'!$O$5:$O$442,"Выручка")
A11: 7 | B11: ТОО REGAL EXPORT | C11: =SUMIFS('Реестр операций'!$M$5:$M$442,'Реестр операций'!$Q$5:$Q$442,"ТОО REGAL EXPORT",'Реестр операций'!$O$5:$O$442,"Выручка") | D11: =C11/SUMIFS('Реестр операций'!$M$5:$M$442,'Реестр операций'!$O$5:$O$442,"Выручка")
A12: 8 | B12: ТОО East Agro Company | C12: =SUMIFS('Реестр операций'!$M$5:$M$442,'Реестр операций'!$Q$5:$Q$442,"ТОО East Agro Company",'Реестр операций'!$O$5:$O$442,"Выручка") | D12: =C12/SUMIFS('Реестр операций'!$M$5:$M$442,'Реестр операций'!$O$5:$O$442,"Выручка")
A13: 9 | B13: ТОО "УСТЬ-КАМЕНОГОРСКИЙ МАСЛО-ЭКСТРАКЦИОННЫЙ | C13: =SUMIFS('Реестр операций'!$M$5:$M$442,'Реестр операций'!$Q$5:$Q$442,"ТОО ""УСТЬ-КАМЕНОГОРСКИЙ МАСЛО-ЭКСТРАКЦИОННЫЙ",'Реестр операций'!$O$5:$O$442,"Выручка") | D13: =C13/SUMIFS('Реестр операций'!$M$5:$M$442,'Реестр операций'!$O$5:$O$442,"Выручка")
A14: 10 | B14: ТОО Агро-Трейд-2030 | C14: =SUMIFS('Реестр операций'!$M$5:$M$442,'Реестр операций'!$Q$5:$Q$442,"ТОО Агро-Трейд-2030",'Реестр операций'!$O$5:$O$442,"Выручка") | D14: =C14/SUMIFS('Реестр операций'!$M$5:$M$442,'Реестр операций'!$O$5:$O$442,"Выручка")
A15: 11 | B15: ТОО Евразиан Каспиан Транс | C15: =SUMIFS('Реестр операций'!$M$5:$M$442,'Реестр операций'!$Q$5:$Q$442,"ТОО Евразиан Каспиан Транс",'Реестр операций'!$O$5:$O$442,"Выручка") | D15: =C15/SUMIFS('Реестр операций'!$M$5:$M$442,'Реестр операций'!$O$5:$O$442,"Выручка")
A16: 12 | B16: ТОО "GREENLIGHTS (ГРИНЛАЙТС)" | C16: =SUMIFS('Реестр операций'!$M$5:$M$442,'Реестр операций'!$Q$5:$Q$442,"ТОО ""GREENLIGHTS (ГРИНЛАЙТС)""",'Реестр операций'!$O$5:$O$442,"Выручка") | D16: =C16/SUMIFS('Реестр операций'!$M$5:$M$442,'Реестр операций'!$O$5:$O$442,"Выручка")
A17: 13 | B17: ТОО Темир Экспресс Логистик | C17: =SUMIFS('Реестр операций'!$M$5:$M$442,'Реестр операций'!$Q$5:$Q$442,"ТОО Темир Экспресс Логистик",'Реестр операций'!$O$5:$O$442,"Выручка") | D17: =C17/SUMIFS('Реестр операций'!$M$5:$M$442,'Реестр операций'!$O$5:$O$442,"Выручка")
A18: 14 | B18: ТОО "TimeAgro" | C18: =SUMIFS('Реестр операций'!$M$5:$M$442,'Реестр операций'!$Q$5:$Q$442,"ТОО ""TimeAgro""",'Реестр операций'!$O$5:$O$442,"Выручка") | D18: =C18/SUMIFS('Реестр операций'!$M$5:$M$442,'Реестр операций'!$O$5:$O$442,"Выручка")
A19: 15 | B19: ТОВАРИЩЕСТВО С ОГРАНИЧЕННОЙ ОТВЕТСТВЕННОСТЬЮ | C19: =SUMIFS('Реестр операций'!$M$5:$M$442,'Реестр операций'!$Q$5:$Q$442,"ТОВАРИЩЕСТВО С ОГРАНИЧЕННОЙ ОТВЕТСТВЕННОСТЬЮ",'Реестр операций'!$O$5:$O$442,"Выручка") | D19: =C19/SUMIFS('Реестр операций'!$M$5:$M$442,'Реестр операций'!$O$5:$O$442,"Выручка")
A20: 16 | B20: ТОО ALTAI MAI | C20: =SUMIFS('Реестр операций'!$M$5:$M$442,'Реестр операций'!$Q$5:$Q$442,"ТОО ALTAI MAI",'Реестр операций'!$O$5:$O$442,"Выручка") | D20: =C20/SUMIFS('Реестр операций'!$M$5:$M$442,'Реестр операций'!$O$5:$O$442,"Выручка")
A21: 17 | B21: ТОО «Atasu Global Trans» | C21: =SUMIFS('Реестр операций'!$M$5:$M$442,'Реестр операций'!$Q$5:$Q$442,"ТОО «Atasu Global Trans»",'Реестр операций'!$O$5:$O$442,"Выручка") | D21: =C21/SUMIFS('Реестр операций'!$M$5:$M$442,'Реестр операций'!$O$5:$O$442,"Выручка")
A22: 18 | B22: ТОО Kaz-Smart Logistics | C22: =SUMIFS('Реестр операций'!$M$5:$M$442,'Реестр операций'!$Q$5:$Q$442,"ТОО Kaz-Smart Logistics",'Реестр операций'!$O$5:$O$442,"Выручка") | D22: =C22/SUMIFS('Реестр операций'!$M$5:$M$442,'Реестр операций'!$O$5:$O$442,"Выручка")
A23: 19 | B23: ТОО EASY BOX | C23: =SUMIFS('Реестр операций'!$M$5:$M$442,'Реестр операций'!$Q$5:$Q$442,"ТОО EASY BOX",'Реестр операций'!$O$5:$O$442,"Выручка") | D23: =C23/SUMIFS('Реестр операций'!$M$5:$M$442,'Реестр операций'!$O$5:$O$442,"Выручка")
A24: 20 | B24: ТОО "AsstrА Almaty" (АсстрА Алматы) | C24: =SUMIFS('Реестр операций'!$M$5:$M$442,'Реестр операций'!$Q$5:$Q$442,"ТОО ""AsstrА Almaty"" (АсстрА Алматы)",'Реестр операций'!$O$5:$O$442,"Выручка") | D24: =C24/SUMIFS('Реестр операций'!$M$5:$M$442,'Реестр операций'!$O$5:$O$442,"Выручка")
A25: 21 | B25: ТОО Rhenus Intermodal Systems | C25: =SUMIFS('Реестр операций'!$M$5:$M$442,'Реестр операций'!$Q$5:$Q$442,"ТОО Rhenus Intermodal Systems",'Реестр операций'!$O$5:$O$442,"Выручка") | D25: =C25/SUMIFS('Реестр операций'!$M$5:$M$442,'Реестр операций'!$O$5:$O$442,"Выручка")
A26: 22 | B26: ТОО Каз Алтын Групп | C26: =SUMIFS('Реестр операций'!$M$5:$M$442,'Реестр операций'!$Q$5:$Q$442,"ТОО Каз Алтын Групп",'Реестр операций'!$O$5:$O$442,"Выручка") | D26: =C26/SUMIFS('Реестр операций'!$M$5:$M$442,'Реестр операций'!$O$5:$O$442,"Выручка")
A27: 23 | B27: ТОО "Максат-2030" | C27: =SUMIFS('Реестр операций'!$M$5:$M$442,'Реестр операций'!$Q$5:$Q$442,"ТОО ""Максат-2030""",'Реестр операций'!$O$5:$O$442,"Выручка") | D27: =C27/SUMIFS('Реестр операций'!$M$5:$M$442,'Реестр операций'!$O$5:$O$442,"Выручка")
A28: 24 | B28: ТОО "FRS logistics" | C28: =SUMIFS('Реестр операций'!$M$5:$M$442,'Реестр операций'!$Q$5:$Q$442,"ТОО ""FRS logistics""",'Реестр операций'!$O$5:$O$442,"Выручка") | D28: =C28/SUMIFS('Реестр операций'!$M$5:$M$442,'Реестр операций'!$O$5:$O$442,"Выручка")
A29: 25 | B29: Данияр Алим | C29: =SUMIFS('Реестр операций'!$M$5:$M$442,'Реестр операций'!$Q$5:$Q$442,"Данияр Алим",'Реестр операций'!$O$5:$O$442,"Выручка") | D29: =C29/SUMIFS('Реестр операций'!$M$5:$M$442,'Реестр операций'!$O$5:$O$442,"Выручка")
B30: ИТОГО (25 контрагентов) | C30: =SUM(C5:C29) | D30: =C30/SUMIFS('Реестр операций'!$M$5:$M$442,'Реестр операций'!$O$5:$O$442,"Выручка")

Sheet Поставщики
A1: Затраты по поставщикам (все 24)
A2: Все поставщики услуг (себестоимость) · формулы SUMIFS по реестру
A4: # | B4: Контрагент | C4: Сумма, ₸ | D4: % себест.
A5: 1 | B5: ТОО «КТЖ-Грузовые перевозки» | C5: =SUMIFS('Реестр операций'!$L$5:$L$442,'Реестр операций'!$Q$5:$Q$442,"ТОО «КТЖ-Грузовые перевозки»",'Реестр операций'!$O$5:$O$442,"Себестоимость") | D5: =C5/SUMIFS('Реестр операций'!$L$5:$L$442,'Реестр операций'!$O$5:$O$442,"Себестоимость")
A6: 2 | B6: MEGA STOCK CO. LTD (Таиланд) | C6: =SUMIFS('Реестр операций'!$L$5:$L$442,'Реестр операций'!$Q$5:$Q$442,"MEGA STOCK CO. LTD (Таиланд)",'Реестр операций'!$O$5:$O$442,"Себестоимость") | D6: =C6/SUMIFS('Реестр операций'!$L$5:$L$442,'Реестр операций'!$O$5:$O$442,"Себестоимость")
A7: 3 | B7: ООО «ТрансАльянс Запад» (РФ) | C7: =SUMIFS('Реестр операций'!$L$5:$L$442,'Реестр операций'!$Q$5:$Q$442,"ООО «ТрансАльянс Запад» (РФ)",'Реестр операций'!$O$5:$O$442,"Себестоимость") | D7: =C7/SUMIFS('Реестр операций'!$L$5:$L$442,'Реестр операций'!$O$5:$O$442,"Себестоимость")
A8: 4 | B8: АО «КазТемирТранс» (КТТ) | C8: =SUMIFS('Реестр операций'!$L$5:$L$442,'Реестр операций'!$Q$5:$Q$442,"АО «КазТемирТранс» (КТТ)",'Реестр операций'!$O$5:$O$442,"Себестоимость") | D8: =C8/SUMIFS('Реестр операций'!$L$5:$L$442,'Реестр операций'!$O$5:$O$442,"Себестоимость")
A9: 5 | B9: ТОО "АРНА" | C9: =SUMIFS('Реестр операций'!$L$5:$L$442,'Реестр операций'!$Q$5:$Q$442,"ТОО ""АРНА""",'Реестр операций'!$O$5:$O$442,"Себестоимость") | D9: =C9/SUMIFS('Реестр операций'!$L$5:$L$442,'Реестр операций'!$O$5:$O$442,"Себестоимость")
A10: 6 | B10: ТОО «InterLog Co» | C10: =SUMIFS('Реестр операций'!$L$5:$L$442,'Реестр операций'!$Q$5:$Q$442,"ТОО «InterLog Co»",'Реестр операций'!$O$5:$O$442,"Себестоимость") | D10: =C10/SUMIFS('Реестр операций'!$L$5:$L$442,'Реестр операций'!$O$5:$O$442,"Себестоимость")
A11: 7 | B11: ТОО "PRATA" | C11: =SUMIFS('Реестр операций'!$L$5:$L$442,'Реестр операций'!$Q$5:$Q$442,"ТОО ""PRATA""",'Реестр операций'!$O$5:$O$442,"Себестоимость") | D11: =C11/SUMIFS('Реестр операций'!$L$5:$L$442,'Реестр операций'!$O$5:$O$442,"Себестоимость")
A12: 8 | B12: LLC Altyn Trans (Узб.) | C12: =SUMIFS('Реестр операций'!$L$5:$L$442,'Реестр операций'!$Q$5:$Q$442,"LLC Altyn Trans (Узб.)",'Реестр операций'!$O$5:$O$442,"Себестоимость") | D12: =C12/SUMIFS('Реестр операций'!$L$5:$L$442,'Реестр операций'!$O$5:$O$442,"Себестоимость")
A13: 9 | B13: ТОО "ЭДЕМ ТРАНС" | C13: =SUMIFS('Реестр операций'!$L$5:$L$442,'Реестр операций'!$Q$5:$Q$442,"ТОО ""ЭДЕМ ТРАНС""",'Реестр операций'!$O$5:$O$442,"Себестоимость") | D13: =C13/SUMIFS('Реестр операций'!$L$5:$L$442,'Реестр операций'!$O$5:$O$442,"Себестоимость")
A14: 10 | B14: ТОО "PetroComLogistics" | C14: =SUMIFS('Реестр операций'!$L$5:$L$442,'Реестр операций'!$Q$5:$Q$442,"ТОО ""PetroComLogistics""",'Реестр операций'!$O$5:$O$442,"Себестоимость") | D14: =C14/SUMIFS('Реестр операций'!$L$5:$L$442,'Реестр операций'!$O$5:$O$442,"Себестоимость")
A15: 11 | B15: ТОО "ЭРСАЛТ РЭЙЛ" | C15: =SUMIFS('Реестр операций'!$L$5:$L$442,'Реестр операций'!$Q$5:$Q$442,"ТОО ""ЭРСАЛТ РЭЙЛ""",'Реестр операций'!$O$5:$O$442,"Себестоимость") | D15: =C15/SUMIFS('Реестр операций'!$L$5:$L$442,'Реестр операций'!$O$5:$O$442,"Себестоимость")
A16: 12 | B16: ТОО "USM-Logistics" | C16: =SUMIFS('Реестр операций'!$L$5:$L$442,'Реестр операций'!$Q$5:$Q$442,"ТОО ""USM-Logistics""",'Реестр операций'!$O$5:$O$442,"Себестоимость") | D16: =C16/SUMIFS('Реестр операций'!$L$5:$L$442,'Реестр операций'!$O$5:$O$442,"Себестоимость")
A17: 13 | B17: ТОО "ResursLogistiс (РесурсЛогистик)" | C17: =SUMIFS('Реестр операций'!$L$5:$L$442,'Реестр операций'!$Q$5:$Q$442,"ТОО ""ResursLogistiс (РесурсЛогистик)""",'Реестр операций'!$O$5:$O$442,"Себестоимость") | D17: =C17/SUMIFS('Реестр операций'!$L$5:$L$442,'Реестр операций'!$O$5:$O$442,"Себестоимость")
A18: 14 | B18: ТОО "Нұр-Альфинур" | C18: =SUMIFS('Реестр операций'!$L$5:$L$442,'Реестр операций'!$Q$5:$Q$442,"ТОО ""Нұр-Альфинур""",'Реестр операций'!$O$5:$O$442,"Себестоимость") | D18: =C18/SUMIFS('Реестр операций'!$L$5:$L$442,'Реестр операций'!$O$5:$O$442,"Себестоимость")
A19: 15 | B19: ТОО "Asia Railways Tracking Service (Азия Рэ | C19: =SUMIFS('Реестр операций'!$L$5:$L$442,'Реестр операций'!$Q$5:$Q$442,"ТОО ""Asia Railways Tracking Service (Азия Рэ",'Реестр операций'!$O$5:$O$442,"Себестоимость") | D19: =C19/SUMIFS('Реестр операций'!$L$5:$L$442,'Реестр операций'!$O$5:$O$442,"Себестоимость")
A20: 16 | B20: Turkmen Demiryol Express (Туркм.) | C20: =SUMIFS('Реестр операций'!$L$5:$L$442,'Реестр операций'!$Q$5:$Q$442,"Turkmen Demiryol Express (Туркм.)",'Реестр операций'!$O$5:$O$442,"Себестоимость") | D20: =C20/SUMIFS('Реестр операций'!$L$5:$L$442,'Реестр операций'!$O$5:$O$442,"Себестоимость")
A21: 17 | B21: ТОО ""SK RAILWAY Service"" | C21: =SUMIFS('Реестр операций'!$L$5:$L$442,'Реестр операций'!$Q$5:$Q$442,"ТОО """"SK RAILWAY Service""""",'Реестр операций'!$O$5:$O$442,"Себестоимость") | D21: =C21/SUMIFS('Реестр операций'!$L$5:$L$442,'Реестр операций'!$O$5:$O$442,"Себестоимость")
A22: 18 | B22: филиал акционерного общества "Национальная к | C22: =SUMIFS('Реестр операций'!$L$5:$L$442,'Реестр операций'!$Q$5:$Q$442,"филиал акционерного общества ""Национальная к",'Реестр операций'!$O$5:$O$442,"Себестоимость") | D22: =C22/SUMIFS('Реестр операций'!$L$5:$L$442,'Реестр операций'!$O$5:$O$442,"Себестоимость")
A23: 19 | B23: ТОО "ТОР Арыс" | C23: =SUMIFS('Реестр операций'!$L$5:$L$442,'Реестр операций'!$Q$5:$Q$442,"ТОО ""ТОР Арыс""",'Реестр операций'!$O$5:$O$442,"Себестоимость") | D23: =C23/SUMIFS('Реестр операций'!$L$5:$L$442,'Реестр операций'!$O$5:$O$442,"Себестоимость")
A24: 20 | B24: ТОО "Olivin.kz (Оливин.кз)" | C24: =SUMIFS('Реестр операций'!$L$5:$L$442,'Реестр операций'!$Q$5:$Q$442,"ТОО ""Olivin.kz (Оливин.кз)""",'Реестр операций'!$O$5:$O$442,"Себестоимость") | D24: =C24/SUMIFS('Реестр операций'!$L$5:$L$442,'Реестр операций'!$O$5:$O$442,"Себестоимость")
A25: 21 | B25: Производственный кооператив "ИБРАЕВ+К" | C25: =SUMIFS('Реестр операций'!$L$5:$L$442,'Реестр операций'!$Q$5:$Q$442,"Производственный кооператив ""ИБРАЕВ+К""",'Реестр операций'!$O$5:$O$442,"Себестоимость") | D25: =C25/SUMIFS('Реестр операций'!$L$5:$L$442,'Реестр операций'!$O$5:$O$442,"Себестоимость")
A26: 22 | B26: ТОО "Объединенное железнодорожное хозяйство" | C26: =SUMIFS('Реестр операций'!$L$5:$L$442,'Реестр операций'!$Q$5:$Q$442,"ТОО ""Объединенное железнодорожное хозяйство""",'Реестр операций'!$O$5:$O$442,"Себестоимость") | D26: =C26/SUMIFS('Реестр операций'!$L$5:$L$442,'Реестр операций'!$O$5:$O$442,"Себестоимость")
A27: 23 | B27: ТОО "АФ АГМ-Табыс" | C27: =SUMIFS('Реестр операций'!$L$5:$L$442,'Реестр операций'!$Q$5:$Q$442,"ТОО ""АФ АГМ-Табыс""",'Реестр операций'!$O$5:$O$442,"Себестоимость") | D27: =C27/SUMIFS('Реестр операций'!$L$5:$L$442,'Реестр операций'!$O$5:$O$442,"Себестоимость")
A28: 24 | B28: Филиал акционерного общества «Национальная к | C28: =SUMIFS('Реестр операций'!$L$5:$L$442,'Реестр операций'!$Q$5:$Q$442,"Филиал акционерного общества «Национальная к",'Реестр операций'!$O$5:$O$442,"Себестоимость") | D28: =C28/SUMIFS('Реестр операций'!$L$5:$L$442,'Реестр операций'!$O$5:$O$442,"Себестоимость")
B29: ИТОГО (24 контрагентов) | C29: =SUM(C5:C28) | D29: =C29/SUMIFS('Реестр операций'!$L$5:$L$442,'Реестр операций'!$O$5:$O$442,"Себестоимость")

Sheet Денежные средства
A1: Денежные средства по счетам
A2: Сверка: остаток на начало + приток − отток = остаток на конец · притоки/оттоки — формулы по реестру
A4: Банк · валюта | B4: ИИК | C4: Ост. на начало | D4: Приток | E4: Отток | F4: Опер. | G4: Ост. на конец
A5: ЦентрКредит · KZT | B5: KZ76...2401 | C5: 67511.82 | D5: =SUMIFS('Реестр операций'!$M$5:$M$442,'Реестр операций'!$B$5:$B$442,"ЦентрКредит",'Реестр операций'!$C$5:$C$442,"KZT") | E5: =SUMIFS('Реестр операций'!$L$5:$L$442,'Реестр операций'!$B$5:$B$442,"ЦентрКредит",'Реестр операций'!$C$5:$C$442,"KZT") | F5: =COUNTIFS('Реестр операций'!$B$5:$B$442,"ЦентрКредит",'Реестр операций'!$C$5:$C$442,"KZT") | G5: =C5+D5-E5
A6: ЦентрКредит · USD | B6: KZ58...6935 | C6: 0 | D6: =SUMIFS('Реестр операций'!$M$5:$M$442,'Реестр операций'!$B$5:$B$442,"ЦентрКредит",'Реестр операций'!$C$5:$C$442,"USD") | E6: =SUMIFS('Реестр операций'!$L$5:$L$442,'Реестр операций'!$B$5:$B$442,"ЦентрКредит",'Реестр операций'!$C$5:$C$442,"USD") | F6: =COUNTIFS('Реестр операций'!$B$5:$B$442,"ЦентрКредит",'Реестр операций'!$C$5:$C$442,"USD") | G6: =C6+D6-E6
A7: ЦентрКредит · RUB | B7: KZ03...8368 | C7: 0 | D7: =SUMIFS('Реестр операций'!$M$5:$M$442,'Реестр операций'!$B$5:$B$442,"ЦентрКредит",'Реестр операций'!$C$5:$C$442,"RUB") | E7: =SUMIFS('Реестр операций'!$L$5:$L$442,'Реестр операций'!$B$5:$B$442,"ЦентрКредит",'Реестр операций'!$C$5:$C$442,"RUB") | F7: =COUNTIFS('Реестр операций'!$B$5:$B$442,"ЦентрКредит",'Реестр операций'!$C$5:$C$442,"RUB") | G7: =C7+D7-E7
A8: Bank RBK · KZT | B8: KZ45...0001 | C8: 5743.83 | D8: =SUMIFS('Реестр операций'!$M$5:$M$442,'Реестр операций'!$B$5:$B$442,"Bank RBK",'Реестр операций'!$C$5:$C$442,"KZT") | E8: =SUMIFS('Реестр операций'!$L$5:$L$442,'Реестр операций'!$B$5:$B$442,"Bank RBK",'Реестр операций'!$C$5:$C$442,"KZT") | F8: =COUNTIFS('Реестр операций'!$B$5:$B$442,"Bank RBK",'Реестр операций'!$C$5:$C$442,"KZT") | G8: =C8+D8-E8
A9: Bank RBK · USD | B9: KZ20...0063 | C9: 0 | D9: =SUMIFS('Реестр операций'!$M$5:$M$442,'Реестр операций'!$B$5:$B$442,"Bank RBK",'Реестр операций'!$C$5:$C$442,"USD") | E9: =SUMIFS('Реестр операций'!$L$5:$L$442,'Реестр операций'!$B$5:$B$442,"Bank RBK",'Реестр операций'!$C$5:$C$442,"USD") | F9: =COUNTIFS('Реестр операций'!$B$5:$B$442,"Bank RBK",'Реестр операций'!$C$5:$C$442,"USD") | G9: =C9+D9-E9
A10: ИТОГО по 5 счетам | C10: =SUM(C5:C9) | D10: =SUM(D5:D9) | E10: =SUM(E5:E9) | F10: =SUM(F5:F9) | G10: =SUM(G5:G9)
A12: СПРАВОЧНО, ₸
A13: Валовой оборот по 5 счетам (приток+отток) | C13: =SUM('Реестр операций'!$L$5:$L$442)+SUM('Реестр операций'!$M$5:$M$442)
A14: Реальный внешний приток | C14: =SUMIFS('Реестр операций'!$M$5:$M$442,'Реестр операций'!$N$5:$N$442,"Внешняя операция")
A15: Реальный внешний расход | C15: =SUMIFS('Реестр операций'!$L$5:$L$442,'Реестр операций'!$N$5:$N$442,"Внешняя операция")
A16: «Шум» (внутр. переводы + конвертация) | C16: =SUM('Реестр операций'!$L$5:$L$442)+SUM('Реестр операций'!$M$5:$M$442)-SUMIFS('Реестр операций'!$M$5:$M$442,'Реестр операций'!$N$5:$N$442,"Внешняя операция")-SUMIFS('Реестр операций'!$L$5:$L$442,'Реестр операций'!$N$5:$N$442,"Внешняя операция")

Sheet Реестр операций
A1: Реестр операций (первичные данные)
A2: Все 438 операций из выписок с классификацией · источник для всех формул · фильтруется
A4: Дата | B4: Банк | C4: Вал | D4: Счёт | E4: Контрагент | F4: БИН | G4: КНП | H4: Назначение платежа | I4: Расход (вал) | J4: Приход (вал) | K4: Курс | L4: Расход, ₸ | M4: Приход, ₸ | N4: Тип | O4: Группа | P4: Статья | Q4: Контрагент (норм.)
A5: 01.07.2026 | B5: ЦентрКредит | C5: KZT | D5: 2401 | E5: Товарищество с ограниченной ответственностью "Shiny river" | F5: 251240008624 | G5: 872 | H5: Счет на оплату № 717 от 01.07.2026 г. Проживание в гостинице Унбетпаев / Доолоткулов с 01.07.2026 по 02.07.2026 | I5: 39000 | K5: 1 | L5: 39000 | N5: Внешняя операция | O5: ФОТ | P5: Командировки и подотчёт | Q5: ТОО "Shiny river"
A6: 01.07.2026 | B6: ЦентрКредит | C6: KZT | D6: 2401 | E6: Доолоткулов Данияр Дулатбекович | F6: 940502350175 | G6: 871 | H6: Суточные расходы на проезд в Астана-Усть-Каменогорск- Семей 30.06-04.07.2026 5 кд *15МРП (4325тг МРП) Приказ №51 от 29.06.2026. Без НДС. Платежи по поездкам | I6: 64875 | K6: 1 | L6: 64875 | N6: Внешняя операция | O6: ФОТ | P6: Командировки и подотчёт | Q6: Доолоткулов Данияр Дулатбекович
A7: 01.07.2026 | B7: ЦентрКредит | C7: KZT | D7: 2401 | E7: Унбетпаев Ернар Байтасович | F7: 840808300582 | G7: 871 | H7: Суточные расходы на проезд в Астана-Усть-Каменогорск- Семей 30.06-04.07.2026 5 кд *20МРП (4325тг МРП) Приказ №51 от 29.06.2026. Без НДС. Платежи по поездкам | I7: 86500 | K7: 1 | L7: 86500 | N7: Внешняя операция | O7: ФОТ | P7: Командировки и подотчёт | Q7: Унбетпаев Ернар Байтасович
A8: 01.07.2026 | B8: ЦентрКредит | C8: KZT | D8: 2401 | E8: Товарищество с ограниченной ответственностью "Olivin.kz (Оливин.кз)" | F8: 210240014486 | G8: 710 | H8: Счет на оплату № 177 от 25.06.2026 г. Магнитный внешний аккумулятор 30 шт | I8: 287400 | K8: 1 | L8: 287400 | N8: Внешняя операция | O8: Себестоимость | P8: Ремонт вагонов и узлов | Q8: ТОО "Olivin.kz (Оливин.кз)"
A9: 01.07.2026 | B9: ЦентрКредит | C9: KZT | D9: 2401 | E9: Товарищество с ограниченной ответственностью "Asia Railways Tracking Service (Азия Рэилвейс Трекинг Сервис)" | F9: 130540005778 | G9: 813 | H9: Счет на оплату № И-1792 от 01.07.2026 г. Договор № D-0071124 от 07.11.2024 г.Авансовая оплата за дислокацию подвижного состава | I9: 500000 | K9: 1 | L9: 500000 | N9: Внешняя операция | O9: Себестоимость | P9: Аренда/предоставление вагонов | Q9: ТОО "Asia Railways Tracking Service (Азия Рэ
A10: 01.07.2026 | B10: ЦентрКредит | C10: KZT | D10: 2401 | E10: Товарищество с ограниченной ответственностью "Нұр-Альфинур" | F10: 111240015961 | G10: 822 | H10: Оплата согласно акт сверки Сумма 2 505 840-78 тенге без налога | I10: 2505840.8 | K10: 1 | L10: 2505840.8 | N10: Внешняя операция | O10: Себестоимость | P10: Ремонт вагонов и узлов | Q10: ТОО "Нұр-Альфинур"
A11: 01.07.2026 | B11: ЦентрКредит | C11: KZT | D11: 2401 | E11: Банк ЦентрКредит для ЗП | F11: 980640000093 | G11: 332 | H11: Для зачисления на картсчета сотрудникам согласно спискам 5 500 000-00 тенге. | I11: 5500000 | K11: 1 | L11: 5500000 | N11: Внешняя операция | O11: ФОТ | P11: Зарплата | Q11: Банк ЦентрКредит для ЗП
A12: 01.07.2026 | B12: ЦентрКредит | C12: KZT | D12: 2401 | E12: Товарищество с ограниченной ответственностью "ResursLogistiс (РесурсЛогистик)" | F12: 230940036377 | G12: 813 | H12: Счет на оплату №124 от 22.06.2026 г. Счет на оплату №124 от 22.06.2026 г. Оплата за аренду вагонов ТОО «WayStar Group» по договору оказания услуг № 17-РЛ/25 от 13.05.2025г. Аренда ЦС за июль | I12: 6724520 | K12: 1 | L12: 6724520 | N12: Внешняя операция | O12: Себестоимость | P12: Аренда/предоставление вагонов | Q12: ТОО "ResursLogistiс (РесурсЛогистик)"
A13: 01.07.2026 | B13: ЦентрКредит | C13: KZT | D13: 2401 | E13: Товарищество с ограниченной ответственностью "WayStar Group" | F13: 240340014287 | G13: 312 | H13: Размещение вклада | I13: 9371424.2 | K13: 1 | L13: 9371424.2 | N13: Внутренний перевод | O13: Технические | P13: Перевод между своими счетами
A14: 01.07.2026 | B14: ЦентрКредит | C14: KZT | D14: 2401 | E14: Товарищество с ограниченной ответственностью "ResursLogistiс (РесурсЛогистик)" | F14: 230940036377 | G14: 880 | H14: Возврат денежных средств Договор №2026/03-14 от 05.03.2026 г. | I14: 10000000 | K14: 1 | L14: 10000000 | N14: Внешняя операция | O14: Прочее | P14: Возврат средств контрагенту | Q14: ТОО "ResursLogistiс (РесурсЛогистик)"
A15: 01.07.2026 | B15: ЦентрКредит | C15: KZT | D15: 2401 | E15: Товарищество с ограниченной ответственностью "WayStar Group" | F15: 240340014287 | G15: 312 | H15: на депозит. Без НДС. Размещение краткосрочных вкладов (не более одного года) | I15: 101543680 | K15: 1 | L15: 101543680 | N15: Внутренний перевод | O15: Технические | P15: Перевод между своими счетами
A16: 01.07.2026 | B16: ЦентрКредит | C16: KZT | D16: 2401 | E16: Товарищество с ограниченной ответственностью "WayStar Group" | F16: 240340014287 | G16: 316 | H16: Выплата начисленного вознаграждения по депозитному договору № 01607034 от 24.07.2025 за период с 29.06.26 по 30.06.26. Вкладчик Товарищество с ограниченной ответственностью "WayStar Group". | J16: 1328.33 | K16: 1 | M16: 1328.33 | N16: Внутренний перевод | O16: Технические | P16: Перевод между своими счетами
A17: 01.07.2026 | B17: ЦентрКредит | C17: KZT | D17: 2401 | E17: Товарищество с ограниченной ответственностью "WayStar Group" | F17: 240340014287 | G17: 322 | H17: Без НДС. Снятие с краткосрочного вклада (не более одного года) | J17: 500000 | K17: 1 | M17: 500000 | N17: Внутренний перевод | O17: Технические | P17: Перевод между своими счетами
A18: 01.07.2026 | B18: ЦентрКредит | C18: KZT | D18: 2401 | E18: Товарищество с ограниченной ответственностью "WayStar Group" | F18: 240340014287 | G18: 322 | H18: Без НДС. Снятие с краткосрочного вклада (не более одного года) | J18: 500000 | K18: 1 | M18: 500000 | N18: Внутренний перевод | O18: Технические | P18: Перевод между своими счетами
A19: 01.07.2026 | B19: ЦентрКредит | C19: KZT | D19: 2401 | E19: ТОО "WayStar Group" | F19: 240340014287 | G19: 343 | H19: перевод на другой счет Переводы клиентом денег со своего текущего счета в одном банке, филиале банка-нерезидента Республики Казахстан на свой текущий счет в другом банке, филиале другого банка-нерезидента Республики Казахстан | J19: 2626000 | K19: 1 | M19: 2626000 | N19: Внутренний перевод | O19: Технические | P19: Перевод между своими счетами
A20: 01.07.2026 | B20: ЦентрКредит | C20: KZT | D20: 2401 | E20: Товарищество с ограниченной ответственностью "WayStar Group" | F20: 240340014287 | G20: 322 | H20: Частичная выплата вклада по депозитному договору № 01607034 от 01.07.2026 в размере 3933799.78 согласно ДП. Вкладчик: Товарищество с ограниченной ответственностью "WayStar Group". | J20: 3933799.8 | K20: 1 | M20: 3933799.8 | N20: Внутренний перевод | O20: Технические | P20: Перевод между своими счетами
A21: 01.07.2026 | B21: ЦентрКредит | C21: KZT | D21: 2401 | E21: ТОО WayStar Group | F21: 240340014287 | G21: 343 | H21: перевод на другой счет Переводы клиентом денег со своего текущего счета в одном банке филиале банка-нерезидента Республики Казахстан на свой текущий счет в другом банке, филиале другого банка-нерезидента Республики Казахстан | J21: 8448600 | K21: 1 | M21: 8448600 | N21: Внутренний перевод | O21: Технические | P21: Перевод между своими счетами
A22: 01.07.2026 | B22: ЦентрКредит | C22: KZT | D22: 2401 | E22: ТОО "WayStar Group" | F22: 240340014287 | G22: 343 | H22: перевод на другой счет Переводы клиентом денег со своего текущего счета в одном банке, филиале банка-нерезидента Республики Казахстан на свой текущий счет в другом банке, филиале другого банка-нерезидента Республики Казахстан | J22: 10900000 | K22: 1 | M22: 10900000 | N22: Внутренний перевод | O22: Технические | P22: Перевод между своими счетами
A23: 01.07.2026 | B23: ЦентрКредит | C23: KZT | D23: 2401 | E23: ТОО "WayStar Group" | F23: 240340014287 | G23: 343 | H23: перевод на другой счет Переводы клиентом денег со своего текущего счета в одном банке, филиале банка-нерезидента Республики Казахстан на свой текущий счет в другом банке, филиале другого банка-нерезидента Республики Казахстан | J23: 109646000 | K23: 1 | M23: 109646000 | N23: Внутренний перевод | O23: Технические | P23: Перевод между своими счетами
A24: 02.07.2026 | B24: ЦентрКредит | C24: KZT | D24: 2401 | E24: РГУ УГД по Алмалинскому району ДГД по городу Алматы КГД МФ РК | F24: 910740000153 | G24: 911 | H24: гос пошлина. Начисленные (исчисленные) и иные обязательства в бюджет | I24: 27641.25 | K24: 1 | L24: 27641.25 | N24: Внешняя операция | O24: Налоги | P24: Налоги и отчисления | Q24: РГУ УГД по Алмалинскому району ДГД по город
A25: 02.07.2026 | B25: ЦентрКредит | C25: KZT | D25: 2401 | E25: Индивидуальный предприниматель "Саметханов Алихан Дарханұлы" | F25: 970527350974 | G25: 872 | H25: Без НДС. Платежи за услуги по проживанию и питанию | I25: 30000 | K25: 1 | L25: 30000 | N25: Внешняя операция | O25: ФОТ | P25: Командировки и подотчёт | Q25: Индивидуальный предприниматель "Саметханов А
A26: 02.07.2026 | B26: ЦентрКредит | C26: KZT | D26: 2401 | E26: Индивидуальный предприниматель "Капизова" | F26: 770127402766 | G26: 859 | H26: Без НДС. Платежи за профессиональные, научные и технические услуги | I26: 50000 | K26: 1 | L26: 50000 | N26: Внешняя операция | O26: Админ/офис | P26: Проф. услуги (бухг./юр./конс.) | Q26: Индивидуальный предприниматель "Капизова"
A27: 02.07.2026 | B27: ЦентрКредит | C27: KZT | D27: 2401 | E27: Акционерное Общество "Банк ЦентрКредит" | F27: 980640000093 | G27: 841 | H27: Интернет-банкинг. MIP. Международные платежи. Перевод OUR, кроме валют стран СНГ с 13:00 по 16:00. Расчетный документ № 1 от 02.07.26 на сумму 100 000.00 USD, в т.ч. НДС 16% | I27: 95852 | K27: 1 | L27: 95852 | N27: Внешняя операция | O27: Финансовые | P27: Банковские комиссии | Q27: Акционерное Общество "Банк ЦентрКредит"
A28: 02.07.2026 | B28: ЦентрКредит | C28: KZT | D28: 2401 | E28: Алим | F28: 020420550046 | G28: 871 | H28: Данияр Алим подотчет. Без НДС. Платежи по поездкам | I28: 986100 | K28: 1 | L28: 986100 | N28: Внешняя операция | O28: ФОТ | P28: Командировки и подотчёт | Q28: Алим
A29: 02.07.2026 | B29: ЦентрКредит | C29: KZT | D29: 2401 | E29: Товарищество с ограниченной ответственностью «InterLog Co» | F29: 061040010307 | G29: 813 | H29: Договор №017 от 30.12.2025 г. Оплата долга по акту сверки. Без НДС. Платежи за услуги железнодорожного транспорта | I29: 1648080 | K29: 1 | L29: 1648080 | N29: Внешняя операция | O29: Себестоимость | P29: Прочие ж/д и ТЭУ услуги | Q29: ТОО «InterLog Co»
A30: 02.07.2026 | B30: ЦентрКредит | C30: KZT | D30: 2401 | E30: ТОО КТЖ-Грузовые перевозки | F30: 031040001799 | G30: 813 | H30: Без НДС, 4185494, Платежи за услуги железнодорожного транспорта | I30: 10000000 | K30: 1 | L30: 10000000 | N30: Внешняя операция | O30: Себестоимость | P30: Тариф КТЖ (ж/д перевозки) | Q30: ТОО «КТЖ-Грузовые перевозки»
A31: 02.07.2026 | B31: ЦентрКредит | C31: KZT | D31: 2401 | E31: Акционерное Общество "Банк ЦентрКредит" | F31: 980640000093 | G31: 213 | H31: Покупка иностранной валюты TOD (день в день), Товарищество с ограниченной ответственностью "WayStar Group", БИН 240340014287. Заявка №615800. Дата вал. 02.07.2026. Покупка USD, продажа KZT. Курс сделки 473.73. Учетный курс 479.26. Получение услуг | I31: 47373000 | K31: 1 | L31: 47373000 | N31: Конвертация валют | O31: Технические | P31: Покупка/продажа валюты
A32: 02.07.2026 | B32: ЦентрКредит | C32: KZT | D32: 2401 | E32: ТОО "WayStar Group" | F32: 240340014287 | G32: 312 | H32: Без НДС. Размещение краткосрочных вкладов (не более одного года) | I32: 1.5574155e+08 | K32: 1 | L32: 1.5574155e+08 | N32: Внутренний перевод | O32: Технические | P32: Перевод между своими счетами
A33: 02.07.2026 | B33: ЦентрКредит | C33: KZT | D33: 2401 | E33: Товарищество с ограниченной ответственностью "WayStar Group" | F33: 240340014287 | G33: 316 | H33: Выплата начисленного вознаграждения по депозитному договору № 01607034 от 24.07.2025 за период с 01.07.26 по 01.07.26. Вкладчик Товарищество с ограниченной ответственностью "WayStar Group". | J33: 37115.17 | K33: 1 | M33: 37115.17 | N33: Внутренний перевод | O33: Технические | P33: Перевод между своими счетами
A34: 02.07.2026 | B34: ЦентрКредит | C34: KZT | D34: 2401 | E34: ТОО "WayStar Group" | F34: 240340014287 | G34: 343 | H34: перевод на другой счет Переводы клиентом денег со своего текущего счета в одном банке, филиале банка-нерезидента Республики Казахстан на свой текущий счет в другом банке, филиале другого банка-нерезидента Республики Казахстан | J34: 24000000 | K34: 1 | M34: 24000000 | N34: Внутренний перевод | O34: Технические | P34: Перевод между своими счетами
A35: 02.07.2026 | B35: ЦентрКредит | C35: KZT | D35: 2401 | E35: ТОО "WayStar Group" | F35: 240340014287 | G35: 343 | H35: перевод на другой счет Переводы клиентом денег со своего текущего счета в одном банке, филиале банка-нерезидента Республики Казахстан на свой текущий счет в другом банке, филиале другого банка-нерезидента Республики Казахстан | J35: 82000000 | K35: 1 | M35: 82000000 | N35: Внутренний перевод | O35: Технические | P35: Перевод между своими счетами
A36: 02.07.2026 | B36: ЦентрКредит | C36: KZT | D36: 2401 | E36: Товарищество с ограниченной ответственностью "WayStar Group" | F36: 240340014287 | G36: 322 | H36: Частичная выплата вклада по депозитному договору № 01607034 от 02.07.2026 в размере 109915104.15 согласно ДП. Вкладчик: Товарищество с ограниченной ответственностью "WayStar Group". | J36: 1.099151e+08 | K36: 1 | M36: 1.099151e+08 | N36: Внутренний перевод | O36: Технические | P36: Перевод между своими счетами
A37: 03.07.2026 | B37: ЦентрКредит | C37: KZT | D37: 2401 | E37: УГД по Есильскому району ДГД по городу Астане КГД МФ РК | F37: 081240013779 | G37: 911 | H37: КПН за нерезидента (доплата). Начисленные (исчисленные) и иные обязательства в бюджет | I37: 15843.69 | K37: 1 | L37: 15843.69 | N37: Внешняя операция | O37: Налоги | P37: Налоги и отчисления | Q37: УГД по Есильскому району ДГД по городу Астан
A38: 03.07.2026 | B38: ЦентрКредит | C38: KZT | D38: 2401 | E38: Товарищество с ограниченной ответственностью "WayStar Group" | F38: 240340014287 | G38: 423 | H38: Погашение вознаграждения по договору № AQ5/2024/U/S/120240/0001L от 06.01.25. Заемщик: Товарищество с ограниченной ответственностью "WayStar Group" | I38: 52589.43 | K38: 1 | L38: 52589.43 | N38: Внутренний перевод | O38: Технические | P38: Перевод между своими счетами
A39: 03.07.2026 | B39: ЦентрКредит | C39: KZT | D39: 2401 | E39: Товарищество с ограниченной ответственностью "WayStar Group" | F39: 240340014287 | G39: 423 | H39: Погашение вознаграждения по договору № AQ5/2024/U/S/120240/0001L от 06.01.25. Заемщик: Товарищество с ограниченной ответственностью "WayStar Group" | I39: 113114.11 | K39: 1 | L39: 113114.11 | N39: Внутренний перевод | O39: Технические | P39: Перевод между своими счетами
A40: 03.07.2026 | B40: ЦентрКредит | C40: KZT | D40: 2401 | E40: Товарищество с ограниченной ответственностью "WayStar Group" | F40: 240340014287 | G40: 423 | H40: Погашение вознаграждения по договору № AQ5/2024/U/S/120240/0001L от 06.01.25. Заемщик: Товарищество с ограниченной ответственностью "WayStar Group" | I40: 117081.71 | K40: 1 | L40: 117081.71 | N40: Внутренний перевод | O40: Технические | P40: Перевод между своими счетами
A41: 03.07.2026 | B41: ЦентрКредит | C41: KZT | D41: 2401 | E41: УГД по Есильскому району ДГД по городу Астане КГД МФ РК | F41: 081240013779 | G41: 911 | H41: ндс за нерезидента июнь 2026. Начисленные (исчисленные) и иные обязательства в бюджет | I41: 2000000 | K41: 1 | L41: 2000000 | N41: Внешняя операция | O41: Налоги | P41: Налоги и отчисления | Q41: УГД по Есильскому району ДГД по городу Астан
A42: 03.07.2026 | B42: ЦентрКредит | C42: KZT | D42: 2401 | E42: Товарищество с ограниченной ответственностью "WayStar Group" | F42: 240340014287 | G42: 423 | H42: Погашение основного долга по договору № AQ5/2024/U/S/120240/0001L от 06.01.25. Заемщик: Товарищество с ограниченной ответственностью "WayStar Group" | I42: 10662874 | K42: 1 | L42: 10662874 | N42: Внутренний перевод | O42: Технические | P42: Перевод между своими счетами
A43: 03.07.2026 | B43: ЦентрКредит | C43: KZT | D43: 2401 | E43: Товарищество с ограниченной ответственностью "WayStar Group" | F43: 240340014287 | G43: 312 | H43: Размещение вклада | I43: 1.4283263e+08 | K43: 1 | L43: 1.4283263e+08 | N43: Внутренний перевод | O43: Технические | P43: Перевод между своими счетами
A44: 03.07.2026 | B44: ЦентрКредит | C44: KZT | D44: 2401 | E44: ТОО "WayStar Group" | F44: 240340014287 | G44: 312 | H44: Без НДС. Размещение краткосрочных вкладов (не более одного года) | I44: 200000000 | K44: 1 | L44: 200000000 | N44: Внутренний перевод | O44: Технические | P44: Перевод между своими счетами
A45: 03.07.2026 | B45: ЦентрКредит | C45: KZT | D45: 2401 | E45: Товарищество с ограниченной ответственностью "WayStar Group" | F45: 240340014287 | G45: 316 | H45: Выплата начисленного вознаграждения по депозитному договору № 01607034 от 24.07.2025 за период с 02.07.26 по 02.07.26. Вкладчик Товарищество с ограниченной ответственностью "WayStar Group". | J45: 52589.43 | K45: 1 | M45: 52589.43 | N45: Внутренний перевод | O45: Технические | P45: Перевод между своими счетами
A46: 03.07.2026 | B46: ЦентрКредит | C46: KZT | D46: 2401 | E46: Товарищество с ограниченной ответственностью "WayStar Group" | F46: 240340014287 | G46: 322 | H46: Частичная выплата вклада по депозитному договору № 01607034 от 03.07.2026 в размере 155741546.07 согласно ДП. Вкладчик: Товарищество с ограниченной ответственностью "WayStar Group". | J46: 1.5574155e+08 | K46: 1 | M46: 1.5574155e+08 | N46: Внутренний перевод | O46: Технические | P46: Перевод между своими счетами
A47: 03.07.2026 | B47: ЦентрКредит | C47: KZT | D47: 2401 | E47: ТОО "WayStar Group" | F47: 240340014287 | G47: 343 | H47: перевод на другой счет Переводы клиентом денег со своего текущего счета в одном банке, филиале банка-нерезидента Республики Казахстан на свой текущий счет в другом банке, филиале другого банка-нерезидента Республики Казахстан | J47: 200000000 | K47: 1 | M47: 200000000 | N47: Внутренний перевод | O47: Технические | P47: Перевод между своими счетами
A48: 04.07.2026 | B48: ЦентрКредит | C48: KZT | D48: 2401 | E48: ТОО КТЖ-Грузовые перевозки | F48: 031040001799 | G48: 813 | H48: Без НДС, 4185494, Платежи за услуги железнодорожного транспорта | I48: 5000000 | K48: 1 | L48: 5000000 | N48: Внешняя операция | O48: Себестоимость | P48: Тариф КТЖ (ж/д перевозки) | Q48: ТОО «КТЖ-Грузовые перевозки»
A49: 04.07.2026 | B49: ЦентрКредит | C49: KZT | D49: 2401 | E49: Товарищество с ограниченной ответственностью "WayStar Group" | F49: 240340014287 | G49: 316 | H49: Выплата начисленного вознаграждения по депозитному договору № 01607034 от 24.07.2025 за период с 03.07.26 по 03.07.26. Вкладчик Товарищество с ограниченной ответственностью "WayStar Group". | J49: 115764.72 | K49: 1 | M49: 115764.72 | N49: Внутренний перевод | O49: Технические | P49: Перевод между своими счетами
A50: 04.07.2026 | B50: ЦентрКредит | C50: KZT | D50: 2401 | E50: ТОО "WayStar Group" | F50: 240340014287 | G50: 322 | H50: Без НДС. Снятие с краткосрочного вклада (не более одного года) | J50: 5000000 | K50: 1 | M50: 5000000 | N50: Внутренний перевод | O50: Технические | P50: Перевод между своими счетами
A51: 05.07.2026 | B51: ЦентрКредит | C51: KZT | D51: 2401 | E51: Товарищество с ограниченной ответственностью "WayStar Group" | F51: 240340014287 | G51: 316 | H51: Выплата начисленного вознаграждения по депозитному договору № 01607034 от 24.07.2025 за период с 04.07.26 по 04.07.26. Вкладчик Товарищество с ограниченной ответственностью "WayStar Group". | J51: 114076.36 | K51: 1 | M51: 114076.36 | N51: Внутренний перевод | O51: Технические | P51: Перевод между своими счетами
A52: 06.07.2026 | B52: ЦентрКредит | C52: KZT | D52: 2401 | E52: Товарищество с ограниченной ответственностью "WayStar Group" | F52: 240340014287 | G52: 316 | H52: Выплата начисленного вознаграждения по депозитному договору № 01607034 от 24.07.2025 за период с 05.07.26 по 05.07.26. Вкладчик Товарищество с ограниченной ответственностью "WayStar Group". | J52: 114076.37 | K52: 1 | M52: 114076.37 | N52: Внутренний перевод | O52: Технические | P52: Перевод между своими счетами
A53: 07.07.2026 | B53: ЦентрКредит | C53: KZT | D53: 2401 | E53: Товарищество с ограниченной ответственностью "Мобайл Телеком - Сервис" | F53: 041140004799 | G53: 851 | H53: Договор №00016379 от 21.10.2025 услуги связи июнь 2026 | I53: 9320 | K53: 1 | L53: 9320 | N53: Внешняя операция | O53: Админ/офис | P53: Связь и ИТ | Q53: ТОО "Мобайл Телеком - Сервис"
A54: 07.07.2026 | B54: ЦентрКредит | C54: KZT | D54: 2401 | E54: Товарищество с ограниченной ответственностью "Современные Печатные технологии " | F54: 151140003068 | G54: 710 | H54: Счет на оплату № 1311-2495 от 3 июля 2026 г. Визитки 84 шт | I54: 11760 | K54: 1 | L54: 11760 | N54: Внешняя операция | O54: Админ/офис | P54: Маркетинг и представит. | Q54: ТОО "Современные Печатные технологии "
A55: 07.07.2026 | B55: ЦентрКредит | C55: KZT | D55: 2401 | E55: Акционерное Общество "Банк ЦентрКредит" | F55: 980741000260 | G55: 841 | H55: Интернет-банкинг. MIP. Международные платежи. Перевод в валютах стран СНГ, OUR с 9:00 до 13:00. Расчетный документ № 1 от 07.07.26 на сумму 8 920 464.00 RUB, в т.ч. НДС 16% | I55: 30000 | K55: 1 | L55: 30000 | N55: Внешняя операция | O55: Финансовые | P55: Банковские комиссии | Q55: Акционерное Общество "Банк ЦентрКредит"
A56: 07.07.2026 | B56: ЦентрКредит | C56: KZT | D56: 2401 | E56: Индивидуальный предприниматель "Катрышева" | F56: 900902450133 | G56: 859 | H56: Счет на оплату № 568 от 03.07.2026 г. Изготовление флага, флагштоков | I56: 35700 | K56: 1 | L56: 35700 | N56: Внешняя операция | O56: Админ/офис | P56: Проф. услуги (бухг./юр./конс.) | Q56: Индивидуальный предприниматель "Катрышева"
A57: 07.07.2026 | B57: ЦентрКредит | C57: KZT | D57: 2401 | E57: Товарищество с ограниченной ответственностью "ALDAR EUROASIA PROPERTY MANAGEMENT" | F57: 191040020896 | G57: 855 | H57: Договор субаренды №SLA-Y-1107-02052025 от 02.05.2025г Счет на оплату № 00000004125 от 2 июля 2026 г. Комуслуги июнь 2026Сумма 38 905-08 тенге в т.ч. НДС(16%) 5 366-22 тенге | I57: 38905.08 | K57: 1 | L57: 38905.08 | N57: Внешняя операция | O57: Админ/офис | P57: Офис, аренда помещений, хоз. | Q57: ТОО "ALDAR EUROASIA PROPERTY MANAGEMENT"
A58: 07.07.2026 | B58: ЦентрКредит | C58: KZT | D58: 2401 | E58: Акционерное Общество "Банк ЦентрКредит" | F58: 980640000093 | G58: 841 | H58: Интернет-банкинг. MIP. Международные платежи. Перевод OUR, кроме валют стран СНГ с 9:00 до 13:00. Расчетный документ № 2 от 07.07.26 на сумму 45 703.30 USD, в т.ч. НДС 16% | I58: 43148.26 | K58: 1 | L58: 43148.26 | N58: Внешняя операция | O58: Финансовые | P58: Банковские комиссии | Q58: Акционерное Общество "Банк ЦентрКредит"
A59: 07.07.2026 | B59: ЦентрКредит | C59: KZT | D59: 2401 | E59: Акционерное общество "Jusan Mobile" | F59: 960340000405 | G59: 851 | H59: Договор №22/ДКП B2B-25 от 21.05.2025г за июнь 2026 | I59: 81392.56 | K59: 1 | L59: 81392.56 | N59: Внешняя операция | O59: Админ/офис | P59: Проф. услуги (бухг./юр./конс.) | Q59: Акционерное общество "Jusan Mobile"
A60: 07.07.2026 | B60: ЦентрКредит | C60: KZT | D60: 2401 | E60: Унбетпаев Ернар Байтасович | F60: 840808300582 | G60: 871 | H60: Суточные расходы на проезд Астана- Саранск-Астана 07.07-09.07.2026 3 кд *24МРП (4325тг МРП) Вне РК 8МРП. Без НДС. Платежи по поездкам | I60: 103800 | K60: 1 | L60: 103800 | N60: Внешняя операция | O60: ФОТ | P60: Командировки и подотчёт | Q60: Унбетпаев Ернар Байтасович
A61: 07.07.2026 | B61: ЦентрКредит | C61: KZT | D61: 2401 | E61: Товарищество с ограниченной ответственностью "ALDAR EUROASIA PROPERTY MANAGEMENT" | F61: 191040020896 | G61: 855 | H61: Договор субаренды №SLA-Y-1107-02052025 от 02.05.2025г Счет на оплату № 00000003857 от 18 июня 2026 г. Аренда паркинга июль 2026 | I61: 121800 | K61: 1 | L61: 121800 | N61: Внешняя операция | O61: Админ/офис | P61: Офис, аренда помещений, хоз. | Q61: ТОО "ALDAR EUROASIA PROPERTY MANAGEMENT"
A62: 07.07.2026 | B62: ЦентрКредит | C62: KZT | D62: 2401 | E62: Банк ЦентрКредит для ЗП | F62: 980640000093 | G62: 332 | H62: Для зачисления на картсчета сотрудникам согласно спискам 159 091-00 тенге. | I62: 159091 | K62: 1 | L62: 159091 | N62: Внешняя операция | O62: ФОТ | P62: Зарплата | Q62: Банк ЦентрКредит для ЗП
A63: 07.07.2026 | B63: ЦентрКредит | C63: KZT | D63: 2401 | E63: Товарищество с ограниченной ответственностью "АВИАТУРАГЕНТСТВО ПАКС" | F63: 181040009040 | G63: 811 | H63: Счет на оплату № 158 от 15 июня 2026 г. Договор №KZ 01/01/2025 от 14.07.2025 NQZ-ALA-NQZ / 15.06 -17.06 TASHMETOV SAKEN 465-5899002569 BAZHIKAYEV ABYLAIKHAN 465-5899002570 | I63: 194096 | K63: 1 | L63: 194096 | N63: Внешняя операция | O63: ФОТ | P63: Командировки и подотчёт | Q63: ТОО "АВИАТУРАГЕНТСТВО ПАКС"
A64: 07.07.2026 | B64: ЦентрКредит | C64: KZT | D64: 2401 | E64: Частная компания WayStar Service Limited | F64: 260540900770 | G64: 411 | H64: выдача займа. Без НДС. Выдача краткосрочных займов (не более одного года) | I64: 200000 | K64: 1 | L64: 200000 | N64: Внутренний перевод | O64: Технические | P64: Перевод между своими счетами
A65: 07.07.2026 | B65: ЦентрКредит | C65: KZT | D65: 2401 | E65: Акционерное общество "Транстелеком" | F65: 991140001226 | G65: 859 | H65: Договор №ТТС/582-22/АСТ от 02.10.2024 г. платежи за услуги связи за май 2026Сумма 201 723-41 теңге без налога | I65: 201723.41 | K65: 1 | L65: 201723.41 | N65: Внешняя операция | O65: Админ/офис | P65: Связь и ИТ | Q65: Акционерное общество "Транстелеком"
A66: 07.07.2026 | B66: ЦентрКредит | C66: KZT | D66: 2401 | E66: Товарищество с ограниченной ответственностью "АФ АГМ-Табыс" | F66: 190940030685 | G66: 822 | H66: Оплата согл акта сверки от 07.07.2026 Текущий ремонт колесных пар с обточкой 0005.889560.18, 1226.19372.2021 | I66: 207649.28 | K66: 1 | L66: 207649.28 | N66: Внешняя операция | O66: Себестоимость | P66: Ремонт вагонов и узлов | Q66: ТОО "АФ АГМ-Табыс"
A67: 07.07.2026 | B67: ЦентрКредит | C67: KZT | D67: 2401 | E67: Товарищество с ограниченной ответственностью "Объединенное железнодорожное хозяйство" | F67: 950440001742 | G67: 819 | H67: Договор № 37-ОЖДХ Счет на оплату № 515 от 03.07.2026 г, ТОР №51261774 | I67: 213075.76 | K67: 1 | L67: 213075.76 | N67: Внешняя операция | O67: Себестоимость | P67: Ремонт вагонов и узлов | Q67: ТОО "Объединенное железнодорожное хозяйство"
A68: 07.07.2026 | B68: ЦентрКредит | C68: KZT | D68: 2401 | E68: Товарищество с ограниченной ответственностью "Нұр-Альфинур" | F68: 111240015961 | G68: 822 | H68: Счет на оплату № 10000000114 от 30.06.2026 г. Средний ремонт колесной парыСумма 290 874-00 тенге в т.ч. НДС(16%) 40 120-55 тенге | I68: 290874 | K68: 1 | L68: 290874 | N68: Внешняя операция | O68: Себестоимость | P68: Ремонт вагонов и узлов | Q68: ТОО "Нұр-Альфинур"
A69: 07.07.2026 | B69: ЦентрКредит | C69: KZT | D69: 2401 | E69: Товарищество с ограниченной ответственностью "LogiSoft" (ЛогиСофт) | F69: 121240002971 | G69: 851 | H69: Договор №633 от 14.02.2025г Счет на оплату № 633/7 от «07» июля 2026 г. Информационные услуги | I69: 300008.48 | K69: 1 | L69: 300008.48 | N69: Внешняя операция | O69: Админ/офис | P69: Связь и ИТ | Q69: ТОО "LogiSoft" (ЛогиСофт)
A70: 07.07.2026 | B70: ЦентрКредит | C70: KZT | D70: 2401 | E70: Товарищество с ограниченной ответственностью "ALDAR EUROASIA PROPERTY MANAGEMENT" | F70: 191040020896 | G70: 855 | H70: Договор субаренды №SLA-Y-1107-02052025 от 02.05.2025г Счет на оплату № 00000003856 от 18 июня 2026 г. Аренда офиса июль 2026Сумма 4 617 380-00 тенге в т.ч. НДС(16%) 636 880-00 тенге | I70: 4617380 | K70: 1 | L70: 4617380 | N70: Внешняя операция | O70: Админ/офис | P70: Офис, аренда помещений, хоз. | Q70: ТОО "ALDAR EUROASIA PROPERTY MANAGEMENT"
A71: 07.07.2026 | B71: ЦентрКредит | C71: KZT | D71: 2401 | E71: Банк ЦентрКредит для ЗП | F71: 980640000093 | G71: 332 | H71: Для зачисления на картсчета сотрудникам согласно спискам 5 000 000-00 тенге. | I71: 5000000 | K71: 1 | L71: 5000000 | N71: Внешняя операция | O71: ФОТ | P71: Зарплата | Q71: Банк ЦентрКредит для ЗП
A72: 07.07.2026 | B72: ЦентрКредит | C72: KZT | D72: 2401 | E72: ТОО КТЖ-Грузовые перевозки | F72: 031040001799 | G72: 813 | H72: Без НДС, 4185494, Платежи за услуги железнодорожного транспорта | I72: 6000000 | K72: 1 | L72: 6000000 | N72: Внешняя операция | O72: Себестоимость | P72: Тариф КТЖ (ж/д перевозки) | Q72: ТОО «КТЖ-Грузовые перевозки»
A73: 07.07.2026 | B73: ЦентрКредит | C73: KZT | D73: 2401 | E73: КТТ (ҚАЗТЕМІРТРАНС) АО | F73: 031040000572 | G73: 813 | H73: Счета на оплату № К-211120/26 , К-211122/26 , К-211124/26 , К-211126/26 от 07.07.2026 г. по Договору № 20-02-2026/14989-НПрк от 20 февраля 2026 от 20.02.2026 Сумма 10 450 442-40 тенге в т.ч. НДС(16%) 1 441 440-34 тенге | I73: 10450442 | K73: 1 | L73: 10450442 | N73: Внешняя операция | O73: Себестоимость | P73: Операторы вагонов (КТТ и др.) | Q73: АО «КазТемирТранс» (КТТ)
A74: 07.07.2026 | B74: ЦентрКредит | C74: KZT | D74: 2401 | E74: КТТ (ҚАЗТЕМІРТРАНС) АО | F74: 031040000572 | G74: 813 | H74: К-211272/26 от 07.07.2026 по Договору № 20-02-2026/14989-НПрк от 20 февраля 2026 от 20.02.2026. Без НДС. Платежи за услуги железнодорожного транспорта | I74: 12696894 | K74: 1 | L74: 12696894 | N74: Внешняя операция | O74: Себестоимость | P74: Операторы вагонов (КТТ и др.) | Q74: АО «КазТемирТранс» (КТТ)
A75: 07.07.2026 | B75: ЦентрКредит | C75: KZT | D75: 2401 | E75: Товарищество с ограниченной ответственностью "PetroComLogistics" | F75: 170540018330 | G75: 855 | H75: Договор аренды подвижного состава №04/27112025 Счет на оплату №44 от 01.07.2026 г. Аренда жд вагонов | I75: 14384000 | K75: 1 | L75: 14384000 | N75: Внешняя операция | O75: Себестоимость | P75: Аренда/предоставление вагонов | Q75: ТОО "PetroComLogistics"
A76: 07.07.2026 | B76: ЦентрКредит | C76: KZT | D76: 2401 | E76: Акционерное Общество "Банк ЦентрКредит" | F76: 980640000093 | G76: 213 | H76: Покупка иностранной валюты TOD (день в день), ТОО "WayStar Group", БИН 240340014287. Заявка №619602. Дата вал. 07.07.2026. Покупка USD, продажа KZT. Курс сделки 472.66. Учетный курс 472.03. Получение услуг | I76: 21602122 | K76: 1 | L76: 21602122 | N76: Конвертация валют | O76: Технические | P76: Покупка/продажа валюты
A77: 07.07.2026 | B77: ЦентрКредит | C77: KZT | D77: 2401 | E77: Акционерное Общество "Банк ЦентрКредит" | F77: 980640000093 | G77: 213 | H77: Покупка иностранной валюты TOD (день в день), ТОО "WayStar Group", БИН 240340014287. Заявка №619618. Дата вал. 07.07.2026. Покупка RUB, продажа KZT. Курс сделки 6.2573. Учетный курс 6.11. Получение услуг | I77: 55818019 | K77: 1 | L77: 55818019 | N77: Конвертация валют | O77: Технические | P77: Покупка/продажа валюты
A78: 07.07.2026 | B78: ЦентрКредит | C78: KZT | D78: 2401 | E78: Товарищество с ограниченной ответственностью "WayStar Group" | F78: 240340014287 | G78: 312 | H78: Размещение вклада | I78: 3.6960824e+08 | K78: 1 | L78: 3.6960824e+08 | N78: Внутренний перевод | O78: Технические | P78: Перевод между своими счетами
A79: 07.07.2026 | B79: ЦентрКредит | C79: KZT | D79: 2401 | E79: Акционерное общество "Фонд развития предпринимательства "Даму" | F79: 970840000277 | G79: 490 | H79: Возврат клиенту ранее погашенной задолженности по субсидированному начисленному вознаграждению Заемщик Товарищество с ограниченной ответственностью "WayStar Group" БИН/ИИН 240340014287 ДБЗ №AQ5/2024/U/S/120240/0001L от 06.01.25 | J79: 113114.11 | K79: 1 | M79: 113114.11 | N79: Внешняя операция | O79: Прочее | P79: Возврат средств | Q79: Акционерное общество "Фонд развития предприн
A80: 07.07.2026 | B80: ЦентрКредит | C80: KZT | D80: 2401 | E80: Товарищество с ограниченной ответственностью "WayStar Group" | F80: 240340014287 | G80: 316 | H80: Выплата начисленного вознаграждения по депозитному договору № 01607034 от 24.07.2025 за период с 06.07.26 по 06.07.26. Вкладчик Товарищество с ограниченной ответственностью "WayStar Group". | J80: 114076.36 | K80: 1 | M80: 114076.36 | N80: Внутренний перевод | O80: Технические | P80: Перевод между своими счетами
A81: 07.07.2026 | B81: ЦентрКредит | C81: KZT | D81: 2401 | E81: ТОО "WayStar Group" | F81: 240340014287 | G81: 322 | H81: Без НДС. Снятие с краткосрочного вклада (не более одного года) | J81: 310000 | K81: 1 | M81: 310000 | N81: Внутренний перевод | O81: Технические | P81: Перевод между своими счетами
A82: 07.07.2026 | B82: ЦентрКредит | C82: KZT | D82: 2401 | E82: ТОО WayStar Group | F82: 240340014287 | G82: 343 | H82: перевод на другой счет Переводы клиентом денег со своего текущего счета в одном банке филиале банка-нерезидента Республики Казахстан на свой текущий счет в другом банке, филиале другого банка-нерезидента Республики Казахстан | J82: 3736375 | K82: 1 | M82: 3736375 | N82: Внутренний перевод | O82: Технические | P82: Перевод между своими счетами
A83: 07.07.2026 | B83: ЦентрКредит | C83: KZT | D83: 2401 | E83: ТОО "WayStar Group" | F83: 240340014287 | G83: 343 | H83: перевод на другой счет Переводы клиентом денег со своего текущего счета в одном банке, филиале банка-нерезидента Республики Казахстан на свой текущий счет в другом банке, филиале другого банка-нерезидента Республики Казахстан | J83: 160100000 | K83: 1 | M83: 160100000 | N83: Внутренний перевод | O83: Технические | P83: Перевод между своими счетами
A84: 07.07.2026 | B84: ЦентрКредит | C84: KZT | D84: 2401 | E84: Товарищество с ограниченной ответственностью "WayStar Group" | F84: 240340014287 | G84: 322 | H84: Частичная выплата вклада по депозитному договору № 01607034 от 07.07.2026 в размере 337832632.84 согласно ДП. Вкладчик: Товарищество с ограниченной ответственностью "WayStar Group". | J84: 3.3783263e+08 | K84: 1 | M84: 3.3783263e+08 | N84: Внутренний перевод | O84: Технические | P84: Перевод между своими счетами
A85: 08.07.2026 | B85: ЦентрКредит | C85: KZT | D85: 2401 | E85: Товарищество с ограниченной ответственностью "Office-Expert.kz" | F85: 110840005091 | G85: 710 | H85: Счет на оплату № 897396 от 03 июля 2026 г. КанцтоварыСумма 21 655-00 тенге в т.ч. НДС(16%) 2 986-90 тенге | I85: 21655 | K85: 1 | L85: 21655 | N85: Внешняя операция | O85: Админ/офис | P85: Хоз. расходы и материалы | Q85: ТОО "Office-Expert.kz"
A86: 08.07.2026 | B86: ЦентрКредит | C86: KZT | D86: 2401 | E86: ТОО КТЖ-Грузовые перевозки | F86: 031040001799 | G86: 813 | H86: Без НДС, 4185494, Платежи за услуги железнодорожного транспорта | I86: 15000000 | K86: 1 | L86: 15000000 | N86: Внешняя операция | O86: Себестоимость | P86: Тариф КТЖ (ж/д перевозки) | Q86: ТОО «КТЖ-Грузовые перевозки»
A87: 08.07.2026 | B87: ЦентрКредит | C87: KZT | D87: 2401 | E87: Товарищество с ограниченной ответственностью "WayStar Group" | F87: 240340014287 | G87: 312 | H87: Размещение вклада | I87: 3.6908084e+08 | K87: 1 | L87: 3.6908084e+08 | N87: Внутренний перевод | O87: Технические | P87: Перевод между своими счетами
A88: 08.07.2026 | B88: ЦентрКредит | C88: KZT | D88: 2401 | E88: Товарищество с ограниченной ответственностью "WayStar Group" | F88: 240340014287 | G88: 316 | H88: Выплата начисленного вознаграждения по депозитному договору № 01607034 от 24.07.2025 за период с 07.07.26 по 07.07.26. Вкладчик Товарищество с ограниченной ответственностью "WayStar Group". | J88: 124701.39 | K88: 1 | M88: 124701.39 | N88: Внутренний перевод | O88: Технические | P88: Перевод между своими счетами
A89: 08.07.2026 | B89: ЦентрКредит | C89: KZT | D89: 2401 | E89: ТОО EASY BOX | F89: 220640049871 | G89: 813 | H89: Оплата согласно эсф № 00000000131 от 19.05.2026г., за услуги оперирования Платежи за услуги железнодорожного транспорта, | J89: 921375 | K89: 1 | M89: 921375 | N89: Внешняя операция | O89: Выручка | P89: Операционная выручка (ТЭО, вагоны) | Q89: ТОО EASY BOX
A90: 08.07.2026 | B90: ЦентрКредит | C90: KZT | D90: 2401 | E90: ТОО WayStar Group | F90: 240340014287 | G90: 343 | H90: перевод на другой счет Переводы клиентом денег со своего текущего счета в одном банке филиале банка-нерезидента Республики Казахстан на свой текущий счет в другом банке, филиале другого банка-нерезидента Республики Казахстан | J90: 6177500 | K90: 1 | M90: 6177500 | N90: Внутренний перевод | O90: Технические | P90: Перевод между своими счетами
A91: 08.07.2026 | B91: ЦентрКредит | C91: KZT | D91: 2401 | E91: ТОО "WayStar Group" | F91: 240340014287 | G91: 343 | H91: перевод на другой счет Переводы клиентом денег со своего текущего счета в одном банке, филиале банка-нерезидента Республики Казахстан на свой текущий счет в другом банке, филиале другого банка-нерезидента Республики Казахстан | J91: 7450000 | K91: 1 | M91: 7450000 | N91: Внутренний перевод | O91: Технические | P91: Перевод между своими счетами
A92: 08.07.2026 | B92: ЦентрКредит | C92: KZT | D92: 2401 | E92: Товарищество с ограниченной ответственностью "WayStar Group" | F92: 240340014287 | G92: 322 | H92: Частичная выплата вклада по депозитному договору № 01607034 от 08.07.2026 в размере 369298236.22 согласно ДП. Вкладчик: Товарищество с ограниченной ответственностью "WayStar Group". | J92: 3.6929824e+08 | K92: 1 | M92: 3.6929824e+08 | N92: Внутренний перевод | O92: Технические | P92: Перевод между своими счетами
A93: 09.07.2026 | B93: ЦентрКредит | C93: KZT | D93: 2401 | E93: Акционерное Общество "Банк ЦентрКредит" | F93: 980741000260 | G93: 841 | H93: Интернет-банкинг. MIP. Международные платежи. Перевод OUR, кроме валют стран СНГ с 9:00 до 13:00. Расчетный документ № 1 от 09.07.26 на сумму 180 000.00 USD, в т.ч. НДС 16% | I93: 100000 | K93: 1 | L93: 100000 | N93: Внешняя операция | O93: Финансовые | P93: Банковские комиссии | Q93: Акционерное Общество "Банк ЦентрКредит"
A94: 09.07.2026 | B94: ЦентрКредит | C94: KZT | D94: 2401 | E94: Алим | F94: 020420550046 | G94: 871 | H94: Данияр Алим подотчет. Без НДС. Платежи по поездкам | I94: 111979 | K94: 1 | L94: 111979 | N94: Внешняя операция | O94: ФОТ | P94: Командировки и подотчёт | Q94: Алим
A95: 09.07.2026 | B95: ЦентрКредит | C95: KZT | D95: 2401 | E95: Индивидуальный предприниматель "JOINMEDIA" | F95: 970710351144 | G95: 859 | H95: Счет на оплату №6 от 09.07.2026 г. Договор № 14/12-25 от 29.12.2025 г.Сумма 1 150 000-00 теңге без НДС | I95: 1150000 | K95: 1 | L95: 1150000 | N95: Внешняя операция | O95: Админ/офис | P95: Проф. услуги (бухг./юр./конс.) | Q95: Индивидуальный предприниматель "JOINMEDIA"
A96: 09.07.2026 | B96: ЦентрКредит | C96: KZT | D96: 2401 | E96: ТОО КТЖ-Грузовые перевозки | F96: 031040001799 | G96: 813 | H96: Без НДС, 4792940, Платежи за услуги железнодорожного транспорта, 150240031511 | I96: 1900000 | K96: 1 | L96: 1900000 | N96: Внешняя операция | O96: Себестоимость | P96: Тариф КТЖ (ж/д перевозки) | Q96: ТОО «КТЖ-Грузовые перевозки»
A97: 09.07.2026 | B97: ЦентрКредит | C97: KZT | D97: 2401 | E97: Банк ЦентрКредит для ЗП | F97: 980640000093 | G97: 332 | H97: Для зачисления на картсчета сотрудникам согласно спискам 2 000 000-00 теңге. | I97: 2000000 | K97: 1 | L97: 2000000 | N97: Внешняя операция | O97: ФОТ | P97: Зарплата | Q97: Банк ЦентрКредит для ЗП
A98: 09.07.2026 | B98: ЦентрКредит | C98: KZT | D98: 2401 | E98: Товарищество с ограниченной ответственностью "Рейл Транспортейшн" | F98: 221040045601 | G98: 813 | H98: Договор RT/151 от 12.11.2024 г INVOICE N 1353 от 03.07.2026 INVOICE N 1282 от 24/06/2026Сумма 4 366 833-75 теңге без налога | I98: 4366833.8 | K98: 1 | L98: 4366833.8 | N98: Внешняя операция | O98: Прочее | P98: Прочие расходы | Q98: ТОО "Рейл Транспортейшн"
A99: 09.07.2026 | B99: ЦентрКредит | C99: KZT | D99: 2401 | E99: Товарищество с ограниченной ответственностью «InterLog Co» | F99: 061040010307 | G99: 813 | H99: Договор №017 от 30.12.2025 г. Счет на оплату №30 от 02.07.2026 г. ТЭУ за зерновозы | I99: 26350000 | K99: 1 | L99: 26350000 | N99: Внешняя операция | O99: Себестоимость | P99: Аренда/предоставление вагонов | Q99: ТОО «InterLog Co»
A100: 09.07.2026 | B100: ЦентрКредит | C100: KZT | D100: 2401 | E100: Товарищество с ограниченной ответственностью "PRATA" | F100: 120540009510 | G100: 813 | H100: Договор №PR-007/2025 от 03.11.2025 г.Счет на оплату № 17 от 02.07.2026 г. ТЭУ | I100: 27590000 | K100: 1 | L100: 27590000 | N100: Внешняя операция | O100: Себестоимость | P100: Прочие ж/д и ТЭУ услуги | Q100: ТОО "PRATA"
A101: 09.07.2026 | B101: ЦентрКредит | C101: KZT | D101: 2401 | E101: Товарищество с ограниченной ответственностью "АРНА" | F101: 970640001862 | G101: 819 | H101: счет на оплату № 69 от 29.06.2026 г Договор №5 от 05.02.2025г Предоставление вагонов в июле 2026 г.Сумма 33 227 040-00 теңге в т.ч. НДС(16%) 4 583 040-00 теңге | I101: 33227040 | K101: 1 | L101: 33227040 | N101: Внешняя операция | O101: Себестоимость | P101: Аренда/предоставление вагонов | Q101: ТОО "АРНА"
...
