Workbook

Sheet Справочник
A1: Справочник технических порогов и амортизации
A2: Параметр | B2: Значение | C2: Ед. | D2: Как используется
A3: Мин. обод после обточки при ДР | B3: 35 | C3: мм | D3: После обточки колесо должно иметь не менее 35 мм
A4: Съем металла при обточке | B4: 15 | C4: мм | D4: По условию расчета при обточке снимается 15 мм
A5: Порог до ДР | B5: =B3+B4 | C5: мм | D5: 35 мм + 15 мм = 50 мм: ниже порога колесная пара не проходит условие после обточки
A6: Текущий эксплуатационный предел | B6: 27 | C6: мм | D6: Предельное текущее значение; не заменяет требование 35 мм после обточки
A7: Макс. поправка на близость ДР | B7: 10 | C7: п.п. | D7: Модельное допущение: дополнительная амортизация при наступившем ДР; изменить при наличии фактической стоимости ДР
A8: Цена новой цистерны | B8: 4650000 | C8: ₽ / вагон | D8: Рыночная база пользователя; 100% стоимости нового вагона

Sheet Параметры
A1: Параметры методики v2 (компонентный затратный подход)
A2: Дата оценки | B2: 46239 | D2: Фиксированная дата расчёта
A3: Цена новой цистерны | B3: =Справочник!B8 | C3: ₽/вагон | D3: Ссылка на Справочник (100% нового вагона)
A4: — Доли компонентов в стоимости нового вагона (Σ = 100%) —
A5: Доля: котёл + рама | B5: 0.55 | D5: ДОПУЩЕНИЕ — уточнить по калькуляции завода
A6: Доля: тележки (литьё: боковые рамы + надрессорные балки) | B6: 0.18 | D6: ДОПУЩЕНИЕ — уточнить
A7: Доля: колёсные пары (4 шт) | B7: 0.2 | D7: ДОПУЩЕНИЕ — уточнить
A8: Доля: прочее (автосцепка, тормоз, арматура) | B8: 0.07 | D8: ДОПУЩЕНИЕ — уточнить
A9: Контроль суммы долей (должно быть 1,00) | B9: =SUM(B5:B8) | D9: Если ≠ 1,00 — исправьте доли
A10: — Ресурсы и пределы —
A11: Нормативный срок службы (fallback), лет | B11: 32 | C11: лет | D11: Используется, если нет даты СС в данных
A12: Срок службы литья тележек, лет | B12: 30 | C12: лет | D12: ДОПУЩЕНИЕ — нормативный срок рам/балок
A13: Толщина обода новой КП | B13: 70 | C13: мм | D13: ДОПУЩЕНИЕ — полный диапазон износа обода
A14: Предельная толщина обода | B14: =Справочник!B6 | C14: мм | D14: Ссылка на Справочник (эксплуатационный предел)
A15: Съём металла при обточке | B15: =Справочник!B4 | C15: мм | D15: Ссылка на Справочник
A16: Мин. обод после обточки (порог годности) | B16: =Справочник!B3 | C16: мм | D16: Ссылка на Справочник
A17: — Стоимости ремонтов, ₽ —
A18: Стоимость предстоящего планового ремонта (ДР) | B18: 300000 | C18: ₽ | D18: ДОПУЩЕНИЕ — заменить фактической сметой ДР
A19: Стоимость замены одной колёсной пары | B19: 220000 | C19: ₽/шт | D19: ДОПУЩЕНИЕ — цена новой/годной КП

Sheet Прайс
A1: Цены собственника (без НДС), по модели и году постройки
A2: Модель вагона | B2: Год постройки | C2: Кол-во | D2: Цена за ед. без НДС, ₽ | E2: Итого без НДС, ₽
A3: 15-1219-1П | B3: 2020 | C3: 60 | D3: 4125000 | E3: =C3*D3
A4: 15-150-04П | B4: 2011 | C4: 21 | D4: 2461000 | E4: =C4*D4
A5: 15-150-04П | B5: 2012 | C5: 7 | D5: 2621500 | E5: =C5*D5
A6: 15-150-04П | B6: 2015 | C6: 14 | D6: 3103000 | E6: =C6*D6
A7: 15-1755П | B7: 2013 | C7: 24 | D7: 2782000 | E7: =C7*D7
A8: 15-1755П | B8: 2014 | C8: 5 | D8: 2942500 | E8: =C8*D8
A9: 15-5103-7П | B9: 2011 | C9: 23 | D9: 2461000 | E9: =C9*D9
A10: 15-5103-7П | B10: 2012 | C10: 3 | D10: 2621500 | E10: =C10*D10
A11: 15-5103-7П | B11: 2015 | C11: 9 | D11: 3103000 | E11: =C11*D11
A12: ИТОГО | C12: =SUM(C3:C11) | E12: =SUM(E3:E11)

Sheet Оценка
A1: Оценка остаточной стоимости 166 цистерн — методика v2 (компонентный затратный подход). Синие/жёлтые ячейки-допущения — на листе «Параметры».
A2: № вагона | B2: Модель | C2: Год постройки | D2: Год оконч. срока службы | E2: Полный срок службы, лет | F2: Возраст вагона, лет | G2: Износ котла+рамы, % | H2: Остаточная котла+рамы, % | I2: Средний год литья тележек | J2: Возраст литья, лет | K2: Износ литья, % | L2: Остаточная литья, % | M2: Мин. обод по КП, мм | N2: Остаточная колёсных пар, % | O2: Остаточная прочего, % | P2: Компонентная стоимость, ₽ | Q2: Последний ремонт | R2: Следующий плановый ремонт | S2: Использовано цикла ДР, % | T2: Остаточный пробег, км | U2: Норма пробега, км | V2: Использовано цикла пробега, % | W2: Позиция обслуживания, % | X2: Обязательство ремонта (ДР), ₽ | Y2: КП не проходят обточку, шт | Z2: Обязательство замены КП, ₽ | AA2: ИТОГОВАЯ стоимость v2, ₽ | AB2: Цена продавца, ₽ (ввод) | AC2: Отклонение рынок−модель, ₽ | AD2: Оценка v1 (справочно), ₽
A3: =Комплектация!A5 | B3: =Комплектация!C5 | C3: =Комплектация!E5 | D3: 2043 | E3: =IF(D3="",Параметры!$B$11,MAX(1,D3-C3)) | F3: =MAX(0,YEAR(Параметры!$B$2)-C3) | G3: =MIN(100,F3/E3*100) | H3: =100-G3 | I3: =AVERAGE(Комплектация!BJ5,Комплектация!BP5,Комплектация!BV5,Комплектация!CB5,Комплектация!CH5,Комплектация!CN5) | J3: =MAX(0,YEAR(Параметры!$B$2)-I3) | K3: =MIN(100,J3/Параметры!$B$12*100) | L3: =100-K3 | M3: =MIN(Комплектация!AA5,Комплектация!AB5,Комплектация!AK5,Комплектация!AL5,Комплектация!AU5,Комплектация!AV5,Комплектация!BE5,Комплектация!BF5) | N3: =AVERAGE((100-MAX(0,MIN(100,(Параметры!$B$13-MIN(Комплектация!AA5,Комплектация!AB5))/(Параметры!$B$13-Параметры!$B$14)*100))),(100-MAX(0,MIN(100,(Параметры!$B$13-MIN(Комплектация!AK5,Комплектация!AL5))/(Параметры!$B$13-Параметры!$B$14)*100))),(100-MAX(0,MIN(100,(Параметры!$B$13-MIN(Комплектация!AU5,Комплектация!AV5))/(Параметры!$B$13-Параметры!$B$14)*100))),(100-MAX(0,MIN(100,(Параметры!$B$13-MIN(Комплектация!BE5,Комплектация!BF5))/(Параметры!$B$13-Параметры!$B$14)*100)))) | O3: =AVERAGE(H3,L3) | P3: =Параметры!$B$3*(Параметры!$B$5*H3+Параметры!$B$6*L3+Параметры!$B$7*N3+Параметры!$B$8*O3)/100 | Q3: 46099 | R3: 47195 | S3: =IF(OR(Q3="",R3="",R3=Q3),"",MAX(0,MIN(100,(Параметры!$B$2-Q3)/(R3-Q3)*100))) | T3: =IF(ISNUMBER(Комплектация!P5),Комплектация!P5,"") | U3: =IF(ISNUMBER(Комплектация!N5),Комплектация!N5,"") | V3: =IF(OR(U3="",T3="",U3=0),"",MAX(0,MIN(100,(U3-T3)/U3*100))) | W3: =MAX(IF(S3="",0,S3),IF(V3="",0,V3)) | X3: =Параметры!$B$18*W3/100 | Y3: =IF(MIN(Комплектация!AA5,Комплектация!AB5)-Параметры!$B$15<Параметры!$B$16,1,0)+IF(MIN(Комплектация!AK5,Комплектация!AL5)-Параметры!$B$15<Параметры!$B$16,1,0)+IF(MIN(Комплектация!AU5,Комплектация!AV5)-Параметры!$B$15<Параметры!$B$16,1,0)+IF(MIN(Комплектация!BE5,Комплектация!BF5)-Параметры!$B$15<Параметры!$B$16,1,0) | Z3: =Y3*Параметры!$B$19 | AA3: =MAX(0,P3-X3-Z3) | AB3: =SUMIFS(Прайс!$D$3:$D$11,Прайс!$A$3:$A$11,B3,Прайс!$B$3:$B$11,C3) | AC3: =IF(AB3="","",AB3-AA3) | AD3: 3198508.4
A4: =Комплектация!A6 | B4: =Комплектация!C6 | C4: =Комплектация!E6 | D4: 2043 | E4: =IF(D4="",Параметры!$B$11,MAX(1,D4-C4)) | F4: =MAX(0,YEAR(Параметры!$B$2)-C4) | G4: =MIN(100,F4/E4*100) | H4: =100-G4 | I4: =AVERAGE(Комплектация!BJ6,Комплектация!BP6,Комплектация!BV6,Комплектация!CB6,Комплектация!CH6,Комплектация!CN6) | J4: =MAX(0,YEAR(Параметры!$B$2)-I4) | K4: =MIN(100,J4/Параметры!$B$12*100) | L4: =100-K4 | M4: =MIN(Комплектация!AA6,Комплектация!AB6,Комплектация!AK6,Комплектация!AL6,Комплектация!AU6,Комплектация!AV6,Комплектация!BE6,Комплектация!BF6) | N4: =AVERAGE((100-MAX(0,MIN(100,(Параметры!$B$13-MIN(Комплектация!AA6,Комплектация!AB6))/(Параметры!$B$13-Параметры!$B$14)*100))),(100-MAX(0,MIN(100,(Параметры!$B$13-MIN(Комплектация!AK6,Комплектация!AL6))/(Параметры!$B$13-Параметры!$B$14)*100))),(100-MAX(0,MIN(100,(Параметры!$B$13-MIN(Комплектация!AU6,Комплектация!AV6))/(Параметры!$B$13-Параметры!$B$14)*100))),(100-MAX(0,MIN(100,(Параметры!$B$13-MIN(Комплектация!BE6,Комплектация!BF6))/(Параметры!$B$13-Параметры!$B$14)*100)))) | O4: =AVERAGE(H4,L4) | P4: =Параметры!$B$3*(Параметры!$B$5*H4+Параметры!$B$6*L4+Параметры!$B$7*N4+Параметры!$B$8*O4)/100 | Q4: 46065 | R4: 46795 | S4: =IF(OR(Q4="",R4="",R4=Q4),"",MAX(0,MIN(100,(Параметры!$B$2-Q4)/(R4-Q4)*100))) | T4: =IF(ISNUMBER(Комплектация!P6),Комплектация!P6,"") | U4: =IF(ISNUMBER(Комплектация!N6),Комплектация!N6,"") | V4: =IF(OR(U4="",T4="",U4=0),"",MAX(0,MIN(100,(U4-T4)/U4*100))) | W4: =MAX(IF(S4="",0,S4),IF(V4="",0,V4)) | X4: =Параметры!$B$18*W4/100 | Y4: =IF(MIN(Комплектация!AA6,Комплектация!AB6)-Параметры!$B$15<Параметры!$B$16,1,0)+IF(MIN(Комплектация!AK6,Комплектация!AL6)-Параметры!$B$15<Параметры!$B$16,1,0)+IF(MIN(Комплектация!AU6,Комплектация!AV6)-Параметры!$B$15<Параметры!$B$16,1,0)+IF(MIN(Комплектация!BE6,Комплектация!BF6)-Параметры!$B$15<Параметры!$B$16,1,0) | Z4: =Y4*Параметры!$B$19 | AA4: =MAX(0,P4-X4-Z4) | AB4: =SUMIFS(Прайс!$D$3:$D$11,Прайс!$A$3:$A$11,B4,Прайс!$B$3:$B$11,C4) | AC4: =IF(AB4="","",AB4-AA4) | AD4: 3170320.6
A5: =Комплектация!A7 | B5: =Комплектация!C7 | C5: =Комплектация!E7 | D5: 2043 | E5: =IF(D5="",Параметры!$B$11,MAX(1,D5-C5)) | F5: =MAX(0,YEAR(Параметры!$B$2)-C5) | G5: =MIN(100,F5/E5*100) | H5: =100-G5 | I5: =AVERAGE(Комплектация!BJ7,Комплектация!BP7,Комплектация!BV7,Комплектация!CB7,Комплектация!CH7,Комплектация!CN7) | J5: =MAX(0,YEAR(Параметры!$B$2)-I5) | K5: =MIN(100,J5/Параметры!$B$12*100) | L5: =100-K5 | M5: =MIN(Комплектация!AA7,Комплектация!AB7,Комплектация!AK7,Комплектация!AL7,Комплектация!AU7,Комплектация!AV7,Комплектация!BE7,Комплектация!BF7) | N5: =AVERAGE((100-MAX(0,MIN(100,(Параметры!$B$13-MIN(Комплектация!AA7,Комплектация!AB7))/(Параметры!$B$13-Параметры!$B$14)*100))),(100-MAX(0,MIN(100,(Параметры!$B$13-MIN(Комплектация!AK7,Комплектация!AL7))/(Параметры!$B$13-Параметры!$B$14)*100))),(100-MAX(0,MIN(100,(Параметры!$B$13-MIN(Комплектация!AU7,Комплектация!AV7))/(Параметры!$B$13-Параметры!$B$14)*100))),(100-MAX(0,MIN(100,(Параметры!$B$13-MIN(Комплектация!BE7,Комплектация!BF7))/(Параметры!$B$13-Параметры!$B$14)*100)))) | O5: =AVERAGE(H5,L5) | P5: =Параметры!$B$3*(Параметры!$B$5*H5+Параметры!$B$6*L5+Параметры!$B$7*N5+Параметры!$B$8*O5)/100 | Q5: 46065 | R5: 46795 | S5: =IF(OR(Q5="",R5="",R5=Q5),"",MAX(0,MIN(100,(Параметры!$B$2-Q5)/(R5-Q5)*100))) | T5: =IF(ISNUMBER(Комплектация!P7),Комплектация!P7,"") | U5: =IF(ISNUMBER(Комплектация!N7),Комплектация!N7,"") | V5: =IF(OR(U5="",T5="",U5=0),"",MAX(0,MIN(100,(U5-T5)/U5*100))) | W5: =MAX(IF(S5="",0,S5),IF(V5="",0,V5)) | X5: =Параметры!$B$18*W5/100 | Y5: =IF(MIN(Комплектация!AA7,Комплектация!AB7)-Параметры!$B$15<Параметры!$B$16,1,0)+IF(MIN(Комплектация!AK7,Комплектация!AL7)-Параметры!$B$15<Параметры!$B$16,1,0)+IF(MIN(Комплектация!AU7,Комплектация!AV7)-Параметры!$B$15<Параметры!$B$16,1,0)+IF(MIN(Комплектация!BE7,Комплектация!BF7)-Параметры!$B$15<Параметры!$B$16,1,0) | Z5: =Y5*Параметры!$B$19 | AA5: =MAX(0,P5-X5-Z5) | AB5: =SUMIFS(Прайс!$D$3:$D$11,Прайс!$A$3:$A$11,B5,Прайс!$B$3:$B$11,C5) | AC5: =IF(AB5="","",AB5-AA5) | AD5: 1659070.6
A6: =Комплектация!A8 | B6: =Комплектация!C8 | C6: =Комплектация!E8 | D6: 2043 | E6: =IF(D6="",Параметры!$B$11,MAX(1,D6-C6)) | F6: =MAX(0,YEAR(Параметры!$B$2)-C6) | G6: =MIN(100,F6/E6*100) | H6: =100-G6 | I6: =AVERAGE(Комплектация!BJ8,Комплектация!BP8,Комплектация!BV8,Комплектация!CB8,Комплектация!CH8,Комплектация!CN8) | J6: =MAX(0,YEAR(Параметры!$B$2)-I6) | K6: =MIN(100,J6/Параметры!$B$12*100) | L6: =100-K6 | M6: =MIN(Комплектация!AA8,Комплектация!AB8,Комплектация!AK8,Комплектация!AL8,Комплектация!AU8,Комплектация!AV8,Комплектация!BE8,Комплектация!BF8) | N6: =AVERAGE((100-MAX(0,MIN(100,(Параметры!$B$13-MIN(Комплектация!AA8,Комплектация!AB8))/(Параметры!$B$13-Параметры!$B$14)*100))),(100-MAX(0,MIN(100,(Параметры!$B$13-MIN(Комплектация!AK8,Комплектация!AL8))/(Параметры!$B$13-Параметры!$B$14)*100))),(100-MAX(0,MIN(100,(Параметры!$B$13-MIN(Комплектация!AU8,Комплектация!AV8))/(Параметры!$B$13-Параметры!$B$14)*100))),(100-MAX(0,MIN(100,(Параметры!$B$13-MIN(Комплектация!BE8,Комплектация!BF8))/(Параметры!$B$13-Параметры!$B$14)*100)))) | O6: =AVERAGE(H6,L6) | P6: =Параметры!$B$3*(Параметры!$B$5*H6+Параметры!$B$6*L6+Параметры!$B$7*N6+Параметры!$B$8*O6)/100 | Q6: 46065 | R6: 46795 | S6: =IF(OR(Q6="",R6="",R6=Q6),"",MAX(0,MIN(100,(Параметры!$B$2-Q6)/(R6-Q6)*100))) | T6: =IF(ISNUMBER(Комплектация!P8),Комплектация!P8,"") | U6: =IF(ISNUMBER(Комплектация!N8),Комплектация!N8,"") | V6: =IF(OR(U6="",T6="",U6=0),"",MAX(0,MIN(100,(U6-T6)/U6*100))) | W6: =MAX(IF(S6="",0,S6),IF(V6="",0,V6)) | X6: =Параметры!$B$18*W6/100 | Y6: =IF(MIN(Комплектация!AA8,Комплектация!AB8)-Параметры!$B$15<Параметры!$B$16,1,0)+IF(MIN(Комплектация!AK8,Комплектация!AL8)-Параметры!$B$15<Параметры!$B$16,1,0)+IF(MIN(Комплектация!AU8,Комплектация!AV8)-Параметры!$B$15<Параметры!$B$16,1,0)+IF(MIN(Комплектация!BE8,Комплектация!BF8)-Параметры!$B$15<Параметры!$B$16,1,0) | Z6: =Y6*Параметры!$B$19 | AA6: =MAX(0,P6-X6-Z6) | AB6: =SUMIFS(Прайс!$D$3:$D$11,Прайс!$A$3:$A$11,B6,Прайс!$B$3:$B$11,C6) | AC6: =IF(AB6="","",AB6-AA6) | AD6: 3216820.6
A7: =Комплектация!A9 | B7: =Комплектация!C9 | C7: =Комплектация!E9 | D7: 2044 | E7: =IF(D7="",Параметры!$B$11,MAX(1,D7-C7)) | F7: =MAX(0,YEAR(Параметры!$B$2)-C7) | G7: =MIN(100,F7/E7*100) | H7: =100-G7 | I7: =AVERAGE(Комплектация!BJ9,Комплектация!BP9,Комплектация!BV9,Комплектация!CB9,Комплектация!CH9,Комплектация!CN9) | J7: =MAX(0,YEAR(Параметры!$B$2)-I7) | K7: =MIN(100,J7/Параметры!$B$12*100) | L7: =100-K7 | M7: =MIN(Комплектация!AA9,Комплектация!AB9,Комплектация!AK9,Комплектация!AL9,Комплектация!AU9,Комплектация!AV9,Комплектация!BE9,Комплектация!BF9) | N7: =AVERAGE((100-MAX(0,MIN(100,(Параметры!$B$13-MIN(Комплектация!AA9,Комплектация!AB9))/(Параметры!$B$13-Параметры!$B$14)*100))),(100-MAX(0,MIN(100,(Параметры!$B$13-MIN(Комплектация!AK9,Комплектация!AL9))/(Параметры!$B$13-Параметры!$B$14)*100))),(100-MAX(0,MIN(100,(Параметры!$B$13-MIN(Комплектация!AU9,Комплектация!AV9))/(Параметры!$B$13-Параметры!$B$14)*100))),(100-MAX(0,MIN(100,(Параметры!$B$13-MIN(Комплектация!BE9,Комплектация!BF9))/(Параметры!$B$13-Параметры!$B$14)*100)))) | O7: =AVERAGE(H7,L7) | P7: =Параметры!$B$3*(Параметры!$B$5*H7+Параметры!$B$6*L7+Параметры!$B$7*N7+Параметры!$B$8*O7)/100 | Q7: 45731 | R7: 46461 | S7: =IF(OR(Q7="",R7="",R7=Q7),"",MAX(0,MIN(100,(Параметры!$B$2-Q7)/(R7-Q7)*100))) | T7: =IF(ISNUMBER(Комплектация!P9),Комплектация!P9,"") | U7: =IF(ISNUMBER(Комплектация!N9),Комплектация!N9,"") | V7: =IF(OR(U7="",T7="",U7=0),"",MAX(0,MIN(100,(U7-T7)/U7*100))) | W7: =MAX(IF(S7="",0,S7),IF(V7="",0,V7)) | X7: =Параметры!$B$18*W7/100 | Y7: =IF(MIN(Комплектация!AA9,Комплектация!AB9)-Параметры!$B$15<Параметры!$B$16,1,0)+IF(MIN(Комплектация!AK9,Комплектация!AL9)-Параметры!$B$15<Параметры!$B$16,1,0)+IF(MIN(Комплектация!AU9,Комплектация!AV9)-Параметры!$B$15<Параметры!$B$16,1,0)+IF(MIN(Комплектация!BE9,Комплектация!BF9)-Параметры!$B$15<Параметры!$B$16,1,0) | Z7: =Y7*Параметры!$B$19 | AA7: =MAX(0,P7-X7-Z7) | AB7: =SUMIFS(Прайс!$D$3:$D$11,Прайс!$A$3:$A$11,B7,Прайс!$B$3:$B$11,C7) | AC7: =IF(AB7="","",AB7-AA7) | AD7: 3163911
A8: =Комплектация!A10 | B8: =Комплектация!C10 | C8: =Комплектация!E10 | D8: 2044 | E8: =IF(D8="",Параметры!$B$11,MAX(1,D8-C8)) | F8: =MAX(0,YEAR(Параметры!$B$2)-C8) | G8: =MIN(100,F8/E8*100) | H8: =100-G8 | I8: =AVERAGE(Комплектация!BJ10,Комплектация!BP10,Комплектация!BV10,Комплектация!CB10,Комплектация!CH10,Комплектация!CN10) | J8: =MAX(0,YEAR(Параметры!$B$2)-I8) | K8: =MIN(100,J8/Параметры!$B$12*100) | L8: =100-K8 | M8: =MIN(Комплектация!AA10,Комплектация!AB10,Комплектация!AK10,Комплектация!AL10,Комплектация!AU10,Комплектация!AV10,Комплектация!BE10,Комплектация!BF10) | N8: =AVERAGE((100-MAX(0,MIN(100,(Параметры!$B$13-MIN(Комплектация!AA10,Комплектация!AB10))/(Параметры!$B$13-Параметры!$B$14)*100))),(100-MAX(0,MIN(100,(Параметры!$B$13-MIN(Комплектация!AK10,Комплектация!AL10))/(Параметры!$B$13-Параметры!$B$14)*100))),(100-MAX(0,MIN(100,(Параметры!$B$13-MIN(Комплектация!AU10,Комплектация!AV10))/(Параметры!$B$13-Параметры!$B$14)*100))),(100-MAX(0,MIN(100,(Параметры!$B$13-MIN(Комплектация!BE10,Комплектация!BF10))/(Параметры!$B$13-Параметры!$B$14)*100)))) | O8: =AVERAGE(H8,L8) | P8: =Параметры!$B$3*(Параметры!$B$5*H8+Параметры!$B$6*L8+Параметры!$B$7*N8+Параметры!$B$8*O8)/100 | Q8: 45750 | R8: 46480 | S8: =IF(OR(Q8="",R8="",R8=Q8),"",MAX(0,MIN(100,(Параметры!$B$2-Q8)/(R8-Q8)*100))) | T8: =IF(ISNUMBER(Комплектация!P10),Комплектация!P10,"") | U8: =IF(ISNUMBER(Комплектация!N10),Комплектация!N10,"") | V8: =IF(OR(U8="",T8="",U8=0),"",MAX(0,MIN(100,(U8-T8)/U8*100))) | W8: =MAX(IF(S8="",0,S8),IF(V8="",0,V8)) | X8: =Параметры!$B$18*W8/100 | Y8: =IF(MIN(Комплектация!AA10,Комплектация!AB10)-Параметры!$B$15<Параметры!$B$16,1,0)+IF(MIN(Комплектация!AK10,Комплектация!AL10)-Параметры!$B$15<Параметры!$B$16,1,0)+IF(MIN(Комплектация!AU10,Комплектация!AV10)-Параметры!$B$15<Параметры!$B$16,1,0)+IF(MIN(Комплектация!BE10,Комплектация!BF10)-Параметры!$B$15<Параметры!$B$16,1,0) | Z8: =Y8*Параметры!$B$19 | AA8: =MAX(0,P8-X8-Z8) | AB8: =SUMIFS(Прайс!$D$3:$D$11,Прайс!$A$3:$A$11,B8,Прайс!$B$3:$B$11,C8) | AC8: =IF(AB8="","",AB8-AA8) | AD8: 3176013.7
A9: =Комплектация!A11 | B9: =Комплектация!C11 | C9: =Комплектация!E11 | D9: 2043 | E9: =IF(D9="",Параметры!$B$11,MAX(1,D9-C9)) | F9: =MAX(0,YEAR(Параметры!$B$2)-C9) | G9: =MIN(100,F9/E9*100) | H9: =100-G9 | I9: =AVERAGE(Комплектация!BJ11,Комплектация!BP11,Комплектация!BV11,Комплектация!CB11,Комплектация!CH11,Комплектация!CN11) | J9: =MAX(0,YEAR(Параметры!$B$2)-I9) | K9: =MIN(100,J9/Параметры!$B$12*100) | L9: =100-K9 | M9: =MIN(Комплектация!AA11,Комплектация!AB11,Комплектация!AK11,Комплектация!AL11,Комплектация!AU11,Комплектация!AV11,Комплектация!BE11,Комплектация!BF11) | N9: =AVERAGE((100-MAX(0,MIN(100,(Параметры!$B$13-MIN(Комплектация!AA11,Комплектация!AB11))/(Параметры!$B$13-Параметры!$B$14)*100))),(100-MAX(0,MIN(100,(Параметры!$B$13-MIN(Комплектация!AK11,Комплектация!AL11))/(Параметры!$B$13-Параметры!$B$14)*100))),(100-MAX(0,MIN(100,(Параметры!$B$13-MIN(Комплектация!AU11,Комплектация!AV11))/(Параметры!$B$13-Параметры!$B$14)*100))),(100-MAX(0,MIN(100,(Параметры!$B$13-MIN(Комплектация!BE11,Комплектация!BF11))/(Параметры!$B$13-Параметры!$B$14)*100)))) | O9: =AVERAGE(H9,L9) | P9: =Параметры!$B$3*(Параметры!$B$5*H9+Параметры!$B$6*L9+Параметры!$B$7*N9+Параметры!$B$8*O9)/100 | Q9: 46067 | R9: 46797 | S9: =IF(OR(Q9="",R9="",R9=Q9),"",MAX(0,MIN(100,(Параметры!$B$2-Q9)/(R9-Q9)*100))) | T9: =IF(ISNUMBER(Комплектация!P11),Комплектация!P11,"") | U9: =IF(ISNUMBER(Комплектация!N11),Комплектация!N11,"") | V9: =IF(OR(U9="",T9="",U9=0),"",MAX(0,MIN(100,(U9-T9)/U9*100))) | W9: =MAX(IF(S9="",0,S9),IF(V9="",0,V9)) | X9: =Параметры!$B$18*W9/100 | Y9: =IF(MIN(Комплектация!AA11,Комплектация!AB11)-Параметры!$B$15<Параметры!$B$16,1,0)+IF(MIN(Комплектация!AK11,Комплектация!AL11)-Параметры!$B$15<Параметры!$B$16,1,0)+IF(MIN(Комплектация!AU11,Комплектация!AV11)-Параметры!$B$15<Параметры!$B$16,1,0)+IF(MIN(Комплектация!BE11,Комплектация!BF11)-Параметры!$B$15<Параметры!$B$16,1,0) | Z9: =Y9*Параметры!$B$19 | AA9: =MAX(0,P9-X9-Z9) | AB9: =SUMIFS(Прайс!$D$3:$D$11,Прайс!$A$3:$A$11,B9,Прайс!$B$3:$B$11,C9) | AC9: =IF(AB9="","",AB9-AA9) | AD9: 3194844.6
A10: =Комплектация!A12 | B10: =Комплектация!C12 | C10: =Комплектация!E12 | D10: 2047 | E10: =IF(D10="",Параметры!$B$11,MAX(1,D10-C10)) | F10: =MAX(0,YEAR(Параметры!$B$2)-C10) | G10: =MIN(100,F10/E10*100) | H10: =100-G10 | I10: =AVERAGE(Комплектация!BJ12,Комплектация!BP12,Комплектация!BV12,Комплектация!CB12,Комплектация!CH12,Комплектация!CN12) | J10: =MAX(0,YEAR(Параметры!$B$2)-I10) | K10: =MIN(100,J10/Параметры!$B$12*100) | L10: =100-K10 | M10: =MIN(Комплектация!AA12,Комплектация!AB12,Комплектация!AK12,Комплектация!AL12,Комплектация!AU12,Комплектация!AV12,Комплектация!BE12,Комплектация!BF12) | N10: =AVERAGE((100-MAX(0,MIN(100,(Параметры!$B$13-MIN(Комплектация!AA12,Комплектация!AB12))/(Параметры!$B$13-Параметры!$B$14)*100))),(100-MAX(0,MIN(100,(Параметры!$B$13-MIN(Комплектация!AK12,Комплектация!AL12))/(Параметры!$B$13-Параметры!$B$14)*100))),(100-MAX(0,MIN(100,(Параметры!$B$13-MIN(Комплектация!AU12,Комплектация!AV12))/(Параметры!$B$13-Параметры!$B$14)*100))),(100-MAX(0,MIN(100,(Параметры!$B$13-MIN(Комплектация!BE12,Комплектация!BF12))/(Параметры!$B$13-Параметры!$B$14)*100)))) | O10: =AVERAGE(H10,L10) | P10: =Параметры!$B$3*(Параметры!$B$5*H10+Параметры!$B$6*L10+Параметры!$B$7*N10+Параметры!$B$8*O10)/100 | Q10: 45889 | R10: 46985 | S10: =IF(OR(Q10="",R10="",R10=Q10),"",MAX(0,MIN(100,(Параметры!$B$2-Q10)/(R10-Q10)*100))) | T10: =IF(ISNUMBER(Комплектация!P12),Комплектация!P12,"") | U10: =IF(ISNUMBER(Комплектация!N12),Комплектация!N12,"") | V10: =IF(OR(U10="",T10="",U10=0),"",MAX(0,MIN(100,(U10-T10)/U10*100))) | W10: =MAX(IF(S10="",0,S10),IF(V10="",0,V10)) | X10: =Параметры!$B$18*W10/100 | Y10: =IF(MIN(Комплектация!AA12,Комплектация!AB12)-Параметры!$B$15<Параметры!$B$16,1,0)+IF(MIN(Комплектация!AK12,Комплектация!AL12)-Параметры!$B$15<Параметры!$B$16,1,0)+IF(MIN(Комплектация!AU12,Комплектация!AV12)-Параметры!$B$15<Параметры!$B$16,1,0)+IF(MIN(Комплектация!BE12,Комплектация!BF12)-Параметры!$B$15<Параметры!$B$16,1,0) | Z10: =Y10*Параметры!$B$19 | AA10: =MAX(0,P10-X10-Z10) | AB10: =SUMIFS(Прайс!$D$3:$D$11,Прайс!$A$3:$A$11,B10,Прайс!$B$3:$B$11,C10) | AC10: =IF(AB10="","",AB10-AA10) | AD10: 3394224.2
A11: =Комплектация!A13 | B11: =Комплектация!C13 | C11: =Комплектация!E13 | D11: 2043 | E11: =IF(D11="",Параметры!$B$11,MAX(1,D11-C11)) | F11: =MAX(0,YEAR(Параметры!$B$2)-C11) | G11: =MIN(100,F11/E11*100) | H11: =100-G11 | I11: =AVERAGE(Комплектация!BJ13,Комплектация!BP13,Комплектация!BV13,Комплектация!CB13,Комплектация!CH13,Комплектация!CN13) | J11: =MAX(0,YEAR(Параметры!$B$2)-I11) | K11: =MIN(100,J11/Параметры!$B$12*100) | L11: =100-K11 | M11: =MIN(Комплектация!AA13,Комплектация!AB13,Комплектация!AK13,Комплектация!AL13,Комплектация!AU13,Комплектация!AV13,Комплектация!BE13,Комплектация!BF13) | N11: =AVERAGE((100-MAX(0,MIN(100,(Параметры!$B$13-MIN(Комплектация!AA13,Комплектация!AB13))/(Параметры!$B$13-Параметры!$B$14)*100))),(100-MAX(0,MIN(100,(Параметры!$B$13-MIN(Комплектация!AK13,Комплектация!AL13))/(Параметры!$B$13-Параметры!$B$14)*100))),(100-MAX(0,MIN(100,(Параметры!$B$13-MIN(Комплектация!AU13,Комплектация!AV13))/(Параметры!$B$13-Параметры!$B$14)*100))),(100-MAX(0,MIN(100,(Параметры!$B$13-MIN(Комплектация!BE13,Комплектация!BF13))/(Параметры!$B$13-Параметры!$B$14)*100)))) | O11: =AVERAGE(H11,L11) | P11: =Параметры!$B$3*(Параметры!$B$5*H11+Параметры!$B$6*L11+Параметры!$B$7*N11+Параметры!$B$8*O11)/100 | Q11: 45890 | R11: 46986 | S11: =IF(OR(Q11="",R11="",R11=Q11),"",MAX(0,MIN(100,(Параметры!$B$2-Q11)/(R11-Q11)*100))) | T11: =IF(ISNUMBER(Комплектация!P13),Комплектация!P13,"") | U11: =IF(ISNUMBER(Комплектация!N13),Комплектация!N13,"") | V11: =IF(OR(U11="",T11="",U11=0),"",MAX(0,MIN(100,(U11-T11)/U11*100))) | W11: =MAX(IF(S11="",0,S11),IF(V11="",0,V11)) | X11: =Параметры!$B$18*W11/100 | Y11: =IF(MIN(Комплектация!AA13,Комплектация!AB13)-Параметры!$B$15<Параметры!$B$16,1,0)+IF(MIN(Комплектация!AK13,Комплектация!AL13)-Параметры!$B$15<Параметры!$B$16,1,0)+IF(MIN(Комплектация!AU13,Комплектация!AV13)-Параметры!$B$15<Параметры!$B$16,1,0)+IF(MIN(Комплектация!BE13,Комплектация!BF13)-Параметры!$B$15<Параметры!$B$16,1,0) | Z11: =Y11*Параметры!$B$19 | AA11: =MAX(0,P11-X11-Z11) | AB11: =SUMIFS(Прайс!$D$3:$D$11,Прайс!$A$3:$A$11,B11,Прайс!$B$3:$B$11,C11) | AC11: =IF(AB11="","",AB11-AA11) | AD11: 3092398.5
A12: =Комплектация!A14 | B12: =Комплектация!C14 | C12: =Комплектация!E14 | D12: 2047 | E12: =IF(D12="",Параметры!$B$11,MAX(1,D12-C12)) | F12: =MAX(0,YEAR(Параметры!$B$2)-C12) | G12: =MIN(100,F12/E12*100) | H12: =100-G12 | I12: =AVERAGE(Комплектация!BJ14,Комплектация!BP14,Комплектация!BV14,Комплектация!CB14,Комплектация!CH14,Комплектация!CN14) | J12: =MAX(0,YEAR(Параметры!$B$2)-I12) | K12: =MIN(100,J12/Параметры!$B$12*100) | L12: =100-K12 | M12: =MIN(Комплектация!AA14,Комплектация!AB14,Комплектация!AK14,Комплектация!AL14,Комплектация!AU14,Комплектация!AV14,Комплектация!BE14,Комплектация!BF14) | N12: =AVERAGE((100-MAX(0,MIN(100,(Параметры!$B$13-MIN(Комплектация!AA14,Комплектация!AB14))/(Параметры!$B$13-Параметры!$B$14)*100))),(100-MAX(0,MIN(100,(Параметры!$B$13-MIN(Комплектация!AK14,Комплектация!AL14))/(Параметры!$B$13-Параметры!$B$14)*100))),(100-MAX(0,MIN(100,(Параметры!$B$13-MIN(Комплектация!AU14,Комплектация!AV14))/(Параметры!$B$13-Параметры!$B$14)*100))),(100-MAX(0,MIN(100,(Параметры!$B$13-MIN(Комплектация!BE14,Комплектация!BF14))/(Параметры!$B$13-Параметры!$B$14)*100)))) | O12: =AVERAGE(H12,L12) | P12: =Параметры!$B$3*(Параметры!$B$5*H12+Параметры!$B$6*L12+Параметры!$B$7*N12+Параметры!$B$8*O12)/100 | Q12: 45889 | R12: 46985 | S12: =IF(OR(Q12="",R12="",R12=Q12),"",MAX(0,MIN(100,(Параметры!$B$2-Q12)/(R12-Q12)*100))) | T12: =IF(ISNUMBER(Комплектация!P14),Комплектация!P14,"") | U12: =IF(ISNUMBER(Комплектация!N14),Комплектация!N14,"") | V12: =IF(OR(U12="",T12="",U12=0),"",MAX(0,MIN(100,(U12-T12)/U12*100))) | W12: =MAX(IF(S12="",0,S12),IF(V12="",0,V12)) | X12: =Параметры!$B$18*W12/100 | Y12: =IF(MIN(Комплектация!AA14,Комплектация!AB14)-Параметры!$B$15<Параметры!$B$16,1,0)+IF(MIN(Комплектация!AK14,Комплектация!AL14)-Параметры!$B$15<Параметры!$B$16,1,0)+IF(MIN(Комплектация!AU14,Комплектация!AV14)-Параметры!$B$15<Параметры!$B$16,1,0)+IF(MIN(Комплектация!BE14,Комплектация!BF14)-Параметры!$B$15<Параметры!$B$16,1,0) | Z12: =Y12*Параметры!$B$19 | AA12: =MAX(0,P12-X12-Z12) | AB12: =SUMIFS(Прайс!$D$3:$D$11,Прайс!$A$3:$A$11,B12,Прайс!$B$3:$B$11,C12) | AC12: =IF(AB12="","",AB12-AA12) | AD12: 1813224.2
A13: =Комплектация!A15 | B13: =Комплектация!C15 | C13: =Комплектация!E15 | D13: 2043 | E13: =IF(D13="",Параметры!$B$11,MAX(1,D13-C13)) | F13: =MAX(0,YEAR(Параметры!$B$2)-C13) | G13: =MIN(100,F13/E13*100) | H13: =100-G13 | I13: =AVERAGE(Комплектация!BJ15,Комплектация!BP15,Комплектация!BV15,Комплектация!CB15,Комплектация!CH15,Комплектация!CN15) | J13: =MAX(0,YEAR(Параметры!$B$2)-I13) | K13: =MIN(100,J13/Параметры!$B$12*100) | L13: =100-K13 | M13: =MIN(Комплектация!AA15,Комплектация!AB15,Комплектация!AK15,Комплектация!AL15,Комплектация!AU15,Комплектация!AV15,Комплектация!BE15,Комплектация!BF15) | N13: =AVERAGE((100-MAX(0,MIN(100,(Параметры!$B$13-MIN(Комплектация!AA15,Комплектация!AB15))/(Параметры!$B$13-Параметры!$B$14)*100))),(100-MAX(0,MIN(100,(Параметры!$B$13-MIN(Комплектация!AK15,Комплектация!AL15))/(Параметры!$B$13-Параметры!$B$14)*100))),(100-MAX(0,MIN(100,(Параметры!$B$13-MIN(Комплектация!AU15,Комплектация!AV15))/(Параметры!$B$13-Параметры!$B$14)*100))),(100-MAX(0,MIN(100,(Параметры!$B$13-MIN(Комплектация!BE15,Комплектация!BF15))/(Параметры!$B$13-Параметры!$B$14)*100)))) | O13: =AVERAGE(H13,L13) | P13: =Параметры!$B$3*(Параметры!$B$5*H13+Параметры!$B$6*L13+Параметры!$B$7*N13+Параметры!$B$8*O13)/100 | Q13: 45891 | R13: 46987 | S13: =IF(OR(Q13="",R13="",R13=Q13),"",MAX(0,MIN(100,(Параметры!$B$2-Q13)/(R13-Q13)*100))) | T13: =IF(ISNUMBER(Комплектация!P15),Комплектация!P15,"") | U13: =IF(ISNUMBER(Комплектация!N15),Комплектация!N15,"") | V13: =IF(OR(U13="",T13="",U13=0),"",MAX(0,MIN(100,(U13-T13)/U13*100))) | W13: =MAX(IF(S13="",0,S13),IF(V13="",0,V13)) | X13: =Параметры!$B$18*W13/100 | Y13: =IF(MIN(Комплектация!AA15,Комплектация!AB15)-Параметры!$B$15<Параметры!$B$16,1,0)+IF(MIN(Комплектация!AK15,Комплектация!AL15)-Параметры!$B$15<Параметры!$B$16,1,0)+IF(MIN(Комплектация!AU15,Комплектация!AV15)-Параметры!$B$15<Параметры!$B$16,1,0)+IF(MIN(Комплектация!BE15,Комплектация!BF15)-Параметры!$B$15<Параметры!$B$16,1,0) | Z13: =Y13*Параметры!$B$19 | AA13: =MAX(0,P13-X13-Z13) | AB13: =SUMIFS(Прайс!$D$3:$D$11,Прайс!$A$3:$A$11,B13,Прайс!$B$3:$B$11,C13) | AC13: =IF(AB13="","",AB13-AA13) | AD13: 3104447.8
A14: =Комплектация!A16 | B14: =Комплектация!C16 | C14: =Комплектация!E16 | D14: 2044 | E14: =IF(D14="",Параметры!$B$11,MAX(1,D14-C14)) | F14: =MAX(0,YEAR(Параметры!$B$2)-C14) | G14: =MIN(100,F14/E14*100) | H14: =100-G14 | I14: =AVERAGE(Комплектация!BJ16,Комплектация!BP16,Комплектация!BV16,Комплектация!CB16,Комплектация!CH16,Комплектация!CN16) | J14: =MAX(0,YEAR(Параметры!$B$2)-I14) | K14: =MIN(100,J14/Параметры!$B$12*100) | L14: =100-K14 | M14: =MIN(Комплектация!AA16,Комплектация!AB16,Комплектация!AK16,Комплектация!AL16,Комплектация!AU16,Комплектация!AV16,Комплектация!BE16,Комплектация!BF16) | N14: =AVERAGE((100-MAX(0,MIN(100,(Параметры!$B$13-MIN(Комплектация!AA16,Комплектация!AB16))/(Параметры!$B$13-Параметры!$B$14)*100))),(100-MAX(0,MIN(100,(Параметры!$B$13-MIN(Комплектация!AK16,Комплектация!AL16))/(Параметры!$B$13-Параметры!$B$14)*100))),(100-MAX(0,MIN(100,(Параметры!$B$13-MIN(Комплектация!AU16,Комплектация!AV16))/(Параметры!$B$13-Параметры!$B$14)*100))),(100-MAX(0,MIN(100,(Параметры!$B$13-MIN(Комплектация!BE16,Комплектация!BF16))/(Параметры!$B$13-Параметры!$B$14)*100)))) | O14: =AVERAGE(H14,L14) | P14: =Параметры!$B$3*(Параметры!$B$5*H14+Параметры!$B$6*L14+Параметры!$B$7*N14+Параметры!$B$8*O14)/100 | Q14: 45923 | R14: 47019 | S14: =IF(OR(Q14="",R14="",R14=Q14),"",MAX(0,MIN(100,(Параметры!$B$2-Q14)/(R14-Q14)*100))) | T14: =IF(ISNUMBER(Комплектация!P16),Комплектация!P16,"") | U14: =IF(ISNUMBER(Комплектация!N16),Комплектация!N16,"") | V14: =IF(OR(U14="",T14="",U14=0),"",MAX(0,MIN(100,(U14-T14)/U14*100))) | W14: =MAX(IF(S14="",0,S14),IF(V14="",0,V14)) | X14: =Параметры!$B$18*W14/100 | Y14: =IF(MIN(Комплектация!AA16,Комплектация!AB16)-Параметры!$B$15<Параметры!$B$16,1,0)+IF(MIN(Комплектация!AK16,Комплектация!AL16)-Параметры!$B$15<Параметры!$B$16,1,0)+IF(MIN(Комплектация!AU16,Комплектация!AV16)-Параметры!$B$15<Параметры!$B$16,1,0)+IF(MIN(Комплектация!BE16,Комплектация!BF16)-Параметры!$B$15<Параметры!$B$16,1,0) | Z14: =Y14*Параметры!$B$19 | AA14: =MAX(0,P14-X14-Z14) | AB14: =SUMIFS(Прайс!$D$3:$D$11,Прайс!$A$3:$A$11,B14,Прайс!$B$3:$B$11,C14) | AC14: =IF(AB14="","",AB14-AA14) | AD14: 3161618.2
... A168: =Комплектация!A170 | B168: =Комплектация!C170 | C168: =Комплектация!E170 | D168: 2043 | E168: =IF(D168="",Параметры!$B$11,MAX(1,D168-C168)) | F168: =MAX(0,YEAR(Параметры!$B$2)-C168) | G168: =MIN(100,F168/E168*100) | H168: =100-G168 | I168: =AVERAGE(Комплектация!BJ170,Комплектация!BP170,Комплектация!BV170,Комплектация!CB170,Комплектация!CH170,Комплектация!CN170) | J168: =MAX(0,YEAR(Параметры!$B$2)-I168) | K168: =MIN(100,J168/Параметры!$B$12*100) | L168: =100-K168 | M168: =MIN(Комплектация!AA170,Комплектация!AB170,Комплектация!AK170,Комплектация!AL170,Комплектация!AU170,Комплектация!AV170,Комплектация!BE170,Комплектация!BF170) | N168: =AVERAGE((100-MAX(0,MIN(100,(Параметры!$B$13-MIN(Комплектация!AA170,Комплектация!AB170))/(Параметры!$B$13-Параметры!$B$14)*100))),(100-MAX(0,MIN(100,(Параметры!$B$13-MIN(Комплектация!AK170,Комплектация!AL170))/(Параметры!$B$13-Параметры!$B$14)*100))),(100-MAX(0,MIN(100,(Параметры!$B$13-MIN(Комплектация!AU170,Комплектация!AV170))/(Параметры!$B$13-Параметры!$B$14)*100))),(100-MAX(0,MIN(100,(Параметры!$B$13-MIN(Комплектация!BE170,Комплектация!BF170))/(Параметры!$B$13-Параметры!$B$14)*100)))) | O168: =AVERAGE(H168,L168) | P168: =Параметры!$B$3*(Параметры!$B$5*H168+Параметры!$B$6*L168+Параметры!$B$7*N168+Параметры!$B$8*O168)/100 | Q168: 45954 | R168: 46684 | S168: =IF(OR(Q168="",R168="",R168=Q168),"",MAX(0,MIN(100,(Параметры!$B$2-Q168)/(R168-Q168)*100))) | T168: =IF(ISNUMBER(Комплектация!P170),Комплектация!P170,"") | U168: =IF(ISNUMBER(Комплектация!N170),Комплектация!N170,"") | V168: =IF(OR(U168="",T168="",U168=0),"",MAX(0,MIN(100,(U168-T168)/U168*100))) | W168: =MAX(IF(S168="",0,S168),IF(V168="",0,V168)) | X168: =Параметры!$B$18*W168/100 | Y168: =IF(MIN(Комплектация!AA170,Комплектация!AB170)-Параметры!$B$15<Параметры!$B$16,1,0)+IF(MIN(Комплектация!AK170,Комплектация!AL170)-Параметры!$B$15<Параметры!$B$16,1,0)+IF(MIN(Комплектация!AU170,Комплектация!AV170)-Параметры!$B$15<Параметры!$B$16,1,0)+IF(MIN(Комплектация!BE170,Комплектация!BF170)-Параметры!$B$15<Параметры!$B$16,1,0) | Z168: =Y168*Параметры!$B$19 | AA168: =MAX(0,P168-X168-Z168) | AB168: =SUMIFS(Прайс!$D$3:$D$11,Прайс!$A$3:$A$11,B168,Прайс!$B$3:$B$11,C168) | AC168: =IF(AB168="","",AB168-AA168) | AD168: 3221677.7

Sheet Свод
A1: Свод оценки — методика v2
A2: Компонентный затратный подход: стоимость = Σ(доля компонента × остаточная %) − обязательства по ремонтам.
A4: Показатель | B4: Значение | C4: Комментарий
A5: Количество вагонов | B5: =COUNT(Оценка!$AA$3:$AA$168) | C5: Оценённых по модели v2
A6: Средняя стоимость v2, ₽ | B6: =AVERAGE(Оценка!$AA$3:$AA$168) | C6: Итоговая с учётом обязательств
A7: Минимальная стоимость v2, ₽ | B7: =MIN(Оценка!$AA$3:$AA$168)
A8: Максимальная стоимость v2, ₽ | B8: =MAX(Оценка!$AA$3:$AA$168)
A9: Суммарная стоимость парка v2, ₽ | B9: =SUM(Оценка!$AA$3:$AA$168) | C9: Итог по 166 вагонам
A11: Средняя оценка v1 (справочно), ₽ | B11: =AVERAGE(Оценка!$AD$3:$AD$168) | C11: Из исходной модели (возраст+обод, 50/50)
A12: Разница средних v2 − v1, ₽ | B12: =AVERAGE(Оценка!$AA$3:$AA$168)-AVERAGE(Оценка!$AD$3:$AD$168) | C12: Влияние новой методики
A13: Разница средних v2 − v1, % | B13: =(AVERAGE(Оценка!$AA$3:$AA$168)-AVERAGE(Оценка!$AD$3:$AD$168))/AVERAGE(Оценка!$AD$3:$AD$168)*100
A15: Сравнение с ценой собственника | B15: Значение | C15: Комментарий
A16: Итого прайс собственника, ₽ | B16: =SUM(Оценка!$AB$3:$AB$168) | C16: Сумма запрошенных цен (без НДС), лист «Прайс»
A17: Итого оценка v2 (износ), ₽ | B17: =SUM(Оценка!$AA$3:$AA$168) | C17: Компонентная стоимость − обязательства
A18: Переоценка прайса к v2, ₽ | B18: =SUM(Оценка!$AB$3:$AB$168)-SUM(Оценка!$AA$3:$AA$168) | C18: Насколько прайс выше стоимости по износу
A19: Переоценка прайса к v2, % | B19: =(SUM(Оценка!$AB$3:$AB$168)-SUM(Оценка!$AA$3:$AA$168))/SUM(Оценка!$AA$3:$AA$168)*100 | C19: Прайс дороже оценки на столько
A20: Итого оценка v1 (справочно), ₽ | B20: =SUM(Оценка!$AD$3:$AD$168) | C20: Почти равна прайсу — v1, как и прайс, ценит по возрасту
A21: Вагонов: прайс ВЫШЕ оценки v2 (переоценены) | B21: =COUNTIF(Оценка!$AC$3:$AC$168,">0") | C21: Есть основание торговаться вниз
A22: Вагонов: прайс НИЖЕ оценки v2 (привлекательны) | B22: =COUNTIF(Оценка!$AC$3:$AC$168,"<0") | C22: Прайс уже ниже стоимости по состоянию
A24: Что изменено в методике v2 против v1:
A25: 1. Компонентная декомпозиция | C25: Котёл+рама / тележки(литьё) / КП / прочее вместо 50-на-50
A26: 2. Индивидуальный срок службы | C26: Износ котла — по дате СС из данных, не общий 32 г.
A27: 3. Литьё тележек как компонент | C27: Использованы годы боковых рам и надрессорных балок
A28: 4. Обод по полному диапазону | C28: Износ обода от новой (70 мм) до предела, а не в полосе 50→27
A29: 5. Пробег как ресурс | C29: Остаточный пробег включён в позицию обслуживания
A30: 6. ДР как обязательство в ₽ | C30: Стоимость предстоящего ремонта вычитается в рублях
A31: 7. Замена негодных КП в ₽ | C31: Негодные к обточке КП — вычет стоимости замены
A32: 8. Рыночная сверка | C32: Колонка «Цена продавца» для сравнения (затратный↔рыночный)
A34: Ограничения — требуют данных/уточнения:
A35: • Толщина гребня | C35: В источнике = 0 (не собрана). Добавить в износ КП после замера.
A36: • Доли компонентов и цены ремонтов | C36: Заданы как допущения на листе «Параметры» — заменить фактикой.
A37: • Состояние котла (коррозия, толщина стенки) | C37: Нет в данных; износ тела аппроксимирован сроком службы.
A38: • Единая цена новой для всех моделей | C38: 2020 г. (15-1219-1П, 69 тн) — премиальная модель; при единой цене новой её оценка занижена, переоценка прайса по ней завышена.
A39: • Функциональный / внешний износ | C39: Не учтён (тип цистерны, ставка аренды, регуляторные лимиты).
A41: Модель / год | B41: Кол-во | C41: Прайс ед., ₽ | D41: Оценка v2 ед., ₽ | E41: Δ прайс−v2, ₽ | F41: Δ, %
A42: 15-1219-1П · 2020 | B42: =COUNTIFS(Оценка!$B$3:$B$168,"15-1219-1П",Оценка!$C$3:$C$168,2020) | C42: =AVERAGEIFS(Оценка!$AB$3:$AB$168,Оценка!$B$3:$B$168,"15-1219-1П",Оценка!$C$3:$C$168,2020) | D42: =AVERAGEIFS(Оценка!$AA$3:$AA$168,Оценка!$B$3:$B$168,"15-1219-1П",Оценка!$C$3:$C$168,2020) | E42: =C42-D42 | F42: =IF(C42=0,0,(C42-D42)/C42*100)
A43: 15-150-04П · 2011 | B43: =COUNTIFS(Оценка!$B$3:$B$168,"15-150-04П",Оценка!$C$3:$C$168,2011) | C43: =AVERAGEIFS(Оценка!$AB$3:$AB$168,Оценка!$B$3:$B$168,"15-150-04П",Оценка!$C$3:$C$168,2011) | D43: =AVERAGEIFS(Оценка!$AA$3:$AA$168,Оценка!$B$3:$B$168,"15-150-04П",Оценка!$C$3:$C$168,2011) | E43: =C43-D43 | F43: =IF(C43=0,0,(C43-D43)/C43*100)
A44: 15-150-04П · 2012 | B44: =COUNTIFS(Оценка!$B$3:$B$168,"15-150-04П",Оценка!$C$3:$C$168,2012) | C44: =AVERAGEIFS(Оценка!$AB$3:$AB$168,Оценка!$B$3:$B$168,"15-150-04П",Оценка!$C$3:$C$168,2012) | D44: =AVERAGEIFS(Оценка!$AA$3:$AA$168,Оценка!$B$3:$B$168,"15-150-04П",Оценка!$C$3:$C$168,2012) | E44: =C44-D44 | F44: =IF(C44=0,0,(C44-D44)/C44*100)
A45: 15-150-04П · 2015 | B45: =COUNTIFS(Оценка!$B$3:$B$168,"15-150-04П",Оценка!$C$3:$C$168,2015) | C45: =AVERAGEIFS(Оценка!$AB$3:$AB$168,Оценка!$B$3:$B$168,"15-150-04П",Оценка!$C$3:$C$168,2015) | D45: =AVERAGEIFS(Оценка!$AA$3:$AA$168,Оценка!$B$3:$B$168,"15-150-04П",Оценка!$C$3:$C$168,2015) | E45: =C45-D45 | F45: =IF(C45=0,0,(C45-D45)/C45*100)
A46: 15-1755П · 2013 | B46: =COUNTIFS(Оценка!$B$3:$B$168,"15-1755П",Оценка!$C$3:$C$168,2013) | C46: =AVERAGEIFS(Оценка!$AB$3:$AB$168,Оценка!$B$3:$B$168,"15-1755П",Оценка!$C$3:$C$168,2013) | D46: =AVERAGEIFS(Оценка!$AA$3:$AA$168,Оценка!$B$3:$B$168,"15-1755П",Оценка!$C$3:$C$168,2013) | E46: =C46-D46 | F46: =IF(C46=0,0,(C46-D46)/C46*100)
A47: 15-1755П · 2014 | B47: =COUNTIFS(Оценка!$B$3:$B$168,"15-1755П",Оценка!$C$3:$C$168,2014) | C47: =AVERAGEIFS(Оценка!$AB$3:$AB$168,Оценка!$B$3:$B$168,"15-1755П",Оценка!$C$3:$C$168,2014) | D47: =AVERAGEIFS(Оценка!$AA$3:$AA$168,Оценка!$B$3:$B$168,"15-1755П",Оценка!$C$3:$C$168,2014) | E47: =C47-D47 | F47: =IF(C47=0,0,(C47-D47)/C47*100)
A48: 15-5103-7П · 2011 | B48: =COUNTIFS(Оценка!$B$3:$B$168,"15-5103-7П",Оценка!$C$3:$C$168,2011) | C48: =AVERAGEIFS(Оценка!$AB$3:$AB$168,Оценка!$B$3:$B$168,"15-5103-7П",Оценка!$C$3:$C$168,2011) | D48: =AVERAGEIFS(Оценка!$AA$3:$AA$168,Оценка!$B$3:$B$168,"15-5103-7П",Оценка!$C$3:$C$168,2011) | E48: =C48-D48 | F48: =IF(C48=0,0,(C48-D48)/C48*100)
A49: 15-5103-7П · 2012 | B49: =COUNTIFS(Оценка!$B$3:$B$168,"15-5103-7П",Оценка!$C$3:$C$168,2012) | C49: =AVERAGEIFS(Оценка!$AB$3:$AB$168,Оценка!$B$3:$B$168,"15-5103-7П",Оценка!$C$3:$C$168,2012) | D49: =AVERAGEIFS(Оценка!$AA$3:$AA$168,Оценка!$B$3:$B$168,"15-5103-7П",Оценка!$C$3:$C$168,2012) | E49: =C49-D49 | F49: =IF(C49=0,0,(C49-D49)/C49*100)
A50: 15-5103-7П · 2015 | B50: =COUNTIFS(Оценка!$B$3:$B$168,"15-5103-7П",Оценка!$C$3:$C$168,2015) | C50: =AVERAGEIFS(Оценка!$AB$3:$AB$168,Оценка!$B$3:$B$168,"15-5103-7П",Оценка!$C$3:$C$168,2015) | D50: =AVERAGEIFS(Оценка!$AA$3:$AA$168,Оценка!$B$3:$B$168,"15-5103-7П",Оценка!$C$3:$C$168,2015) | E50: =C50-D50 | F50: =IF(C50=0,0,(C50-D50)/C50*100)
A51: ИТОГО / среднее | B51: =SUM(B42:B50) | C51: =SUM(Оценка!$AB$3:$AB$168)/166 | D51: =SUM(Оценка!$AA$3:$AA$168)/166 | E51: =C51-D51 | F51: =(C51-D51)/C51*100

Sheet Комплектация
A1: Номер вагона / контейнера | B1: Род вагона | C1: Модель | D1: Дата постройки | E1: Год постройки | F1: Срок службы | G1: Дата последнего деповского ремонта | H1: Депопоследнего деповского ремонта | I1: Дата капитального | J1: Депо капитального | K1: Очередной вид ремонта | L1: Дата очередного плановго ремонта | M1: Собственник | N1: Норма пробега | O1: Пробег общий | P1: Остаточный пробег | Q1: Дата ремонта по пробегу | R1: Дата изменения комплектации | T1: Колесная пара 1 | AD1: Колесная пара 2 | AN1: Колесная пара 3 | AX1: Колесная пара 4 | BH1: Надрессорная балка 1 | BN1: Надрессорная балка 2 | BT1: Боковая рама 1 | BZ1: Боковая рама 2 | CF1: Боковая рама 3 | CL1: Боковая рама 4
T2: Номер детали | U2: Клеймо | V2: Год постр | W2: Депо | X2: Дата | Y2: Толщина гребня | AA2: Толщина обода | AD2: Номер детали | AE2: Клеймо | AF2: Год постр | AG2: Депо | AH2: Дата | AI2: Толщина гребня | AK2: Толщина обода | AN2: Номер детали | AO2: Клеймо | AP2: Год постр | AQ2: Депо | AR2: Дата | AS2: Толщина гребня | AU2: Толщина обода | AX2: Номер детали | AY2: Клеймо | AZ2: Год постр | BA2: Депо | BB2: Дата | BC2: Толщина гребня | BE2: Толщина обода | BH2: Номер детали | BI2: Клеймо | BJ2: Год постр | BK2: Депо | BL2: Дата | BN2: Номер детали | BO2: Клеймо | BP2: Год постр | BQ2: Депо | BR2: Дата | BT2: Номер детали | BU2: Клеймо | BV2: Год постр | BW2: Депо | BX2: Дата | BZ2: Номер детали | CA2: Клеймо | CB2: Год постр | CC2: Депо | CD2: Дата | CF2: Номер детали | CG2: Клеймо | CH2: Год постр | CI2: Депо | CJ2: Дата | CL2: Номер детали | CM2: Клеймо | CN2: Год постр | CO2: Депо | CP2: Дата
Y3: ЛЕВ. | Z3: ПРАВ. | AA3: ЛЕВ. | AB3: ПРАВ. | AI3: ЛЕВ. | AJ3: ПРАВ. | AK3: ЛЕВ. | AL3: ПРАВ. | AS3: ЛЕВ. | AT3: ПРАВ. | AU3: ЛЕВ. | AV3: ПРАВ. | BC3: ЛЕВ. | BD3: ПРАВ. | BE3: ЛЕВ. | BF3: ПРАВ.
A5: 77223766 | B5: Цистерна для перевозки продуктов | C5: 15-5103-7П | D5: 12.09.2011 | E5: 2011 | F5: 12.09.2043 | G5: 31.03.2023 | H5: ВРД Кочетовка – филиал ООО "НВК" | I5: 18.03.2026 | J5: Усть-Каменогорское ВРД | K5: Деповской | L5: 18.03.2029 | M5: ООО "ТрансАльянс Запад" | N5: 160000 | O5: 7663 | P5: 152337 | Q5: 11.07.2033 | R5: 18.03.2026 | T5: 107741 | U5: 0005 | V5: 2005 | W5: 745 | X5: мар.26 | Y5: 0 | Z5: 0 | AA5: 73 | AB5: 73 | AD5: 52282 | AE5: 1175 | AF5: 2012 | AG5: 745 | AH5: мар.26 | AI5: 0 | AJ5: 0 | AK5: 71 | AL5: 71 | AN5: 750688 | AO5: 0005 | AP5: 2017 | AQ5: 745 | AR5: мар.26 | AS5: 0 | AT5: 0 | AU5: 73 | AV5: 73 | AX5: 812280 | AY5: 0005 | AZ5: 2018 | BA5: 745 | BB5: мар.26 | BC5: 0 | BD5: 0 | BE5: 74 | BF5: 74 | BH5: 69894 | BI5: 0014 | BJ5: 2011 | BN5: 66505 | BO5: 0014 | BP5: 2011 | BT5: 117185 | BU5: 0014 | BV5: 2011 | BZ5: 117258 | CA5: 0014 | CB5: 2011 | CF5: 116917 | CG5: 0014 | CH5: 2011 | CL5: 117136 | CM5: 0014 | CN5: 2011
A6: 77206126 | B6: Цистерна для перевозки продуктов | C6: 15-1755П | D6: 20.06.2013 | E6: 2013 | F6: 20.06.2043 | G6: 12.02.2026 | H6: Усть-Каменогорское ВРД | I6: 02.02.2024 | J6: ВЧД Унеча-ООО "НВК" | K6: Деповской | L6: 12.02.2028 | M6: ООО "ТрансАльянс Запад" | N6: 160000 | O6: 20933 | P6: 139067 | Q6: 04.07.2029 | R6: 12.02.2026 | T6: 107656 | U6: 0005 | V6: 2014 | W6: 745 | X6: фев.26 | Y6: 0 | Z6: 0 | AA6: 72 | AB6: 72 | AD6: 227365 | AE6: 0005 | AF6: 2019 | AG6: 745 | AH6: фев.26 | AI6: 0 | AJ6: 0 | AK6: 72 | AL6: 72 | AN6: 16504 | AO6: 1175 | AP6: 2008 | AQ6: 745 | AR6: фев.26 | AS6: 0 | AT6: 0 | AU6: 74 | AV6: 74 | AX6: 844904 | AY6: 0029 | AZ6: 1990 | BA6: 745 | BB6: фев.26 | BC6: 0 | BD6: 0 | BE6: 72 | BF6: 72 | BH6: 15188 | BI6: 1291 | BJ6: 2013 | BN6: 15246 | BO6: 1291 | BP6: 2013 | BT6: 42930 | BU6: 1291 | BV6: 2013 | BZ6: 42424 | CA6: 1291 | CB6: 2013 | CF6: 38356 | CG6: 1291 | CH6: 2013 | CL6: 43316 | CM6: 1291 | CN6: 2013
A7: 77205912 | B7: Цистерна для перевозки продуктов | C7: 15-1755П | D7: 20.06.2013 | E7: 2013 | F7: 20.06.2043 | G7: 12.02.2026 | H7: Усть-Каменогорское ВРД | I7: 08.02.2024 | J7: ВРД Кочетовка – филиал ООО "НВК" | K7: Деповской | L7: 12.02.2028 | M7: ООО "ТрансАльянс Запад" | N7: 160000 | O7: 15958 | P7: 144042 | Q7: 25.07.2030 | R7: 15.06.2026 | T7: 392521 | U7: 0029 | V7: 2013 | W7: 4036 | X7: июнь.26 | Y7: 0 | Z7: 0 | AA7: 38 | AB7: 38 | AD7: 370222 | AE7: 0029 | AF7: 2012 | AG7: 4036 | AH7: июнь.26 | AI7: 0 | AJ7: 0 | AK7: 38 | AL7: 38 | AN7: 459384 | AO7: 0029 | AP7: 2013 | AQ7: 4036 | AR7: июнь.26 | AS7: 0 | AT7: 0 | AU7: 32 | AV7: 32 | AX7: 460013 | AY7: 0029 | AZ7: 2013 | BA7: 4036 | BB7: июнь.26 | BC7: 0 | BD7: 0 | BE7: 37 | BF7: 37 | BH7: 15648 | BI7: 1291 | BJ7: 2013 | BN7: 15896 | BO7: 1291 | BP7: 2013 | BT7: 46279 | BU7: 1291 | BV7: 2013 | BZ7: 45962 | CA7: 1291 | CB7: 2013 | CF7: 37854 | CG7: 1291 | CH7: 2013 | CL7: 45456 | CM7: 1291 | CN7: 2013
A8: 77206159 | B8: Цистерна для перевозки продуктов | C8: 15-1755П | D8: 20.06.2013 | E8: 2013 | F8: 20.06.2043 | G8: 12.02.2026 | H8: Усть-Каменогорское ВРД | I8: 05.02.2024 | J8: ТОО "Аждар и К" | K8: Деповской | L8: 12.02.2028 | M8: ООО "ТрансАльянс Запад" | N8: 160000 | O8: 15958 | P8: 144042 | Q8: 25.07.2030 | R8: 15.06.2026 | T8: 3029 | U8: 1175 | V8: 2011 | W8: 4036 | X8: июнь.26 | Y8: 0 | Z8: 0 | AA8: 75 | AB8: 75 | AD8: 884003 | AE8: 0029 | AF8: 2010 | AG8: 4036 | AH8: июнь.26 | AI8: 0 | AJ8: 0 | AK8: 75 | AL8: 75 | AN8: 134498 | AO8: 0005 | AP8: 2010 | AQ8: 4036 | AR8: июнь.26 | AS8: 0 | AT8: 0 | AU8: 66 | AV8: 66 | AX8: 696276 | AY8: 0029 | AZ8: 2008 | BA8: 4036 | BB8: июнь.26 | BC8: 0 | BD8: 0 | BE8: 75 | BF8: 75 | BH8: 15682 | BI8: 1291 | BJ8: 2013 | BN8: 52443 | BO8: 1291 | BP8: 2013 | BT8: 42733 | BU8: 1291 | BV8: 2013 | BZ8: 45183 | CA8: 1291 | CB8: 2013 | CF8: 42604 | CG8: 1291 | CH8: 2013 | CL8: 46047 | CM8: 1291 | CN8: 2013
A9: 77222149 | B9: Цистерна для перевозки продуктов | C9: 15-1755П | D9: 16.04.2014 | E9: 2014 | F9: 16.04.2044 | G9: 16.04.2023 | H9: ТОО "Аждар и К" | I9: 15.03.2025 | J9: ВРД Кочетовка – филиал ООО "НВК" | K9: Деповской | L9: 15.03.2027 | M9: ООО "ТрансАльянс Запад" | N9: 160000 | O9: 45837 | P9: 114163 | Q9: 10.12.2029 | R9: 15.03.2025 | T9: 444025 | U9: 0029 | V9: 2013 | W9: 301 | X9: мар.25 | Y9: 33 | Z9: 33 | AA9: 75 | AB9: 75 | AD9: 458607 | AE9: 0029 | AF9: 2013 | AG9: 301 | AH9: мар.25 | AI9: 33 | AJ9: 33 | AK9: 75 | AL9: 75 | AN9: 523344 | AO9: 0029 | AP9: 2014 | AQ9: 301 | AR9: мар.25 | AS9: 33 | AT9: 33 | AU9: 75 | AV9: 75 | AX9: 523382 | AY9: 0029 | AZ9: 2014 | BA9: 301 | BB9: мар.25 | BC9: 33 | BD9: 33 | BE9: 75 | BF9: 75 | BH9: 50753 | BI9: 1291 | BJ9: 2014 | BN9: 50876 | BO9: 1291 | BP9: 2014 | BT9: 3954 | BU9: 1291 | BV9: 2014 | BZ9: 3946 | CA9: 1291 | CB9: 2014 | CF9: 4551 | CG9: 1291 | CH9: 2014 | CL9: 3969 | CM9: 1291 | CN9: 2014
A10: 77222214 | B10: Цистерна для перевозки продуктов | C10: 15-1755П | D10: 16.04.2014 | E10: 2014 | F10: 16.04.2044 | G10: 22.03.2023 | H10: ВРД Кочетовка – филиал ООО "НВК" | I10: 03.04.2025 | J10: ВРД Кочетовка – филиал ООО "НВК" | K10: Деповской | L10: 03.04.2027 | M10: ООО "ТрансАльянс Запад" | N10: 160000 | O10: 48240 | P10: 111760 | Q10: 02.08.2029 | R10: 16.03.2026 | T10: 516474 | U10: 0029 | V10: 2013 | W10: 4046 | X10: мар.26 | Y10: 0 | Z10: 0 | AA10: 75 | AB10: 75 | AD10: 516476 | AE10: 0029 | AF10: 2013 | AG10: 4046 | AH10: мар.26 | AI10: 0 | AJ10: 0 | AK10: 75 | AL10: 75 | AN10: 523018 | AO10: 0029 | AP10: 2014 | AQ10: 4046 | AR10: мар.26 | AS10: 0 | AT10: 0 | AU10: 75 | AV10: 75 | AX10: 522934 | AY10: 0029 | AZ10: 2014 | BA10: 4046 | BB10: мар.26 | BC10: 0 | BD10: 0 | BE10: 75 | BF10: 75 | BH10: 51520 | BI10: 1291 | BJ10: 2014 | BN10: 51484 | BO10: 1291 | BP10: 2014 | BT10: 3898 | BU10: 1291 | BV10: 2014 | BZ10: 3949 | CA10: 1291 | CB10: 2014 | CF10: 403 | CG10: 1291 | CH10: 2014 | CL10: 2470 | CM10: 1291 | CN10: 2014
A11: 77206076 | B11: Цистерна для перевозки продуктов | C11: 15-1755П | D11: 20.06.2013 | E11: 2013 | F11: 20.06.2043 | G11: 14.02.2026 | H11: Усть-Каменогорское ВРД | I11: 04.02.2024 | J11: ТОО "Аждар и К" | K11: Деповской | L11: 14.02.2028 | M11: ООО "ТрансАльянс Запад" | N11: 160000 | O11: 15959 | P11: 144041 | Q11: 07.07.2030 | R11: 14.02.2026 | T11: 17411 | U11: 0039 | V11: 2005 | W11: 745 | X11: фев.26 | Y11: 0 | Z11: 0 | AA11: 75 | AB11: 75 | AD11: 61059 | AE11: 1175 | AF11: 2013 | AG11: 745 | AH11: фев.26 | AI11: 0 | AJ11: 0 | AK11: 72 | AL11: 72 | AN11: 27784 | AO11: 1175 | AP11: 2007 | AQ11: 745 | AR11: фев.26 | AS11: 0 | AT11: 0 | AU11: 71 | AV11: 71 | AX11: 61686 | AY11: 0039 | AZ11: 2010 | BA11: 745 | BB11: фев.26 | BC11: 0 | BD11: 0 | BE11: 70 | BF11: 70 | BH11: 14096 | BI11: 1291 | BJ11: 2013 | BN11: 13922 | BO11: 1291 | BP11: 2013 | BT11: 41746 | BU11: 1291 | BV11: 2013 | BZ11: 41214 | CA11: 1291 | CB11: 2013 | CF11: 42087 | CG11: 1291 | CH11: 2013 | CL11: 41710 | CM11: 1291 | CN11: 2013
A12: 77228781 | B12: Цистерна для перевозки продуктов | C12: 15-5103-7П | D12: 19.01.2015 | E12: 2015 | F12: 19.01.2047 | G12: 20.08.2025 | H12: Орский ВРЗ-филиал ООО "НВК" | K12: Капитальный | L12: 20.08.2028 | M12: ООО "ТрансАльянс Запад" | N12: 160000 | O12: 45251 | P12: 114749 | Q12: 27.11.2028 | R12: 20.08.2025 | T12: 881967 | U12: 0029 | V12: 2010 | W12: 2348 | X12: авг.25 | Y12: 30 | Z12: 30 | AA12: 60 | AB12: 60 | AD12: 133082 | AE12: 0005 | AF12: 2014 | AG12: 2348 | AH12: авг.25 | AI12: 30 | AJ12: 30 | AK12: 60 | AL12: 60 | AN12: 132197 | AO12: 0005 | AP12: 2014 | AQ12: 2348 | AR12: авг.25 | AS12: 30 | AT12: 30 | AU12: 58 | AV12: 58 | AX12: 389220 | AY12: 0005 | AZ12: 2013 | BA12: 2348 | BB12: авг.25 | BC12: 30 | BD12: 30 | BE12: 59 | BF12: 58 | BH12: 34861 | BI12: 0005 | BJ12: 2014 | BN12: 35626 | BO12: 0005 | BP12: 2014 | BT12: 920 | BU12: 0005 | BV12: 2015 | BZ12: 1398 | CA12: 0005 | CB12: 2015 | CF12: 1466 | CG12: 0005 | CH12: 2015 | CL12: 1898 | CM12: 0005 | CN12: 2015
A13: 77221810 | B13: Цистерна для перевозки продуктов | C13: 15-5103-7П | D13: 06.09.2011 | E13: 2011 | F13: 06.09.2043 | G13: 21.12.2022 | H13: ВЧДР Ульяновск – ОСП АО "ОМК Стальной путь" | I13: 21.08.2025 | J13: ВРЗ Челябинск – филиал ООО "НВК" | K13: Деповской | L13: 21.08.2028 | M13: ООО "ТрансАльянс Запад" | N13: 160000 | O13: 36954 | P13: 123046 | Q13: 19.08.2029 | R13: 21.08.2025 | T13: 387818 | U13: 0005 | V13: 2013 | W13: 600 | X13: авг.25 | Y13: 33 | Z13: 33 | AA13: 71 | AB13: 70 | AD13: 285936 | AE13: 0005 | AF13: 2011 | AG13: 600 | AH13: авг.25 | AI13: 33 | AJ13: 33 | AK13: 74 | AL13: 74 | AN13: 144857 | AO13: 0005 | AP13: 2014 | AQ13: 600 | AR13: авг.25 | AS13: 33 | AT13: 33 | AU13: 71 | AV13: 71 | AX13: 285133 | AY13: 0005 | AZ13: 2011 | BA13: 600 | BB13: авг.25 | BC13: 33 | BD13: 33 | BE13: 73 | BF13: 73 | BH13: 38533 | BI13: 0005 | BJ13: 2011 | BN13: 38400 | BO13: 0005 | BP13: 2011 | BT13: 64559 | BU13: 0005 | BV13: 2011 | BZ13: 67459 | CA13: 0005 | CB13: 2011 | CF13: 67635 | CG13: 0005 | CH13: 2011 | CL13: 66238 | CM13: 0005 | CN13: 2011
A14: 77228724 | B14: Цистерна для перевозки продуктов | C14: 15-5103-7П | D14: 19.01.2015 | E14: 2015 | F14: 19.01.2047 | G14: 20.08.2025 | H14: Орский ВРЗ-филиал ООО "НВК" | K14: Капитальный | L14: 20.08.2028 | M14: ООО "ТрансАльянс Запад" | N14: 160000 | O14: 36244 | P14: 123756 | Q14: 20.09.2029 | R14: 20.08.2025 | T14: 300837 | U14: 0005 | V14: 2015 | W14: 2348 | X14: авг.25 | Y14: 30 | Z14: 30 | AA14: 47 | AB14: 47 | AD14: 303165 | AE14: 0005 | AF14: 2015 | AG14: 2348 | AH14: авг.25 | AI14: 30 | AJ14: 30 | AK14: 43 | AL14: 43 | AN14: 301420 | AO14: 0005 | AP14: 2015 | AQ14: 2348 | AR14: авг.25 | AS14: 30 | AT14: 30 | AU14: 41 | AV14: 41 | AX14: 207759 | AY14: 0005 | AZ14: 2014 | BA14: 2348 | BB14: авг.25 | BC14: 30 | BD14: 30 | BE14: 42 | BF14: 42 | BH14: 35428 | BI14: 0005 | BJ14: 2014 | BN14: 35655 | BO14: 0005 | BP14: 2014 | BT14: 2572 | BU14: 0005 | BV14: 2015 | BZ14: 1213 | CA14: 0005 | CB14: 2015 | CF14: 1582 | CG14: 0005 | CH14: 2015 | CL14: 1625 | CM14: 0005 | CN14: 2015
A15: 77222040 | B15: Цистерна для перевозки продуктов | C15: 15-150-04П | D15: 31.08.2011 | E15: 2011 | F15: 31.08.2043 | G15: 19.01.2023 | H15: ВРД Кочетовка – филиал ООО "НВК" | I15: 22.08.2025 | J15: ВРЗ Челябинск – филиал ООО "НВК" | K15: Деповской | L15: 22.08.2028 | M15: ООО "ТрансАльянс Запад" | N15: 160000 | O15: 36020 | P15: 123980 | Q15: 23.09.2029 | R15: 22.08.2025 | T15: 361758 | U15: 0005 | V15: 2013 | W15: 600 | X15: авг.25 | Y15: 29 | Z15: 29 | AA15: 64 | AB15: 63 | AD15: 283089 | AE15: 0005 | AF15: 2011 | AG15: 600 | AH15: авг.25 | AI15: 29 | AJ15: 29 | AK15: 66 | AL15: 67 | AN15: 361783 | AO15: 0005 | AP15: 2013 | AQ15: 600 | AR15: авг.25 | AS15: 29 | AT15: 29 | AU15: 67 | AV15: 67 | AX15: 178288 | AY15: 0005 | AZ15: 2014 | BA15: 600 | BB15: авг.25 | BC15: 29 | BD15: 29 | BE15: 68 | BF15: 68 | BH15: 37526 | BI15: 0005 | BJ15: 2011 | BN15: 36840 | BO15: 0005 | BP15: 2011 | BT15: 65174 | BU15: 0005 | BV15: 2011 | BZ15: 64960 | CA15: 0005 | CB15: 2011 | CF15: 66375 | CG15: 0005 | CH15: 2011 | CL15: 66315 | CM15: 0005 | CN15: 2011
A16: 77227080 | B16: Цистерна для перевозки продуктов | C16: 15-5103-7П | D16: 19.01.2012 | E16: 2012 | F16: 19.01.2044 | G16: 29.09.2022 | H16: ВЧД Унеча-ООО "НВК" | I16: 23.09.2025 | J16: ВРЗ Челябинск – филиал ООО "НВК" | K16: Деповской | L16: 23.09.2028 | M16: ООО "ТрансАльянс Запад" | N16: 160000 | O16: 42876 | P16: 117124 | Q16: 31.10.2028 | R16: 23.09.2025 | T16: 122882 | U16: 0005 | V16: 2012 | W16: 600 | X16: сен.25 | Y16: 29 | Z16: 29 | AA16: 71 | AB16: 71 | AD16: 123143 | AE16: 0005 | AF16: 2012 | AG16: 600 | AH16: сен.25 | AI16: 29 | AJ16: 29 | AK16: 71 | AL16: 71 | AN16: 305740 | AO16: 0005 | AP16: 2011 | AQ16: 600 | AR16: сен.25 | AS16: 29 | AT16: 29 | AU16: 72 | AV16: 71 | AX16: 315082 | AY16: 0005 | AZ16: 2011 | BA16: 600 | BB16: сен.25 | BC16: 29 | BD16: 29 | BE16: 72 | BF16: 73 | BH16: 49779 | BI16: 0005 | BJ16: 2011 | BN16: 3063 | BO16: 0005 | BP16: 2012 | BT16: 88660 | BU16: 0005 | BV16: 2011 | BZ16: 86578 | CA16: 0005 | CB16: 2011 | CF16: 95277 | CG16: 0005 | CH16: 2012 | CL16: 5895 | CM16: 0005 | CN16: 2012
A17: 77228773 | B17: Цистерна для перевозки продуктов | C17: 15-5103-7П | D17: 19.01.2015 | E17: 2015 | F17: 19.01.2047 | G17: 24.08.2025 | H17: Орский ВРЗ-филиал ООО "НВК" | K17: Капитальный | L17: 24.08.2028 | M17: ООО "ТрансАльянс Запад" | N17: 160000 | O17: 39135 | P17: 120865 | Q17: 21.05.2029 | R17: 24.08.2025 | T17: 975384 | U17: 0029 | V17: 2011 | W17: 2348 | X17: авг.25 | Y17: 30 | Z17: 30 | AA17: 53 | AB17: 51 | AD17: 26652 | AE17: 0039 | AF17: 2006 | AG17: 2348 | AH17: авг.25 | AI17: 30 | AJ17: 30 | AK17: 56 | AL17: 55 | AN17: 861974 | AO17: 0029 | AP17: 1990 | AQ17: 2348 | AR17: авг.25 | AS17: 30 | AT17: 30 | AU17: 58 | AV17: 58 | AX17: 108425 | AY17: 0005 | AZ17: 2006 | BA17: 2348 | BB17: авг.25 | BC17: 30 | BD17: 30 | BE17: 58 | BF17: 57 | BH17: 35195 | BI17: 0005 | BJ17: 2014 | BN17: 34646 | BO17: 0005 | BP17: 2014 | BT17: 69675 | BU17: 0005 | BV17: 2014 | BZ17: 69237 | CA17: 0005 | CB17: 2014 | CF17: 69365 | CG17: 0005 | CH17: 2014 | CL17: 69725 | CM17: 0005 | CN17: 2014
A18: 77221950 | B18: Цистерна для перевозки продуктов | C18: 15-150-04П | D18: 28.02.2012 | E18: 2012 | F18: 28.02.2044 | G18: 19.09.2022 | H18: ВРД Кочетовка – филиал ООО "НВК" | I18: 21.08.2025 | J18: ВРЗ Челябинск – филиал ООО "НВК" | K18: Деповской | L18: 21.08.2028 | M18: ООО "ТрансАльянс Запад" | N18: 160000 | O18: 34259 | P18: 125741 | Q18: 12.12.2029 | R18: 21.08.2025 | T18: 170868 | U18: 0005 | V18: 2007 | W18: 600 | X18: авг.25 | Y18: 33 | Z18: 33 | AA18: 73 | AB18: 73 | AD18: 151700 | AE18: 0029 | AF18: 1992 | AG18: 600 | AH18: авг.25 | AI18: 33 | AJ18: 33 | AK18: 74 | AL18: 74 | AN18: 122486 | AO18: 0005 | AP18: 2012 | AQ18: 600 | AR18: авг.25 | AS18: 33 | AT18: 33 | AU18: 74 | AV18: 74 | AX18: 123286 | AY18: 0005 | AZ18: 2012 | BA18: 600 | BB18: авг.25 | BC18: 33 | BD18: 33 | BE18: 74 | BF18: 73 | BH18: 10219 | BI18: 0014 | BJ18: 2012 | BN18: 3246 | BO18: 0014 | BP18: 2012 | BT18: 10126 | BU18: 0014 | BV18: 2012 | BZ18: 504892 | CA18: 0014 | CB18: 2012 | CF18: 14196 | CG18: 0014 | CH18: 2012 | CL18: 306 | CM18: 0014 | CN18: 2012
A19: 77205664 | B19: Цистерна для перевозки продуктов | C19: 15-1755П | D19: 20.06.2013 | E19: 2013 | F19: 20.06.2043 | G19: 29.08.2025 | H19: Орский ВРЗ-филиал ООО "НВК" | I19: 27.01.2024 | J19: ВРЗ Челябинск – филиал ООО "НВК" | K19: Деповской | L19: 29.08.2027 | M19: ООО "ТрансАльянс Запад" | N19: 160000 | O19: 35111 | P19: 124889 | Q19: 06.10.2029 | R19: 29.08.2025 | T19: 442976 | U19: 0029 | V19: 2013 | W19: 2348 | X19: авг.25 | Y19: 33 | Z19: 33 | AA19: 74 | AB19: 74 | AD19: 459729 | AE19: 0029 | AF19: 2013 | AG19: 2348 | AH19: авг.25 | AI19: 33 | AJ19: 33 | AK19: 74 | AL19: 74 | AN19: 459998 | AO19: 0029 | AP19: 2013 | AQ19: 2348 | AR19: авг.25 | AS19: 33 | AT19: 33 | AU19: 74 | AV19: 74 | AX19: 459372 | AY19: 0029 | AZ19: 2013 | BA19: 2348 | BB19: авг.25 | BC19: 33 | BD19: 33 | BE19: 74 | BF19: 74 | BH19: 52104 | BI19: 1291 | BJ19: 2013 | BN19: 14349 | BO19: 1291 | BP19: 2013 | BT19: 37899 | BU19: 1291 | BV19: 2013 | BZ19: 38264 | CA19: 1291 | CB19: 2013 | CF19: 42407 | CG19: 1291 | CH19: 2013 | CL19: 42444 | CM19: 1291 | CN19: 2013
A20: 77205706 | B20: Цистерна для перевозки продуктов | C20: 15-1755П | D20: 20.06.2013 | E20: 2013 | F20: 20.06.2043 | G20: 06.09.2025 | H20: Орский ВРЗ-филиал ООО "НВК" | I20: 17.01.2024 | J20: ВЧД Унеча-ООО "НВК" | K20: Деповской | L20: 06.09.2027 | M20: ООО "ТрансАльянс Запад" | N20: 160000 | O20: 36116 | P20: 123884 | Q20: 29.07.2029 | R20: 06.09.2025 | T20: 369126 | U20: 0029 | V20: 2012 | W20: 2348 | X20: сен.25 | Y20: 30 | Z20: 30 | AA20: 55 | AB20: 55 | AD20: 51638 | AE20: 2412 | AF20: 2024 | AG20: 2348 | AH20: сен.25 | AI20: 30 | AJ20: 30 | AK20: 54 | AL20: 54 | AN20: 325321 | AO20: 0029 | AP20: 2012 | AQ20: 2348 | AR20: сен.25 | AS20: 30 | AT20: 30 | AU20: 48 | AV20: 48 | AX20: 308575 | AY20: 0029 | AZ20: 2012 | BA20: 2348 | BB20: сен.25 | BC20: 30 | BD20: 30 | BE20: 51 | BF20: 51 | BH20: 14317 | BI20: 1291 | BJ20: 2013 | BN20: 14674 | BO20: 1291 | BP20: 2013 | BT20: 42624 | BU20: 1291 | BV20: 2013 | BZ20: 40631 | CA20: 1291 | CB20: 2013 | CF20: 44747 | CG20: 1291 | CH20: 2013 | CL20: 44767 | CM20: 1291 | CN20: 2013
A21: 77205888 | B21: Цистерна для перевозки продуктов | C21: 15-1755П | D21: 20.06.2013 | E21: 2013 | F21: 20.06.2043 | G21: 24.08.2025 | H21: Орский ВРЗ-филиал ООО "НВК" | I21: 31.01.2024 | J21: ВРД Кочетовка – филиал ООО "НВК" | K21: Деповской | L21: 24.08.2027 | M21: ООО "ТрансАльянс Запад" | N21: 160000 | O21: 31425 | P21: 128575 | Q21: 21.04.2030 | R21: 24.08.2025 | T21: 444796 | U21: 0029 | V21: 2013 | W21: 2348 | X21: авг.25 | Y21: 30 | Z21: 30 | AA21: 62 | AB21: 61 | AD21: 443687 | AE21: 0029 | AF21: 2013 | AG21: 2348 | AH21: авг.25 | AI21: 30 | AJ21: 30 | AK21: 63 | AL21: 63 | AN21: 443345 | AO21: 0029 | AP21: 2013 | AQ21: 2348 | AR21: авг.25 | AS21: 30 | AT21: 30 | AU21: 59 | AV21: 59 | AX21: 455903 | AY21: 0029 | AZ21: 2013 | BA21: 2348 | BB21: авг.25 | BC21: 30 | BD21: 30 | BE21: 62 | BF21: 62 | BH21: 15045 | BI21: 1291 | BJ21: 2013 | BN21: 15233 | BO21: 1291 | BP21: 2013 | BT21: 44652 | BU21: 1291 | BV21: 2013 | BZ21: 44087 | CA21: 1291 | CB21: 2013 | CF21: 42795 | CG21: 1291 | CH21: 2013 | CL21: 42357 | CM21: 1291 | CN21: 2013
A22: 77221919 | B22: Цистерна для перевозки продуктов | C22: 15-5103-7П | D22: 06.09.2011 | E22: 2011 | F22: 06.09.2043 | G22: 20.02.2023 | H22: ВРД Кочетовка – филиал ООО "НВК" | I22: 02.02.2025 | J22: ВЧД Унеча-ООО "НВК" | K22: Деповской | L22: 02.02.2028 | M22: ООО "ТрансАльянс Запад" | N22: 160000 | O22: 45858 | P22: 114142 | Q22: 22.03.2030 | R22: 02.02.2025 | T22: 285774 | U22: 0005 | V22: 2011 | W22: 357 | X22: фев.25 | Y22: 33 | Z22: 33 | AA22: 74 | AB22: 74 | AD22: 285824 | AE22: 0005 | AF22: 2011 | AG22: 357 | AH22: фев.25 | AI22: 33 | AJ22: 33 | AK22: 73 | AL22: 73 | AN22: 180370 | AO22: 0005 | AP22: 2014 | AQ22: 357 | AR22: фев.25 | AS22: 33 | AT22: 33 | AU22: 73 | AV22: 73 | AX22: 286908 | AY22: 0005 | AZ22: 2011 | BA22: 357 | BB22: фев.25 | BC22: 33 | BD22: 33 | BE22: 73 | BF22: 73 | BH22: 38613 | BI22: 0005 | BJ22: 2011 | BN22: 38286 | BO22: 0005 | BP22: 2011 | BT22: 63621 | BU22: 0005 | BV22: 2011 | BZ22: 67432 | CA22: 0005 | CB22: 2011 | CF22: 67508 | CG22: 0005 | CH22: 2011 | CL22: 67584 | CM22: 0005 | CN22: 2011
A23: 77221844 | B23: Цистерна для перевозки продуктов | C23: 15-150-04П | D23: 31.08.2011 | E23: 2011 | F23: 31.08.2043 | G23: 18.02.2023 | H23: ВРД Кочетовка – филиал ООО "НВК" | I23: 26.03.2026 | J23: Усть-Каменогорское ВРД | K23: Деповской | L23: 26.03.2029 | M23: ООО "ТрансАльянс Запад" | N23: 160000 | O23: 8028 | P23: 151972 | Q23: 12.10.2032 | R23: 26.03.2026 | T23: 363178 | U23: 0005 | V23: 2013 | W23: 745 | X23: мар.26 | Y23: 0 | Z23: 0 | AA23: 73 | AB23: 73 | AD23: 285305 | AE23: 0005 | AF23: 2011 | AG23: 745 | AH23: мар.26 | AI23: 0 | AJ23: 0 | AK23: 73 | AL23: 73 | AN23: 282111 | AO23: 0005 | AP23: 2011 | AQ23: 745 | AR23: мар.26 | AS23: 0 | AT23: 0 | AU23: 72 | AV23: 72 | AX23: 285278 | AY23: 0005 | AZ23: 2011 | BA23: 745 | BB23: мар.26 | BC23: 0 | BD23: 0 | BE23: 73 | BF23: 73 | BH23: 37070 | BI23: 0005 | BJ23: 2011 | BN23: 37413 | BO23: 0005 | BP23: 2011 | BT23: 66136 | BU23: 0005 | BV23: 2011 | BZ23: 65255 | CA23: 0005 | CB23: 2011 | CF23: 66052 | CG23: 0005 | CH23: 2011 | CL23: 63648 | CM23: 0005 | CN23: 2011
A24: 75183491 | B24: Цистерна для перевозки продуктов | C24: 15-1219-1П | D24: 08.10.2020 | E24: 2020 | F24: 08.10.2050 | G24: 30.10.2025 | H24: ВРД Зелецино - филиал ООО "НВК" | K24: Деповской | L24: 30.10.2027 | M24: ООО "ТрансАльянс Запад" | N24: 160000 | O24: 25151 | P24: 134849 | Q24: 25.06.2030 | R24: 30.10.2025 | T24: 12278 | U24: 2002 | V24: 2020 | W24: 1173 | X24: окт.25 | Y24: 30 | Z24: 30 | AA24: 50 | AB24: 52 | AD24: 446185 | AE24: 0005 | AF24: 2020 | AG24: 1173 | AH24: окт.25 | AI24: 30 | AJ24: 30 | AK24: 43 | AL24: 45 | AN24: 446107 | AO24: 0005 | AP24: 2020 | AQ24: 1173 | AR24: окт.25 | AS24: 30 | AT24: 30 | AU24: 51 | AV24: 53 | AX24: 446117 | AY24: 0005 | AZ24: 2020 | BA24: 1173 | BB24: окт.25 | BC24: 30 | BD24: 29 | BE24: 53 | BF24: 55 | BH24: 27363 | BI24: 1275 | BJ24: 2020 | BN24: 27358 | BO24: 1275 | BP24: 2020 | BT24: 45585 | BU24: 1275 | BV24: 2020 | BZ24: 45569 | CA24: 1275 | CB24: 2020 | CF24: 41311 | CG24: 1275 | CH24: 2020 | CL24: 45586 | CM24: 1275 | CN24: 2020
A25: 75184093 | B25: Цистерна для перевозки продуктов | C25: 15-1219-1П | D25: 08.10.2020 | E25: 2020 | F25: 08.10.2050 | G25: 19.10.2025 | H25: ВРД Зелецино - филиал ООО "НВК" | K25: Деповской | L25: 19.10.2027 | M25: ООО "ТрансАльянс Запад" | N25: 160000 | O25: 26103 | P25: 133897 | Q25: 19.06.2030 | R25: 19.10.2025 | T25: 735030 | U25: 0029 | V25: 2020 | W25: 1173 | X25: окт.25 | Y25: 30 | Z25: 30 | AA25: 61 | AB25: 60 | AD25: 753604 | AE25: 0029 | AF25: 2020 | AG25: 1173 | AH25: окт.25 | AI25: 29 | AJ25: 29 | AK25: 59 | AL25: 61 | AN25: 448491 | AO25: 0005 | AP25: 2020 | AQ25: 1173 | AR25: окт.25 | AS25: 29 | AT25: 29 | AU25: 56 | AV25: 54 | AX25: 449053 | AY25: 0005 | AZ25: 2020 | BA25: 1173 | BB25: окт.25 | BC25: 29 | BD25: 30 | BE25: 61 | BF25: 62 | BH25: 27088 | BI25: 1275 | BJ25: 2020 | BN25: 27518 | BO25: 1275 | BP25: 2020 | BT25: 46122 | BU25: 1275 | BV25: 2020 | BZ25: 45988 | CA25: 1275 | CB25: 2020 | CF25: 44631 | CG25: 1275 | CH25: 2020 | CL25: 45967 | CM25: 1275 | CN25: 2020
A26: 75184598 | B26: Цистерна для перевозки продуктов | C26: 15-1219-1П | D26: 08.10.2020 | E26: 2020 | F26: 08.10.2050 | G26: 22.09.2025 | H26: ВРД Зелецино - филиал ООО "НВК" | K26: Деповской | L26: 22.09.2027 | M26: ООО "ТрансАльянс Запад" | N26: 160000 | O26: 19620 | P26: 140380 | Q26: 14.07.2032 | R26: 22.09.2025 | T26: 741894 | U26: 0029 | V26: 2020 | W26: 1173 | X26: сен.25 | Y26: 29 | Z26: 30 | AA26: 57 | AB26: 56 | AD26: 12169 | AE26: 2002 | AF26: 2020 | AG26: 1173 | AH26: сен.25 | AI26: 30 | AJ26: 30 | AK26: 58 | AL26: 58 | AN26: 12264 | AO26: 2002 | AP26: 2020 | AQ26: 1173 | AR26: сен.25 | AS26: 30 | AT26: 30 | AU26: 58 | AV26: 60 | AX26: 742389 | AY26: 0029 | AZ26: 2020 | BA26: 1173 | BB26: сен.25 | BC26: 30 | BD26: 30 | BE26: 64 | BF26: 64 | BH26: 27548 | BI26: 1275 | BJ26: 2020 | BN26: 25966 | BO26: 1275 | BP26: 2020 | BT26: 46331 | BU26: 1275 | BV26: 2020 | BZ26: 46029 | CA26: 1275 | CB26: 2020 | CF26: 46344 | CG26: 1275 | CH26: 2020 | CL26: 46300 | CM26: 1275 | CN26: 2020
A27: 75186890 | B27: Цистерна для перевозки продуктов | C27: 15-1219-1П | D27: 14.10.2020 | E27: 2020 | F27: 14.10.2050 | G27: 10.12.2025 | H27: ВРД Зелецино - филиал ООО "НВК" | K27: Деповской | L27: 10.12.2027 | M27: ООО "ТрансАльянс Запад" | N27: 160000 | O27: 27005 | P27: 132995 | Q27: 10.08.2029 | R27: 10.12.2025 | T27: 751445 | U27: 0029 | V27: 2020 | W27: 1173 | X27: дек.25 | Y27: 30 | Z27: 29 | AA27: 64 | AB27: 65 | AD27: 749474 | AE27: 0029 | AF27: 2020 | AG27: 1173 | AH27: дек.25 | AI27: 29 | AJ27: 30 | AK27: 68 | AL27: 68 | AN27: 753559 | AO27: 0029 | AP27: 2020 | AQ27: 1173 | AR27: дек.25 | AS27: 29 | AT27: 29 | AU27: 55 | AV27: 55 | AX27: 753540 | AY27: 0029 | AZ27: 2020 | BA27: 1173 | BB27: дек.25 | BC27: 30 | BD27: 30 | BE27: 63 | BF27: 62 | BH27: 25753 | BI27: 1275 | BJ27: 2020 | BN27: 25641 | BO27: 1275 | BP27: 2020 | BT27: 41210 | BU27: 1275 | BV27: 2020 | BZ27: 42182 | CA27: 1275 | CB27: 2020 | CF27: 42410 | CG27: 1275 | CH27: 2020 | CL27: 42415 | CM27: 1275 | CN27: 2020
A28: 75186999 | B28: Цистерна для перевозки продуктов | C28: 15-1219-1П | D28: 14.10.2020 | E28: 2020 | F28: 14.10.2050 | G28: 23.10.2025 | H28: ВРД Зелецино - филиал ООО "НВК" | K28: Деповской | L28: 23.10.2027 | M28: ООО "ТрансАльянс Запад" | N28: 160000 | O28: 26045 | P28: 133955 | Q28: 02.06.2030 | R28: 23.10.2025 | T28: 748958 | U28: 0029 | V28: 2020 | W28: 1173 | X28: окт.25 | Y28: 30 | Z28: 30 | AA28: 62 | AB28: 63 | AD28: 749500 | AE28: 0029 | AF28: 2020 | AG28: 1173 | AH28: окт.25 | AI28: 30 | AJ28: 30 | AK28: 62 | AL28: 62 | AN28: 751448 | AO28: 0029 | AP28: 2020 | AQ28: 1173 | AR28: окт.25 | AS28: 30 | AT28: 30 | AU28: 62 | AV28: 62 | AX28: 751392 | AY28: 0029 | AZ28: 2020 | BA28: 1173 | BB28: окт.25 | BC28: 30 | BD28: 30 | BE28: 63 | BF28: 64 | BH28: 27596 | BI28: 1275 | BJ28: 2020 | BN28: 27613 | BO28: 1275 | BP28: 2020 | BT28: 37202 | BU28: 1275 | BV28: 2020 | BZ28: 41164 | CA28: 1275 | CB28: 2020 | CF28: 41074 | CG28: 1275 | CH28: 2020 | CL28: 41622 | CM28: 1275 | CN28: 2020
A29: 75187294 | B29: Цистерна для перевозки продуктов | C29: 15-1219-1П | D29: 14.10.2020 | E29: 2020 | F29: 14.10.2050 | G29: 25.11.2025 | H29: ВРД Зелецино - филиал ООО "НВК" | K29: Деповской | L29: 25.11.2027 | M29: ООО "ТрансАльянс Запад" | N29: 160000 | O29: 23948 | P29: 136052 | Q29: 23.04.2030 | R29: 25.11.2025 | T29: 9889 | U29: 2002 | V29: 2020 | W29: 1173 | X29: ноя.25 | Y29: 29 | Z29: 30 | AA29: 58 | AB29: 57 | AD29: 9611 | AE29: 2002 | AF29: 2020 | AG29: 1173 | AH29: ноя.25 | AI29: 30 | AJ29: 29 | AK29: 56 | AL29: 56 | AN29: 751708 | AO29: 0029 | AP29: 2020 | AQ29: 1173 | AR29: ноя.25 | AS29: 29 | AT29: 29 | AU29: 59 | AV29: 60 | AX29: 448991 | AY29: 0005 | AZ29: 2020 | BA29: 1173 | BB29: ноя.25 | BC29: 30 | BD29: 30 | BE29: 62 | BF29: 61 | BH29: 27641 | BI29: 1275 | BJ29: 2020 | BN29: 27401 | BO29: 1275 | BP29: 2020 | BT29: 45594 | BU29: 1275 | BV29: 2020 | BZ29: 44524 | CA29: 1275 | CB29: 2020 | CF29: 45667 | CG29: 1275 | CH29: 2020 | CL29: 46138 | CM29: 1275 | CN29: 2020
A30: 75187898 | B30: Цистерна для перевозки продуктов | C30: 15-1219-1П | D30: 14.10.2020 | E30: 2020 | F30: 14.10.2050 | G30: 22.09.2025 | H30: ВРД Зелецино - филиал ООО "НВК" | K30: Деповской | L30: 22.09.2027 | M30: ООО "ТрансАльянс Запад" | N30: 160000 | O30: 19964 | P30: 140036 | Q30: 01.06.2032 | R30: 22.09.2025 | T30: 749590 | U30: 0029 | V30: 2020 | W30: 1173 | X30: сен.25 | Y30: 30 | Z30: 29 | AA30: 56 | AB30: 56 | AD30: 749499 | AE30: 0029 | AF30: 2020 | AG30: 1173 | AH30: сен.25 | AI30: 29 | AJ30: 29 | AK30: 63 | AL30: 63 | AN30: 751805 | AO30: 0029 | AP30: 2020 | AQ30: 1173 | AR30: сен.25 | AS30: 30 | AT30: 30 | AU30: 63 | AV30: 63 | AX30: 9731 | AY30: 2002 | AZ30: 2020 | BA30: 1173 | BB30: сен.25 | BC30: 30 | BD30: 29 | BE30: 64 | BF30: 64 | BH30: 27717 | BI30: 1275 | BJ30: 2020 | BN30: 27757 | BO30: 1275 | BP30: 2020 | BT30: 45607 | BU30: 1275 | BV30: 2020 | BZ30: 46549 | CA30: 1275 | CB30: 2020 | CF30: 46616 | CG30: 1275 | CH30: 2020 | CL30: 46475 | CM30: 1275 | CN30: 2020
A31: 75188094 | B31: Цистерна для перевозки продуктов | C31: 15-1219-1П | D31: 14.10.2020 | E31: 2020 | F31: 14.10.2050 | G31: 21.12.2025 | H31: ВРД Зелецино - филиал ООО "НВК" | K31: Деповской | L31: 21.12.2027 | M31: ООО "ТрансАльянс Запад" | N31: 160000 | O31: 19853 | P31: 140147 | Q31: 19.09.2030 | R31: 21.12.2025 | T31: 447880 | U31: 0005 | V31: 2020 | W31: 1173 | X31: дек.25 | Y31: 30 | Z31: 31 | AA31: 63 | AB31: 64 | AD31: 749336 | AE31: 0029 | AF31: 2020 | AG31: 1173 | AH31: дек.25 | AI31: 31 | AJ31: 31 | AK31: 63 | AL31: 63 | AN31: 448054 | AO31: 0005 | AP31: 2020 | AQ31: 1173 | AR31: дек.25 | AS31: 30 | AT31: 30 | AU31: 63 | AV31: 61 | AX31: 447874 | AY31: 0005 | AZ31: 2020 | BA31: 1173 | BB31: дек.25 | BC31: 30 | BD31: 30 | BE31: 62 | BF31: 62 | BH31: 27656 | BI31: 1275 | BJ31: 2020 | BN31: 27645 | BO31: 1275 | BP31: 2020 | BT31: 45699 | BU31: 1275 | BV31: 2020 | BZ31: 45957 | CA31: 1275 | CB31: 2020 | CF31: 46542 | CG31: 1275 | CH31: 2020 | CL31: 46234 | CM31: 1275 | CN31: 2020
A32: 75188292 | B32: Цистерна для перевозки продуктов | C32: 15-1219-1П | D32: 14.10.2020 | E32: 2020 | F32: 14.10.2050 | G32: 30.09.2025 | H32: ВРД Зелецино - филиал ООО "НВК" | K32: Деповской | L32: 30.09.2027 | M32: ООО "ТрансАльянс Запад" | N32: 160000 | O32: 27206 | P32: 132794 | Q32: 13.07.2030 | R32: 30.09.2025 | T32: 749620 | U32: 0029 | V32: 2020 | W32: 1173 | X32: сен.25 | Y32: 30 | Z32: 30 | AA32: 59 | AB32: 61 | AD32: 12219 | AE32: 2002 | AF32: 2020 | AG32: 1173 | AH32: сен.25 | AI32: 30 | AJ32: 30 | AK32: 62 | AL32: 60 | AN32: 749442 | AO32: 0029 | AP32: 2020 | AQ32: 1173 | AR32: сен.25 | AS32: 30 | AT32: 30 | AU32: 61 | AV32: 59 | AX32: 751928 | AY32: 0029 | AZ32: 2020 | BA32: 1173 | BB32: сен.25 | BC32: 30 | BD32: 30 | BE32: 61 | BF32: 63 | BH32: 27727 | BI32: 1275 | BJ32: 2020 | BN32: 27753 | BO32: 1275 | BP32: 2020 | BT32: 46593 | BU32: 1275 | BV32: 2020 | BZ32: 46587 | CA32: 1275 | CB32: 2020 | CF32: 44783 | CG32: 1275 | CH32: 2020 | CL32: 45764 | CM32: 1275 | CN32: 2020
A33: 75188599 | B33: Цистерна для перевозки продуктов | C33: 15-1219-1П | D33: 14.10.2020 | E33: 2020 | F33: 14.10.2050 | G33: 13.09.2025 | H33: ВРД Зелецино - филиал ООО "НВК" | K33: Деповской | L33: 13.09.2027 | M33: ООО "ТрансАльянс Запад" | N33: 160000 | O33: 33128 | P33: 126872 | Q33: 08.11.2029 | R33: 13.09.2025 | T33: 9849 | U33: 2002 | V33: 2020 | W33: 1173 | X33: сен.25 | Y33: 30 | Z33: 31 | AA33: 63 | AB33: 64 | AD33: 751713 | AE33: 0029 | AF33: 2020 | AG33: 1173 | AH33: сен.25 | AI33: 30 | AJ33: 31 | AK33: 62 | AL33: 63 | AN33: 749420 | AO33: 0029 | AP33: 2020 | AQ33: 1173 | AR33: сен.25 | AS33: 31 | AT33: 30 | AU33: 63 | AV33: 64 | AX33: 749361 | AY33: 0029 | AZ33: 2020 | BA33: 1173 | BB33: сен.25 | BC33: 31 | BD33: 30 | BE33: 61 | BF33: 61 | BH33: 23094 | BI33: 1275 | BJ33: 2020 | BN33: 23233 | BO33: 1275 | BP33: 2020 | BT33: 46846 | BU33: 1275 | BV33: 2020 | BZ33: 46809 | CA33: 1275 | CB33: 2020 | CF33: 46823 | CG33: 1275 | CH33: 2020 | CL33: 46521 | CM33: 1275 | CN33: 2020
A34: 75188797 | B34: Цистерна для перевозки продуктов | C34: 15-1219-1П | D34: 14.10.2020 | E34: 2020 | F34: 14.10.2050 | G34: 26.11.2025 | H34: ВРД Кочетовка – филиал ООО "НВК" | K34: Деповской | L34: 26.11.2027 | M34: ООО "ТрансАльянс Запад" | N34: 160000 | O34: 18972 | P34: 141028 | Q34: 12.06.2031 | R34: 26.11.2025 | T34: 749444 | U34: 0029 | V34: 2020 | W34: 301 | X34: ноя.25 | Y34: 31 | Z34: 31 | AA34: 57 | AB34: 57 | AD34: 748962 | AE34: 0029 | AF34: 2020 | AG34: 301 | AH34: ноя.25 | AI34: 31 | AJ34: 31 | AK34: 55 | AL34: 55 | AN34: 445133 | AO34: 0005 | AP34: 2020 | AQ34: 301 | AR34: ноя.25 | AS34: 30 | AT34: 30 | AU34: 58 | AV34: 58 | AX34: 748715 | AY34: 0029 | AZ34: 2020 | BA34: 301 | BB34: ноя.25 | BC34: 31 | BD34: 31 | BE34: 61 | BF34: 61 | BH34: 27666 | BI34: 1275 | BJ34: 2020 | BN34: 27662 | BO34: 1275 | BP34: 2020 | BT34: 45856 | BU34: 1275 | BV34: 2020 | BZ34: 45679 | CA34: 1275 | CB34: 2020 | CF34: 45971 | CG34: 1275 | CH34: 2020 | CL34: 45819 | CM34: 1275 | CN34: 2020
A35: 75188995 | B35: Цистерна для перевозки продуктов | C35: 15-1219-1П | D35: 14.10.2020 | E35: 2020 | F35: 14.10.2050 | G35: 29.10.2025 | H35: ВРД Зелецино - филиал ООО "НВК" | K35: Деповской | L35: 29.10.2027 | M35: ООО "ТрансАльянс Запад" | N35: 160000 | O35: 25200 | P35: 134800 | Q35: 27.06.2030 | R35: 29.10.2025 | T35: 749353 | U35: 0029 | V35: 2020 | W35: 1173 | X35: окт.25 | Y35: 29 | Z35: 30 | AA35: 63 | AB35: 64 | AD35: 748973 | AE35: 0029 | AF35: 2020 | AG35: 1173 | AH35: окт.25 | AI35: 30 | AJ35: 30 | AK35: 60 | AL35: 60 | AN35: 749282 | AO35: 0029 | AP35: 2020 | AQ35: 1173 | AR35: окт.25 | AS35: 30 | AT35: 30 | AU35: 65 | AV35: 67 | AX35: 749194 | AY35: 0029 | AZ35: 2020 | BA35: 1173 | BB35: окт.25 | BC35: 30 | BD35: 30 | BE35: 60 | BF35: 60 | BH35: 27405 | BI35: 1275 | BJ35: 2020 | BN35: 27580 | BO35: 1275 | BP35: 2020 | BT35: 45906 | BU35: 1275 | BV35: 2020 | BZ35: 46466 | CA35: 1275 | CB35: 2020 | CF35: 46415 | CG35: 1275 | CH35: 2020 | CL35: 46290 | CM35: 1275 | CN35: 2020
A36: 75183293 | B36: Цистерна для перевозки продуктов | C36: 15-1219-1П | D36: 08.10.2020 | E36: 2020 | F36: 08.10.2050 | G36: 12.01.2026 | H36: ВРД Зелецино - филиал ООО "НВК" | K36: Деповской | L36: 12.01.2028 | M36: ООО "ТрансАльянс Запад" | N36: 160000 | O36: 17120 | P36: 142880 | Q36: 21.12.2030 | R36: 12.01.2026 | T36: 751278 | U36: 0029 | V36: 2020 | W36: 1173 | X36: янв.26 | Y36: 30 | Z36: 30 | AA36: 57 | AB36: 58 | AD36: 742771 | AE36: 0029 | AF36: 2020 | AG36: 1173 | AH36: янв.26 | AI36: 29 | AJ36: 29 | AK36: 54 | AL36: 55 | AN36: 12260 | AO36: 2002 | AP36: 2020 | AQ36: 1173 | AR36: янв.26 | AS36: 30 | AT36: 29 | AU36: 59 | AV36: 60 | AX36: 447596 | AY36: 0005 | AZ36: 2020 | BA36: 1173 | BB36: янв.26 | BC36: 30 | BD36: 29 | BE36: 64 | BF36: 64 | BH36: 27347 | BI36: 1275 | BJ36: 2020 | BN36: 27188 | BO36: 1275 | BP36: 2020 | BT36: 45670 | BU36: 1275 | BV36: 2020 | BZ36: 45653 | CA36: 1275 | CB36: 2020 | CF36: 45557 | CG36: 1275 | CH36: 2020 | CL36: 45619 | CM36: 1275 | CN36: 2020
A37: 75176891 | B37: Цистерна для перевозки продуктов | C37: 15-1219-1П | D37: 05.10.2020 | E37: 2020 | F37: 05.10.2050 | G37: 23.11.2025 | H37: ВРД Зелецино - филиал ООО "НВК" | K37: Деповской | L37: 23.11.2027 | M37: ООО "ТрансАльянс Запад" | N37: 160000 | O37: 22364 | P37: 137636 | Q37: 28.08.2030 | R37: 23.11.2025 | T37: 742452 | U37: 0029 | V37: 2020 | W37: 1173 | X37: ноя.25 | Y37: 30 | Z37: 30 | AA37: 56 | AB37: 55 | AD37: 751460 | AE37: 0029 | AF37: 2020 | AG37: 1173 | AH37: ноя.25 | AI37: 29 | AJ37: 29 | AK37: 49 | AL37: 47 | AN37: 742779 | AO37: 0029 | AP37: 2020 | AQ37: 1173 | AR37: ноя.25 | AS37: 31 | AT37: 29 | AU37: 57 | AV37: 56 | AX37: 751528 | AY37: 0029 | AZ37: 2020 | BA37: 1173 | BB37: ноя.25 | BC37: 30 | BD37: 30 | BE37: 56 | BF37: 57 | BH37: 27175 | BI37: 1275 | BJ37: 2020 | BN37: 27187 | BO37: 1275 | BP37: 2020 | BT37: 45138 | BU37: 1275 | BV37: 2020 | BZ37: 45271 | CA37: 1275 | CB37: 2020 | CF37: 45205 | CG37: 1275 | CH37: 2020 | CL37: 45137 | CM37: 1275 | CN37: 2020
A38: 75176990 | B38: Цистерна для перевозки продуктов | C38: 15-1219-1П | D38: 05.10.2020 | E38: 2020 | F38: 05.10.2050 | G38: 13.09.2025 | H38: ВРД Зелецино - филиал ООО "НВК" | K38: Деповской | L38: 13.09.2027 | M38: ООО "ТрансАльянс Запад" | N38: 160000 | O38: 26672 | P38: 133328 | Q38: 10.11.2030 | R38: 13.09.2025 | T38: 742426 | U38: 0029 | V38: 2020 | W38: 1173 | X38: сен.25 | Y38: 30 | Z38: 30 | AA38: 57 | AB38: 59 | AD38: 751754 | AE38: 0029 | AF38: 2020 | AG38: 1173 | AH38: сен.25 | AI38: 30 | AJ38: 30 | AK38: 56 | AL38: 56 | AN38: 744464 | AO38: 0029 | AP38: 2020 | AQ38: 1173 | AR38: сен.25 | AS38: 30 | AT38: 30 | AU38: 56 | AV38: 58 | AX38: 744583 | AY38: 0029 | AZ38: 2020 | BA38: 1173 | BB38: сен.25 | BC38: 30 | BD38: 30 | BE38: 52 | BF38: 54 | BH38: 26695 | BI38: 1275 | BJ38: 2020 | BN38: 26351 | BO38: 1275 | BP38: 2020 | BT38: 44801 | BU38: 1275 | BV38: 2020 | BZ38: 45001 | CA38: 1275 | CB38: 2020 | CF38: 44499 | CG38: 1275 | CH38: 2020 | CL38: 45014 | CM38: 1275 | CN38: 2020
A39: 75182998 | B39: Цистерна для перевозки продуктов | C39: 15-1219-1П | D39: 08.10.2020 | E39: 2020 | F39: 08.10.2050 | G39: 14.10.2025 | H39: ВРД Зелецино - филиал ООО "НВК" | K39: Деповской | L39: 14.10.2027 | M39: ООО "ТрансАльянс Запад" | N39: 160000 | O39: 25637 | P39: 134363 | Q39: 15.08.2030 | R39: 14.10.2025 | T39: 752092 | U39: 0029 | V39: 2020 | W39: 1173 | X39: окт.25 | Y39: 29 | Z39: 30 | AA39: 60 | AB39: 59 | AD39: 751519 | AE39: 0029 | AF39: 2020 | AG39: 1173 | AH39: окт.25 | AI39: 30 | AJ39: 29 | AK39: 61 | AL39: 62 | AN39: 448311 | AO39: 0005 | AP39: 2020 | AQ39: 1173 | AR39: окт.25 | AS39: 29 | AT39: 29 | AU39: 53 | AV39: 51 | AX39: 448225 | AY39: 0005 | AZ39: 2020 | BA39: 1173 | BB39: окт.25 | BC39: 29 | BD39: 29 | BE39: 58 | BF39: 60 | BH39: 27322 | BI39: 1275 | BJ39: 2020 | BN39: 27291 | BO39: 1275 | BP39: 2020 | BT39: 45376 | BU39: 1275 | BV39: 2020 | BZ39: 45446 | CA39: 1275 | CB39: 2020 | CF39: 43704 | CG39: 1275 | CH39: 2020 | CL39: 45053 | CM39: 1275 | CN39: 2020
A40: 75164996 | B40: Цистерна для перевозки продуктов | C40: 15-1219-1П | D40: 29.09.2020 | E40: 2020 | F40: 29.09.2050 | G40: 21.11.2025 | H40: ВРД Зелецино - филиал ООО "НВК" | K40: Деповской | L40: 21.11.2027 | M40: ООО "ТрансАльянс Запад" | N40: 160000 | O40: 22050 | P40: 137950 | Q40: 04.10.2030 | R40: 21.11.2025 | T40: 747301 | U40: 0029 | V40: 2020 | W40: 1173 | X40: ноя.25 | Y40: 29 | Z40: 30 | AA40: 60 | AB40: 58 | AD40: 731174 | AE40: 0029 | AF40: 2020 | AG40: 1173 | AH40: ноя.25 | AI40: 29 | AJ40: 30 | AK40: 51 | AL40: 52 | AN40: 731022 | AO40: 0029 | AP40: 2020 | AQ40: 1173 | AR40: ноя.25 | AS40: 30 | AT40: 29 | AU40: 60 | AV40: 61 | AX40: 749169 | AY40: 0029 | AZ40: 2020 | BA40: 1173 | BB40: ноя.25 | BC40: 29 | BD40: 29 | BE40: 60 | BF40: 60 | BH40: 26103 | BI40: 1275 | BJ40: 2020 | BN40: 26176 | BO40: 1275 | BP40: 2020 | BT40: 43735 | BU40: 1275 | BV40: 2020 | BZ40: 43314 | CA40: 1275 | CB40: 2020 | CF40: 43752 | CG40: 1275 | CH40: 2020 | CL40: 43860 | CM40: 1275 | CN40: 2020
A41: 75165399 | B41: Цистерна для перевозки продуктов | C41: 15-1219-1П | D41: 29.09.2020 | E41: 2020 | F41: 29.09.2050 | G41: 07.11.2025 | H41: ВРД Зелецино - филиал ООО "НВК" | K41: Деповской | L41: 07.11.2027 | M41: ООО "ТрансАльянс Запад" | N41: 160000 | O41: 25042 | P41: 134958 | Q41: 20.05.2030 | R41: 07.11.2025 | T41: 729623 | U41: 0029 | V41: 2020 | W41: 1173 | X41: ноя.25 | Y41: 30 | Z41: 29 | AA41: 55 | AB41: 54 | AD41: 445845 | AE41: 0005 | AF41: 2020 | AG41: 1173 | AH41: ноя.25 | AI41: 30 | AJ41: 29 | AK41: 55 | AL41: 55 | AN41: 446150 | AO41: 0005 | AP41: 2020 | AQ41: 1173 | AR41: ноя.25 | AS41: 31 | AT41: 31 | AU41: 60 | AV41: 61 | AX41: 729627 | AY41: 0029 | AZ41: 2020 | BA41: 1173 | BB41: ноя.25 | BC41: 31 | BD41: 31 | BE41: 64 | BF41: 62 | BH41: 26778 | BI41: 1275 | BJ41: 2020 | BN41: 26782 | BO41: 1275 | BP41: 2020 | BT41: 43830 | BU41: 1275 | BV41: 2020 | BZ41: 44399 | CA41: 1275 | CB41: 2020 | CF41: 44265 | CG41: 1275 | CH41: 2020 | CL41: 44424 | CM41: 1275 | CN41: 2020
A42: 75165498 | B42: Цистерна для перевозки продуктов | C42: 15-1219-1П | D42: 29.09.2020 | E42: 2020 | F42: 29.09.2050 | G42: 05.11.2025 | H42: ВРД Зелецино - филиал ООО "НВК" | K42: Деповской | L42: 05.11.2027 | M42: ООО "ТрансАльянс Запад" | N42: 160000 | O42: 22600 | P42: 137400 | Q42: 27.11.2030 | R42: 05.11.2025 | T42: 417555 | U42: 0005 | V42: 2020 | W42: 1173 | X42: ноя.25 | Y42: 30 | Z42: 32 | AA42: 56 | AB42: 58 | AD42: 419327 | AE42: 0005 | AF42: 2020 | AG42: 1173 | AH42: ноя.25 | AI42: 31 | AJ42: 30 | AK42: 60 | AL42: 60 | AN42: 419386 | AO42: 0005 | AP42: 2020 | AQ42: 1173 | AR42: ноя.25 | AS42: 30 | AT42: 30 | AU42: 61 | AV42: 61 | AX42: 419297 | AY42: 0005 | AZ42: 2020 | BA42: 1173 | BB42: ноя.25 | BC42: 30 | BD42: 31 | BE42: 61 | BF42: 62 | BH42: 26569 | BI42: 1275 | BJ42: 2020 | BN42: 25713 | BO42: 1275 | BP42: 2020 | BT42: 43821 | BU42: 1275 | BV42: 2020 | BZ42: 43795 | CA42: 1275 | CB42: 2020 | CF42: 43834 | CG42: 1275 | CH42: 2020 | CL42: 43861 | CM42: 1275 | CN42: 2020
A43: 75175091 | B43: Цистерна для перевозки продуктов | C43: 15-1219-1П | D43: 05.10.2020 | E43: 2020 | F43: 05.10.2050 | G43: 17.11.2025 | H43: ВРД Зелецино - филиал ООО "НВК" | K43: Деповской | L43: 17.11.2027 | M43: ООО "ТрансАльянс Запад" | N43: 160000 | O43: 28125 | P43: 131875 | Q43: 04.10.2029 | R43: 17.11.2025 | T43: 751152 | U43: 0029 | V43: 2020 | W43: 1173 | X43: ноя.25 | Y43: 29 | Z43: 29 | AA43: 62 | AB43: 63 | AD43: 749473 | AE43: 0029 | AF43: 2020 | AG43: 1173 | AH43: ноя.25 | AI43: 29 | AJ43: 29 | AK43: 60 | AL43: 60 | AN43: 751300 | AO43: 0029 | AP43: 2020 | AQ43: 1173 | AR43: ноя.25 | AS43: 29 | AT43: 29 | AU43: 62 | AV43: 61 | AX43: 445763 | AY43: 0005 | AZ43: 2020 | BA43: 1173 | BB43: ноя.25 | BC43: 31 | BD43: 30 | BE43: 57 | BF43: 56 | BH43: 26644 | BI43: 1275 | BJ43: 2020 | BN43: 26423 | BO43: 1275 | BP43: 2020 | BT43: 42771 | BU43: 1275 | BV43: 2020 | BZ43: 44277 | CA43: 1275 | CB43: 2020 | CF43: 40855 | CG43: 1275 | CH43: 2020 | CL43: 43683 | CM43: 1275 | CN43: 2020
A44: 75175497 | B44: Цистерна для перевозки продуктов | C44: 15-1219-1П | D44: 05.10.2020 | E44: 2020 | F44: 05.10.2050 | G44: 16.09.2025 | H44: ВРД Зелецино - филиал ООО "НВК" | K44: Деповской | L44: 16.09.2027 | M44: ООО "ТрансАльянс Запад" | N44: 160000 | O44: 24795 | P44: 135205 | Q44: 16.03.2031 | R44: 16.09.2025 | T44: 446050 | U44: 0005 | V44: 2020 | W44: 1173 | X44: сен.25 | Y44: 30 | Z44: 30 | AA44: 62 | AB44: 63 | AD44: 749521 | AE44: 0029 | AF44: 2020 | AG44: 1173 | AH44: сен.25 | AI44: 30 | AJ44: 30 | AK44: 63 | AL44: 63 | AN44: 446689 | AO44: 0005 | AP44: 2020 | AQ44: 1173 | AR44: сен.25 | AS44: 30 | AT44: 30 | AU44: 50 | AV44: 49 | AX44: 749562 | AY44: 0029 | AZ44: 2020 | BA44: 1173 | BB44: сен.25 | BC44: 30 | BD44: 30 | BE44: 56 | BF44: 57 | BH44: 26789 | BI44: 1275 | BJ44: 2020 | BN44: 26860 | BO44: 1275 | BP44: 2020 | BT44: 44431 | BU44: 1275 | BV44: 2020 | BZ44: 44477 | CA44: 1275 | CB44: 2020 | CF44: 37781 | CG44: 1275 | CH44: 2020 | CL44: 37564 | CM44: 1275 | CN44: 2020
A45: 75176297 | B45: Цистерна для перевозки продуктов | C45: 15-1219-1П | D45: 05.10.2020 | E45: 2020 | F45: 05.10.2050 | G45: 08.12.2025 | H45: ВРД Зелецино - филиал ООО "НВК" | K45: Деповской | L45: 08.12.2027 | M45: ООО "ТрансАльянс Запад" | N45: 160000 | O45: 27046 | P45: 132954 | Q45: 18.08.2029 | R45: 08.12.2025 | T45: 749398 | U45: 0029 | V45: 2020 | W45: 1173 | X45: дек.25 | Y45: 33 | Z45: 33 | AA45: 59 | AB45: 60 | AD45: 742789 | AE45: 0029 | AF45: 2020 | AG45: 1173 | AH45: дек.25 | AI45: 30 | AJ45: 30 | AK45: 62 | AL45: 61 | AN45: 751490 | AO45: 0029 | AP45: 2020 | AQ45: 1173 | AR45: дек.25 | AS45: 30 | AT45: 30 | AU45: 54 | AV45: 55 | AX45: 741994 | AY45: 0029 | AZ45: 2020 | BA45: 1173 | BB45: дек.25 | BC45: 30 | BD45: 30 | BE45: 60 | BF45: 60 | BH45: 26904 | BI45: 1275 | BJ45: 2020 | BN45: 27057 | BO45: 1275 | BP45: 2020 | BT45: 44440 | BU45: 1275 | BV45: 2020 | BZ45: 44735 | CA45: 1275 | CB45: 2020 | CF45: 45061 | CG45: 1275 | CH45: 2020 | CL45: 45043 | CM45: 1275 | CN45: 2020
A46: 75176396 | B46: Цистерна для перевозки продуктов | C46: 15-1219-1П | D46: 05.10.2020 | E46: 2020 | F46: 05.10.2050 | G46: 31.08.2025 | H46: ВРД Зелецино - филиал ООО "НВК" | K46: Деповской | L46: 31.08.2027 | M46: ООО "ТрансАльянс Запад" | N46: 160000 | O46: 27142 | P46: 132858 | Q46: 11.12.2030 | R46: 31.08.2025 | T46: 742387 | U46: 0029 | V46: 2020 | W46: 1173 | X46: авг.25 | Y46: 30 | Z46: 29 | AA46: 54 | AB46: 53 | AD46: 742768 | AE46: 0029 | AF46: 2020 | AG46: 1173 | AH46: авг.25 | AI46: 29 | AJ46: 29 | AK46: 48 | AL46: 49 | AN46: 445844 | AO46: 0005 | AP46: 2020 | AQ46: 1173 | AR46: авг.25 | AS46: 29 | AT46: 29 | AU46: 62 | AV46: 62 | AX46: 744638 | AY46: 0029 | AZ46: 2020 | BA46: 1173 | BB46: авг.25 | BC46: 29 | BD46: 29 | BE46: 58 | BF46: 59 | BH46: 26982 | BI46: 1275 | BJ46: 2020 | BN46: 26935 | BO46: 1275 | BP46: 2020 | BT46: 44968 | BU46: 1275 | BV46: 2020 | BZ46: 44961 | CA46: 1275 | CB46: 2020 | CF46: 43936 | CG46: 1275 | CH46: 2020 | CL46: 45123 | CM46: 1275 | CN46: 2020
A47: 75163998 | B47: Цистерна для перевозки продуктов | C47: 15-1219-1П | D47: 29.09.2020 | E47: 2020 | F47: 29.09.2050 | G47: 14.11.2025 | H47: ВРД Зелецино - филиал ООО "НВК" | K47: Деповской | L47: 14.11.2027 | M47: ООО "ТрансАльянс Запад" | N47: 160000 | O47: 23923 | P47: 136077 | Q47: 26.06.2030 | R47: 14.11.2025 | T47: 444949 | U47: 0005 | V47: 2020 | W47: 1173 | X47: ноя.25 | Y47: 30 | Z47: 30 | AA47: 52 | AB47: 53 | AD47: 444991 | AE47: 0005 | AF47: 2020 | AG47: 1173 | AH47: ноя.25 | AI47: 30 | AJ47: 30 | AK47: 55 | AL47: 55 | AN47: 730979 | AO47: 0029 | AP47: 2020 | AQ47: 1173 | AR47: ноя.25 | AS47: 30 | AT47: 30 | AU47: 54 | AV47: 55 | AX47: 444811 | AY47: 0005 | AZ47: 2020 | BA47: 1173 | BB47: ноя.25 | BC47: 30 | BD47: 30 | BE47: 52 | BF47: 52 | BH47: 25643 | BI47: 1275 | BJ47: 2020 | BN47: 25444 | BO47: 1275 | BP47: 2020 | BT47: 42745 | BU47: 1275 | BV47: 2020 | BZ47: 43316 | CA47: 1275 | CB47: 2020 | CF47: 42892 | CG47: 1275 | CH47: 2020 | CL47: 42683 | CM47: 1275 | CN47: 2020
A48: 75164293 | B48: Цистерна для перевозки продуктов | C48: 15-1219-1П | D48: 29.09.2020 | E48: 2020 | F48: 29.09.2050 | G48: 26.08.2025 | H48: ВРД Зелецино - филиал ООО "НВК" | K48: Деповской | L48: 26.08.2027 | M48: ООО "ТрансАльянс Запад" | N48: 160000 | O48: 23036 | P48: 136964 | Q48: 19.12.2031 | R48: 21.04.2026 | T48: 746406 | U48: 0029 | V48: 2020 | W48: 9711 | X48: апр.26 | Y48: 0 | Z48: 0 | AA48: 54 | AB48: 53 | AD48: 730891 | AE48: 0029 | AF48: 2020 | AG48: 9711 | AH48: апр.26 | AI48: 0 | AJ48: 0 | AK48: 52 | AL48: 53 | AN48: 445003 | AO48: 0005 | AP48: 2020 | AQ48: 9711 | AR48: апр.26 | AS48: 0 | AT48: 0 | AU48: 62 | AV48: 63 | AX48: 444688 | AY48: 0005 | AZ48: 2020 | BA48: 9711 | BB48: апр.26 | BC48: 0 | BD48: 0 | BE48: 57 | BF48: 55 | BH48: 26384 | BI48: 1275 | BJ48: 2020 | BN48: 26403 | BO48: 1275 | BP48: 2020 | BT48: 42884 | BU48: 1275 | BV48: 2020 | BZ48: 42438 | CA48: 1275 | CB48: 2020 | CF48: 43127 | CG48: 1275 | CH48: 2020 | CL48: 43640 | CM48: 1275 | CN48: 2020
... A56: 75184697 | B56: Цистерна для перевозки продуктов | C56: 15-1219-1П | D56: 08.10.2020 | E56: 2020 | F56: 08.10.2050 | G56: 02.11.2025 | H56: ВРД Кочетовка – филиал ООО "НВК" | K56: Деповской | L56: 02.11.2027 | M56: ООО "ТрансАльянс Запад" | N56: 160000 | O56: 24389 | P56: 135611 | Q56: 31.07.2030 | R56: 02.11.2025 | T56: 448185 | U56: 0005 | V56: 2020 | W56: 301 | X56: ноя.25 | Y56: 31 | Z56: 31 | AA56: 63 | AB56: 63 | AD56: 151452 | AE56: 0029 | AF56: 2020 | AG56: 301 | AH56: ноя.25 | AI56: 32 | AJ56: 32 | AK56: 63 | AL56: 63 | AN56: 446166 | AO56: 0005 | AP56: 2020 | AQ56: 301 | AR56: ноя.25 | AS56: 30 | AT56: 30 | AU56: 63 | AV56: 63 | AX56: 744714 | AY56: 0029 | AZ56: 2020 | BA56: 301 | BB56: ноя.25 | BC56: 32 | BD56: 32 | BE56: 64 | BF56: 64 | BH56: 27485 | BI56: 1275 | BJ56: 2020 | BN56: 27636 | BO56: 1275 | BP56: 2020 | BT56: 46358 | BU56: 1275 | BV56: 2020 | BZ56: 45693 | CA56: 1275 | CB56: 2020 | CF56: 46379 | CG56: 1275 | CH56: 2020 | CL56: 46147 | CM56: 1275 | CN56: 2020
A57: 75183392 | B57: Цистерна для перевозки продуктов | C57: 15-1219-1П | D57: 08.10.2020 | E57: 2020 | F57: 08.10.2050 | G57: 02.11.2025 | H57: ВРД Кочетовка – филиал ООО "НВК" | K57: Деповской | L57: 02.11.2027 | M57: ООО "ТрансАльянс Запад" | N57: 160000 | O57: 27197 | P57: 132803 | Q57: 02.02.2030 | R57: 02.11.2025 | T57: 446706 | U57: 0005 | V57: 2020 | W57: 301 | X57: ноя.25 | Y57: 31 | Z57: 31 | AA57: 55 | AB57: 55 | AD57: 744703 | AE57: 0029 | AF57: 2020 | AG57: 301 | AH57: ноя.25 | AI57: 31 | AJ57: 31 | AK57: 61 | AL57: 61 | AN57: 446485 | AO57: 0005 | AP57: 2020 | AQ57: 301 | AR57: ноя.25 | AS57: 30 | AT57: 30 | AU57: 63 | AV57: 63 | AX57: 12291 | AY57: 2002 | AZ57: 2020 | BA57: 301 | BB57: ноя.25 | BC57: 30 | BD57: 30 | BE57: 65 | BF57: 65 | BH57: 27409 | BI57: 1275 | BJ57: 2020 | BN57: 27297 | BO57: 1275 | BP57: 2020 | BT57: 45643 | BU57: 1275 | BV57: 2020 | BZ57: 45648 | CA57: 1275 | CB57: 2020 | CF57: 44763 | CG57: 1275 | CH57: 2020 | CL57: 45664 | CM57: 1275 | CN57: 2020
A58: 75165092 | B58: Цистерна для перевозки продуктов | C58: 15-1219-1П | D58: 29.09.2020 | E58: 2020 | F58: 29.09.2050 | G58: 16.09.2025 | H58: ВРД Зелецино - филиал ООО "НВК" | K58: Деповской | L58: 16.09.2027 | M58: ООО "ТрансАльянс Запад" | N58: 160000 | O58: 28723 | P58: 131277 | Q58: 14.06.2030 | R58: 16.09.2025 | T58: 730973 | U58: 0029 | V58: 2020 | W58: 1173 | X58: сен.25 | Y58: 29 | Z58: 29 | AA58: 63 | AB58: 64 | AD58: 746788 | AE58: 0029 | AF58: 2020 | AG58: 1173 | AH58: сен.25 | AI58: 29 | AJ58: 30 | AK58: 63 | AL58: 63 | AN58: 746753 | AO58: 0029 | AP58: 2020 | AQ58: 1173 | AR58: сен.25 | AS58: 29 | AT58: 29 | AU58: 63 | AV58: 64 | AX58: 734696 | AY58: 0029 | AZ58: 2020 | BA58: 1173 | BB58: сен.25 | BC58: 29 | BD58: 29 | BE58: 63 | BF58: 62 | BH58: 26462 | BI58: 1275 | BJ58: 2020 | BN58: 26724 | BO58: 1275 | BP58: 2020 | BT58: 37203 | BU58: 1275 | BV58: 2020 | BZ58: 41890 | CA58: 1275 | CB58: 2020 | CF58: 41986 | CG58: 1275 | CH58: 2020 | CL58: 41900 | CM58: 1275 | CN58: 2020
A59: 75163899 | B59: Цистерна для перевозки продуктов | C59: 15-1219-1П | D59: 29.09.2020 | E59: 2020 | F59: 29.09.2050 | G59: 14.10.2025 | H59: ВРЗ Челябинск – филиал ООО "НВК" | K59: Деповской | L59: 14.10.2027 | M59: ООО "ТрансАльянс Запад" | N59: 160000 | O59: 26006 | P59: 133994 | Q59: 21.07.2030 | R59: 14.10.2025 | T59: 747121 | U59: 0029 | V59: 2020 | W59: 600 | X59: окт.25 | Y59: 30 | Z59: 30 | AA59: 47 | AB59: 47 | AD59: 444751 | AE59: 0005 | AF59: 2020 | AG59: 600 | AH59: окт.25 | AI59: 30 | AJ59: 30 | AK59: 54 | AL59: 53 | AN59: 745690 | AO59: 0029 | AP59: 2020 | AQ59: 600 | AR59: окт.25 | AS59: 30 | AT59: 30 | AU59: 58 | AV59: 59 | AX59: 731649 | AY59: 0029 | AZ59: 2020 | BA59: 600 | BB59: окт.25 | BC59: 30 | BD59: 30 | BE59: 62 | BF59: 62 | BH59: 26284 | BI59: 1275 | BJ59: 2020 | BN59: 26222 | BO59: 1275 | BP59: 2020 | BT59: 43522 | BU59: 1275 | BV59: 2020 | BZ59: 43061 | CA59: 1275 | CB59: 2020 | CF59: 43591 | CG59: 1275 | CH59: 2020 | CL59: 42700 | CM59: 1275 | CN59: 2020
A60: 75165191 | B60: Цистерна для перевозки продуктов | C60: 15-1219-1П | D60: 29.09.2020 | E60: 2020 | F60: 29.09.2050 | G60: 14.10.2025 | H60: ВРЗ Челябинск – филиал ООО "НВК" | K60: Деповской | L60: 14.10.2027 | M60: ООО "ТрансАльянс Запад" | N60: 160000 | O60: 22560 | P60: 137440 | Q60: 13.04.2031 | R60: 14.10.2025 | T60: 746993 | U60: 0029 | V60: 2020 | W60: 600 | X60: окт.25 | Y60: 30 | Z60: 30 | AA60: 54 | AB60: 54 | AD60: 733312 | AE60: 0029 | AF60: 2020 | AG60: 600 | AH60: окт.25 | AI60: 30 | AJ60: 30 | AK60: 56 | AL60: 56 | AN60: 733288 | AO60: 0029 | AP60: 2020 | AQ60: 600 | AR60: окт.25 | AS60: 30 | AT60: 30 | AU60: 57 | AV60: 57 | AX60: 731202 | AY60: 0029 | AZ60: 2020 | BA60: 600 | BB60: окт.25 | BC60: 30 | BD60: 30 | BE60: 57 | BF60: 57 | BH60: 25908 | BI60: 1275 | BJ60: 2020 | BN60: 25772 | BO60: 1275 | BP60: 2020 | BT60: 28960 | BU60: 1275 | BV60: 2020 | BZ60: 37655 | CA60: 1275 | CB60: 2020 | CF60: 39082 | CG60: 1275 | CH60: 2020 | CL60: 40830 | CM60: 1275 | CN60: 2020
A61: 75175596 | B61: Цистерна для перевозки продуктов | C61: 15-1219-1П | D61: 05.10.2020 | E61: 2020 | F61: 05.10.2050 | G61: 16.12.2025 | H61: ВРД Кочетовка – филиал ООО "НВК" | K61: Деповской | L61: 16.12.2027 | M61: ООО "ТрансАльянс Запад" | N61: 160000 | O61: 27733 | P61: 132267 | Q61: 07.06.2029 | R61: 16.12.2025 | T61: 419148 | U61: 0005 | V61: 2020 | W61: 301 | X61: дек.25 | Y61: 30 | Z61: 30 | AA61: 53 | AB61: 53 | AD61: 302292 | AE61: 0005 | AF61: 2019 | AG61: 301 | AH61: дек.25 | AI61: 30 | AJ61: 30 | AK61: 55 | AL61: 55 | AN61: 302540 | AO61: 0005 | AP61: 2019 | AQ61: 301 | AR61: дек.25 | AS61: 31 | AT61: 31 | AU61: 49 | AV61: 49 | AX61: 302301 | AY61: 0005 | AZ61: 2019 | BA61: 301 | BB61: дек.25 | BC61: 31 | BD61: 31 | BE61: 49 | BF61: 49 | BH61: 26604 | BI61: 1275 | BJ61: 2020 | BN61: 26376 | BO61: 1275 | BP61: 2020 | BT61: 44838 | BU61: 1275 | BV61: 2020 | BZ61: 44724 | CA61: 1275 | CB61: 2020 | CF61: 44690 | CG61: 1275 | CH61: 2020 | CL61: 44697 | CM61: 1275 | CN61: 2020
A62: 75187393 | B62: Цистерна для перевозки продуктов | C62: 15-1219-1П | D62: 14.10.2020 | E62: 2020 | F62: 14.10.2050 | G62: 27.11.2025 | H62: ВРД Зелецино - филиал ООО "НВК" | K62: Деповской | L62: 27.11.2027 | M62: ООО "ТрансАльянс Запад" | N62: 160000 | O62: 16855 | P62: 143145 | Q62: 13.02.2032 | R62: 27.11.2025 | T62: 447713 | U62: 0005 | V62: 2020 | W62: 1173 | X62: ноя.25 | Y62: 30 | Z62: 30 | AA62: 62 | AB62: 64 | AD62: 751815 | AE62: 0029 | AF62: 2020 | AG62: 1173 | AH62: ноя.25 | AI62: 29 | AJ62: 30 | AK62: 62 | AL62: 60 | AN62: 448186 | AO62: 0005 | AP62: 2020 | AQ62: 1173 | AR62: ноя.25 | AS62: 30 | AT62: 30 | AU62: 58 | AV62: 57 | AX62: 753569 | AY62: 0029 | AZ62: 2020 | BA62: 1173 | BB62: ноя.25 | BC62: 30 | BD62: 29 | BE62: 57 | BF62: 58 | BH62: 27644 | BI62: 1275 | BJ62: 2020 | BN62: 27566 | BO62: 1275 | BP62: 2020 | BT62: 45529 | BU62: 1275 | BV62: 2020 | BZ62: 46180 | CA62: 1275 | CB62: 2020 | CF62: 45672 | CG62: 1275 | CH62: 2020 | CL62: 46470 | CM62: 1275 | CN62: 2020
A63: 75188698 | B63: Цистерна для перевозки продуктов | C63: 15-1219-1П | D63: 14.10.2020 | E63: 2020 | F63: 14.10.2050 | G63: 23.09.2025 | H63: ВРД Зелецино - филиал ООО "НВК" | K63: Деповской | L63: 23.09.2027 | M63: ООО "ТрансАльянс Запад" | N63: 160000 | O63: 26582 | P63: 133418 | Q63: 27.09.2030 | R63: 23.09.2025 | T63: 749182 | U63: 0029 | V63: 2020 | W63: 1173 | X63: сен.25 | Y63: 29 | Z63: 29 | AA63: 63 | AB63: 63 | AD63: 749069 | AE63: 0029 | AF63: 2020 | AG63: 1173 | AH63: сен.25 | AI63: 30 | AJ63: 30 | AK63: 59 | AL63: 60 | AN63: 9773 | AO63: 2002 | AP63: 2020 | AQ63: 1173 | AR63: сен.25 | AS63: 29 | AT63: 30 | AU63: 58 | AV63: 60 | AX63: 444832 | AY63: 0005 | AZ63: 2020 | BA63: 1173 | BB63: сен.25 | BC63: 30 | BD63: 29 | BE63: 61 | BF63: 62 | BH63: 27629 | BI63: 1275 | BJ63: 2020 | BN63: 27618 | BO63: 1275 | BP63: 2020 | BT63: 45543 | BU63: 1275 | BV63: 2020 | BZ63: 46196 | CA63: 1275 | CB63: 2020 | CF63: 46115 | CG63: 1275 | CH63: 2020 | CL63: 46214 | CM63: 1275 | CN63: 2020
A64: 75165597 | B64: Цистерна для перевозки продуктов | C64: 15-1219-1П | D64: 29.09.2020 | E64: 2020 | F64: 29.09.2050 | G64: 28.11.2025 | H64: ВРД Зелецино - филиал ООО "НВК" | K64: Деповской | L64: 28.11.2027 | M64: ООО "ТрансАльянс Запад" | N64: 160000 | O64: 16761 | P64: 143239 | Q64: 17.02.2032 | R64: 28.11.2025 | T64: 419457 | U64: 0005 | V64: 2020 | W64: 1173 | X64: ноя.25 | Y64: 30 | Z64: 31 | AA64: 57 | AB64: 57 | AD64: 419207 | AE64: 0005 | AF64: 2020 | AG64: 1173 | AH64: ноя.25 | AI64: 30 | AJ64: 30 | AK64: 61 | AL64: 60 | AN64: 419383 | AO64: 0005 | AP64: 2020 | AQ64: 1173 | AR64: ноя.25 | AS64: 30 | AT64: 30 | AU64: 54 | AV64: 55 | AX64: 419427 | AY64: 0005 | AZ64: 2020 | BA64: 1173 | BB64: ноя.25 | BC64: 30 | BD64: 30 | BE64: 59 | BF64: 59 | BH64: 22856 | BI64: 1275 | BJ64: 2020 | BN64: 22560 | BO64: 1275 | BP64: 2020 | BT64: 43361 | BU64: 1275 | BV64: 2020 | BZ64: 43721 | CA64: 1275 | CB64: 2020 | CF64: 43172 | CG64: 1275 | CH64: 2020 | CL64: 43786 | CM64: 1275 | CN64: 2020
A65: 75164392 | B65: Цистерна для перевозки продуктов | C65: 15-1219-1П | D65: 29.09.2020 | E65: 2020 | F65: 29.09.2050 | G65: 15.01.2026 | H65: ВРД Зелецино - филиал ООО "НВК" | K65: Деповской | L65: 15.01.2028 | M65: ООО "ТрансАльянс Запад" | N65: 160000 | O65: 24113 | P65: 135887 | Q65: 29.06.2029 | R65: 15.01.2026 | T65: 746188 | U65: 0029 | V65: 2020 | W65: 1173 | X65: янв.26 | Y65: 29 | Z65: 30 | AA65: 59 | AB65: 59 | AD65: 728819 | AE65: 0029 | AF65: 2020 | AG65: 1173 | AH65: янв.26 | AI65: 30 | AJ65: 29 | AK65: 60 | AL65: 60 | AN65: 444912 | AO65: 0005 | AP65: 2020 | AQ65: 1173 | AR65: янв.26 | AS65: 30 | AT65: 29 | AU65: 56 | AV65: 56 | AX65: 747213 | AY65: 0029 | AZ65: 2020 | BA65: 1173 | BB65: янв.26 | BC65: 30 | BD65: 30 | BE65: 57 | BF65: 57 | BH65: 25993 | BI65: 1275 | BJ65: 2020 | BN65: 24731 | BO65: 1275 | BP65: 2020 | BT65: 42740 | BU65: 1275 | BV65: 2020 | BZ65: 43658 | CA65: 1275 | CB65: 2020 | CF65: 43451 | CG65: 1275 | CH65: 2020 | CL65: 43204 | CM65: 1275 | CN65: 2020
A66: 77221786 | B66: Цистерна для перевозки продуктов | C66: 15-5103-7П | D66: 05.09.2011 | E66: 2011 | F66: 05.09.2043 | G66: 30.01.2023 | H66: ВРД Кочетовка – филиал ООО "НВК" | I66: 27.08.2025 | J66: ВРЗ Челябинск – филиал ООО "НВК" | K66: Деповской | L66: 27.08.2028 | M66: ООО "ТрансАльянс Запад" | N66: 160000 | O66: 32538 | P66: 127462 | Q66: 10.02.2030 | R66: 27.08.2025 | T66: 89405 | U66: 1175 | V66: 2010 | W66: 600 | X66: авг.25 | Y66: 30 | Z66: 30 | AA66: 68 | AB66: 69 | AD66: 285203 | AE66: 0005 | AF66: 2011 | AG66: 600 | AH66: авг.25 | AI66: 30 | AJ66: 30 | AK66: 68 | AL66: 68 | AN66: 8283 | AO66: 1175 | AP66: 2001 | AQ66: 600 | AR66: авг.25 | AS66: 30 | AT66: 30 | AU66: 69 | AV66: 68 | AX66: 277301 | AY66: 0005 | AZ66: 2011 | BA66: 600 | BB66: авг.25 | BC66: 30 | BD66: 30 | BE66: 68 | BF66: 68 | BH66: 36619 | BI66: 0005 | BJ66: 2011 | BN66: 36921 | BO66: 0005 | BP66: 2011 | BT66: 64381 | BU66: 0005 | BV66: 2011 | BZ66: 64614 | CA66: 0005 | CB66: 2011 | CF66: 65006 | CG66: 0005 | CH66: 2011 | CL66: 62393 | CM66: 0005 | CN66: 2011
A67: 77205748 | B67: Цистерна для перевозки продуктов | C67: 15-1755П | D67: 20.06.2013 | E67: 2013 | F67: 20.06.2043 | G67: 20.08.2025 | H67: Орский ВРЗ-филиал ООО "НВК" | I67: 23.01.2024 | J67: ВЧД Унеча-ООО "НВК" | K67: Деповской | L67: 20.08.2027 | M67: ООО "ТрансАльянс Запад" | N67: 160000 | O67: 37765 | P67: 122235 | Q67: 22.07.2029 | R67: 20.08.2025 | T67: 443241 | U67: 0029 | V67: 2013 | W67: 2348 | X67: авг.25 | Y67: 30 | Z67: 30 | AA67: 60 | AB67: 60 | AD67: 370515 | AE67: 0029 | AF67: 2012 | AG67: 2348 | AH67: авг.25 | AI67: 30 | AJ67: 30 | AK67: 61 | AL67: 61 | AN67: 447128 | AO67: 0029 | AP67: 2013 | AQ67: 2348 | AR67: авг.25 | AS67: 30 | AT67: 30 | AU67: 62 | AV67: 62 | AX67: 381216 | AY67: 0029 | AZ67: 2012 | BA67: 2348 | BB67: авг.25 | BC67: 30 | BD67: 30 | BE67: 64 | BF67: 64 | BH67: 14087 | BI67: 1291 | BJ67: 2013 | BN67: 15433 | BO67: 1291 | BP67: 2013 | BT67: 39407 | BU67: 1291 | BV67: 2013 | BZ67: 43956 | CA67: 1291 | CB67: 2013 | CF67: 203132 | CG67: 1291 | CH67: 2013 | CL67: 44589 | CM67: 1291 | CN67: 2013
A68: 77205847 | B68: Цистерна для перевозки продуктов | C68: 15-1755П | D68: 20.06.2013 | E68: 2013 | F68: 20.06.2043 | G68: 30.05.2025 | H68: ВРД Кочетовка – филиал ООО "НВК" | I68: 28.07.2023 | J68: ВЧД Унеча-ООО "НВК" | K68: Деповской | L68: 30.05.2027 | M68: ООО "ТрансАльянс Запад" | N68: 160000 | O68: 41004 | P68: 118996 | Q68: 24.11.2029 | R68: 30.05.2025 | T68: 447270 | U68: 0029 | V68: 2013 | W68: 301 | X68: май.25 | Y68: 32 | Z68: 33 | AA68: 69 | AB68: 69 | AD68: 434206 | AE68: 0029 | AF68: 2013 | AG68: 301 | AH68: май.25 | AI68: 33 | AJ68: 33 | AK68: 69 | AL68: 69 | AN68: 447274 | AO68: 0029 | AP68: 2013 | AQ68: 301 | AR68: май.25 | AS68: 33 | AT68: 33 | AU68: 68 | AV68: 68 | AX68: 442764 | AY68: 0029 | AZ68: 2013 | BA68: 301 | BB68: май.25 | BC68: 33 | BD68: 33 | BE68: 67 | BF68: 67 | BH68: 15855 | BI68: 1291 | BJ68: 2013 | BN68: 15865 | BO68: 1291 | BP68: 2013 | BT68: 45714 | BU68: 1291 | BV68: 2013 | BZ68: 45439 | CA68: 1291 | CB68: 2013 | CF68: 44848 | CG68: 1291 | CH68: 2013 | CL68: 203125 | CM68: 1291 | CN68: 2013
A69: 77205946 | B69: Цистерна для перевозки продуктов | C69: 15-1755П | D69: 20.06.2013 | E69: 2013 | F69: 20.06.2043 | G69: 13.02.2026 | H69: Усть-Каменогорское ВРД | I69: 30.03.2024 | J69: ВРД Кочетовка – филиал ООО "НВК" | K69: Деповской | L69: 13.02.2028 | M69: ООО "ТрансАльянс Запад" | N69: 160000 | O69: 15306 | P69: 144694 | Q69: 23.09.2030 | R69: 03.03.2026 | T69: 75030 | U69: 0039 | V69: 1995 | W69: 4045 | X69: мар.26 | Y69: 0 | Z69: 0 | AA69: 76 | AB69: 76 | AD69: 271454 | AE69: 0005 | AF69: 2008 | AG69: 4045 | AH69: мар.26 | AI69: 0 | AJ69: 0 | AK69: 72 | AL69: 72 | AN69: 36390 | AO69: 1175 | AP69: 2009 | AQ69: 4045 | AR69: мар.26 | AS69: 0 | AT69: 0 | AU69: 72 | AV69: 72 | AX69: 319365 | AY69: 0039 | AZ69: 1983 | BA69: 4045 | BB69: мар.26 | BC69: 0 | BD69: 0 | BE69: 72 | BF69: 72 | BH69: 15332 | BI69: 1291 | BJ69: 2013 | BN69: 52255 | BO69: 1291 | BP69: 2013 | BT69: 44028 | BU69: 1291 | BV69: 2013 | BZ69: 42873 | CA69: 1291 | CB69: 2013 | CF69: 40770 | CG69: 1291 | CH69: 2013 | CL69: 41754 | CM69: 1291 | CN69: 2013
A70: 77221976 | B70: Цистерна для перевозки продуктов | C70: 15-150-04П | D70: 06.09.2011 | E70: 2011 | F70: 06.09.2043 | G70: 30.04.2023 | H70: ВРД Кочетовка – филиал ООО "НВК" | I70: 09.04.2026 | J70: Усть-Каменогорское ВРД | K70: Деповской | L70: 09.04.2029 | M70: ООО "ТрансАльянс Запад" | N70: 160000 | O70: 7525 | P70: 152475 | Q70: 10.06.2032 | R70: 09.04.2026 | T70: 285001 | U70: 0005 | V70: 2011 | W70: 745 | X70: апр.26 | Y70: 0 | Z70: 0 | AA70: 67 | AB70: 67 | AD70: 7445 | AE70: 1226 | AF70: 2013 | AG70: 745 | AH70: апр.26 | AI70: 0 | AJ70: 0 | AK70: 67 | AL70: 67 | AN70: 523372 | AO70: 0029 | AP70: 2014 | AQ70: 745 | AR70: апр.26 | AS70: 0 | AT70: 0 | AU70: 66 | AV70: 66 | AX70: 277426 | AY70: 0005 | AZ70: 2011 | BA70: 745 | BB70: апр.26 | BC70: 0 | BD70: 0 | BE70: 65 | BF70: 65 | BH70: 69798 | BI70: 0014 | BJ70: 2011 | BN70: 70344 | BO70: 0014 | BP70: 2011 | BT70: 117177 | BU70: 0014 | BV70: 2011 | BZ70: 117000 | CA70: 0014 | CB70: 2011 | CF70: 116555 | CG70: 0014 | CH70: 2011 | CL70: 115931 | CM70: 0014 | CN70: 2011
A71: 77224475 | B71: Цистерна для перевозки продуктов | C71: 15-5103-7П | D71: 05.09.2011 | E71: 2011 | F71: 05.09.2043 | G71: 22.09.2022 | H71: ВЧД Унеча-ООО "НВК" | I71: 31.10.2025 | J71: Орский ВРЗ-филиал ООО "НВК" | K71: Деповской | L71: 31.10.2028 | M71: ООО "ТрансАльянс Запад" | N71: 160000 | O71: 21645 | P71: 138355 | Q71: 20.03.2031 | R71: 31.10.2025 | T71: 284490 | U71: 0005 | V71: 2011 | W71: 2348 | X71: окт.25 | Y71: 33 | Z71: 33 | AA71: 74 | AB71: 74 | AD71: 284930 | AE71: 0005 | AF71: 2011 | AG71: 2348 | AH71: окт.25 | AI71: 33 | AJ71: 33 | AK71: 74 | AL71: 74 | AN71: 283015 | AO71: 0005 | AP71: 2011 | AQ71: 2348 | AR71: окт.25 | AS71: 33 | AT71: 33 | AU71: 74 | AV71: 74 | AX71: 284278 | AY71: 0005 | AZ71: 2011 | BA71: 2348 | BB71: окт.25 | BC71: 33 | BD71: 33 | BE71: 74 | BF71: 74 | BH71: 37397 | BI71: 0005 | BJ71: 2011 | BN71: 37414 | BO71: 0005 | BP71: 2011 | BT71: 66129 | BU71: 0005 | BV71: 2011 | BZ71: 63808 | CA71: 0005 | CB71: 2011 | CF71: 65158 | CG71: 0005 | CH71: 2011 | CL71: 65694 | CM71: 0005 | CN71: 2011
A72: 77221778 | B72: Цистерна для перевозки продуктов | C72: 15-150-04П | D72: 06.09.2011 | E72: 2011 | F72: 06.09.2043 | G72: 19.02.2023 | H72: ВРД Кавказская – филиал ООО "НВК" | I72: 20.03.2026 | J72: Усть-Каменогорское ВРД | K72: Деповской | L72: 20.03.2029 | M72: ООО "ТрансАльянс Запад" | N72: 160000 | O72: 7855 | P72: 152145 | Q72: 30.03.2033 | R72: 20.03.2026 | T72: 302187 | U72: 0005 | V72: 2013 | W72: 745 | X72: мар.26 | Y72: 0 | Z72: 0 | AA72: 74 | AB72: 74 | AD72: 320181 | AE72: 0005 | AF72: 2013 | AG72: 745 | AH72: мар.26 | AI72: 0 | AJ72: 0 | AK72: 73 | AL72: 73 | AN72: 308672 | AO72: 0005 | AP72: 2013 | AQ72: 745 | AR72: мар.26 | AS72: 0 | AT72: 0 | AU72: 72 | AV72: 72 | AX72: 122255 | AY72: 0005 | AZ72: 2012 | BA72: 745 | BB72: мар.26 | BC72: 0 | BD72: 0 | BE72: 72 | BF72: 72 | BH72: 38418 | BI72: 0005 | BJ72: 2011 | BN72: 38450 | BO72: 0005 | BP72: 2011 | BT72: 64262 | BU72: 0005 | BV72: 2011 | BZ72: 64504 | CA72: 0005 | CB72: 2011 | CF72: 67103 | CG72: 0005 | CH72: 2011 | CL72: 66097 | CM72: 0005 | CN72: 2011
A73: 77206183 | B73: Цистерна для перевозки продуктов | C73: 15-1755П | D73: 20.06.2013 | E73: 2013 | F73: 20.06.2043 | G73: 24.10.2025 | H73: ВРД Тольятти – филиал ООО "НВК" | I73: 21.04.2024 | J73: ВРД Кочетовка – филиал ООО "НВК" | K73: Деповской | L73: 24.10.2027 | M73: ООО "ТрансАльянс Запад" | N73: 160000 | O73: 16514 | P73: 143486 | Q73: 20.01.2033 | R73: 24.10.2025 | T73: 155694 | U73: 1175 | V73: 2019 | W73: 2080 | X73: окт.25 | Y73: 32 | Z73: 32 | AA73: 59 | AB73: 59 | AD73: 434190 | AE73: 0029 | AF73: 2013 | AG73: 2080 | AH73: окт.25 | AI73: 33 | AJ73: 33 | AK73: 60 | AL73: 60 | AN73: 381004 | AO73: 0029 | AP73: 2012 | AQ73: 2080 | AR73: окт.25 | AS73: 29 | AT73: 29 | AU73: 61 | AV73: 61 | AX73: 442566 | AY73: 0029 | AZ73: 2013 | BA73: 2080 | BB73: окт.25 | BC73: 29 | BD73: 29 | BE73: 58 | BF73: 58 | BH73: 15252 | BI73: 1291 | BJ73: 2013 | BN73: 52449 | BO73: 1291 | BP73: 2013 | BT73: 42235 | BU73: 1291 | BV73: 2013 | BZ73: 46300 | CA73: 1291 | CB73: 2013 | CF73: 46310 | CG73: 1291 | CH73: 2013 | CL73: 11391 | CM73: 0033 | CN73: 2014
A74: 77206001 | B74: Цистерна для перевозки продуктов | C74: 15-1755П | D74: 20.06.2013 | E74: 2013 | F74: 20.06.2043 | G74: 24.10.2025 | H74: ВРД Тольятти – филиал ООО "НВК" | I74: 06.02.2024 | J74: ВРД Кочетовка – филиал ООО "НВК" | K74: Деповской | L74: 24.10.2027 | M74: ООО "ТрансАльянс Запад" | N74: 160000 | O74: 16514 | P74: 143486 | Q74: 20.01.2033 | R74: 24.10.2025 | T74: 447139 | U74: 0029 | V74: 2013 | W74: 2080 | X74: окт.25 | Y74: 33 | Z74: 33 | AA74: 74 | AB74: 74 | AD74: 434222 | AE74: 0029 | AF74: 2013 | AG74: 2080 | AH74: окт.25 | AI74: 33 | AJ74: 33 | AK74: 74 | AL74: 74 | AN74: 455965 | AO74: 0029 | AP74: 2013 | AQ74: 2080 | AR74: окт.25 | AS74: 33 | AT74: 33 | AU74: 74 | AV74: 74 | AX74: 18198 | AY74: 1226 | AZ74: 2012 | BA74: 2080 | BB74: окт.25 | BC74: 33 | BD74: 33 | BE74: 74 | BF74: 74 | BH74: 13950 | BI74: 1291 | BJ74: 2013 | BN74: 13855 | BO74: 1291 | BP74: 2013 | BT74: 40962 | BU74: 1291 | BV74: 2013 | BZ74: 39313 | CA74: 1291 | CB74: 2013 | CF74: 40081 | CG74: 1291 | CH74: 2013 | CL74: 39031 | CM74: 1291 | CN74: 2013
A75: 77206175 | B75: Цистерна для перевозки продуктов | C75: 15-1755П | D75: 20.06.2013 | E75: 2013 | F75: 20.06.2043 | G75: 24.10.2025 | H75: ВРД Тольятти – филиал ООО "НВК" | I75: 27.01.2024 | J75: ВРЗ Челябинск – филиал ООО "НВК" | K75: Деповской | L75: 24.10.2027 | M75: ООО "ТрансАльянс Запад" | N75: 160000 | O75: 16514 | P75: 143486 | Q75: 20.01.2033 | R75: 24.10.2025 | T75: 459234 | U75: 0029 | V75: 2013 | W75: 2080 | X75: окт.25 | Y75: 30 | Z75: 30 | AA75: 70 | AB75: 70 | AD75: 459174 | AE75: 0029 | AF75: 2013 | AG75: 2080 | AH75: окт.25 | AI75: 33 | AJ75: 33 | AK75: 66 | AL75: 66 | AN75: 459342 | AO75: 0029 | AP75: 2013 | AQ75: 2080 | AR75: окт.25 | AS75: 33 | AT75: 33 | AU75: 68 | AV75: 68 | AX75: 443938 | AY75: 0029 | AZ75: 2013 | BA75: 2080 | BB75: окт.25 | BC75: 30 | BD75: 30 | BE75: 68 | BF75: 68 | BH75: 14431 | BI75: 1291 | BJ75: 2013 | BN75: 13706 | BO75: 1291 | BP75: 2013 | BT75: 40811 | BU75: 1291 | BV75: 2013 | BZ75: 41478 | CA75: 1291 | CB75: 2013 | CF75: 42410 | CG75: 1291 | CH75: 2013 | CL75: 41806 | CM75: 1291 | CN75: 2013
A76: 77205763 | B76: Цистерна для перевозки продуктов | C76: 15-1755П | D76: 20.06.2013 | E76: 2013 | F76: 20.06.2043 | G76: 28.06.2025 | H76: ВРД Кочетовка – филиал ООО "НВК" | I76: 25.07.2023 | J76: ВРД Кочетовка – филиал ООО "НВК" | K76: Деповской | L76: 28.06.2027 | M76: ООО "ТрансАльянс Запад" | N76: 160000 | O76: 40035 | P76: 119965 | Q76: 08.10.2029 | R76: 28.06.2025 | T76: 444243 | U76: 0029 | V76: 2013 | W76: 301 | X76: июнь.25 | Y76: 33 | Z76: 32 | AA76: 64 | AB76: 64 | AD76: 442967 | AE76: 0029 | AF76: 2013 | AG76: 301 | AH76: июнь.25 | AI76: 33 | AJ76: 32 | AK76: 57 | AL76: 57 | AN76: 711939 | AO76: 0039 | AP76: 1990 | AQ76: 301 | AR76: июнь.25 | AS76: 30 | AT76: 29 | AU76: 65 | AV76: 65 | AX76: 444375 | AY76: 0029 | AZ76: 2013 | BA76: 301 | BB76: июнь.25 | BC76: 30 | BD76: 31 | BE76: 65 | BF76: 65 | BH76: 1574 | BI76: 1291 | BJ76: 2013 | BN76: 15778 | BO76: 1291 | BP76: 2013 | BT76: 38833 | BU76: 1291 | BV76: 2013 | BZ76: 38799 | CA76: 1291 | CB76: 2013 | CF76: 38561 | CG76: 1291 | CH76: 2013 | CL76: 38236 | CM76: 1291 | CN76: 2013
A77: 77205920 | B77: Цистерна для перевозки продуктов | C77: 15-1755П | D77: 20.06.2013 | E77: 2013 | F77: 20.06.2043 | G77: 14.02.2026 | H77: Усть-Каменогорское ВРД | I77: 25.02.2024 | J77: ТОО "Аждар и К" | K77: Деповской | L77: 14.02.2028 | M77: ООО "ТрансАльянс Запад" | N77: 160000 | O77: 14375 | P77: 145625 | Q77: 31.12.2030 | R77: 14.02.2026 | T77: 62581 | U77: 1175 | V77: 2013 | W77: 745 | X77: фев.26 | Y77: 0 | Z77: 0 | AA77: 74 | AB77: 74 | AD77: 777116 | AE77: 0005 | AF77: 2017 | AG77: 745 | AH77: фев.26 | AI77: 0 | AJ77: 0 | AK77: 75 | AL77: 75 | AN77: 67833 | AO77: 0005 | AP77: 2004 | AQ77: 745 | AR77: фев.26 | AS77: 0 | AT77: 0 | AU77: 72 | AV77: 72 | AX77: 51464 | AY77: 1175 | AZ77: 2005 | BA77: 745 | BB77: фев.26 | BC77: 0 | BD77: 0 | BE77: 71 | BF77: 71 | BH77: 52345 | BI77: 1291 | BJ77: 2013 | BN77: 15827 | BO77: 1291 | BP77: 2013 | BT77: 45743 | BU77: 1291 | BV77: 2013 | BZ77: 45956 | CA77: 1291 | CB77: 2013 | CF77: 45943 | CG77: 1291 | CH77: 2013 | CL77: 46299 | CM77: 1291 | CN77: 2013
A78: 75187997 | B78: Цистерна для перевозки продуктов | C78: 15-1219-1П | D78: 14.10.2020 | E78: 2020 | F78: 14.10.2050 | G78: 14.10.2025 | H78: ВРД Зелецино - филиал ООО "НВК" | K78: Деповской | L78: 14.10.2027 | M78: ООО "ТрансАльянс Запад" | N78: 160000 | O78: 25105 | P78: 134895 | Q78: 22.09.2030 | R78: 14.10.2025 | T78: 748888 | U78: 0029 | V78: 2020 | W78: 1173 | X78: окт.25 | Y78: 30 | Z78: 30 | AA78: 59 | AB78: 58 | AD78: 749344 | AE78: 0029 | AF78: 2020 | AG78: 1173 | AH78: окт.25 | AI78: 29 | AJ78: 30 | AK78: 63 | AL78: 62 | AN78: 9727 | AO78: 2002 | AP78: 2020 | AQ78: 1173 | AR78: окт.25 | AS78: 30 | AT78: 30 | AU78: 60 | AV78: 58 | AX78: 749335 | AY78: 0029 | AZ78: 2020 | BA78: 1173 | BB78: окт.25 | BC78: 29 | BD78: 30 | BE78: 61 | BF78: 61 | BH78: 27723 | BI78: 1275 | BJ78: 2020 | BN78: 27749 | BO78: 1275 | BP78: 2020 | BT78: 46168 | BU78: 1275 | BV78: 2020 | BZ78: 46473 | CA78: 1275 | CB78: 2020 | CF78: 46281 | CG78: 1275 | CH78: 2020 | CL78: 46507 | CM78: 1275 | CN78: 2020
A79: 75184291 | B79: Цистерна для перевозки продуктов | C79: 15-1219-1П | D79: 08.10.2020 | E79: 2020 | F79: 08.10.2050 | G79: 22.12.2025 | H79: ВРД Зелецино - филиал ООО "НВК" | K79: Деповской | L79: 22.12.2027 | M79: ООО "ТрансАльянс Запад" | N79: 160000 | O79: 24544 | P79: 135456 | Q79: 17.10.2029 | R79: 22.12.2025 | T79: 446221 | U79: 0005 | V79: 2020 | W79: 1173 | X79: дек.25 | Y79: 30 | Z79: 29 | AA79: 58 | AB79: 58 | AD79: 448518 | AE79: 0005 | AF79: 2020 | AG79: 1173 | AH79: дек.25 | AI79: 30 | AJ79: 29 | AK79: 61 | AL79: 60 | AN79: 753582 | AO79: 0029 | AP79: 2020 | AQ79: 1173 | AR79: дек.25 | AS79: 30 | AT79: 30 | AU79: 59 | AV79: 58 | AX79: 753596 | AY79: 0029 | AZ79: 2020 | BA79: 1173 | BB79: дек.25 | BC79: 30 | BD79: 30 | BE79: 60 | BF79: 61 | BH79: 27588 | BI79: 1275 | BJ79: 2020 | BN79: 27253 | BO79: 1275 | BP79: 2020 | BT79: 45674 | BU79: 1275 | BV79: 2020 | BZ79: 46141 | CA79: 1275 | CB79: 2020 | CF79: 45961 | CG79: 1275 | CH79: 2020 | CL79: 46162 | CM79: 1275 | CN79: 2020
A80: 75188193 | B80: Цистерна для перевозки продуктов | C80: 15-1219-1П | D80: 14.10.2020 | E80: 2020 | F80: 14.10.2050 | G80: 22.12.2025 | H80: ВРД Зелецино - филиал ООО "НВК" | K80: Деповской | L80: 22.12.2027 | M80: ООО "ТрансАльянс Запад" | N80: 160000 | O80: 26017 | P80: 133983 | Q80: 30.07.2029 | R80: 22.12.2025 | T80: 749419 | U80: 0029 | V80: 2020 | W80: 1173 | X80: дек.25 | Y80: 30 | Z80: 30 | AA80: 62 | AB80: 62 | AD80: 447885 | AE80: 0005 | AF80: 2020 | AG80: 1173 | AH80: дек.25 | AI80: 30 | AJ80: 30 | AK80: 61 | AL80: 62 | AN80: 749409 | AO80: 0029 | AP80: 2020 | AQ80: 1173 | AR80: дек.25 | AS80: 30 | AT80: 30 | AU80: 58 | AV80: 58 | AX80: 445922 | AY80: 0005 | AZ80: 2020 | BA80: 1173 | BB80: дек.25 | BC80: 30 | BD80: 30 | BE80: 61 | BF80: 61 | BH80: 27752 | BI80: 1275 | BJ80: 2020 | BN80: 27715 | BO80: 1275 | BP80: 2020 | BT80: 45937 | BU80: 1275 | BV80: 2020 | BZ80: 45884 | CA80: 1275 | CB80: 2020 | CF80: 46082 | CG80: 1275 | CH80: 2020 | CL80: 46186 | CM80: 1275 | CN80: 2020
A81: 77228856 | B81: Цистерна для перевозки продуктов | C81: 15-150-04П | D81: 22.01.2015 | E81: 2015 | F81: 22.01.2047 | G81: 22.08.2025 | H81: Орский ВРЗ-филиал ООО "НВК" | K81: Капитальный | L81: 22.08.2028 | M81: ООО "ТрансАльянс Запад" | N81: 160000 | O81: 37803 | P81: 122197 | Q81: 14.07.2029 | R81: 22.08.2025 | T81: 212330 | U81: 0005 | V81: 2014 | W81: 2348 | X81: авг.25 | Y81: 33 | Z81: 33 | AA81: 73 | AB81: 74 | AD81: 301445 | AE81: 0005 | AF81: 2015 | AG81: 2348 | AH81: авг.25 | AI81: 33 | AJ81: 33 | AK81: 74 | AL81: 74 | AN81: 301382 | AO81: 0005 | AP81: 2015 | AQ81: 2348 | AR81: авг.25 | AS81: 33 | AT81: 33 | AU81: 74 | AV81: 74 | AX81: 301003 | AY81: 0005 | AZ81: 2015 | BA81: 2348 | BB81: авг.25 | BC81: 33 | BD81: 33 | BE81: 74 | BF81: 74 | BH81: 412 | BI81: 0005 | BJ81: 2015 | BN81: 480 | BO81: 0005 | BP81: 2015 | BT81: 1004 | BU81: 0005 | BV81: 2015 | BZ81: 1887 | CA81: 0005 | CB81: 2015 | CF81: 2576 | CG81: 0005 | CH81: 2015 | CL81: 2313 | CM81: 0005 | CN81: 2015
A82: 77228757 | B82: Цистерна для перевозки продуктов | C82: 15-5103-7П | D82: 19.01.2015 | E82: 2015 | F82: 19.01.2047 | G82: 24.08.2025 | H82: Орский ВРЗ-филиал ООО "НВК" | K82: Капитальный | L82: 24.08.2028 | M82: ООО "ТрансАльянс Запад" | N82: 160000 | O82: 37272 | P82: 122728 | Q82: 28.07.2029 | R82: 24.08.2025 | T82: 4473 | U82: 1557 | V82: 2018 | W82: 2348 | X82: авг.25 | Y82: 30 | Z82: 30 | AA82: 60 | AB82: 60 | AD82: 4469 | AE82: 1557 | AF82: 2018 | AG82: 2348 | AH82: авг.25 | AI82: 30 | AJ82: 30 | AK82: 57 | AL82: 56 | AN82: 5766 | AO82: 1557 | AP82: 2018 | AQ82: 2348 | AR82: авг.25 | AS82: 30 | AT82: 30 | AU82: 53 | AV82: 52 | AX82: 4376 | AY82: 1557 | AZ82: 2018 | BA82: 2348 | BB82: авг.25 | BC82: 30 | BD82: 30 | BE82: 48 | BF82: 48 | BH82: 35388 | BI82: 0005 | BJ82: 2014 | BN82: 33949 | BO82: 0005 | BP82: 2014 | BT82: 864 | BU82: 0005 | BV82: 2015 | BZ82: 2521 | CA82: 0005 | CB82: 2015 | CF82: 627 | CG82: 0005 | CH82: 2015 | CL82: 268 | CM82: 0005 | CN82: 2015
A83: 77228823 | B83: Цистерна для перевозки продуктов | C83: 15-150-04П | D83: 22.01.2015 | E83: 2015 | F83: 22.01.2047 | G83: 21.08.2025 | H83: ВРД Кочетовка – филиал ООО "НВК" | K83: Капитальный | L83: 21.08.2028 | M83: ООО "ТрансАльянс Запад" | N83: 160000 | O83: 30800 | P83: 129200 | Q83: 07.06.2030 | R83: 21.08.2025 | T83: 302726 | U83: 0005 | V83: 2015 | W83: 301 | X83: авг.25 | Y83: 30 | Z83: 30 | AA83: 37 | AB83: 37 | AD83: 285960 | AE83: 0005 | AF83: 2011 | AG83: 301 | AH83: авг.25 | AI83: 30 | AJ83: 30 | AK83: 39 | AL83: 39 | AN83: 517186 | AO83: 0029 | AP83: 2013 | AQ83: 301 | AR83: авг.25 | AS83: 30 | AT83: 30 | AU83: 38 | AV83: 38 | AX83: 24325 | AY83: 0039 | AZ83: 2004 | BA83: 301 | BB83: авг.25 | BC83: 30 | BD83: 30 | BE83: 39 | BF83: 38 | BH83: 35621 | BI83: 0005 | BJ83: 2014 | BN83: 34894 | BO83: 0005 | BP83: 2014 | BT83: 1069 | BU83: 0005 | BV83: 2015 | BZ83: 1997 | CA83: 0005 | CB83: 2015 | CF83: 451 | CG83: 0005 | CH83: 2015 | CL83: 247 | CM83: 0005 | CN83: 2015
A84: 77224582 | B84: Цистерна для перевозки продуктов | C84: 15-5103-7П | D84: 16.01.2012 | E84: 2012 | F84: 16.01.2044 | G84: 29.09.2022 | H84: ВЧД Унеча-ООО "НВК" | I84: 30.10.2025 | J84: Орский ВРЗ-филиал ООО "НВК" | K84: Деповской | L84: 30.10.2028 | M84: ООО "ТрансАльянс Запад" | N84: 160000 | O84: 16955 | P84: 143045 | Q84: 23.09.2032 | R84: 30.10.2025 | T84: 284927 | U84: 0005 | V84: 2011 | W84: 2348 | X84: окт.25 | Y84: 33 | Z84: 33 | AA84: 74 | AB84: 74 | AD84: 284920 | AE84: 0005 | AF84: 2011 | AG84: 2348 | AH84: окт.25 | AI84: 33 | AJ84: 33 | AK84: 74 | AL84: 74 | AN84: 276353 | AO84: 0005 | AP84: 2011 | AQ84: 2348 | AR84: окт.25 | AS84: 33 | AT84: 33 | AU84: 74 | AV84: 74 | AX84: 122142 | AY84: 0005 | AZ84: 2012 | BA84: 2348 | BB84: окт.25 | BC84: 33 | BD84: 33 | BE84: 74 | BF84: 74 | BH84: 10500 | BI84: 0005 | BJ84: 2012 | BN84: 10307 | BO84: 0005 | BP84: 2012 | BT84: 1277 | BU84: 0005 | BV84: 2012 | BZ84: 2699 | CA84: 0005 | CB84: 2012 | CF84: 18254 | CG84: 0005 | CH84: 2012 | CL84: 18142 | CM84: 0005 | CN84: 2012
A85: 77228971 | B85: Цистерна для перевозки продуктов | C85: 15-150-04П | D85: 23.01.2015 | E85: 2015 | F85: 23.01.2047 | G85: 02.02.2024 | H85: ВРД Кочетовка – филиал ООО "НВК" | K85: Деповской | L85: 02.02.2027 | M85: ООО "ТрансАльянс Запад" | N85: 160000 | O85: 101271 | P85: 58729 | Q85: 30.12.2027 | R85: 02.02.2024 | T85: 186384 | U85: 0005 | V85: 2014 | W85: 301 | X85: фев.24 | Y85: 30 | Z85: 30 | AA85: 46 | AB85: 46 | AD85: 303269 | AE85: 0005 | AF85: 2015 | AG85: 301 | AH85: фев.24 | AI85: 30 | AJ85: 30 | AK85: 50 | AL85: 50 | AN85: 301389 | AO85: 0005 | AP85: 2015 | AQ85: 301 | AR85: фев.24 | AS85: 28 | AT85: 30 | AU85: 48 | AV85: 48 | AX85: 301207 | AY85: 0005 | AZ85: 2015 | BA85: 301 | BB85: фев.24 | BC85: 30 | BD85: 30 | BE85: 50 | BF85: 50 | BH85: 35127 | BI85: 0005 | BJ85: 2014 | BN85: 35382 | BO85: 0005 | BP85: 2014 | BT85: 1627 | BU85: 0005 | BV85: 2015 | BZ85: 619 | CA85: 0005 | CB85: 2015 | CF85: 1459 | CG85: 0005 | CH85: 2015 | CL85: 2190 | CM85: 0005 | CN85: 2015
A86: 77222073 | B86: Цистерна для перевозки продуктов | C86: 15-5103-7П | D86: 05.09.2011 | E86: 2011 | F86: 05.09.2043 | G86: 31.03.2023 | H86: ВРД Кочетовка – филиал ООО "НВК" | I86: 13.07.2025 | J86: ВРД Кочетовка – филиал ООО "НВК" | K86: Деповской | L86: 13.07.2028 | M86: ООО "ТрансАльянс Запад" | N86: 160000 | O86: 29541 | P86: 130459 | Q86: 08.02.2031 | R86: 13.07.2025 | T86: 277359 | U86: 0005 | V86: 2011 | W86: 301 | X86: июль.25 | Y86: 33 | Z86: 33 | AA86: 75 | AB86: 75 | AD86: 15693 | AE86: 0029 | AF86: 2011 | AG86: 301 | AH86: июль.25 | AI86: 33 | AJ86: 33 | AK86: 75 | AL86: 75 | AN86: 556901 | AO86: 0029 | AP86: 2007 | AQ86: 301 | AR86: июль.25 | AS86: 33 | AT86: 33 | AU86: 75 | AV86: 75 | AX86: 285166 | AY86: 0005 | AZ86: 2011 | BA86: 301 | BB86: июль.25 | BC86: 33 | BD86: 33 | BE86: 75 | BF86: 75 | BH86: 36980 | BI86: 0005 | BJ86: 2011 | BN86: 37538 | BO86: 0005 | BP86: 2011 | BT86: 64325 | BU86: 0005 | BV86: 2011 | BZ86: 65324 | CA86: 0005 | CB86: 2011 | CF86: 65761 | CG86: 0005 | CH86: 2011 | CL86: 66112 | CM86: 0005 | CN86: 2011
A87: 77222230 | B87: Цистерна для перевозки продуктов | C87: 15-1755П | D87: 16.04.2014 | E87: 2014 | F87: 16.04.2044 | G87: 30.04.2023 | H87: ВРД Кочетовка – филиал ООО "НВК" | I87: 27.03.2025 | J87: ВРД Кочетовка – филиал ООО "НВК" | K87: Деповской | L87: 27.03.2027 | M87: ООО "ТрансАльянс Запад" | N87: 160000 | O87: 43721 | P87: 116279 | Q87: 31.01.2030 | R87: 27.03.2025 | T87: 368154 | U87: 0029 | V87: 2012 | W87: 301 | X87: мар.25 | Y87: 32 | Z87: 32 | AA87: 55 | AB87: 55 | AD87: 69556 | AE87: 1175 | AF87: 2013 | AG87: 301 | AH87: мар.25 | AI87: 32 | AJ87: 32 | AK87: 64 | AL87: 64 | AN87: 340062 | AO87: 0029 | AP87: 2012 | AQ87: 301 | AR87: мар.25 | AS87: 32 | AT87: 32 | AU87: 67 | AV87: 67 | AX87: 123239 | AY87: 0005 | AZ87: 2012 | BA87: 301 | BB87: мар.25 | BC87: 32 | BD87: 32 | BE87: 67 | BF87: 67 | BH87: 50922 | BI87: 1291 | BJ87: 2014 | BN87: 50734 | BO87: 1291 | BP87: 2014 | BT87: 4355 | BU87: 1291 | BV87: 2014 | BZ87: 5241 | CA87: 1291 | CB87: 2014 | CF87: 3790 | CG87: 1291 | CH87: 2014 | CL87: 3960 | CM87: 1291 | CN87: 2014
A88: 77205755 | B88: Цистерна для перевозки продуктов | C88: 15-1755П | D88: 20.06.2013 | E88: 2013 | F88: 20.06.2043 | G88: 09.03.2026 | H88: Аякозское ВРД | I88: 30.03.2024 | J88: ВРД Кочетовка – филиал ООО "НВК" | K88: Деповской | L88: 09.03.2028 | M88: ООО "ТрансАльянс Запад" | N88: 160000 | O88: 5895 | P88: 154105 | Q88: 13.05.2036 | R88: 09.03.2026 | T88: 123374 | U88: 0005 | V88: 2012 | W88: 698 | X88: мар.26 | Y88: 0 | Z88: 0 | AA88: 66 | AB88: 68 | AD88: 122769 | AE88: 0005 | AF88: 2012 | AG88: 698 | AH88: мар.26 | AI88: 0 | AJ88: 0 | AK88: 68 | AL88: 68 | AN88: 73335 | AO88: 1175 | AP88: 2012 | AQ88: 698 | AR88: мар.26 | AS88: 0 | AT88: 0 | AU88: 67 | AV88: 71 | AX88: 444011 | AY88: 0029 | AZ88: 2013 | BA88: 698 | BB88: мар.26 | BC88: 0 | BD88: 0 | BE88: 67 | BF88: 69 | BH88: 13958 | BI88: 1291 | BJ88: 2013 | BN88: 15621 | BO88: 1291 | BP88: 2013 | BT88: 39577 | BU88: 1291 | BV88: 2013 | BZ88: 39399 | CA88: 1291 | CB88: 2013 | CF88: 40699 | CG88: 1291 | CH88: 2013 | CL88: 44644 | CM88: 1291 | CN88: 2013
A89: 77205805 | B89: Цистерна для перевозки продуктов | C89: 15-1755П | D89: 20.06.2013 | E89: 2013 | F89: 20.06.2043 | G89: 09.03.2026 | H89: Аякозское ВРД | I89: 22.03.2024 | J89: Орский ВРЗ-филиал ООО "НВК" | K89: Деповской | L89: 09.03.2028 | M89: ООО "ТрансАльянс Запад" | N89: 160000 | O89: 5895 | P89: 154105 | Q89: 13.05.2036 | R89: 09.03.2026 | T89: 456628 | U89: 0029 | V89: 2013 | W89: 698 | X89: мар.26 | Y89: 0 | Z89: 0 | AA89: 68 | AB89: 68 | AD89: 447125 | AE89: 0029 | AF89: 2013 | AG89: 698 | AH89: мар.26 | AI89: 0 | AJ89: 0 | AK89: 66 | AL89: 67 | AN89: 434247 | AO89: 0029 | AP89: 2013 | AQ89: 698 | AR89: мар.26 | AS89: 0 | AT89: 0 | AU89: 64 | AV89: 65 | AX89: 444321 | AY89: 0029 | AZ89: 2013 | BA89: 698 | BB89: мар.26 | BC89: 0 | BD89: 0 | BE89: 64 | BF89: 66 | BH89: 15739 | BI89: 1291 | BJ89: 2013 | BN89: 15693 | BO89: 1291 | BP89: 2013 | BT89: 44593 | BU89: 1291 | BV89: 2013 | BZ89: 203200 | CA89: 1291 | CB89: 2013 | CF89: 43516 | CG89: 1291 | CH89: 2013 | CL89: 45037 | CM89: 1291 | CN89: 2013
A90: 77206019 | B90: Цистерна для перевозки продуктов | C90: 15-1755П | D90: 20.06.2013 | E90: 2013 | F90: 20.06.2043 | G90: 10.03.2026 | H90: Усть-Каменогорское ВРД | I90: 04.04.2024 | J90: ВРД Кочетовка – филиал ООО "НВК" | K90: Деповской | L90: 10.03.2028 | M90: ООО "ТрансАльянс Запад" | N90: 110000 | O90: 5531 | P90: 104469 | Q90: 05.08.2033 | R90: 10.03.2026 | T90: 370093 | U90: 0029 | V90: 2012 | W90: 745 | X90: мар.26 | Y90: 0 | Z90: 0 | AA90: 30 | AB90: 30 | AD90: 443422 | AE90: 0029 | AF90: 2013 | AG90: 745 | AH90: мар.26 | AI90: 0 | AJ90: 0 | AK90: 33 | AL90: 33 | AN90: 442785 | AO90: 0029 | AP90: 2013 | AQ90: 745 | AR90: мар.26 | AS90: 0 | AT90: 0 | AU90: 32 | AV90: 32 | AX90: 318853 | AY90: 0029 | AZ90: 2012 | BA90: 745 | BB90: мар.26 | BC90: 0 | BD90: 0 | BE90: 32 | BF90: 32 | BH90: 15545 | BI90: 1291 | BJ90: 2013 | BN90: 15768 | BO90: 1291 | BP90: 2013 | BT90: 203111 | BU90: 1291 | BV90: 2013 | BZ90: 203202 | CA90: 1291 | CB90: 2013 | CF90: 44842 | CG90: 1291 | CH90: 2013 | CL90: 44870 | CM90: 1291 | CN90: 2013
A91: 77228880 | B91: Цистерна для перевозки продуктов | C91: 15-150-04П | D91: 22.01.2015 | E91: 2015 | F91: 22.01.2047 | G91: 22.08.2025 | H91: Орский ВРЗ-филиал ООО "НВК" | K91: Капитальный | L91: 22.08.2028 | M91: ООО "ТрансАльянс Запад" | N91: 160000 | O91: 43319 | P91: 116681 | Q91: 14.01.2029 | R91: 22.08.2025 | T91: 205478 | U91: 0005 | V91: 2014 | W91: 2348 | X91: авг.25 | Y91: 30 | Z91: 30 | AA91: 42 | AB91: 41 | AD91: 880609 | AE91: 0005 | AF91: 2018 | AG91: 2348 | AH91: авг.25 | AI91: 30 | AJ91: 30 | AK91: 51 | AL91: 50 | AN91: 301072 | AO91: 0005 | AP91: 2015 | AQ91: 2348 | AR91: авг.25 | AS91: 30 | AT91: 30 | AU91: 44 | AV91: 43 | AX91: 814596 | AY91: 0005 | AZ91: 2018 | BA91: 2348 | BB91: авг.25 | BC91: 30 | BD91: 30 | BE91: 43 | BF91: 43 | BH91: 275 | BI91: 0005 | BJ91: 2015 | BN91: 35284 | BO91: 0005 | BP91: 2014 | BT91: 67279 | BU91: 0005 | BV91: 2014 | BZ91: 1263 | CA91: 0005 | CB91: 2015 | CF91: 641 | CG91: 0005 | CH91: 2015 | CL91: 2057 | CM91: 0005 | CN91: 2015
A92: 77228955 | B92: Цистерна для перевозки продуктов | C92: 15-150-04П | D92: 23.01.2015 | E92: 2015 | F92: 23.01.2047 | G92: 25.08.2025 | H92: Орский ВРЗ-филиал ООО "НВК" | K92: Капитальный | L92: 25.08.2028 | M92: ООО "ТрансАльянс Запад" | N92: 160000 | O92: 39794 | P92: 120206 | Q92: 25.04.2029 | R92: 25.08.2025 | T92: 300048 | U92: 0005 | V92: 2015 | W92: 2348 | X92: авг.25 | Y92: 33 | Z92: 33 | AA92: 75 | AB92: 75 | AD92: 301224 | AE92: 0005 | AF92: 2015 | AG92: 2348 | AH92: авг.25 | AI92: 33 | AJ92: 33 | AK92: 75 | AL92: 75 | AN92: 302361 | AO92: 0005 | AP92: 2015 | AQ92: 2348 | AR92: авг.25 | AS92: 33 | AT92: 33 | AU92: 75 | AV92: 75 | AX92: 301688 | AY92: 0005 | AZ92: 2015 | BA92: 2348 | BB92: авг.25 | BC92: 33 | BD92: 33 | BE92: 75 | BF92: 75 | BH92: 35252 | BI92: 0005 | BJ92: 2014 | BN92: 35305 | BO92: 0005 | BP92: 2014 | BT92: 228 | BU92: 0005 | BV92: 2015 | BZ92: 1584 | CA92: 0005 | CB92: 2015 | CF92: 2609 | CG92: 0005 | CH92: 2015 | CL92: 1334 | CM92: 0005 | CN92: 2015
A93: 77228872 | B93: Цистерна для перевозки продуктов | C93: 15-150-04П | D93: 22.01.2015 | E93: 2015 | F93: 22.01.2047 | G93: 20.08.2025 | H93: Орский ВРЗ-филиал ООО "НВК" | K93: Капитальный | L93: 20.08.2028 | M93: ООО "ТрансАльянс Запад" | N93: 160000 | O93: 36456 | P93: 123544 | Q93: 11.09.2029 | R93: 20.08.2025 | T93: 302807 | U93: 0005 | V93: 2015 | W93: 2348 | X93: авг.25 | Y93: 33 | Z93: 33 | AA93: 74 | AB93: 74 | AD93: 302089 | AE93: 0005 | AF93: 2015 | AG93: 2348 | AH93: авг.25 | AI93: 33 | AJ93: 33 | AK93: 74 | AL93: 74 | AN93: 206198 | AO93: 0005 | AP93: 2014 | AQ93: 2348 | AR93: авг.25 | AS93: 33 | AT93: 33 | AU93: 74 | AV93: 74 | AX93: 206591 | AY93: 0005 | AZ93: 2014 | BA93: 2348 | BB93: авг.25 | BC93: 33 | BD93: 33 | BE93: 74 | BF93: 74 | BH93: 35184 | BI93: 0005 | BJ93: 2014 | BN93: 634 | BO93: 0005 | BP93: 2015 | BT93: 2289 | BU93: 0005 | BV93: 2015 | BZ93: 2048 | CA93: 0005 | CB93: 2015 | CF93: 434 | CG93: 0005 | CH93: 2015 | CL93: 1886 | CM93: 0005 | CN93: 2015
A94: 77228765 | B94: Цистерна для перевозки продуктов | C94: 15-5103-7П | D94: 19.01.2015 | E94: 2015 | F94: 19.01.2047 | G94: 24.08.2025 | H94: Орский ВРЗ-филиал ООО "НВК" | K94: Капитальный | L94: 24.08.2028 | M94: ООО "ТрансАльянс Запад" | N94: 160000 | O94: 35335 | P94: 124665 | Q94: 14.10.2029 | R94: 24.08.2025 | T94: 303157 | U94: 0005 | V94: 2015 | W94: 2348 | X94: авг.25 | Y94: 33 | Z94: 33 | AA94: 75 | AB94: 75 | AD94: 205747 | AE94: 0005 | AF94: 2014 | AG94: 2348 | AH94: авг.25 | AI94: 33 | AJ94: 33 | AK94: 75 | AL94: 75 | AN94: 302086 | AO94: 0005 | AP94: 2015 | AQ94: 2348 | AR94: авг.25 | AS94: 33 | AT94: 33 | AU94: 75 | AV94: 75 | AX94: 301314 | AY94: 0005 | AZ94: 2015 | BA94: 2348 | BB94: авг.25 | BC94: 33 | BD94: 33 | BE94: 74 | BF94: 74 | BH94: 28782 | BI94: 0005 | BJ94: 2014 | BN94: 33337 | BO94: 0005 | BP94: 2014 | BT94: 1078 | BU94: 0005 | BV94: 2015 | BZ94: 1203 | CA94: 0005 | CB94: 2015 | CF94: 788 | CG94: 0005 | CH94: 2015 | CL94: 95068 | CM94: 0005 | CN94: 2015
A95: 77222057 | B95: Цистерна для перевозки продуктов | C95: 15-150-04П | D95: 31.08.2011 | E95: 2011 | F95: 31.08.2043 | G95: 06.02.2023 | H95: ВРЗ Челябинск – филиал ООО "НВК" | I95: 06.03.2026 | J95: Усть-Каменогорское ВРД | K95: Деповской | L95: 06.03.2029 | M95: ООО "ТрансАльянс Запад" | N95: 160000 | O95: 14069 | P95: 145931 | Q95: 15.07.2030 | R95: 06.03.2026 | T95: 279078 | U95: 0005 | V95: 2011 | W95: 745 | X95: мар.26 | Y95: 0 | Z95: 0 | AA95: 58 | AB95: 58 | AD95: 403484 | AE95: 0005 | AF95: 2013 | AG95: 745 | AH95: мар.26 | AI95: 0 | AJ95: 0 | AK95: 56 | AL95: 56 | AN95: 23981 | AO95: 0039 | AP95: 2011 | AQ95: 745 | AR95: мар.26 | AS95: 0 | AT95: 0 | AU95: 67 | AV95: 67 | AX95: 283920 | AY95: 0005 | AZ95: 2011 | BA95: 745 | BB95: мар.26 | BC95: 0 | BD95: 0 | BE95: 66 | BF95: 66 | BH95: 37179 | BI95: 0005 | BJ95: 2011 | BN95: 37342 | BO95: 0005 | BP95: 2011 | BT95: 66199 | BU95: 0005 | BV95: 2011 | BZ95: 65306 | CA95: 0005 | CB95: 2011 | CF95: 65937 | CG95: 0005 | CH95: 2011 | CL95: 65915 | CM95: 0005 | CN95: 2011
A96: 77228948 | B96: Цистерна для перевозки продуктов | C96: 15-150-04П | D96: 23.01.2015 | E96: 2015 | F96: 23.01.2047 | G96: 23.10.2025 | H96: ВРД Тольятти – филиал ООО "НВК" | K96: Капитальный | L96: 23.10.2028 | M96: ООО "ТрансАльянс Запад" | N96: 160000 | O96: 24614 | P96: 135386 | Q96: 08.09.2030 | R96: 23.10.2025 | T96: 300901 | U96: 0005 | V96: 2015 | W96: 2080 | X96: окт.25 | Y96: 30 | Z96: 30 | AA96: 42 | AB96: 42 | AD96: 301909 | AE96: 0005 | AF96: 2015 | AG96: 2080 | AH96: окт.25 | AI96: 30 | AJ96: 30 | AK96: 36 | AL96: 36 | AN96: 318861 | AO96: 0029 | AP96: 2012 | AQ96: 2080 | AR96: окт.25 | AS96: 30 | AT96: 30 | AU96: 35 | AV96: 35 | AX96: 443805 | AY96: 0029 | AZ96: 2013 | BA96: 2080 | BB96: окт.25 | BC96: 30 | BD96: 30 | BE96: 35 | BF96: 35 | BH96: 35599 | BI96: 0005 | BJ96: 2014 | BN96: 32757 | BO96: 0005 | BP96: 2014 | BT96: 1348 | BU96: 0005 | BV96: 2015 | BZ96: 1814 | CA96: 0005 | CB96: 2015 | CF96: 1823 | CG96: 0005 | CH96: 2015 | CL96: 960 | CM96: 0005 | CN96: 2015
A97: 77228963 | B97: Цистерна для перевозки продуктов | C97: 15-150-04П | D97: 23.01.2015 | E97: 2015 | F97: 23.01.2047 | G97: 20.08.2025 | H97: Орский ВРЗ-филиал ООО "НВК" | K97: Капитальный | L97: 20.08.2028 | M97: ООО "ТрансАльянс Запад" | N97: 160000 | O97: 32636 | P97: 127364 | Q97: 04.03.2030 | R97: 20.08.2025 | T97: 212321 | U97: 0005 | V97: 2014 | W97: 2348 | X97: авг.25 | Y97: 30 | Z97: 30 | AA97: 45 | AB97: 45 | AD97: 300869 | AE97: 0005 | AF97: 2015 | AG97: 2348 | AH97: авг.25 | AI97: 30 | AJ97: 30 | AK97: 45 | AL97: 45 | AN97: 301127 | AO97: 0005 | AP97: 2015 | AQ97: 2348 | AR97: авг.25 | AS97: 30 | AT97: 30 | AU97: 35 | AV97: 35 | AX97: 207109 | AY97: 0005 | AZ97: 2014 | BA97: 2348 | BB97: авг.25 | BC97: 30 | BD97: 30 | BE97: 35 | BF97: 35 | BH97: 35111 | BI97: 0005 | BJ97: 2014 | BN97: 34209 | BO97: 0005 | BP97: 2014 | BT97: 582 | BU97: 0005 | BV97: 2015 | BZ97: 1062 | CA97: 0005 | CB97: 2015 | CF97: 1634 | CG97: 0005 | CH97: 2015 | CL97: 2447 | CM97: 0005 | CN97: 2015
A98: 77228922 | B98: Цистерна для перевозки продуктов | C98: 15-150-04П | D98: 22.01.2015 | E98: 2015 | F98: 22.01.2047 | G98: 29.07.2024 | H98: ВЧД Унеча-ООО "НВК" | K98: Деповской | L98: 29.07.2027 | M98: ООО "ТрансАльянс Запад" | N98: 110000 | O98: 80291 | P98: 29709 | Q98: 18.04.2027 | R98: 29.07.2024 | T98: 205340 | U98: 0005 | V98: 2014 | W98: 357 | X98: июль.24 | Y98: 30 | Z98: 30 | AA98: 30 | AB98: 30 | AD98: 301050 | AE98: 0005 | AF98: 2015 | AG98: 357 | AH98: июль.24 | AI98: 30 | AJ98: 30 | AK98: 30 | AL98: 30 | AN98: 301215 | AO98: 0005 | AP98: 2015 | AQ98: 357 | AR98: июль.24 | AS98: 30 | AT98: 30 | AU98: 36 | AV98: 36 | AX98: 205465 | AY98: 0005 | AZ98: 2014 | BA98: 357 | BB98: июль.24 | BC98: 30 | BD98: 30 | BE98: 37 | BF98: 37 | BH98: 35104 | BI98: 0005 | BJ98: 2014 | BN98: 334 | BO98: 0005 | BP98: 2015 | BT98: 2082 | BU98: 0005 | BV98: 2015 | BZ98: 2380 | CA98: 0005 | CB98: 2015 | CF98: 1235 | CG98: 0005 | CH98: 2015 | CL98: 2672 | CM98: 0005 | CN98: 2015
A99: 77221885 | B99: Цистерна для перевозки продуктов | C99: 15-5103-7П | D99: 06.09.2011 | E99: 2011 | F99: 06.09.2043 | G99: 24.02.2023 | H99: ВРД Кочетовка – филиал ООО "НВК" | I99: 10.03.2026 | J99: Усть-Каменогорское ВРД | K99: Деповской | L99: 10.03.2029 | M99: ООО "ТрансАльянс Запад" | N99: 160000 | O99: 14079 | P99: 145921 | Q99: 03.06.2030 | R99: 10.03.2026 | T99: 285054 | U99: 0005 | V99: 2011 | W99: 745 | X99: мар.26 | Y99: 0 | Z99: 0 | AA99: 62 | AB99: 62 | AD99: 284962 | AE99: 0005 | AF99: 2011 | AG99: 745 | AH99: мар.26 | AI99: 0 | AJ99: 0 | AK99: 60 | AL99: 60 | AN99: 387489 | AO99: 0005 | AP99: 2013 | AQ99: 745 | AR99: мар.26 | AS99: 0 | AT99: 0 | AU99: 66 | AV99: 66 | AX99: 279750 | AY99: 0005 | AZ99: 2011 | BA99: 745 | BB99: мар.26 | BC99: 0 | BD99: 0 | BE99: 64 | BF99: 64 | BH99: 37855 | BI99: 0005 | BJ99: 2011 | BN99: 37442 | BO99: 0005 | BP99: 2011 | BT99: 66604 | BU99: 0005 | BV99: 2011 | BZ99: 66235 | CA99: 0005 | CB99: 2011 | CF99: 66630 | CG99: 0005 | CH99: 2011 | CL99: 66283 | CM99: 0005 | CN99: 2011
A100: 77221802 | B100: Цистерна для перевозки продуктов | C100: 15-5103-7П | D100: 05.09.2011 | E100: 2011 | F100: 05.09.2043 | G100: 02.03.2023 | H100: ВРД Кочетовка – филиал ООО "НВК" | I100: 29.10.2025 | J100: Орский ВРЗ-филиал ООО "НВК" | K100: Деповской | L100: 29.10.2028 | M100: ООО "ТрансАльянс Запад" | N100: 160000 | O100: 22146 | P100: 137854 | Q100: 16.02.2031 | R100: 29.10.2025 | T100: 174585 | U100: 0005 | V100: 2012 | W100: 2348 | X100: окт.25 | Y100: 30 | Z100: 30 | AA100: 65 | AB100: 65 | AD100: 280880 | AE100: 0005 | AF100: 2011 | AG100: 2348 | AH100: окт.25 | AI100: 30 | AJ100: 30 | AK100: 69 | AL100: 69 | AN100: 285721 | AO100: 0005 | AP100: 2011 | AQ100: 2348 | AR100: окт.25 | AS100: 30 | AT100: 30 | AU100: 67 | AV100: 67 | AX100: 279763 | AY100: 0005 | AZ100: 2011 | BA100: 2348 | BB100: окт.25 | BC100: 30 | BD100: 30 | BE100: 68 | BF100: 68 | BH100: 37629 | BI100: 0005 | BJ100: 2011 | BN100: 37546 | BO100: 0005 | BP100: 2011 | BT100: 62051 | BU100: 0005 | BV100: 2011 | BZ100: 66325 | CA100: 0005 | CB100: 2011 | CF100: 65715 | CG100: 0005 | CH100: 2011 | CL100: 65069 | CM100: 0005 | CN100: 2011
A101: 77222016 | B101: Цистерна для перевозки продуктов | C101: 15-5103-7П | D101: 12.09.2011 | E101: 2011 | F101: 12.09.2043 | G101: 27.01.2023 | H101: ВРД Кочетовка – филиал ООО "НВК" | I101: 23.08.2025 | J101: ВРЗ Челябинск – филиал ООО "НВК" | K101: Деповской | L101: 23.08.2028 | M101: ООО "ТрансАльянс Запад" | N101: 160000 | O101: 37096 | P101: 122904 | Q101: 07.08.2029 | R101: 23.08.2025 | T101: 282793 | U101: 0005 | V101: 2011 | W101: 600 | X101: авг.25 | Y101: 33 | Z101: 33 | AA101: 73 | AB101: 73 | AD101: 283845 | AE101: 0005 | AF101: 2011 | AG101: 600 | AH101: авг.25 | AI101: 33 | AJ101: 33 | AK101: 73 | AL101: 73 | AN101: 284445 | AO101: 0005 | AP101: 2011 | AQ101: 600 | AR101: авг.25 | AS101: 33 | AT101: 33 | AU101: 75 | AV101: 75 | AX101: 283448 | AY101: 0005 | AZ101: 2011 | BA101: 600 | BB101: авг.25 | BC101: 33 | BD101: 33 | BE101: 75 | BF101: 75 | BH101: 36737 | BI101: 0005 | BJ101: 2011 | BN101: 37455 | BO101: 0005 | BP101: 2011 | BT101: 63109 | BU101: 0005 | BV101: 2011 | BZ101: 63193 | CA101: 0005 | CB101: 2011 | CF101: 64922 | CG101: 0005 | CH101: 2011 | CL101: 64302 | CM101: 0005 | CN101: 2011
A102: 77228807 | B102: Цистерна для перевозки продуктов | C102: 15-5103-7П | D102: 19.01.2015 | E102: 2015 | F102: 19.01.2047 | G102: 24.08.2025 | H102: Орский ВРЗ-филиал ООО "НВК" | K102: Капитальный | L102: 24.08.2028 | M102: ООО "ТрансАльянс Запад" | N102: 160000 | O102: 39757 | P102: 120243 | Q102: 29.04.2029 | R102: 10.11.2025 | T102: 301258 | U102: 0005 | V102: 2015 | W102: 4046 | X102: ноя.25 | Y102: 0 | Z102: 0 | AA102: 48 | AB102: 48 | AD102: 301723 | AE102: 0005 | AF102: 2015 | AG102: 4046 | AH102: ноя.25 | AI102: 0 | AJ102: 0 | AK102: 48 | AL102: 48 | AN102: 301008 | AO102: 0005 | AP102: 2015 | AQ102: 4046 | AR102: ноя.25 | AS102: 0 | AT102: 0 | AU102: 37 | AV102: 36 | AX102: 301673 | AY102: 0005 | AZ102: 2015 | BA102: 4046 | BB102: ноя.25 | BC102: 0 | BD102: 0 | BE102: 45 | BF102: 45 | BH102: 916 | BI102: 0005 | BJ102: 2015 | BN102: 34860 | BO102: 0005 | BP102: 2014 | BT102: 702 | BU102: 0005 | BV102: 2015 | BZ102: 2510 | CA102: 0005 | CB102: 2015 | CF102: 818 | CG102: 0005 | CH102: 2015 | CL102: 1524 | CM102: 0005 | CN102: 2015
A103: 77228831 | B103: Цистерна для перевозки продуктов | C103: 15-150-04П | D103: 22.01.2015 | E103: 2015 | F103: 22.01.2047 | G103: 09.11.2023 | H103: ВРД Кочетовка – филиал ООО "НВК" | K103: Деповской | L103: 09.11.2026 | M103: ООО "ТрансАльянс Запад" | N103: 160000 | O103: 103736 | P103: 56264 | Q103: 11.01.2028 | R103: 09.12.2024 | T103: 301035 | U103: 0005 | V103: 2015 | W103: 837 | X103: дек.24 | Y103: 30 | Z103: 30 | AA103: 28 | AB103: 28 | AD103: 868910 | AE103: 0005 | AF103: 2018 | AG103: 837 | AH103: дек.24 | AI103: 30 | AJ103: 30 | AK103: 29 | AL103: 29 | AN103: 370593 | AO103: 0029 | AP103: 2012 | AQ103: 837 | AR103: дек.24 | AS103: 30 | AT103: 30 | AU103: 37 | AV103: 37 | AX103: 301036 | AY103: 0005 | AZ103: 2015 | BA103: 837 | BB103: дек.24 | BC103: 30 | BD103: 30 | BE103: 37 | BF103: 37 | BH103: 33360 | BI103: 0005 | BJ103: 2014 | BN103: 35576 | BO103: 0005 | BP103: 2014 | BT103: 1172 | BU103: 0005 | BV103: 2015 | BZ103: 468 | CA103: 0005 | CB103: 2015 | CF103: 1207 | CG103: 0005 | CH103: 2015 | CL103: 673 | CM103: 0005 | CN103: 2015
A104: 77221968 | B104: Цистерна для перевозки продуктов | C104: 15-150-04П | D104: 28.02.2012 | E104: 2012 | F104: 28.02.2044 | G104: 29.09.2022 | H104: ВЧД Унеча-ООО "НВК" | I104: 11.08.2025 | J104: ВРД Кочетовка – филиал ООО "НВК" | K104: Деповской | L104: 11.08.2027 | M104: ООО "ТрансАльянс Запад" | N104: Вагон не ремонтируется по пробегу. | R104: 11.08.2025 | T104: 120396 | U104: 0005 | V104: 2012 | W104: 301 | X104: авг.25 | Y104: 30 | Z104: 29 | AA104: 39 | AB104: 39 | AD104: 122483 | AE104: 0005 | AF104: 2012 | AG104: 301 | AH104: авг.25 | AI104: 30 | AJ104: 31 | AK104: 36 | AL104: 36 | AN104: 523308 | AO104: 0029 | AP104: 2014 | AQ104: 301 | AR104: авг.25 | AS104: 30 | AT104: 29 | AU104: 40 | AV104: 40 | AX104: 443982 | AY104: 0029 | AZ104: 2013 | BA104: 301 | BB104: авг.25 | BC104: 30 | BD104: 29 | BE104: 44 | BF104: 44 | BH104: 10391 | BI104: 0005 | BJ104: 2012 | BN104: 10631 | BO104: 0005 | BP104: 2012 | BT104: 3751 | BU104: 0005 | BV104: 2012 | BZ104: 3778 | CA104: 0005 | CB104: 2012 | CF104: 3702 | CG104: 0005 | CH104: 2012 | CL104: 3914 | CM104: 0005 | CN104: 2012
A105: 77221869 | B105: Цистерна для перевозки продуктов | C105: 15-5103-7П | D105: 05.09.2011 | E105: 2011 | F105: 05.09.2043 | G105: 30.01.2023 | H105: ВРД Кочетовка – филиал ООО "НВК" | I105: 29.10.2025 | J105: Орский ВРЗ-филиал ООО "НВК" | K105: Деповской | L105: 29.10.2028 | M105: ООО "ТрансАльянс Запад" | N105: 160000 | O105: 13600 | P105: 146400 | Q105: 17.06.2034 | R105: 29.10.2025 | T105: 178513 | U105: 0005 | V105: 2014 | W105: 2348 | X105: окт.25 | Y105: 30 | Z105: 30 | AA105: 68 | AB105: 68 | AD105: 284807 | AE105: 0005 | AF105: 2011 | AG105: 2348 | AH105: окт.25 | AI105: 30 | AJ105: 30 | AK105: 68 | AL105: 68 | AN105: 277168 | AO105: 0005 | AP105: 2011 | AQ105: 2348 | AR105: окт.25 | AS105: 30 | AT105: 30 | AU105: 68 | AV105: 68 | AX105: 284925 | AY105: 0005 | AZ105: 2011 | BA105: 2348 | BB105: окт.25 | BC105: 30 | BD105: 30 | BE105: 69 | BF105: 69 | BH105: 68491 | BI105: 0014 | BJ105: 2011 | BN105: 68176 | BO105: 0014 | BP105: 2011 | BT105: 525689 | BU105: 0014 | BV105: 2011 | BZ105: 113471 | CA105: 0014 | CB105: 2011 | CF105: 115126 | CG105: 0014 | CH105: 2011 | CL105: 114995 | CM105: 0014 | CN105: 2011
A106: 77228815 | B106: Цистерна для перевозки продуктов | C106: 15-5103-7П | D106: 20.01.2015 | E106: 2015 | F106: 20.01.2047 | G106: 05.08.2025 | H106: ВЧД Унеча-ООО "НВК" | K106: Капитальный | L106: 05.08.2028 | M106: ООО "ТрансАльянс Запад" | N106: 160000 | O106: 24492 | P106: 135508 | Q106: 28.11.2031 | R106: 05.08.2025 | T106: 302267 | U106: 0005 | V106: 2015 | W106: 357 | X106: авг.25 | Y106: 33 | Z106: 33 | AA106: 77 | AB106: 77 | AD106: 212362 | AE106: 0005 | AF106: 2014 | AG106: 357 | AH106: авг.25 | AI106: 33 | AJ106: 33 | AK106: 77 | AL106: 77 | AN106: 11280 | AO106: 0005 | AP106: 1998 | AQ106: 357 | AR106: авг.25 | AS106: 33 | AT106: 33 | AU106: 74 | AV106: 74 | AX106: 460020 | AY106: 0029 | AZ106: 2013 | BA106: 357 | BB106: авг.25 | BC106: 33 | BD106: 33 | BE106: 75 | BF106: 75 | BH106: 34753 | BI106: 0005 | BJ106: 2014 | BN106: 35629 | BO106: 0005 | BP106: 2014 | BT106: 204 | BU106: 0005 | BV106: 2015 | BZ106: 1396 | CA106: 0005 | CB106: 2015 | CF106: 2285 | CG106: 0005 | CH106: 2015 | CL106: 1583 | CM106: 0005 | CN106: 2015
A107: 77221927 | B107: Цистерна для перевозки продуктов | C107: 15-5103-7П | D107: 12.09.2011 | E107: 2011 | F107: 12.09.2043 | G107: 13.02.2023 | H107: ВРД Кавказская – филиал ООО "НВК" | I107: 20.10.2025 | J107: ВЧД Унеча-ООО "НВК" | K107: Деповской | L107: 20.10.2028 | M107: ООО "ТрансАльянс Запад" | N107: 160000 | O107: 19494 | P107: 140506 | Q107: 10.01.2032 | R107: 20.10.2025 | T107: 283784 | U107: 0005 | V107: 2011 | W107: 357 | X107: окт.25 | Y107: 33 | Z107: 33 | AA107: 74 | AB107: 74 | AD107: 313587 | AE107: 0005 | AF107: 2013 | AG107: 357 | AH107: окт.25 | AI107: 33 | AJ107: 33 | AK107: 74 | AL107: 73 | AN107: 283990 | AO107: 0005 | AP107: 2011 | AQ107: 357 | AR107: окт.25 | AS107: 33 | AT107: 33 | AU107: 74 | AV107: 73 | AX107: 283994 | AY107: 0005 | AZ107: 2011 | BA107: 357 | BB107: окт.25 | BC107: 33 | BD107: 33 | BE107: 74 | BF107: 73 | BH107: 37258 | BI107: 0005 | BJ107: 2011 | BN107: 36576 | BO107: 0005 | BP107: 2011 | BT107: 64521 | BU107: 0005 | BV107: 2011 | BZ107: 35668 | CA107: 0005 | CB107: 2011 | CF107: 65097 | CG107: 0005 | CH107: 2011 | CL107: 65680 | CM107: 0005 | CN107: 2011
A108: 77206043 | B108: Цистерна для перевозки продуктов | C108: 15-1755П | D108: 20.06.2013 | E108: 2013 | F108: 20.06.2043 | G108: 28.07.2025 | H108: ВРД Кочетовка – филиал ООО "НВК" | I108: 25.08.2023 | J108: ВРД Кочетовка – филиал ООО "НВК" | K108: Деповской | L108: 28.07.2027 | M108: ООО "ТрансАльянс Запад" | N108: 160000 | O108: 27738 | P108: 132262 | Q108: 10.04.2031 | R108: 28.07.2025 | T108: 44844 | U108: 0039 | V108: 1985 | W108: 301 | X108: июль.25 | Y108: 33 | Z108: 32 | AA108: 68 | AB108: 68 | AD108: 846740 | AE108: 0029 | AF108: 2010 | AG108: 301 | AH108: июль.25 | AI108: 33 | AJ108: 32 | AK108: 66 | AL108: 66 | AN108: 5314 | AO108: 1175 | AP108: 2007 | AQ108: 301 | AR108: июль.25 | AS108: 30 | AT108: 31 | AU108: 56 | AV108: 56 | AX108: 716466 | AY108: 0029 | AZ108: 1997 | BA108: 301 | BB108: июль.25 | BC108: 33 | BD108: 32 | BE108: 63 | BF108: 63 | BH108: 13578 | BI108: 1291 | BJ108: 2013 | BN108: 52109 | BO108: 1291 | BP108: 2013 | BT108: 39383 | BU108: 1291 | BV108: 2013 | BZ108: 40264 | CA108: 1291 | CB108: 2013 | CF108: 41649 | CG108: 1291 | CH108: 2013 | CL108: 41630 | CM108: 1291 | CN108: 2013
...
