Workbook

Sheet Сценарии
A1: СЦЕНАРИИ БЮДЖЕТА · H2 2026
A2: Чувствительность к нормализации выручки (риск концентрации QAZAQ-ASTYQ) и марже
A4: Сценарий | B4: Предпосылки | C4: Выручка H2 | D4: EBITDA H2 | E4: Чистая приб. H2 | F4: Остаток ден. на конец
A5: Консервативный | B5: норм. 70%, COGS +2 п.п., рост 0% | C5: 3857696687 | D5: 808609173 | E5: 578492376 | F5: 691903878
A6: Базовый (рекоменд.) | B6: норм. 85%, COGS факт, рост 0% | C6: 4684345977 | D6: 1132555971 | E6: 889827914 | F6: 1003239416
A7: Оптимистичный | B7: норм. 100%, рост +2%/мес, COGS −1 п.п. | C7: 5794004129 | D7: 1521780048 | E7: 1262123184 | F7: 1375534686
A9: Метрики (базовый):
A10: Выручка H2 | C10: 4684345977
A11: EBITDA-маржа | C11: 0.24177462
A12: Чистая маржа | C12: 0.18995777
A13: Средняя чистая прибыль/мес | C13: 148304652
A14: Прирост денежных средств за H2 | C14: 889827914

Sheet Бюджет P&L
A1: БЮДЖЕТ · ОТЧЁТ О ПРИБЫЛЯХ И УБЫТКАХ · H2 2026
A2: ТОО «WayStar Group» (БИН 240340014287) · ₸ · кассовый метод (формулы от листа «Предпосылки»)
A4: Показатель | C4: Июль 2026 | D4: Август 2026 | E4: Сентябрь 2026 | F4: Октябрь 2026 | G4: Ноябрь 2026 | H4: Декабрь 2026 | I4: ИТОГО H2
A5: Выручка — Аренда | C5: ='Предпосылки'!$B$5*'Предпосылки'!$B$7*'Предпосылки'!$C$10*(1+'Предпосылки'!$B$8)^0 | D5: ='Предпосылки'!$B$5*'Предпосылки'!$B$7*'Предпосылки'!$D$10*(1+'Предпосылки'!$B$8)^1 | E5: ='Предпосылки'!$B$5*'Предпосылки'!$B$7*'Предпосылки'!$E$10*(1+'Предпосылки'!$B$8)^2 | F5: ='Предпосылки'!$B$5*'Предпосылки'!$B$7*'Предпосылки'!$F$10*(1+'Предпосылки'!$B$8)^3 | G5: ='Предпосылки'!$B$5*'Предпосылки'!$B$7*'Предпосылки'!$G$10*(1+'Предпосылки'!$B$8)^4 | H5: ='Предпосылки'!$B$5*'Предпосылки'!$B$7*'Предпосылки'!$H$10*(1+'Предпосылки'!$B$8)^5 | I5: =SUM(C5:H5)
A6: Выручка — ТЭО | C6: ='Предпосылки'!$B$6*'Предпосылки'!$B$7*'Предпосылки'!$C$10*(1+'Предпосылки'!$B$8)^0 | D6: ='Предпосылки'!$B$6*'Предпосылки'!$B$7*'Предпосылки'!$D$10*(1+'Предпосылки'!$B$8)^1 | E6: ='Предпосылки'!$B$6*'Предпосылки'!$B$7*'Предпосылки'!$E$10*(1+'Предпосылки'!$B$8)^2 | F6: ='Предпосылки'!$B$6*'Предпосылки'!$B$7*'Предпосылки'!$F$10*(1+'Предпосылки'!$B$8)^3 | G6: ='Предпосылки'!$B$6*'Предпосылки'!$B$7*'Предпосылки'!$G$10*(1+'Предпосылки'!$B$8)^4 | H6: ='Предпосылки'!$B$6*'Предпосылки'!$B$7*'Предпосылки'!$H$10*(1+'Предпосылки'!$B$8)^5 | I6: =SUM(C6:H6)
A7: Выручка, итого | C7: =C5+C6 | D7: =D5+D6 | E7: =E5+E6 | F7: =F5+F6 | G7: =G5+G6 | H7: =H5+H6 | I7: =SUM(C7:H7)
A8: COGS — Аренда | C8: =-C5*'Предпосылки'!$B$13 | D8: =-D5*'Предпосылки'!$B$13 | E8: =-E5*'Предпосылки'!$B$13 | F8: =-F5*'Предпосылки'!$B$13 | G8: =-G5*'Предпосылки'!$B$13 | H8: =-H5*'Предпосылки'!$B$13 | I8: =SUM(C8:H8)
A9: COGS — ТЭО | C9: =-C6*'Предпосылки'!$B$14 | D9: =-D6*'Предпосылки'!$B$14 | E9: =-E6*'Предпосылки'!$B$14 | F9: =-F6*'Предпосылки'!$B$14 | G9: =-G6*'Предпосылки'!$B$14 | H9: =-H6*'Предпосылки'!$B$14 | I9: =SUM(C9:H9)
A10: Себестоимость, итого | C10: =C8+C9 | D10: =D8+D9 | E10: =E8+E9 | F10: =F8+F9 | G10: =G8+G9 | H10: =H8+H9 | I10: =SUM(C10:H10)
A11: ВАЛОВАЯ ПРИБЫЛЬ | C11: =C7+C10 | D11: =D7+D10 | E11: =E7+E10 | F11: =F7+F10 | G11: =G7+G10 | H11: =H7+H10 | I11: =SUM(C11:H11)
A12: Операционные расходы (SG&A) | C12: =-'Предпосылки'!$B$17*(1+'Предпосылки'!$B$18)^0 | D12: =-'Предпосылки'!$B$17*(1+'Предпосылки'!$B$18)^1 | E12: =-'Предпосылки'!$B$17*(1+'Предпосылки'!$B$18)^2 | F12: =-'Предпосылки'!$B$17*(1+'Предпосылки'!$B$18)^3 | G12: =-'Предпосылки'!$B$17*(1+'Предпосылки'!$B$18)^4 | H12: =-'Предпосылки'!$B$17*(1+'Предпосылки'!$B$18)^5 | I12: =SUM(C12:H12)
A13: EBITDA | C13: =C11+C12 | D13: =D11+D12 | E13: =E11+E12 | F13: =F11+F12 | G13: =G11+G12 | H13: =H11+H12 | I13: =SUM(C13:H13)
A14: Налоги | C14: =-C7*'Предпосылки'!$B$19 | D14: =-D7*'Предпосылки'!$B$19 | E14: =-E7*'Предпосылки'!$B$19 | F14: =-F7*'Предпосылки'!$B$19 | G14: =-G7*'Предпосылки'!$B$19 | H14: =-H7*'Предпосылки'!$B$19 | I14: =SUM(C14:H14)
A15: Финансовые доходы (% депозиты) | C15: ='Предпосылки'!$B$22 | D15: ='Предпосылки'!$B$22 | E15: ='Предпосылки'!$B$22 | F15: ='Предпосылки'!$B$22 | G15: ='Предпосылки'!$B$22 | H15: ='Предпосылки'!$B$22 | I15: =SUM(C15:H15)
A16: Финансовые расходы (% кредиты) | C16: =-'Предпосылки'!$B$23 | D16: =-'Предпосылки'!$B$23 | E16: =-'Предпосылки'!$B$23 | F16: =-'Предпосылки'!$B$23 | G16: =-'Предпосылки'!$B$23 | H16: =-'Предпосылки'!$B$23 | I16: =SUM(C16:H16)
A17: ЧИСТАЯ ПРИБЫЛЬ | C17: =C13+C14+C15+C16 | D17: =D13+D14+D15+D16 | E17: =E13+E14+E15+E16 | F17: =F13+F14+F15+F16 | G17: =G13+G14+G15+G16 | H17: =H13+H14+H15+H16 | I17: =SUM(C17:H17)
A19: Справочно — маржа, %
A20: Валовая маржа | C20: =IFERROR(C11/C7,0) | D20: =IFERROR(D11/D7,0) | E20: =IFERROR(E11/E7,0) | F20: =IFERROR(F11/F7,0) | G20: =IFERROR(G11/G7,0) | H20: =IFERROR(H11/H7,0) | I20: =IFERROR(I11/I7,0)
A21: EBITDA-маржа | C21: =IFERROR(C13/C7,0) | D21: =IFERROR(D13/D7,0) | E21: =IFERROR(E13/E7,0) | F21: =IFERROR(F13/F7,0) | G21: =IFERROR(G13/G7,0) | H21: =IFERROR(H13/H7,0) | I21: =IFERROR(I13/I7,0)
A22: Чистая маржа | C22: =IFERROR(C17/C7,0) | D22: =IFERROR(D17/D7,0) | E22: =IFERROR(E17/E7,0) | F22: =IFERROR(F17/F7,0) | G22: =IFERROR(G17/G7,0) | H22: =IFERROR(H17/H7,0) | I22: =IFERROR(I17/I7,0)

Sheet Бюджет ДДС
A1: БЮДЖЕТ · ДВИЖЕНИЕ ДЕНЕЖНЫХ СРЕДСТВ · H2 2026
A2: ТОО «WayStar Group» (БИН 240340014287) · ₸
A4: Статья | C4: Июль 2026 | D4: Август 2026 | E4: Сентябрь 2026 | F4: Октябрь 2026 | G4: Ноябрь 2026 | H4: Декабрь 2026 | I4: ИТОГО H2
A5: Денежные средства на начало месяца | C5: ='Предпосылки'!$B$26 | D5: =C10 | E5: =D10 | F5: =E10 | G5: =F10 | H5: =G10 | I5: =C5
A6: Чистая прибыль (операц. поток) | C6: ='Бюджет P&L'!C17 | D6: ='Бюджет P&L'!D17 | E6: ='Бюджет P&L'!E17 | F6: ='Бюджет P&L'!F17 | G6: ='Бюджет P&L'!G17 | H6: ='Бюджет P&L'!H17 | I6: =SUM(C6:H6)
A7: Погашение основного долга | C7: =-'Предпосылки'!$B$24 | D7: =-'Предпосылки'!$B$24 | E7: =-'Предпосылки'!$B$24 | F7: =-'Предпосылки'!$B$24 | G7: =-'Предпосылки'!$B$24 | H7: =-'Предпосылки'!$B$24 | I7: =SUM(C7:H7)
A8: Новые займы / транши | C8: ='Предпосылки'!$B$25 | D8: ='Предпосылки'!$B$25 | E8: ='Предпосылки'!$B$25 | F8: ='Предпосылки'!$B$25 | G8: ='Предпосылки'!$B$25 | H8: ='Предпосылки'!$B$25 | I8: =SUM(C8:H8)
A9: Чистый денежный поток за месяц | C9: =C6+C7+C8 | D9: =D6+D7+D8 | E9: =E6+E7+E8 | F9: =F6+F7+F8 | G9: =G6+G7+G8 | H9: =H6+H7+H8 | I9: =SUM(C9:H9)
A10: Денежные средства на конец месяца | C10: =C5+C9 | D10: =D5+D9 | E10: =E5+E9 | F10: =F5+F9 | G10: =G5+G9 | H10: =H5+H9 | I10: =H10
A12: Свободный денежный поток (для депозитов/дивидендов) | C12: =C6+C7 | D12: =D6+D7 | E12: =E6+E7 | F12: =F6+F7 | G12: =G6+G7 | H12: =H6+H7 | I12: =SUM(C12:H12)

Sheet Предпосылки
A1: ПРЕДПОСЫЛКИ БЮДЖЕТА · H2 2026 (июль–декабрь)
A2: ТОО «WayStar Group» (БИН 240340014287) · жёлтые ячейки — редактируемые драйверы; отчёты пересчитываются автоматически
A4: ВЫРУЧКА (база — факт 15.06–15.07.2026, ₸/мес)
A5: Базовая выручка — Аренда (сдача вагонов/цистерн) | B5: 56187810 | C5: из факт-месяца
A6: Базовая выручка — ТЭО (экспедирование, тариф) | B6: 862311401 | C6: из факт-месяца
A7: Нормализация базы, % | B7: 0.85 | C7: хайркат под разовые авансы QAZAQ (ТЭО 200+160 млн)
A8: Рост выручки, %/мес | B8: 0 | C8: органический рост month-over-month
A9: Сезонность по месяцам (коэффициент): | C9: Июль | D9: Август | E9: Сентябрь | F9: Октябрь | G9: Ноябрь | H9: Декабрь
A10: коэффициент сезонности | C10: 1 | D10: 1 | E10: 1 | F10: 1 | G10: 1 | H10: 1
A12: СЕБЕСТОИМОСТЬ (% от выручки сегмента)
A13: COGS Аренда, % от выручки Аренда | B13: 0.781 | C13: аренда вагонов у собственников
A14: COGS ТЭО, % от выручки ТЭО | B14: 0.696 | C14: ж/д тариф РК + иностр. транзит + ремонт
A16: ОПЕРАЦИОННЫЕ РАСХОДЫ И НАЛОГИ
A17: OPEX базовый (ЗП, аренда, банк, связь), ₸/мес | B17: 44322821 | C17: условно-постоянные
A18: Инфляция OPEX, %/мес | B18: 0
A19: Налоги, % от выручки (касс. оценка) | B19: 0.0153 | C19: payroll+соц.+КПН за нерезид.
A21: ФИНАНСЫ И ДЕНЕЖНЫЕ СРЕДСТВА (₸/мес)
A22: Доход по депозитам | B22: 3904212 | C22: % на размещённые средства
A23: Проценты по кредитам | B23: 32448254 | C23: обслуживание долга (факт вкл. пени)
A24: Погашение основного долга | B24: 0 | C24: плановое, если есть график
A25: Новые займы / транши | B25: 0 | C25: привлечение финансирования
A26: Остаток денежных средств на начало H2 | B26: 113411502 | C26: =остаток на 15.07.2026 (4 счёта)

Sheet База (факт)
A1: БАЗА БЮДЖЕТА — ФАКТ ЗА 15.06–15.07.2026 (₸/мес)
A2: Месячный run-rate из консолидированной управленческой отчётности (4 счёта)
A4: Показатель | B4: ₸/мес | C4: % выручки
A5: Выручка — Аренда | B5: 56187810 | C5: 0.061173498
A6: Выручка — ТЭО | B6: 862311401 | C6: 0.9388265
A7: Выручка, итого | B7: 918499211 | C7: 1
A8: COGS — Аренда | B8: -43894920 | C8: -0.047789829
A9: COGS — ТЭО | B9: -600389998 | C9: -0.65366414
A10: Себестоимость, итого | B10: -644284918 | C10: -0.70145397
A11: ВАЛОВАЯ ПРИБЫЛЬ | B11: 274214293 | C11: 0.29854603
A12: Операционные расходы | B12: -44322821 | C12: -0.048255698
A13: EBITDA | B13: 229891472 | C13: 0.25029033
A14: Налоги | B14: -14012510 | C14: -0.015255876
A15: Финансовые доходы | B15: 3904212 | C15: 0.0042506422
A16: Финансовые расходы | B16: -32448254 | C16: -0.035327471
A17: ЧИСТАЯ ПРИБЫЛЬ | B17: 187334920 | C17: 0.20395763
A19: Оговорка: база — 1 месяц. Крупные авансовые платежи QAZAQ-ASTYQ (ТЭО «предоставление цистерн» 200 и 160 млн ₸) могут покрывать несколько месяцев, поэтому в бюджете применяется нормализация (по умолчанию 85%). Отчётность кассовая. Рекомендуется калибровать базовую выручку по договорам/нескольким месяцам факта.
