Workbook

Sheet Резюме
A1: УПРАВЛЕНЧЕСКАЯ ОТЧЁТНОСТЬ
A2: ТОО «WayStar Group» (БИН 240340014287)
A3: Период: 15.06.2026 – 15.07.2026 · выписки 3 банков (БЦК, Halyk, Bank RBK) · валюта: KZT
A4: Метод: кассовый (по фактическому движению денег). Все показатели — формулы.
A6: КЛЮЧЕВЫЕ ПОКАЗАТЕЛИ (₸)
A7: Выручка (поступления от клиентов) | D7: ='P&L (кассовый)'!B5
A8: Себестоимость (ж/д тариф, вагоны, ремонт) | D8: ='P&L (кассовый)'!B10
A9: ВАЛОВАЯ ПРИБЫЛЬ | D9: ='P&L (кассовый)'!B11
A10: валовая маржа, % | D10: =IFERROR('P&L (кассовый)'!B11/'P&L (кассовый)'!B7,0)
A11: Операционные расходы (SG&A) | D11: ='P&L (кассовый)'!B19
A12: EBITDA | D12: ='P&L (кассовый)'!B20
A13: Налоги уплаченные | D13: ='P&L (кассовый)'!B21
A14: Финансовые доходы / расходы | D14: ='P&L (кассовый)'!B22+'P&L (кассовый)'!B23
A15: ЧИСТАЯ ПРИБЫЛЬ (кассовая) | D15: ='P&L (кассовый)'!B24
A16: чистая маржа, % | D16: =IFERROR('P&L (кассовый)'!B24/'P&L (кассовый)'!B7,0)
A17: ДВИЖЕНИЕ ДЕНЕЖНЫХ СРЕДСТВ (свод, ₸)
A18: Денежные средства на начало периода | D18: =297933.26
A19: Операционный денежный поток | D19: ='P&L (кассовый)'!B24
A20: Инвестиц./казначейские (депозиты, валюта) | D20: =SUMIFS('Реестр операций'!$F:$F,'Реестр операций'!$I:$I,"TREASURY")-SUMIFS('Реестр операций'!$G:$G,'Реестр операций'!$I:$I,"TREASURY")
A21: Финансовые потоки (займы, кредиты) | D21: =SUMIFS('Реестр операций'!$F:$F,'Реестр операций'!$I:$I,"FINANCING")-SUMIFS('Реестр операций'!$G:$G,'Реестр операций'!$I:$I,"FINANCING")
A22: Переводы на прочие счета компании (КЛС и пр.) | D22: =SUMIFS('Реестр операций'!$F:$F,'Реестр операций'!$I:$I,"INTERNAL")-SUMIFS('Реестр операций'!$G:$G,'Реестр операций'!$I:$I,"INTERNAL")
A23: Прочее | D23: =SUMIFS('Реестр операций'!$F:$F,'Реестр операций'!$I:$I,"OTHER_IN")
A24: Денежные средства на конец периода | D24: =113411502.27

Sheet Реестр операций
A1: РЕЕСТР ОПЕРАЦИЙ (классифицированный) — источник данных для формул
A3: Банк | B3: Дата | C3: Контрагент | D3: Контрагент (норм.) | E3: БИН | F3: Поступление | G3: Выплата | H3: КНП | I3: Тип | J3: Категория | K3: Направление | L3: Назначение платежа
A4: Halyk | B4: 15.06.2026 | C4: ТОО "FRS logistics" | D4: FRS logistics | E4: 260140008159 | F4: 940000 | H4: 813 | I4: REVENUE | J4: Выручка: транспортно-логистические услуги | K4: ТЭО | L4: Референс 3982960604 Оперирование вагонов по маршруту жилаево-сороковая согласно счета №130
A5: БЦК | B5: 15.06.2026 | C5: ТАШМЕТОВ САКЕН КУАНЫШЕВИЧ | D5: ТАШМЕТОВ САКЕН КУАНЫШЕВИЧ | E5: 820426301729 | G5: 51900 | H5: 871 | I5: OPEX | J5: Командировочные / поездки | L5: Суточные расходы на проезд в Астана- Алматы -Астана 15-17.06.2026 3рд*4МРП(4325 МРП) (V еж
A6: БЦК | B6: 15.06.2026 | C6: Бажикаев Абылайхан Серикович | D6: Бажикаев Абылайхан Серикович | E6: 941019350088 | G6: 51900 | H6: 871 | I6: OPEX | J6: Командировочные / поездки | L6: Суточные расходы на проезд в Астана- Алматы -Астана 15-17.06.2026 3рд*4МРП(4325 МРП) (V еж
A7: БЦК | B7: 15.06.2026 | C7: Товарищество с ограниченной ответственностью | D7: WayStar Group | E7: 240340014287 | G7: 112175.18 | H7: 423 | I7: FIN_COST | J7: Проценты и пени по кредитам | L7: Погашение вознаграждения по договору № AQ5/2024/U/S/120240/0002L от 25.11.25. Заемщик: Тов
A8: БЦК | B8: 15.06.2026 | C8: Товарищество с ограниченной ответственностью | D8: WayStar Group | E8: 240340014287 | G8: 510874.29 | H8: 423 | I8: FIN_COST | J8: Проценты и пени по кредитам | L8: Погашение вознаграждения по договору № AQ5/2024/U/S/120240/0002L от 25.11.25. Заемщик: Тов
A9: БЦК | B9: 15.06.2026 | C9: Товарищество с ограниченной ответственностью | D9: WayStar Group | E9: 240340014287 | G9: 3854907.2 | H9: 423 | I9: FINANCING | J9: Погашение / выдача займов | L9: Погашение основного долга по договору № AQ5/2024/U/S/120240/0002L от 25.11.25. Заемщик: То
A10: БЦК | B10: 15.06.2026 | C10: ТОО КТЖ-Грузовые перевозки | D10: КТЖ-Грузовые перевозки | E10: 031040001799 | G10: 20000000 | H10: 813 | I10: COGS | J10: Ж/д тариф, вагоны, услуги перевозчиков | K10: ТЭО | L10: Без НДС, 4185494, Платежи за услуги железнодорожного транспорта
A11: БЦК | B11: 15.06.2026 | C11: Товарищество с ограниченной ответственностью | D11: WayStar Group | E11: 240340014287 | G11: 1.0494287e+08 | H11: 312 | I11: TREASURY | J11: Размещение депозита | L11: Размещение вклада
A12: БЦК | B12: 15.06.2026 | C12: Товарищество с ограниченной ответственностью | D12: WayStar Group | E12: 240340014287 | F12: 36828.94 | H12: 316 | I12: FIN_INCOME | J12: % по депозиту | L12: Выплата начисленного вознаграждения по депозитному договору № 01607034 от 24.07.2025 за пе
A13: БЦК | B13: 15.06.2026 | C13: ТОО "UE LOGISTIC" | D13: UE LOGISTIC | E13: 200940000330 | F13: 345000 | H13: 813 | I13: REVENUE | J13: Выручка: транспортно-логистические услуги | K13: ТЭО | L13: оплата по счету № 118 от 29.06.2026. Без НДС. Платежи за услуги железнодорожного транспорт
A14: БЦК | B14: 15.06.2026 | C14: Товарищество с ограниченной ответственностью | D14: WayStar Group | E14: 240340014287 | F14: 20000000 | H14: 322 | I14: TREASURY | J14: Снятие/возврат депозита | L14: Без НДС. Снятие с краткосрочного вклада (не более одного года)
A15: БЦК | B15: 15.06.2026 | C15: Товарищество с ограниченной ответственностью | D15: WayStar Group | E15: 240340014287 | F15: 1.0906745e+08 | H15: 322 | I15: TREASURY | J15: Снятие/возврат депозита | L15: Частичная выплата вклада по депозитному договору № 01607034 от 15.06.2026 в размере 109067
A16: БЦК | B16: 16.06.2026 | C16: МАРАТОВ РАУАН РУСТЕМОВИЧ | D16: МАРАТОВ РАУАН РУСТЕМОВИЧ | E16: 000327551085 | G16: 85000 | H16: 332 | I16: OPEX | J16: Оплата труда | L16: Аванс июнь 2026. Без НДС. Перечисление юридическим лицом в банк, филиал банка-нерезидента
A17: БЦК | B17: 16.06.2026 | C17: Товарищество с ограниченной ответственностью | D17: 7 Дом | E17: 180140037700 | G17: 236400 | H17: 710 | I17: OPEX | J17: ТМЦ / офисные расходы | L17: Счет на оплату № 85 от 09.06.2026 г. Ежедневник датированный А5 формат 40 шт
A18: БЦК | B18: 16.06.2026 | C18: Товарищество с ограниченной ответственностью | D18: Asia Railways Tracking Service (Азия Рэилвейс Трекинг Сервис) | E18: 130540005778 | G18: 500000 | H18: 813 | I18: COGS | J18: Ж/д тариф, вагоны, услуги перевозчиков | K18: ТЭО | L18: Счет на оплату №И-1760 от 16.06.2026 г. Авансовая оплата за дислокацию подвижного состава.
A19: БЦК | B19: 16.06.2026 | C19: Акционерное общество "Страховая компания "Евр | D19: Страховая компания "Евразия | E19: 950540000024 | G19: 575000 | H19: 833 | I19: OPEX | J19: Страхование | L19: Счет на оплату № 116425 от 16 июня 2026 г Страхование имущества от ущерба Страховая премия
A20: БЦК | B20: 16.06.2026 | C20: Товарищество с ограниченной ответственностью | D20: Қамқор Вагон | E20: 030440002799 | G20: 627229.4 | H20: 822 | I20: COGS | J20: Ж/д тариф, вагоны, услуги перевозчиков | K20: ТЭО | L20: филиал Аякозское депо Қамқор Вагон ТОО оплата долга согл акта сверки
A21: БЦК | B21: 16.06.2026 | C21: Данияр Алим | D21: Данияр Алим | E21: 020420550046 | G21: 1135000 | H21: 419 | I21: FINANCING | J21: Погашение / выдача займов | L21: займ. Без НДС. Выдача прочих займов (бессрочных займов и других займов)
A22: БЦК | B22: 16.06.2026 | C22: Товарищество с ограниченной ответственностью | D22: MAT Group | E22: 170940027374 | G22: 3795000 | H22: 813 | I22: COGS | J22: Ж/д тариф, вагоны, услуги перевозчиков | K22: ТЭО | L22: Договор № ТЭЭ-030626/260 от 04.06.2026 г. Счет на оплату № К-12878/26 от 15.06.2026 г. Пре
A23: БЦК | B23: 16.06.2026 | C23: Товарищество с ограниченной ответственностью | D23: WayStar Group | E23: 240340014287 | G23: 68954462 | H23: 312 | I23: TREASURY | J23: Размещение депозита | L23: Размещение вклада
A24: БЦК | B24: 16.06.2026 | C24: Товарищество с ограниченной ответственностью | D24: WayStar Group | E24: 240340014287 | F24: 25240.21 | H24: 316 | I24: FIN_INCOME | J24: % по депозиту | L24: Выплата начисленного вознаграждения по депозитному договору № 01607034 от 24.07.2025 за пе
A25: БЦК | B25: 16.06.2026 | C25: Товарищество с ограниченной ответственностью | D25: WayStar Group | E25: 240340014287 | F25: 1135000 | H25: 322 | I25: TREASURY | J25: Снятие/возврат депозита | L25: Снятие с депозита. Без НДС. Снятие с краткосрочного вклада (не более одного года)
A26: БЦК | B26: 16.06.2026 | C26: Товарищество с ограниченной ответственностью | D26: WayStar Group | E26: 240340014287 | F26: 74747851 | H26: 322 | I26: TREASURY | J26: Снятие/возврат депозита | L26: Частичная выплата вклада по депозитному договору № 01607034 от 16.06.2026 в размере 747478
A27: RBK | B27: 17.06.2026 | C27: ТОО East Agro Company | D27: East Agro Company | E27: 230340042290 | F27: 17936232 | I27: REVENUE | J27: Выручка: транспортно-логистические услуги | K27: ТЭО | L27: Оплата за услуги по счету 135 от 15.06.2026 Без налога (НДС) Договор: 2026/06-45 от 11.06.
A28: RBK | B28: 17.06.2026 | C28: ТОО Altyn Shyghys | D28: Altyn Shyghys | E28: 190140000545 | F28: 42353600 | I28: REVENUE | J28: Выручка: транспортно-логистические услуги | K28: ТЭО | L28: Оплата за услуги по счету 136 от 15.06.2026 Без налога (НДС) Договор: 2026/01-04 ТЭУ от 13
A29: RBK | B29: 17.06.2026 | C29: ФИЛИАЛ АО "BANK RBK" В Г.АСТАНА | D29: ФИЛИАЛ АО "BANK RBK" В Г.АСТАНА | E29: 111141019679 | G29: 1300 | I29: OPEX | J29: Прочие услуги и расходы | L29: Комиссия Банка за переводные операции по платежному документу № 1175 от 17/06/2026, в т.ч.
A30: RBK | B30: 17.06.2026 | C30: ТОО "WayStar Group" | D30: WayStar Group | E30: 240340014287 | G30: 42353600 | I30: INTERNAL | J30: Переводы между своими счетами | L30: перевод на другой счет Переводы клиентом денег со своего текущего счета в одном банке, фил
A31: БЦК | B31: 17.06.2026 | C31: Акционерное Общество "Банк ЦентрКредит" | D31: Банк ЦентрКредит | E31: 980640000093 | G31: 97434 | H31: 841 | I31: OPEX | J31: Банковские услуги | L31: Интернет-банкинг. MIP. Международные платежи. Перевод OUR, кроме валют стран СНГ с 13:00 п
A32: БЦК | B32: 17.06.2026 | C32: ТОО КТЖ-Грузовые перевозки | D32: КТЖ-Грузовые перевозки | E32: 031040001799 | G32: 10000000 | H32: 813 | I32: COGS | J32: Ж/д тариф, вагоны, услуги перевозчиков | K32: ТЭО | L32: Без НДС, 4185494, Платежи за услуги железнодорожного транспорта
A33: БЦК | B33: 17.06.2026 | C33: Акционерное Общество "Банк ЦентрКредит" | D33: Банк ЦентрКредит | E33: 980640000093 | G33: 48950000 | H33: 213 | I33: TREASURY | J33: Покупка валюты (FX) | L33: Покупка иностранной валюты TOD (день в день), Товарищество с ограниченной ответственностью
A34: БЦК | B34: 17.06.2026 | C34: Товарищество с ограниченной ответственностью | D34: WayStar Group | E34: 240340014287 | G34: 53882653 | H34: 312 | I34: TREASURY | J34: Размещение депозита | L34: Размещение вклада
A35: БЦК | B35: 17.06.2026 | C35: Товарищество с ограниченной ответственностью | D35: WayStar Group | E35: 240340014287 | F35: 22900.67 | H35: 316 | I35: FIN_INCOME | J35: % по депозиту | L35: Выплата начисленного вознаграждения по депозитному договору № 01607034 от 24.07.2025 за пе
A36: БЦК | B36: 17.06.2026 | C36: ТОО Rhenus Intermodal Systems | D36: Rhenus Intermodal Systems | E36: 081040014452 | F36: 2734125 | H36: 814 | I36: REVENUE | J36: Выручка: транспортно-логистические услуги | K36: ТЭО | L36: оплата эсф 152 от 31.05.26 оперирование ПС Платежи за услуги иного сухопутного транспорта,
A37: БЦК | B37: 17.06.2026 | C37: ТОО "WayStar Group" | D37: WayStar Group | E37: 240340014287 | F37: 42353600 | H37: 343 | I37: INTERNAL | J37: Переводы между своими счетами | L37: перевод на другой счет Переводы клиентом денег со своего текущего счета в одном банке, фил
A38: БЦК | B38: 17.06.2026 | C38: Товарищество с ограниченной ответственностью | D38: WayStar Group | E38: 240340014287 | F38: 67819462 | H38: 322 | I38: TREASURY | J38: Снятие/возврат депозита | L38: Частичная выплата вклада по депозитному договору № 01607034 от 17.06.2026 в размере 678194
A39: RBK | B39: 18.06.2026 | C39: ФИЛИАЛ АО "BANK RBK" В Г.АСТАНА | D39: ФИЛИАЛ АО "BANK RBK" В Г.АСТАНА | E39: 111141019679 | G39: 932 | I39: OPEX | J39: Прочие услуги и расходы | L39: Комиссия Банка за переводные операции по платежному документу № 1176 от 18/06/2026, в т.ч.
A40: RBK | B40: 18.06.2026 | C40: ТОО "WayStar Group" | D40: WayStar Group | E40: 240340014287 | G40: 17934000 | I40: INTERNAL | J40: Переводы между своими счетами | L40: перевод на другой счет Переводы клиентом денег со своего текущего счета в одном банке, фил
A41: БЦК | B41: 18.06.2026 | C41: Акционерное Общество "Банк ЦентрКредит" | D41: Банк ЦентрКредит | E41: 980741000260 | G41: 2500 | H41: 841 | I41: OPEX | J41: Банковские услуги | L41: Интернет-банкинг. MIP. Международные платежи. Перевод в валютах стран СНГ, OUR с 9:00 до
A42: БЦК | B42: 18.06.2026 | C42: Товарищество с ограниченной ответственностью | D42: Современные Печатные технологии | E42: 151140003068 | G42: 18060 | H42: 710 | I42: OPEX | J42: ТМЦ / офисные расходы | L42: Счет на оплату № 1311-2260 от 18 июня 2026 г. Визитки 84 шт,Счет на оплату 1311-2224 от 17
A43: БЦК | B43: 18.06.2026 | C43: Акционерное Общество "Банк ЦентрКредит" | D43: Банк ЦентрКредит | E43: 980640000093 | G43: 162393.59 | H43: 213 | I43: TREASURY | J43: Покупка валюты (FX) | L43: Покупка иностранной валюты TOD (день в день), Товарищество с ограниченной ответственностью
A44: БЦК | B44: 18.06.2026 | C44: Акционерное общество "ОЛЖА" | D44: ОЛЖА | E44: 980240003083 | G44: 330000 | H44: 822 | I44: COGS | J44: Ж/д тариф, вагоны, услуги перевозчиков | K44: ТЭО | L44: Счет на оплату № 557 от 17.06.2026 г. ТЭУ крытых вагонов Жана -Есиль -ПредгорнаяСумма 330
A45: БЦК | B45: 18.06.2026 | C45: Товарищество с ограниченной ответственностью | D45: Ремвагон | E45: 210740025281 | G45: 606216 | H45: 822 | I45: OPEX | J45: Прочие услуги и расходы | L45: Счет на оплату № 20000000651 от 16.06.2026 ТОР
A46: БЦК | B46: 18.06.2026 | C46: Акционерное общество "Банк "Bank RBK" | D46: Банк "Bank RBK | E46: 920440001102 | G46: 1000000 | H46: 332 | I46: OPEX | J46: Оплата труда | L46: Аубакиров Алимбек Ерикович аванс РБК июнь 2026
A47: БЦК | B47: 18.06.2026 | C47: Товарищество с ограниченной ответственностью | D47: WayStar Group | E47: 240340014287 | G47: 12392426 | H47: 342 | I47: INTERNAL | J47: Переводы между своими счетами | L47: Перевод на КЛС. Без НДС. Переводы клиентом денег с одного своего текущего счета, открытого
A48: БЦК | B48: 18.06.2026 | C48: Товарищество с ограниченной ответственностью | D48: WayStar Group | E48: 240340014287 | G48: 57323252 | H48: 312 | I48: TREASURY | J48: Размещение депозита | L48: Размещение вклада
A49: БЦК | B49: 18.06.2026 | C49: Товарищество с ограниченной ответственностью | D49: WayStar Group | E49: 240340014287 | F49: 18194.62 | H49: 316 | I49: FIN_INCOME | J49: % по депозиту | L49: Выплата начисленного вознаграждения по депозитному договору № 01607034 от 24.07.2025 за пе
A50: БЦК | B50: 18.06.2026 | C50: ТОО "WayStar Group" | D50: WayStar Group | E50: 240340014287 | F50: 17934000 | H50: 343 | I50: INTERNAL | J50: Переводы между своими счетами | L50: перевод на другой счет Переводы клиентом денег со своего текущего счета в одном банке, фил
A51: БЦК | B51: 18.06.2026 | C51: Товарищество с ограниченной ответственностью | D51: WayStar Group | E51: 240340014287 | F51: 53882653 | H51: 322 | I51: TREASURY | J51: Снятие/возврат депозита | L51: Частичная выплата вклада по депозитному договору № 01607034 от 18.06.2026 в размере 538826
A52: Halyk | B52: 19.06.2026 | C52: ТОО "WayStar Group" | D52: WayStar Group | E52: 240340014287 | G52: 11263537 | H52: 343 | I52: INTERNAL | J52: Переводы между своими счетами | L52: Референс 3990386775 перевод на др счет Переводы клиентом денег со своего текущего счета в
A53: Halyk | B53: 19.06.2026 | C53: ТОО "GREENLIGHTS (ГРИНЛАЙТС)" | D53: GREENLIGHTS (ГРИНЛАЙТС) | E53: 210840025853 | F53: 9000000 | H53: 813 | I53: REVENUE | J53: Выручка: транспортно-логистические услуги | K53: ТЭО | L53: Референс 3990350285 Оперирование собстенным ПС согл счету №133 от 12.06.2026 Сумма 9000000
A54: Halyk | B54: 19.06.2026 | C54: STAR TRANS | D54: STAR TRANS | E54: 060340001920 | F54: 1101950 | H54: 813 | I54: REVENUE | J54: Выручка: транспортно-логистические услуги | K54: ТЭО | L54: Референс 3990091198 Предоплата за услуги оператора вагонами , согласно счет - фактура № 15
A55: БЦК | B55: 19.06.2026 | C55: Индивидуальный предприниматель "Катрышева" | D55: Катрышева | E55: 900902450133 | G55: 32500 | H55: 859 | I55: OPEX | J55: Прочие услуги и расходы | L55: Счет на оплату № 523 от 19.06.2026 г. Изготовление листовок 100 шт
A56: БЦК | B56: 19.06.2026 | C56: Товарищество с ограниченной ответственностью | D56: STRATACxO | E56: 210640000619 | G56: 800000 | H56: 861 | I56: OPEX | J56: Прочие услуги и расходы | L56: Договор № 76/26 от 27 апреля 2026 года Счет на оплату № 19 от 20 мая 2026 г. Проведение би
A57: БЦК | B57: 19.06.2026 | C57: Товарищество с ограниченной ответственностью | D57: Рейл Транспортейшн | E57: 221040045601 | G57: 3646962 | H57: 813 | I57: COGS | J57: Ж/д тариф, вагоны, услуги перевозчиков | K57: ТЭО | L57: Договор RT/151 от 12.11.2024 г. INVOICE N 1253 от 18.06.2026 INVOICE N 1237 от 16/06/2026
A58: БЦК | B58: 19.06.2026 | C58: Товарищество с ограниченной ответственностью | D58: WayStar Group | E58: 240340014287 | G58: 11263537 | H58: 312 | I58: TREASURY | J58: Размещение депозита | L58: Без НДС. Размещение краткосрочных вкладов (не более одного года)
A59: БЦК | B59: 19.06.2026 | C59: КТТ (ҚАЗТЕМІРТРАНС) АО | D59: КТТ (ҚАЗТЕМІРТРАНС) АО | E59: 031040000572 | G59: 12098184 | H59: 813 | I59: COGS | J59: Ж/д тариф, вагоны, услуги перевозчиков | K59: ТЭО | L59: предоплата согласно счета № К-206321/26 от 19.06.2026 Договор № 20-02-2026/14989-НПрк от 2
A60: БЦК | B60: 19.06.2026 | C60: ТОО КТЖ-Грузовые перевозки | D60: КТЖ-Грузовые перевозки | E60: 031040001799 | G60: 17000000 | H60: 813 | I60: COGS | J60: Ж/д тариф, вагоны, услуги перевозчиков | K60: ТЭО | L60: Без НДС, 4185494, Платежи за услуги железнодорожного транспорта
A61: БЦК | B61: 19.06.2026 | C61: Товарищество с ограниченной ответственностью | D61: WayStar Group | E61: 240340014287 | G61: 24636338 | H61: 312 | I61: TREASURY | J61: Размещение депозита | L61: Размещение вклада
A62: БЦК | B62: 19.06.2026 | C62: Товарищество с ограниченной ответственностью | D62: WayStar Group | E62: 240340014287 | G62: 40000000 | H62: 312 | I62: TREASURY | J62: Размещение депозита | L62: Размещение вклада
A63: БЦК | B63: 19.06.2026 | C63: Товарищество с ограниченной ответственностью | D63: WayStar Group | E63: 240340014287 | F63: 19356.41 | H63: 316 | I63: FIN_INCOME | J63: % по депозиту | L63: Выплата начисленного вознаграждения по депозитному договору № 01607034 от 24.07.2025 за пе
A64: БЦК | B64: 19.06.2026 | C64: Товарищество с ограниченной ответственностью | D64: Максат-2030 | E64: 000340002422 | F64: 871375 | H64: 813 | I64: REVENUE | J64: Выручка: транспортно-логистические услуги | K64: ТЭО | L64: Оплата за услуги по оперированию вагонов, контейнеров. ЭСФ №140 от 31.05.2026. Платежи за
A65: БЦК | B65: 19.06.2026 | C65: ТОО WayStar Group | D65: WayStar Group | E65: 240340014287 | F65: 11263537 | H65: 343 | I65: INTERNAL | J65: Переводы между своими счетами | L65: перевод на др счет Переводы клиентом денег со своего текущего счета в одном банке филиале
A66: БЦК | B66: 19.06.2026 | C66: ТОО "Mining Consulting Group" | D66: Mining Consulting Group | E66: 190440040941 | F66: 40000000 | H66: 411 | I66: FINANCING | J66: Займы полученные / возврат выданных | L66: За выдачу краткосрочных займов (не более одного года). Выплата согласно Договора о временн
A67: БЦК | B67: 19.06.2026 | C67: Товарищество с ограниченной ответственностью | D67: WayStar Group | E67: 240340014287 | F67: 57323252 | H67: 322 | I67: TREASURY | J67: Снятие/возврат депозита | L67: Частичная выплата вклада по депозитному договору № 01607034 от 19.06.2026 в размере 573232
A68: БЦК | B68: 20.06.2026 | C68: Товарищество с ограниченной ответственностью | D68: WayStar Group | E68: 240340014287 | G68: 3803.38 | H68: 421 | I68: FINANCING | J68: Погашение / выдача займов | L68: Погашение просроченного основного долга по договору № AST/2025/U/O/1034171681 от . Заемщик
A69: БЦК | B69: 20.06.2026 | C69: Товарищество с ограниченной ответственностью | D69: WayStar Group | E69: 240340014287 | F69: 3803.38 | H69: 316 | I69: FIN_INCOME | J69: % по депозиту | L69: Выплата начисленного вознаграждения по депозитному договору № 01607034 от 24.07.2025 за пе
A70: Halyk | B70: 21.06.2026 | C70: ТОО "КТЖ-ГРУЗОВЫЕ ПЕРЕВОЗКИ" | D70: КТЖ-ГРУЗОВЫЕ ПЕРЕВОЗКИ | E70: 031040001799 | G70: 1000 | H70: 813 | I70: COGS | J70: Ж/д тариф, вагоны, услуги перевозчиков | K70: ТЭО | L70: Референс 3992518218 4185494, Без НДС, Платежи за услуги железнодорожного транспортаПлатежи
A71: БЦК | B71: 21.06.2026 | C71: Центральное отделение №0401 | D71: Центральное отделение №0401 | E71: 980741000260 | G71: 3803.37 | H71: 119 | I71: FIN_COST | J71: Проценты и пени по кредитам | L71: Погашение начисленных пени по просроченному основному долгу по договору № AST/2025/U/O/103
A72: БЦК | B72: 21.06.2026 | C72: АО "Банк ЦентрКредит" | D72: Банк ЦентрКредит | E72: 980640000093 | G72: 10000 | H72: 423 | I72: FIN_COST | J72: Проценты и пени по кредитам | L72: ПТ № 4776499 от 21.06.2026. Частичная оплата К2.Безакцептное погашение задолженности Товар
A73: БЦК | B73: 21.06.2026 | C73: Товарищество с ограниченной ответственностью | D73: WayStar Group | E73: 240340014287 | F73: 3803.37 | H73: 316 | I73: FIN_INCOME | J73: % по депозиту | L73: Выплата начисленного вознаграждения по депозитному договору № 01607034 от 24.07.2025 за пе
A74: БЦК | B74: 21.06.2026 | C74: Данияр Алим | D74: Данияр Алим | E74: 020420550046 | F74: 10000 | H74: 421 | I74: FINANCING | J74: Займы полученные / возврат выданных | L74: Перевод с счета KZ658562204136676815 на счета KZ768562203136652401 через систему BCC.KZ. И
A75: Halyk | B75: 22.06.2026 | C75: ТОО K-Portal | D75: K-Portal | E75: 160740003695 | F75: 1000000 | H75: 813 | I75: REVENUE | J75: Выручка: транспортно-логистические услуги | K75: ТЭО | L75: Референс 3993913795 За предоставление вагонов по счету на оплату № 000000104 от 15.05.2026
A76: Halyk | B76: 22.06.2026 | C76: Данияр Алим | D76: Данияр Алим | E76: 020420550046 | F76: 10000 | H76: 119 | I76: FIN_COST | J76: Проценты и пени по кредитам | L76: Референс 3993102969 Прочие безвозмездные переводы. Безналичный перевод. ИИН/БИН получателя
A77: Halyk | B77: 22.06.2026 | C77: Данияр Алим | D77: Данияр Алим | E77: 020420550046 | F77: 10000 | H77: 119 | I77: FIN_COST | J77: Проценты и пени по кредитам | L77: Референс 3993102905 Прочие безвозмездные переводы. Безналичный перевод. ИИН/БИН получателя
A78: Halyk | B78: 22.06.2026 | C78: Астанинский городской филиал Народного Банка | D78: Астанинский городской филиал Народного Банка Казахстана | E78: 950341000052 | G78: 5000 | H78: 841 | I78: OPEX | J78: Банковские услуги | L78: Референс 3993100649 Оплата К2 Комиссия за операцию "Абонентская плата" согласно тарифам ба
A79: Halyk | B79: 22.06.2026 | C79: Данияр Алим | D79: Данияр Алим | E79: 020420550046 | F79: 100000 | H79: 610 | I79: OTHER_IN | J79: Прочие поступления | L79: Референс 3993100006 Покупка, выкуп акций и документов, подтверждающих участие в уставном к
A80: Halyk | B80: 22.06.2026 | C80: Данияр Алим | D80: Данияр Алим | E80: 020420550046 | F80: 10000 | H80: 119 | I80: FIN_COST | J80: Проценты и пени по кредитам | L80: Референс 3993097042 Прочие безвозмездные переводы. Безналичный перевод. ИИН/БИН получателя
A81: Halyk | B81: 22.06.2026 | C81: Данияр Алим | D81: Данияр Алим | E81: 020420550046 | F81: 800 | H81: 119 | I81: FIN_COST | J81: Проценты и пени по кредитам | L81: Референс 3993030741 СУБП: Homebank. Прочие безвозмездные переводы денег. Референс: 9C36598
A82: RBK | B82: 22.06.2026 | C82: Товарищество с ограниченной ответственностью | D82: WayStar Group | E82: 240340014287 | F82: 5400000 | I82: INTERNAL | J82: Переводы между своими счетами | L82: перевод на другой счет. Без НДС. Переводы клиентом денег со своего текущего счета в одном
A83: RBK | B83: 22.06.2026 | C83: ФИЛИАЛ АО "BANK RBK" В Г.АСТАНА | D83: ФИЛИАЛ АО "BANK RBK" В Г.АСТАНА | E83: 111141019679 | G83: 368 | I83: OPEX | J83: Прочие услуги и расходы | L83: Просроченные комисионные доходы Комиссия Банка за переводные операции по платежному докуме
A84: RBK | B84: 22.06.2026 | C84: АО "Банк "Bank RBK" | D84: Банк "Bank RBK | E84: 920440001102 | G84: 748 | I84: OPEX | J84: Прочие услуги и расходы | L84: Гашение учтенной пени за процнты по договору номер КЛЮ629600/005-25/5 от 15.05.26 согласно
A85: RBK | B85: 22.06.2026 | C85: АО "Банк "Bank RBK" | D85: Банк "Bank RBK | E85: 920440001102 | G85: 1078 | I85: OPEX | J85: Прочие услуги и расходы | L85: Гашение учтенной пени за процнты по договору номер КЛЮ629600/005-25/7 от 21.05.26 согласно
A86: RBK | B86: 22.06.2026 | C86: АО "Банк "Bank RBK" | D86: Банк "Bank RBK | E86: 920440001102 | G86: 3486 | I86: OPEX | J86: Прочие услуги и расходы | L86: Гашение учтенной пени за процнты по договору номер КЛЮ629600/005-25/6 от 21.05.26 согласно
A87: RBK | B87: 22.06.2026 | C87: АО "Банк "Bank RBK" | D87: Банк "Bank RBK | E87: 920440001102 | G87: 4233 | I87: OPEX | J87: Прочие услуги и расходы | L87: Гашение учтенной пени за процнты по договору номер КЛЮ629600/005-25/4 от 15.05.26 согласно
A88: RBK | B88: 22.06.2026 | C88: АО "Банк "Bank RBK" | D88: Банк "Bank RBK | E88: 920440001102 | G88: 12600 | I88: OPEX | J88: Прочие услуги и расходы | L88: Гашение учтенной пени за процнты по договору номер КЛЮ791149/005-26/1 от 06.03.26 согласно
A89: RBK | B89: 22.06.2026 | C89: АО "Банк "Bank RBK" | D89: Банк "Bank RBK | E89: 920440001102 | G89: 249333.33 | I89: FIN_COST | J89: Проценты и пени по кредитам | L89: Погашение просроченного вознаграждения по договору ТОО "WayStar Group", согласно кредитно
A90: RBK | B90: 22.06.2026 | C90: АО "Банк "Bank RBK" | D90: Банк "Bank RBK | E90: 920440001102 | G90: 359333.33 | I90: FIN_COST | J90: Проценты и пени по кредитам | L90: Погашение просроченного вознаграждения по договору ТОО "WayStar Group", согласно кредитно
A91: RBK | B91: 22.06.2026 | C91: АО "Банк "Bank RBK" | D91: Банк "Bank RBK | E91: 920440001102 | G91: 1162000 | I91: FIN_COST | J91: Проценты и пени по кредитам | L91: Погашение просроченного вознаграждения по договору ТОО "WayStar Group", согласно кредитно
A92: RBK | B92: 22.06.2026 | C92: АО "Банк "Bank RBK" | D92: Банк "Bank RBK | E92: 920440001102 | G92: 1411000 | I92: FIN_COST | J92: Проценты и пени по кредитам | L92: Погашение просроченного вознаграждения по договору ТОО "WayStar Group", согласно кредитно
A93: RBK | B93: 22.06.2026 | C93: АО "Банк "Bank RBK" | D93: Банк "Bank RBK | E93: 920440001102 | G93: 2100000 | I93: FIN_COST | J93: Проценты и пени по кредитам | L93: Погашение просроченного вознаграждения по договору ТОО "WayStar Group", согласно кредитно
A94: БЦК | B94: 22.06.2026 | C94: Банк ЦентрКредит для ЗП | D94: Банк ЦентрКредит для ЗП | E94: 980640000093 | G94: 129535 | H94: 332 | I94: OPEX | J94: Оплата труда | L94: Для зачисления на картсчета сотрудникам согласно спискам 129 535-00 .
A95: БЦК | B95: 22.06.2026 | C95: Центральное отделение №0401 | D95: Центральное отделение №0401 | E95: 980741000260 | G95: 210329.25 | H95: 119 | I95: FIN_COST | J95: Проценты и пени по кредитам | L95: Погашение начисленных пени по просроченному основному долгу по договору № AST/2025/U/O/103
A96: БЦК | B96: 22.06.2026 | C96: Товарищество с ограниченной ответственностью | D96: WayStar Group | E96: 240340014287 | G96: 2768801.2 | H96: 342 | I96: INTERNAL | J96: Переводы между своими счетами | L96: перевод на клс. Без НДС. Переводы клиентом денег с одного своего текущего счета, открытого
A97: БЦК | B97: 22.06.2026 | C97: ТОО КТЖ-Грузовые перевозки | D97: КТЖ-Грузовые перевозки | E97: 031040001799 | G97: 3000000 | H97: 813 | I97: COGS | J97: Ж/д тариф, вагоны, услуги перевозчиков | K97: ТЭО | L97: Без НДС, 4185494, Платежи за услуги железнодорожного транспорта
A98: БЦК | B98: 22.06.2026 | C98: ТОО КТЖ-Грузовые перевозки | D98: КТЖ-Грузовые перевозки | E98: 031040001799 | G98: 5000000 | H98: 813 | I98: COGS | J98: Ж/д тариф, вагоны, услуги перевозчиков | K98: ТЭО | L98: Без НДС, 4185494, Платежи за услуги железнодорожного транспорта
A99: БЦК | B99: 22.06.2026 | C99: Товарищество с ограниченной ответственностью | D99: WayStar Group | E99: 240340014287 | G99: 5400000 | H99: 343 | I99: INTERNAL | J99: Переводы между своими счетами | L99: перевод на другой счет. Без НДС. Переводы клиентом денег со своего текущего счета в одном
A100: БЦК | B100: 22.06.2026 | C100: Товарищество с ограниченной ответственностью | D100: WayStar Group | E100: 240340014287 | G100: 5887713 | H100: 312 | I100: TREASURY | J100: Размещение депозита | L100: Размещение вклада
A101: БЦК | B101: 22.06.2026 | C101: АО "Банк ЦентрКредит" | D101: Банк ЦентрКредит | E101: 980640000093 | G101: 25327822 | H101: 423 | I101: FIN_COST | J101: Проценты и пени по кредитам | L101: ПТ № 4776499 от 21.06.2026. Частичная оплата К2.Безакцептное погашение задолженности Товар
...

Sheet P&L (кассовый)
A1: ОТЧЁТ О ПРИБЫЛЯХ И УБЫТКАХ (кассовый метод)
A2: ТОО «WayStar Group» (БИН 240340014287) · 15.06.2026 – 15.07.2026 · ₸
A4: Показатель | B4: Сумма, ₸ | C4: % к чист. выручке
A5: Выручка от реализации услуг | B5: =SUMIFS('Реестр операций'!$F:$F,'Реестр операций'!$I:$I,"REVENUE") | C5: =IFERROR(B5/$B$7,0)
A6: минус: возврат средств клиентам | B6: =-SUMIFS('Реестр операций'!$G:$G,'Реестр операций'!$I:$I,"CONTRA") | C6: =IFERROR(B6/$B$7,0)
A7: Чистая выручка | B7: =B5+B6 | C7: =IFERROR(B7/$B$7,0)
A8: минус: Ж/д тариф, вагоны, услуги перевозчиков | B8: =-SUMIFS('Реестр операций'!$G:$G,'Реестр операций'!$I:$I,"COGS",'Реестр операций'!$J:$J,"Ж/д тариф, вагоны, услуги перевозчиков")
A9: минус: Ремонт и ТО вагонов | B9: =-SUMIFS('Реестр операций'!$G:$G,'Реестр операций'!$I:$I,"COGS",'Реестр операций'!$J:$J,"Ремонт и ТО вагонов")
A10: Себестоимость услуг, итого | B10: =-SUMIFS('Реестр операций'!$G:$G,'Реестр операций'!$I:$I,"COGS") | C10: =IFERROR(B10/$B$7,0)
A11: ВАЛОВАЯ ПРИБЫЛЬ | B11: =B7+B10 | C11: =IFERROR(B11/$B$7,0)
A12: минус: Оплата труда | B12: =-SUMIFS('Реестр операций'!$G:$G,'Реестр операций'!$I:$I,"OPEX",'Реестр операций'!$J:$J,"Оплата труда")
A13: минус: Прочие услуги и расходы | B13: =-SUMIFS('Реестр операций'!$G:$G,'Реестр операций'!$I:$I,"OPEX",'Реестр операций'!$J:$J,"Прочие услуги и расходы")
A14: минус: Аренда офиса | B14: =-SUMIFS('Реестр операций'!$G:$G,'Реестр операций'!$I:$I,"OPEX",'Реестр операций'!$J:$J,"Аренда офиса")
A15: минус: Командировочные / поездки | B15: =-SUMIFS('Реестр операций'!$G:$G,'Реестр операций'!$I:$I,"OPEX",'Реестр операций'!$J:$J,"Командировочные / поездки")
A16: минус: ТМЦ / офисные расходы | B16: =-SUMIFS('Реестр операций'!$G:$G,'Реестр операций'!$I:$I,"OPEX",'Реестр операций'!$J:$J,"ТМЦ / офисные расходы")
A17: минус: Банковские услуги | B17: =-SUMIFS('Реестр операций'!$G:$G,'Реестр операций'!$I:$I,"OPEX",'Реестр операций'!$J:$J,"Банковские услуги")
A18: минус: Страхование | B18: =-SUMIFS('Реестр операций'!$G:$G,'Реестр операций'!$I:$I,"OPEX",'Реестр операций'!$J:$J,"Страхование")
A19: Операционные расходы, итого | B19: =-SUMIFS('Реестр операций'!$G:$G,'Реестр операций'!$I:$I,"OPEX") | C19: =IFERROR(B19/$B$7,0)
A20: EBITDA | B20: =B11+B19 | C20: =IFERROR(B20/$B$7,0)
A21: минус: налоги и социальные платежи | B21: =-SUMIFS('Реестр операций'!$G:$G,'Реестр операций'!$I:$I,"TAX") | C21: =IFERROR(B21/$B$7,0)
A22: плюс: финансовые доходы (% по депозитам) | B22: =SUMIFS('Реестр операций'!$F:$F,'Реестр операций'!$I:$I,"FIN_INCOME")+SUMIFS('Реестр операций'!$F:$F,'Реестр операций'!$I:$I,"FIN_COST") | C22: =IFERROR(B22/$B$7,0)
A23: минус: финансовые расходы (% и пени) | B23: =-SUMIFS('Реестр операций'!$G:$G,'Реестр операций'!$I:$I,"FIN_COST") | C23: =IFERROR(B23/$B$7,0)
A24: ЧИСТАЯ ПРИБЫЛЬ | B24: =B20+B21+B22+B23 | C24: =IFERROR(B24/$B$7,0)
A26: Кассовый метод по банковским выпискам: «выручка» = поступления от клиентов, «расходы» = фактические платежи за период. Не учитывает начисления, дебиторскую/кредиторскую задолженность, амортизацию, НДС к зачёту/уплате. Депозиты, займы и переводы между своими счетами исключены из P&L (см. ДДС). Все суммы — формулы SUMIFS по листу «Реестр операций».

Sheet P&L по клиентам
A1: P&L В РАЗБИВКЕ ПО КЛИЕНТАМ — Аренда и ТЭО
A2: ТОО «WayStar Group» (БИН 240340014287) · 15.06.2026 – 15.07.2026 · ₸
A3: Выручка по клиентам — фактическая, из назначений платежей разнесена на «Аренду» (сдача вагонов/цистерн) и «ТЭО» (экспедирование, ж/д тариф, предоставление ПС). Прямые расходы распределены по клиентам пропорционально их выручке в соответствующем направлении; накладные — пропорционально общей выручке (в выписках нет привязки платежей поставщикам к клиенту).
A5: Клиент | B5: Выручка: Аренда | C5: Выручка: ТЭО | D5: Выручка ИТОГО | E5: Расходы: Аренда | F5: Расходы: ТЭО | G5: Прямые расходы ИТОГО | H5: Валовая прибыль | I5: GM % | J5: Накладные (распр.) | K5: Чистая прибыль
A6: QAZAQ-ASTYQ GROUP | B6: =SUMIFS('Реестр операций'!$F:$F,'Реестр операций'!$D:$D,$A6,'Реестр операций'!$I:$I,"REVENUE",'Реестр операций'!$K:$K,"Аренда") | C6: =SUMIFS('Реестр операций'!$F:$F,'Реестр операций'!$D:$D,$A6,'Реестр операций'!$I:$I,"REVENUE",'Реестр операций'!$K:$K,"ТЭО") | D6: =B6+C6 | E6: =IFERROR($E$34*B6/$B$34,0) | F6: =IFERROR($F$34*C6/$C$34,0) | G6: =E6+F6 | H6: =D6-G6 | I6: =IFERROR(H6/D6,0) | J6: =IFERROR($J$34*D6/$D$34,0) | K6: =H6-J6
A7: Altyn Shyghys | B7: =SUMIFS('Реестр операций'!$F:$F,'Реестр операций'!$D:$D,$A7,'Реестр операций'!$I:$I,"REVENUE",'Реестр операций'!$K:$K,"Аренда") | C7: =SUMIFS('Реестр операций'!$F:$F,'Реестр операций'!$D:$D,$A7,'Реестр операций'!$I:$I,"REVENUE",'Реестр операций'!$K:$K,"ТЭО") | D7: =B7+C7 | E7: =IFERROR($E$34*B7/$B$34,0) | F7: =IFERROR($F$34*C7/$C$34,0) | G7: =E7+F7 | H7: =D7-G7 | I7: =IFERROR(H7/D7,0) | J7: =IFERROR($J$34*D7/$D$34,0) | K7: =H7-J7
A8: East Agro Company | B8: =SUMIFS('Реестр операций'!$F:$F,'Реестр операций'!$D:$D,$A8,'Реестр операций'!$I:$I,"REVENUE",'Реестр операций'!$K:$K,"Аренда") | C8: =SUMIFS('Реестр операций'!$F:$F,'Реестр операций'!$D:$D,$A8,'Реестр операций'!$I:$I,"REVENUE",'Реестр операций'!$K:$K,"ТЭО") | D8: =B8+C8 | E8: =IFERROR($E$34*B8/$B$34,0) | F8: =IFERROR($F$34*C8/$C$34,0) | G8: =E8+F8 | H8: =D8-G8 | I8: =IFERROR(H8/D8,0) | J8: =IFERROR($J$34*D8/$D$34,0) | K8: =H8-J8
A9: Экспорт-М | B9: =SUMIFS('Реестр операций'!$F:$F,'Реестр операций'!$D:$D,$A9,'Реестр операций'!$I:$I,"REVENUE",'Реестр операций'!$K:$K,"Аренда") | C9: =SUMIFS('Реестр операций'!$F:$F,'Реестр операций'!$D:$D,$A9,'Реестр операций'!$I:$I,"REVENUE",'Реестр операций'!$K:$K,"ТЭО") | D9: =B9+C9 | E9: =IFERROR($E$34*B9/$B$34,0) | F9: =IFERROR($F$34*C9/$C$34,0) | G9: =E9+F9 | H9: =D9-G9 | I9: =IFERROR(H9/D9,0) | J9: =IFERROR($J$34*D9/$D$34,0) | K9: =H9-J9
A10: GREENLIGHTS (ГРИНЛАЙТС) | B10: =SUMIFS('Реестр операций'!$F:$F,'Реестр операций'!$D:$D,$A10,'Реестр операций'!$I:$I,"REVENUE",'Реестр операций'!$K:$K,"Аренда") | C10: =SUMIFS('Реестр операций'!$F:$F,'Реестр операций'!$D:$D,$A10,'Реестр операций'!$I:$I,"REVENUE",'Реестр операций'!$K:$K,"ТЭО") | D10: =B10+C10 | E10: =IFERROR($E$34*B10/$B$34,0) | F10: =IFERROR($F$34*C10/$C$34,0) | G10: =E10+F10 | H10: =D10-G10 | I10: =IFERROR(H10/D10,0) | J10: =IFERROR($J$34*D10/$D$34,0) | K10: =H10-J10
A11: ResursLogistiс (РесурсЛогистик) | B11: =SUMIFS('Реестр операций'!$F:$F,'Реестр операций'!$D:$D,$A11,'Реестр операций'!$I:$I,"REVENUE",'Реестр операций'!$K:$K,"Аренда") | C11: =SUMIFS('Реестр операций'!$F:$F,'Реестр операций'!$D:$D,$A11,'Реестр операций'!$I:$I,"REVENUE",'Реестр операций'!$K:$K,"ТЭО") | D11: =B11+C11 | E11: =IFERROR($E$34*B11/$B$34,0) | F11: =IFERROR($F$34*C11/$C$34,0) | G11: =E11+F11 | H11: =D11-G11 | I11: =IFERROR(H11/D11,0) | J11: =IFERROR($J$34*D11/$D$34,0) | K11: =H11-J11
A12: ШыгысАгроТорг | B12: =SUMIFS('Реестр операций'!$F:$F,'Реестр операций'!$D:$D,$A12,'Реестр операций'!$I:$I,"REVENUE",'Реестр операций'!$K:$K,"Аренда") | C12: =SUMIFS('Реестр операций'!$F:$F,'Реестр операций'!$D:$D,$A12,'Реестр операций'!$I:$I,"REVENUE",'Реестр операций'!$K:$K,"ТЭО") | D12: =B12+C12 | E12: =IFERROR($E$34*B12/$B$34,0) | F12: =IFERROR($F$34*C12/$C$34,0) | G12: =E12+F12 | H12: =D12-G12 | I12: =IFERROR(H12/D12,0) | J12: =IFERROR($J$34*D12/$D$34,0) | K12: =H12-J12
A13: АРАЙ ТОО | B13: =SUMIFS('Реестр операций'!$F:$F,'Реестр операций'!$D:$D,$A13,'Реестр операций'!$I:$I,"REVENUE",'Реестр операций'!$K:$K,"Аренда") | C13: =SUMIFS('Реестр операций'!$F:$F,'Реестр операций'!$D:$D,$A13,'Реестр операций'!$I:$I,"REVENUE",'Реестр операций'!$K:$K,"ТЭО") | D13: =B13+C13 | E13: =IFERROR($E$34*B13/$B$34,0) | F13: =IFERROR($F$34*C13/$C$34,0) | G13: =E13+F13 | H13: =D13-G13 | I13: =IFERROR(H13/D13,0) | J13: =IFERROR($J$34*D13/$D$34,0) | K13: =H13-J13
A14: ROYAL EXPORT | B14: =SUMIFS('Реестр операций'!$F:$F,'Реестр операций'!$D:$D,$A14,'Реестр операций'!$I:$I,"REVENUE",'Реестр операций'!$K:$K,"Аренда") | C14: =SUMIFS('Реестр операций'!$F:$F,'Реестр операций'!$D:$D,$A14,'Реестр операций'!$I:$I,"REVENUE",'Реестр операций'!$K:$K,"ТЭО") | D14: =B14+C14 | E14: =IFERROR($E$34*B14/$B$34,0) | F14: =IFERROR($F$34*C14/$C$34,0) | G14: =E14+F14 | H14: =D14-G14 | I14: =IFERROR(H14/D14,0) | J14: =IFERROR($J$34*D14/$D$34,0) | K14: =H14-J14
A15: Темир Экспресс Логистик | B15: =SUMIFS('Реестр операций'!$F:$F,'Реестр операций'!$D:$D,$A15,'Реестр операций'!$I:$I,"REVENUE",'Реестр операций'!$K:$K,"Аренда") | C15: =SUMIFS('Реестр операций'!$F:$F,'Реестр операций'!$D:$D,$A15,'Реестр операций'!$I:$I,"REVENUE",'Реестр операций'!$K:$K,"ТЭО") | D15: =B15+C15 | E15: =IFERROR($E$34*B15/$B$34,0) | F15: =IFERROR($F$34*C15/$C$34,0) | G15: =E15+F15 | H15: =D15-G15 | I15: =IFERROR(H15/D15,0) | J15: =IFERROR($J$34*D15/$D$34,0) | K15: =H15-J15
A16: Rhenus Intermodal Systems | B16: =SUMIFS('Реестр операций'!$F:$F,'Реестр операций'!$D:$D,$A16,'Реестр операций'!$I:$I,"REVENUE",'Реестр операций'!$K:$K,"Аренда") | C16: =SUMIFS('Реестр операций'!$F:$F,'Реестр операций'!$D:$D,$A16,'Реестр операций'!$I:$I,"REVENUE",'Реестр операций'!$K:$K,"ТЭО") | D16: =B16+C16 | E16: =IFERROR($E$34*B16/$B$34,0) | F16: =IFERROR($F$34*C16/$C$34,0) | G16: =E16+F16 | H16: =D16-G16 | I16: =IFERROR(H16/D16,0) | J16: =IFERROR($J$34*D16/$D$34,0) | K16: =H16-J16
A17: SYSTEM LTD | B17: =SUMIFS('Реестр операций'!$F:$F,'Реестр операций'!$D:$D,$A17,'Реестр операций'!$I:$I,"REVENUE",'Реестр операций'!$K:$K,"Аренда") | C17: =SUMIFS('Реестр операций'!$F:$F,'Реестр операций'!$D:$D,$A17,'Реестр операций'!$I:$I,"REVENUE",'Реестр операций'!$K:$K,"ТЭО") | D17: =B17+C17 | E17: =IFERROR($E$34*B17/$B$34,0) | F17: =IFERROR($F$34*C17/$C$34,0) | G17: =E17+F17 | H17: =D17-G17 | I17: =IFERROR(H17/D17,0) | J17: =IFERROR($J$34*D17/$D$34,0) | K17: =H17-J17
... A33: ALTYN EXPO | B33: =SUMIFS('Реестр операций'!$F:$F,'Реестр операций'!$D:$D,$A33,'Реестр операций'!$I:$I,"REVENUE",'Реестр операций'!$K:$K,"Аренда") | C33: =SUMIFS('Реестр операций'!$F:$F,'Реестр операций'!$D:$D,$A33,'Реестр операций'!$I:$I,"REVENUE",'Реестр операций'!$K:$K,"ТЭО") | D33: =B33+C33 | E33: =IFERROR($E$34*B33/$B$34,0) | F33: =IFERROR($F$34*C33/$C$34,0) | G33: =E33+F33 | H33: =D33-G33 | I33: =IFERROR(H33/D33,0) | J33: =IFERROR($J$34*D33/$D$34,0) | K33: =H33-J33
A34: ИТОГО | B34: =SUMIFS('Реестр операций'!$F:$F,'Реестр операций'!$I:$I,"REVENUE",'Реестр операций'!$K:$K,"Аренда") | C34: =SUMIFS('Реестр операций'!$F:$F,'Реестр операций'!$I:$I,"REVENUE",'Реестр операций'!$K:$K,"ТЭО") | D34: =B34+C34 | E34: =SUMIFS('Реестр операций'!$G:$G,'Реестр операций'!$I:$I,"COGS",'Реестр операций'!$K:$K,"Аренда") | F34: =SUMIFS('Реестр операций'!$G:$G,'Реестр операций'!$I:$I,"COGS",'Реестр операций'!$K:$K,"ТЭО") | G34: =E34+F34 | H34: =D34-G34 | I34: =IFERROR(H34/D34,0) | J34: =SUMIFS('Реестр операций'!$G:$G,'Реестр операций'!$I:$I,"OPEX")+SUMIFS('Реестр операций'!$G:$G,'Реестр операций'!$I:$I,"TAX")+SUMIFS('Реестр операций'!$G:$G,'Реестр операций'!$I:$I,"FIN_COST")+SUMIFS('Реестр операций'!$G:$G,'Реестр операций'!$I:$I,"CONTRA")-SUMIFS('Реестр операций'!$F:$F,'Реестр операций'!$I:$I,"FIN_INCOME")-SUMIFS('Реестр операций'!$F:$F,'Реестр операций'!$I:$I,"FIN_COST") | K34: =H34-J34

Sheet ДДС (Cash Flow)
A1: ОТЧЁТ О ДВИЖЕНИИ ДЕНЕЖНЫХ СРЕДСТВ (прямой метод)
A2: ТОО «WayStar Group» (БИН 240340014287) · 15.06.2026 – 15.07.2026 · ₸
A4: Статья | B4: Поступления | C4: Выплаты | D4: Итого
A5: Остаток денежных средств на начало периода | B5: =297933.26 | D5: =IFERROR(B5,0)+IFERROR(C5,0)
A6: ОПЕРАЦИОННАЯ ДЕЯТЕЛЬНОСТЬ
A7: Поступления от клиентов | B7: =SUMIFS('Реестр операций'!$F:$F,'Реестр операций'!$I:$I,"REVENUE") | D7: =IFERROR(B7,0)+IFERROR(C7,0)
A8: Возврат средств клиентам | C8: =-SUMIFS('Реестр операций'!$G:$G,'Реестр операций'!$I:$I,"CONTRA") | D8: =IFERROR(B8,0)+IFERROR(C8,0)
A9: Оплата перевозчикам / ж/д тариф / вагоны (COGS) | C9: =-SUMIFS('Реестр операций'!$G:$G,'Реестр операций'!$I:$I,"COGS") | D9: =IFERROR(B9,0)+IFERROR(C9,0)
A10: Операционные расходы (ЗП, аренда, банк, связь) | C10: =-SUMIFS('Реестр операций'!$G:$G,'Реестр операций'!$I:$I,"OPEX") | D10: =IFERROR(B10,0)+IFERROR(C10,0)
A11: Налоги и социальные платежи | C11: =-SUMIFS('Реестр операций'!$G:$G,'Реестр операций'!$I:$I,"TAX") | D11: =IFERROR(B11,0)+IFERROR(C11,0)
A12: Проценты и пени по кредитам | C12: =-SUMIFS('Реестр операций'!$G:$G,'Реестр операций'!$I:$I,"FIN_COST") | D12: =IFERROR(B12,0)+IFERROR(C12,0)
A13: Проценты по депозитам | B13: =SUMIFS('Реестр операций'!$F:$F,'Реестр операций'!$I:$I,"FIN_INCOME") | D13: =IFERROR(B13,0)+IFERROR(C13,0)
A14: Итого по операционной деятельности | D14: =SUM(D7:D13)
A15: ИНВЕСТИЦИОННАЯ / КАЗНАЧЕЙСКАЯ ДЕЯТЕЛЬНОСТЬ
A16: Снятие / возврат депозитов | B16: =SUMIFS('Реестр операций'!$F:$F,'Реестр операций'!$J:$J,"Снятие/возврат депозита") | D16: =IFERROR(B16,0)+IFERROR(C16,0)
A17: Размещение депозитов | C17: =-SUMIFS('Реестр операций'!$G:$G,'Реестр операций'!$J:$J,"Размещение депозита") | D17: =IFERROR(B17,0)+IFERROR(C17,0)
A18: Покупка иностранной валюты (FX) | C18: =-SUMIFS('Реестр операций'!$G:$G,'Реестр операций'!$J:$J,"Покупка валюты (FX)") | D18: =IFERROR(B18,0)+IFERROR(C18,0)
A19: Итого по инвестиц./казнач. деятельности | D19: =SUM(D16:D18)
A20: ФИНАНСОВАЯ ДЕЯТЕЛЬНОСТЬ
A21: Займы полученные / возврат выданных займов | B21: =SUMIFS('Реестр операций'!$F:$F,'Реестр операций'!$I:$I,"FINANCING") | D21: =IFERROR(B21,0)+IFERROR(C21,0)
A22: Погашение и выдача займов | C22: =-SUMIFS('Реестр операций'!$G:$G,'Реестр операций'!$I:$I,"FINANCING") | D22: =IFERROR(B22,0)+IFERROR(C22,0)
A23: Итого по финансовой деятельности | D23: =SUM(D21:D22)
A24: ВНУТРЕННИЕ ПЕРЕВОДЫ И ПРОЧЕЕ
A25: Переводы между собственными счетами (в т.ч. КЛС) | B25: =SUMIFS('Реестр операций'!$F:$F,'Реестр операций'!$I:$I,"INTERNAL") | C25: =-SUMIFS('Реестр операций'!$G:$G,'Реестр операций'!$I:$I,"INTERNAL") | D25: =IFERROR(B25,0)+IFERROR(C25,0)
A26: Прочие поступления | B26: =SUMIFS('Реестр операций'!$F:$F,'Реестр операций'!$I:$I,"OTHER_IN") | D26: =IFERROR(B26,0)+IFERROR(C26,0)
A27: ЧИСТОЕ ИЗМЕНЕНИЕ ДЕНЕЖНЫХ СРЕДСТВ | D27: =D14+D19+D23+D25+D26
A28: Остаток денежных средств на конец периода | B28: =113411502.27 | D28: =D5+D27
A30: Сверка по банковским счетам (контроль):
A31: Банк / счёт | B31: Остаток на начало | C31: Остаток на конец
A32: АО «Банк ЦентрКредит» | B32: 75346.24 | C32: 1.1084035e+08
A33: АО «Народный Банк» | B33: 222587.02 | C33: 2526900
A34: АО «Bank RBK» | B34: 0 | C34: 44256.05
A35: ИТОГО по 3 счетам | B35: =SUM(B32:B34) | C35: =SUM(C32:C34)

Sheet Выручка по клиентам
A1: ВЫРУЧКА ПО КЛИЕНТАМ
A2: 15.06.2026 – 15.07.2026 · ₸
A4: Клиент | B4: Аренда | C4: ТЭО | D4: Операций | E4: Сумма ИТОГО | F4: Доля
A5: QAZAQ-ASTYQ GROUP | B5: =SUMIFS('Реестр операций'!$F:$F,'Реестр операций'!$D:$D,$A5,'Реестр операций'!$I:$I,"REVENUE",'Реестр операций'!$K:$K,"Аренда") | C5: =SUMIFS('Реестр операций'!$F:$F,'Реестр операций'!$D:$D,$A5,'Реестр операций'!$I:$I,"REVENUE",'Реестр операций'!$K:$K,"ТЭО") | D5: =COUNTIFS('Реестр операций'!$D:$D,$A5,'Реестр операций'!$I:$I,"REVENUE") | E5: =B5+C5 | F5: =IFERROR(E5/$E$33,0)
A6: Altyn Shyghys | B6: =SUMIFS('Реестр операций'!$F:$F,'Реестр операций'!$D:$D,$A6,'Реестр операций'!$I:$I,"REVENUE",'Реестр операций'!$K:$K,"Аренда") | C6: =SUMIFS('Реестр операций'!$F:$F,'Реестр операций'!$D:$D,$A6,'Реестр операций'!$I:$I,"REVENUE",'Реестр операций'!$K:$K,"ТЭО") | D6: =COUNTIFS('Реестр операций'!$D:$D,$A6,'Реестр операций'!$I:$I,"REVENUE") | E6: =B6+C6 | F6: =IFERROR(E6/$E$33,0)
A7: East Agro Company | B7: =SUMIFS('Реестр операций'!$F:$F,'Реестр операций'!$D:$D,$A7,'Реестр операций'!$I:$I,"REVENUE",'Реестр операций'!$K:$K,"Аренда") | C7: =SUMIFS('Реестр операций'!$F:$F,'Реестр операций'!$D:$D,$A7,'Реестр операций'!$I:$I,"REVENUE",'Реестр операций'!$K:$K,"ТЭО") | D7: =COUNTIFS('Реестр операций'!$D:$D,$A7,'Реестр операций'!$I:$I,"REVENUE") | E7: =B7+C7 | F7: =IFERROR(E7/$E$33,0)
A8: Экспорт-М | B8: =SUMIFS('Реестр операций'!$F:$F,'Реестр операций'!$D:$D,$A8,'Реестр операций'!$I:$I,"REVENUE",'Реестр операций'!$K:$K,"Аренда") | C8: =SUMIFS('Реестр операций'!$F:$F,'Реестр операций'!$D:$D,$A8,'Реестр операций'!$I:$I,"REVENUE",'Реестр операций'!$K:$K,"ТЭО") | D8: =COUNTIFS('Реестр операций'!$D:$D,$A8,'Реестр операций'!$I:$I,"REVENUE") | E8: =B8+C8 | F8: =IFERROR(E8/$E$33,0)
A9: GREENLIGHTS (ГРИНЛАЙТС) | B9: =SUMIFS('Реестр операций'!$F:$F,'Реестр операций'!$D:$D,$A9,'Реестр операций'!$I:$I,"REVENUE",'Реестр операций'!$K:$K,"Аренда") | C9: =SUMIFS('Реестр операций'!$F:$F,'Реестр операций'!$D:$D,$A9,'Реестр операций'!$I:$I,"REVENUE",'Реестр операций'!$K:$K,"ТЭО") | D9: =COUNTIFS('Реестр операций'!$D:$D,$A9,'Реестр операций'!$I:$I,"REVENUE") | E9: =B9+C9 | F9: =IFERROR(E9/$E$33,0)
A10: ResursLogistiс (РесурсЛогистик) | B10: =SUMIFS('Реестр операций'!$F:$F,'Реестр операций'!$D:$D,$A10,'Реестр операций'!$I:$I,"REVENUE",'Реестр операций'!$K:$K,"Аренда") | C10: =SUMIFS('Реестр операций'!$F:$F,'Реестр операций'!$D:$D,$A10,'Реестр операций'!$I:$I,"REVENUE",'Реестр операций'!$K:$K,"ТЭО") | D10: =COUNTIFS('Реестр операций'!$D:$D,$A10,'Реестр операций'!$I:$I,"REVENUE") | E10: =B10+C10 | F10: =IFERROR(E10/$E$33,0)
A11: ШыгысАгроТорг | B11: =SUMIFS('Реестр операций'!$F:$F,'Реестр операций'!$D:$D,$A11,'Реестр операций'!$I:$I,"REVENUE",'Реестр операций'!$K:$K,"Аренда") | C11: =SUMIFS('Реестр операций'!$F:$F,'Реестр операций'!$D:$D,$A11,'Реестр операций'!$I:$I,"REVENUE",'Реестр операций'!$K:$K,"ТЭО") | D11: =COUNTIFS('Реестр операций'!$D:$D,$A11,'Реестр операций'!$I:$I,"REVENUE") | E11: =B11+C11 | F11: =IFERROR(E11/$E$33,0)
A12: АРАЙ ТОО | B12: =SUMIFS('Реестр операций'!$F:$F,'Реестр операций'!$D:$D,$A12,'Реестр операций'!$I:$I,"REVENUE",'Реестр операций'!$K:$K,"Аренда") | C12: =SUMIFS('Реестр операций'!$F:$F,'Реестр операций'!$D:$D,$A12,'Реестр операций'!$I:$I,"REVENUE",'Реестр операций'!$K:$K,"ТЭО") | D12: =COUNTIFS('Реестр операций'!$D:$D,$A12,'Реестр операций'!$I:$I,"REVENUE") | E12: =B12+C12 | F12: =IFERROR(E12/$E$33,0)
A13: ROYAL EXPORT | B13: =SUMIFS('Реестр операций'!$F:$F,'Реестр операций'!$D:$D,$A13,'Реестр операций'!$I:$I,"REVENUE",'Реестр операций'!$K:$K,"Аренда") | C13: =SUMIFS('Реестр операций'!$F:$F,'Реестр операций'!$D:$D,$A13,'Реестр операций'!$I:$I,"REVENUE",'Реестр операций'!$K:$K,"ТЭО") | D13: =COUNTIFS('Реестр операций'!$D:$D,$A13,'Реестр операций'!$I:$I,"REVENUE") | E13: =B13+C13 | F13: =IFERROR(E13/$E$33,0)
A14: Темир Экспресс Логистик | B14: =SUMIFS('Реестр операций'!$F:$F,'Реестр операций'!$D:$D,$A14,'Реестр операций'!$I:$I,"REVENUE",'Реестр операций'!$K:$K,"Аренда") | C14: =SUMIFS('Реестр операций'!$F:$F,'Реестр операций'!$D:$D,$A14,'Реестр операций'!$I:$I,"REVENUE",'Реестр операций'!$K:$K,"ТЭО") | D14: =COUNTIFS('Реестр операций'!$D:$D,$A14,'Реестр операций'!$I:$I,"REVENUE") | E14: =B14+C14 | F14: =IFERROR(E14/$E$33,0)
A15: Rhenus Intermodal Systems | B15: =SUMIFS('Реестр операций'!$F:$F,'Реестр операций'!$D:$D,$A15,'Реестр операций'!$I:$I,"REVENUE",'Реестр операций'!$K:$K,"Аренда") | C15: =SUMIFS('Реестр операций'!$F:$F,'Реестр операций'!$D:$D,$A15,'Реестр операций'!$I:$I,"REVENUE",'Реестр операций'!$K:$K,"ТЭО") | D15: =COUNTIFS('Реестр операций'!$D:$D,$A15,'Реестр операций'!$I:$I,"REVENUE") | E15: =B15+C15 | F15: =IFERROR(E15/$E$33,0)
A16: SYSTEM LTD | B16: =SUMIFS('Реестр операций'!$F:$F,'Реестр операций'!$D:$D,$A16,'Реестр операций'!$I:$I,"REVENUE",'Реестр операций'!$K:$K,"Аренда") | C16: =SUMIFS('Реестр операций'!$F:$F,'Реестр операций'!$D:$D,$A16,'Реестр операций'!$I:$I,"REVENUE",'Реестр операций'!$K:$K,"ТЭО") | D16: =COUNTIFS('Реестр операций'!$D:$D,$A16,'Реестр операций'!$I:$I,"REVENUE") | E16: =B16+C16 | F16: =IFERROR(E16/$E$33,0)
... A32: ALTYN EXPO | B32: =SUMIFS('Реестр операций'!$F:$F,'Реестр операций'!$D:$D,$A32,'Реестр операций'!$I:$I,"REVENUE",'Реестр операций'!$K:$K,"Аренда") | C32: =SUMIFS('Реестр операций'!$F:$F,'Реестр операций'!$D:$D,$A32,'Реестр операций'!$I:$I,"REVENUE",'Реестр операций'!$K:$K,"ТЭО") | D32: =COUNTIFS('Реестр операций'!$D:$D,$A32,'Реестр операций'!$I:$I,"REVENUE") | E32: =B32+C32 | F32: =IFERROR(E32/$E$33,0)
A33: ИТОГО | B33: =SUMIFS('Реестр операций'!$F:$F,'Реестр операций'!$I:$I,"REVENUE",'Реестр операций'!$K:$K,"Аренда") | C33: =SUMIFS('Реестр операций'!$F:$F,'Реестр операций'!$I:$I,"REVENUE",'Реестр операций'!$K:$K,"ТЭО") | D33: =COUNTIFS('Реестр операций'!$I:$I,"REVENUE") | E33: =B33+C33 | F33: =1

Sheet Расходы
A1: РАСХОДЫ ПО КАТЕГОРИЯМ И ПОСТАВЩИКАМ
A2: 15.06.2026 – 15.07.2026 · ₸
A4: По категориям
A5: Категория | B5: Сумма, ₸
A6: COGS · Ж/д тариф, вагоны, услуги перевозчиков | B6: =SUMIFS('Реестр операций'!$G:$G,'Реестр операций'!$I:$I,"COGS",'Реестр операций'!$J:$J,"Ж/д тариф, вагоны, услуги перевозчиков")
A7: COGS · Ремонт и ТО вагонов | B7: =SUMIFS('Реестр операций'!$G:$G,'Реестр операций'!$I:$I,"COGS",'Реестр операций'!$J:$J,"Ремонт и ТО вагонов")
A8: OPEX · Оплата труда | B8: =SUMIFS('Реестр операций'!$G:$G,'Реестр операций'!$I:$I,"OPEX",'Реестр операций'!$J:$J,"Оплата труда")
A9: OPEX · Прочие услуги и расходы | B9: =SUMIFS('Реестр операций'!$G:$G,'Реестр операций'!$I:$I,"OPEX",'Реестр операций'!$J:$J,"Прочие услуги и расходы")
A10: OPEX · Аренда офиса | B10: =SUMIFS('Реестр операций'!$G:$G,'Реестр операций'!$I:$I,"OPEX",'Реестр операций'!$J:$J,"Аренда офиса")
A11: OPEX · Командировочные / поездки | B11: =SUMIFS('Реестр операций'!$G:$G,'Реестр операций'!$I:$I,"OPEX",'Реестр операций'!$J:$J,"Командировочные / поездки")
A12: OPEX · ТМЦ / офисные расходы | B12: =SUMIFS('Реестр операций'!$G:$G,'Реестр операций'!$I:$I,"OPEX",'Реестр операций'!$J:$J,"ТМЦ / офисные расходы")
A13: OPEX · Банковские услуги | B13: =SUMIFS('Реестр операций'!$G:$G,'Реестр операций'!$I:$I,"OPEX",'Реестр операций'!$J:$J,"Банковские услуги")
A14: OPEX · Страхование | B14: =SUMIFS('Реестр операций'!$G:$G,'Реестр операций'!$I:$I,"OPEX",'Реестр операций'!$J:$J,"Страхование")
A15: Налоги и соц. платежи | B15: =SUMIFS('Реестр операций'!$G:$G,'Реестр операций'!$I:$I,"TAX")
A16: Проценты и пени по кредитам | B16: =SUMIFS('Реестр операций'!$G:$G,'Реестр операций'!$I:$I,"FIN_COST")
A17: ИТОГО (без займов/депозитов/переводов) | B17: =SUM(B6:B16)
A19: Топ-20 поставщиков (COGS + OPEX)
A20: Поставщик | B20: Сумма, ₸
A21: КТЖ-Грузовые перевозки | B21: =SUMIFS('Реестр операций'!$G:$G,'Реестр операций'!$D:$D,$A21,'Реестр операций'!$I:$I,"COGS")+SUMIFS('Реестр операций'!$G:$G,'Реестр операций'!$D:$D,$A21,'Реестр операций'!$I:$I,"OPEX")
A22: КТТ (ҚАЗТЕМІРТРАНС) АО | B22: =SUMIFS('Реестр операций'!$G:$G,'Реестр операций'!$D:$D,$A22,'Реестр операций'!$I:$I,"COGS")+SUMIFS('Реестр операций'!$G:$G,'Реестр операций'!$D:$D,$A22,'Реестр операций'!$I:$I,"OPEX")
A23: АРНА | B23: =SUMIFS('Реестр операций'!$G:$G,'Реестр операций'!$D:$D,$A23,'Реестр операций'!$I:$I,"COGS")+SUMIFS('Реестр операций'!$G:$G,'Реестр операций'!$D:$D,$A23,'Реестр операций'!$I:$I,"OPEX")
A24: Рейл Транспортейшн | B24: =SUMIFS('Реестр операций'!$G:$G,'Реестр операций'!$D:$D,$A24,'Реестр операций'!$I:$I,"COGS")+SUMIFS('Реестр операций'!$G:$G,'Реестр операций'!$D:$D,$A24,'Реестр операций'!$I:$I,"OPEX")
A25: InterLog Co | B25: =SUMIFS('Реестр операций'!$G:$G,'Реестр операций'!$D:$D,$A25,'Реестр операций'!$I:$I,"COGS")+SUMIFS('Реестр операций'!$G:$G,'Реестр операций'!$D:$D,$A25,'Реестр операций'!$I:$I,"OPEX")
A26: PRATA | B26: =SUMIFS('Реестр операций'!$G:$G,'Реестр операций'!$D:$D,$A26,'Реестр операций'!$I:$I,"COGS")+SUMIFS('Реестр операций'!$G:$G,'Реестр операций'!$D:$D,$A26,'Реестр операций'!$I:$I,"OPEX")
A27: Банк ЦентрКредит для ЗП | B27: =SUMIFS('Реестр операций'!$G:$G,'Реестр операций'!$D:$D,$A27,'Реестр операций'!$I:$I,"COGS")+SUMIFS('Реестр операций'!$G:$G,'Реестр операций'!$D:$D,$A27,'Реестр операций'!$I:$I,"OPEX")
A28: PetroComLogistics | B28: =SUMIFS('Реестр операций'!$G:$G,'Реестр операций'!$D:$D,$A28,'Реестр операций'!$I:$I,"COGS")+SUMIFS('Реестр операций'!$G:$G,'Реестр операций'!$D:$D,$A28,'Реестр операций'!$I:$I,"OPEX")
A29: ЭДЕМ ТРАНС | B29: =SUMIFS('Реестр операций'!$G:$G,'Реестр операций'!$D:$D,$A29,'Реестр операций'!$I:$I,"COGS")+SUMIFS('Реестр операций'!$G:$G,'Реестр операций'!$D:$D,$A29,'Реестр операций'!$I:$I,"OPEX")
A30: ЭРСАЛТ РЭЙЛ | B30: =SUMIFS('Реестр операций'!$G:$G,'Реестр операций'!$D:$D,$A30,'Реестр операций'!$I:$I,"COGS")+SUMIFS('Реестр операций'!$G:$G,'Реестр операций'!$D:$D,$A30,'Реестр операций'!$I:$I,"OPEX")
A31: КТЖ-ГРУЗОВЫЕ ПЕРЕВОЗКИ | B31: =SUMIFS('Реестр операций'!$G:$G,'Реестр операций'!$D:$D,$A31,'Реестр операций'!$I:$I,"COGS")+SUMIFS('Реестр операций'!$G:$G,'Реестр операций'!$D:$D,$A31,'Реестр операций'!$I:$I,"OPEX")
A32: Банк "Bank RBK | B32: =SUMIFS('Реестр операций'!$G:$G,'Реестр операций'!$D:$D,$A32,'Реестр операций'!$I:$I,"COGS")+SUMIFS('Реестр операций'!$G:$G,'Реестр операций'!$D:$D,$A32,'Реестр операций'!$I:$I,"OPEX")
... A40: JOINMEDIA | B40: =SUMIFS('Реестр операций'!$G:$G,'Реестр операций'!$D:$D,$A40,'Реестр операций'!$I:$I,"COGS")+SUMIFS('Реестр операций'!$G:$G,'Реестр операций'!$D:$D,$A40,'Реестр операций'!$I:$I,"OPEX")
